Workbook

Sheet БИПЦ_НДС
A1: Совпадение ключей названия | B1: Новое название | C1: Старое основное название | D1: Итог | E1: Базовая ставка | F1: Примечания
A2: =EXACT(B2,C2) -> TRUE | B2: Говядина (кроме бескостного мяса), кг | C2: Говядина (кроме бескостного мяса), кг | D2: 10 | E2: =IF(D2=20,1,0) -> 0 | F2: https://base.garant.ru/12138471/#block_1000 | G2: https://normativ.kontur.ru/document?moduleId=1&documentId=422375&ysclid=l59k44nnc9669497702&promocode=0957&utm_source=yandex&utm_medium=organic&utm_campaign=content-link-buhonline&utm_content=tag-nds&utm_term=forum729121&utm_referrer=https%3A%2F%2Fyandex.ru#h2259
A3: =EXACT(B3,C3) -> TRUE | B3: Говядина бескостная, кг | C3: Говядина бескостная, кг | D3: 10 | E3: =IF(D3=20,1,0) -> 0
A4: =EXACT(B4,C4) -> TRUE | B4: Свинина (кроме бескостного мяса), кг | C4: Свинина (кроме бескостного мяса), кг | D4: 10 | E4: =IF(D4=20,1,0) -> 0
A5: =EXACT(B5,C5) -> TRUE | B5: Свинина бескостная, кг | C5: Свинина бескостная, кг | D5: 10 | E5: =IF(D5=20,1,0) -> 0
A6: =EXACT(B6,C6) -> TRUE | B6: Баранина (кроме бескостного мяса), кг | C6: Баранина (кроме бескостного мяса), кг | D6: 10 | E6: =IF(D6=20,1,0) -> 0
A7: =EXACT(B7,C7) -> TRUE | B7: Куры охлажденные и мороженые, кг | C7: Куры охлажденные и мороженые, кг | D7: 10 | E7: =IF(D7=20,1,0) -> 0
A8: =EXACT(B8,C8) -> TRUE | B8: Окорочка куриные, кг | C8: Окорочка куриные, кг | D8: 10 | E8: =IF(D8=20,1,0) -> 0
A9: =EXACT(B9,C9) -> TRUE | B9: Мясо индейки, кг | C9: Мясо индейки, кг | D9: 10 | E9: =IF(D9=20,1,0) -> 0
A10: =EXACT(B10,C10) -> TRUE | B10: Печень говяжья, свиная, кг | C10: Печень говяжья, свиная, кг | D10: 10 | E10: =IF(D10=20,1,0) -> 0
A11: =EXACT(B11,C11) -> TRUE | B11: Фарш мясной, кг | C11: Фарш мясной, кг | D11: 10 | E11: =IF(D11=20,1,0) -> 0
A12: =EXACT(B12,C12) -> TRUE | B12: Пельмени, манты, равиоли, кг | C12: Пельмени, манты, равиоли, кг | D12: 10 | E12: =IF(D12=20,1,0) -> 0
A13: =EXACT(B13,C13) -> TRUE | B13: Сосиски, сардельки, кг | C13: Сосиски, сардельки, кг | D13: 10 | E13: =IF(D13=20,1,0) -> 0
A14: =EXACT(B14,C14) -> TRUE | B14: Колбаса полукопченая и варено-копченая, кг | C14: Колбаса полукопченая и варено-копченая, кг | D14: 10 | E14: =IF(D14=20,1,0) -> 0
... A28: =EXACT(B28,C28) -> TRUE | B28: Филе рыбное, кг | C28: Филе рыбное, кг | D28: 10 | E28: =IF(D28=20,1,0) -> 0
A29: =EXACT(B29,C29) -> FALSE | B29: Креветки мороженые, неразделанные, кг | C29: Креветки мороженые неразделанные, кг | D29: 10 | E29: =IF(D29=20,1,0) -> 0 | F29: https://base.garant.ru/12138471/#block_1000
A30: =EXACT(B30,C30) -> FALSE | B30: Кальмары мороженые, кг | C30: Кальмары мороженые,кг | D30: 10 | E30: =IF(D30=20,1,0) -> 0 | F30: https://enterfin.ru/q_a_31418/
A31: =EXACT(B31,C31) -> TRUE | B31: Сельдь соленая, кг | C31: Сельдь соленая, кг | D31: 10 | E31: =IF(D31=20,1,0) -> 0
A32: =EXACT(B32,C32) -> TRUE | B32: Филе сельди соленое, кг | C32: Филе сельди соленое, кг | D32: 10 | E32: =IF(D32=20,1,0) -> 0
A33: =EXACT(B33,C33) -> TRUE | B33: Консервы рыбные натуральные и с добавлением масла, кг | C33: Консервы рыбные натуральные и с добавлением масла, кг | D33: 10 | E33: =IF(D33=20,1,0) -> 0
A34: =EXACT(B34,C34) -> TRUE | B34: Консервы рыбные в томатном соусе, кг | C34: Консервы рыбные в томатном соусе, кг | D34: 10 | E34: =IF(D34=20,1,0) -> 0
A35: =EXACT(B35,C35) -> TRUE | B35: Масло сливочное, кг | C35: Масло сливочное, кг | D35: 10 | E35: =IF(D35=20,1,0) -> 0
A36: =EXACT(B36,C36) -> TRUE | B36: Масло подсолнечное, л | C36: Масло подсолнечное, л | D36: 10 | E36: =IF(D36=20,1,0) -> 0
A37: =EXACT(B37,C37) -> TRUE | B37: Масло оливковое, л | C37: Масло оливковое, л | D37: 10 | E37: =IF(D37=20,1,0) -> 0
A38: =EXACT(B38,C38) -> TRUE | B38: Маргарин, кг | C38: Маргарин, кг | D38: 10 | E38: =IF(D38=20,1,0) -> 0
A39: =EXACT(B39,C39) -> TRUE | B39: Молоко питьевое цельное пастеризованное 2,5-3,2% жирности, л | C39: Молоко питьевое цельное пастеризованное 2,5-3,2% жирности, л | D39: 10 | E39: =IF(D39=20,1,0) -> 0
A40: =EXACT(B40,C40) -> TRUE | B40: Молоко питьевое цельное ультрапастеризованное 2,5-3,2% жирности, л | C40: Молоко питьевое цельное ультрапастеризованное 2,5-3,2% жирности, л | D40: 10 | E40: =IF(D40=20,1,0) -> 0
A41: =EXACT(B41,C41) -> TRUE | B41: Молоко питьевое цельное пастеризованное более 3,2% жирности, л | C41: Молоко питьевое цельное пастеризованное более 3,2% жирности, л | D41: 10 | E41: =IF(D41=20,1,0) -> 0
A42: =EXACT(B42,C42) -> TRUE | B42: Сметана, кг | C42: Сметана, кг | D42: 10 | E42: =IF(D42=20,1,0) -> 0
... A52: =EXACT(B52,C52) -> TRUE | B52: Национальные сыры и брынза, кг | C52: Национальные сыры и брынза, кг | D52: 10 | E52: =IF(D52=20,1,0) -> 0
A53: =EXACT(B53,C53) -> TRUE | B53: Овощи натуральные консервированные, маринованные, кг | C53: Овощи натуральные консервированные, маринованные, кг | D53: 20 | E53: =IF(D53=20,1,0) -> 1 | F53: https://www.alta.ru/tnved/code/0711400000/
A54: =EXACT(B54,C54) -> TRUE | B54: Горошек зеленый консервированный, кг | C54: Горошек зеленый консервированный, кг | D54: 20 | E54: =IF(D54=20,1,0) -> 1 | F54: https://www.alta.ru/tnved/code/2005400000/ https://www.buhonline.ru/forum/index?g=posts&t=469410
A55: =EXACT(B55,C55) -> TRUE | B55: Консервы овощные для детского питания, кг | C55: Консервы овощные для детского питания, кг | D55: 10 | E55: =IF(D55=20,1,0) -> 0
A56: =EXACT(B56,C56) -> TRUE | B56: Консервы томатные, кг | C56: Консервы томатные, кг | D56: 20 | E56: =IF(D56=20,1,0) -> 1 | F56: https://www.alta.ru/tnved/code/2002101000/
A57: =EXACT(B57,C57) -> TRUE | B57: Соки фруктовые, л | C57: Соки фруктовые, л | D57: 10 | E57: =IF(D57=20,1,0) -> 0
A58: =EXACT(B58,C58) -> TRUE | B58: Консервы фруктово-ягодные для детского питания, кг | C58: Консервы фруктово-ягодные для детского питания, кг | D58: 10 | E58: =IF(D58=20,1,0) -> 0
A59: =EXACT(B59,C59) -> TRUE | B59: Зефир, пастила, кг | C59: Зефир, пастила, кг | D59: 20 | E59: =IF(D59=20,1,0) -> 1
A60: =EXACT(B60,C60) -> TRUE | B60: Карамель, кг | C60: Карамель, кг | D60: 20 | E60: =IF(D60=20,1,0) -> 1 | F60: https://www.alta.ru/tnved/code/1704907100/
A61: =EXACT(B61,C61) -> TRUE | B61: Шоколад, кг | C61: Шоколад, кг | D61: 20 | E61: =IF(D61=20,1,0) -> 1 | F61: https://www.alta.ru/tnved/code/1806903100/
A62: =EXACT(B62,C62) -> TRUE | B62: Конфеты мягкие, глазированные шоколадом, кг | C62: Конфеты мягкие, глазированные шоколадом, кг | D62: 20 | E62: =IF(D62=20,1,0) -> 1
A63: =EXACT(B63,C63) -> TRUE | B63: Конфеты шоколадные натуральные и с добавками, кг | C63: Конфеты шоколадные натуральные и с добавками, кг | D63: 20 | E63: =IF(D63=20,1,0) -> 1 | F63: https://www.alta.ru/tnved/code/1806901900/
A64: =EXACT(B64,C64) -> TRUE | B64: Жевательная резинка, упаковка | C64: Жевательная резинка, упаковка | D64: 20 | E64: =IF(D64=20,1,0) -> 1
A65: =EXACT(B65,C65) -> TRUE | B65: Печенье, кг | C65: Печенье, кг | D65: 20 | E65: =IF(D65=20,1,0) -> 1
A66: =EXACT(B66,C66) -> TRUE | B66: Пряники, кг | C66: Пряники, кг | D66: 20 | E66: =IF(D66=20,1,0) -> 1
A67: =EXACT(B67,C67) -> TRUE | B67: Кексы, рулеты, кг | C67: Кексы, рулеты, кг | D67: 20 | E67: =IF(D67=20,1,0) -> 1
A68: =EXACT(B68,C68) -> TRUE | B68: Торты, кг | C68: Торты, кг | D68: 20 | E68: =IF(D68=20,1,0) -> 1
A69: =EXACT(B69,C69) -> TRUE | B69: Варенье, джем, повидло, кг | C69: Варенье, джем, повидло, кг | D69: 20 | E69: =IF(D69=20,1,0) -> 1 | F69: https://www.alta.ru/tnved/code/2007995008/
A70: =EXACT(B70,C70) -> TRUE | B70: Мёд пчелиный натуральный, кг | C70: Мёд пчелиный натуральный, кг | D70: 20 | E70: =IF(D70=20,1,0) -> 1 | F70: https://www.alta.ru/tnved/code/0409000000/
A71: =EXACT(B71,C71) -> TRUE | B71: Кофе натуральный растворимый, кг | C71: Кофе натуральный растворимый, кг | D71: 20 | E71: =IF(D71=20,1,0) -> 1 | F71: https://www.alta.ru/tnved/code/2101110013/
A72: =EXACT(B72,C72) -> TRUE | B72: Кофе натуральный в зернах и молотый, кг | C72: Кофе натуральный в зернах и молотый, кг | D72: 20 | E72: =IF(D72=20,1,0) -> 1 | F72: https://www.glavbukh.ru/hl/239727-kofe-latte-s-kakoy-protsentnoy-stavkoy-budet-prodavatsya
A73: =EXACT(B73,C73) -> TRUE | B73: Чай черный байховый, кг | C73: Чай черный байховый, кг | D73: 20 | E73: =IF(D73=20,1,0) -> 1 | F73: https://www.alta.ru/tnved/code/0902400000/
A74: =EXACT(B74,C74) -> TRUE | B74: Чай черный байховый пакетированный, 25 пакетиков | C74: Чай черный байховый пакетированный, 25 пакетиков | D74: 20 | E74: =IF(D74=20,1,0) -> 1
A75: =EXACT(B75,C75) -> TRUE | B75: Чай зеленый, кг | C75: Чай зеленый, кг | D75: 20 | E75: =IF(D75=20,1,0) -> 1 | F75: https://www.alta.ru/tnved/code/0902100001/
A76: =EXACT(B76,C76) -> TRUE | B76: Какао, кг | C76: Какао, кг | D76: 20 | E76: =IF(D76=20,1,0) -> 1 | F76: https://www.alta.ru/tnved/code/1805000000/
A77: =EXACT(B77,C77) -> TRUE | B77: Майонез, кг | C77: Майонез, кг | D77: 20 | E77: =IF(D77=20,1,0) -> 1 | F77: https://www.alta.ru/tnved/code/2103909001/
A78: =EXACT(B78,C78) -> TRUE | B78: Кетчуп, кг | C78: Кетчуп, кг | D78: 20 | E78: =IF(D78=20,1,0) -> 1 | F78: https://www.alta.ru/tnved/code/2103200000/
A79: =EXACT(B79,C79) -> TRUE | B79: Соль поваренная пищевая, кг | C79: Соль поваренная пищевая, кг | D79: 10 | E79: =IF(D79=20,1,0) -> 0 | F79: https://base.garant.ru/12138471/
A80: =EXACT(B80,C80) -> TRUE | B80: Сухие приправы, специи, кг | C80: Сухие приправы, специи, кг | D80: 20 | E80: =IF(D80=20,1,0) -> 1
A81: =EXACT(B81,C81) -> TRUE | B81: Сухие супы в пакетах, кг | C81: Сухие супы в пакетах, кг | D81: 20 | E81: =IF(D81=20,1,0) -> 1
A82: =EXACT(B82,C82) -> TRUE | B82: Мука пшеничная, кг | C82: Мука пшеничная, кг | D82: 10 | E82: =IF(D82=20,1,0) -> 0
A83: =EXACT(B83,C83) -> TRUE | B83: Хлеб из ржаной муки и из смеси муки ржаной и пшеничной, кг | C83: Хлеб из ржаной муки и из смеси муки ржаной и пшеничной, кг | D83: 10 | E83: =IF(D83=20,1,0) -> 0
A84: =EXACT(B84,C84) -> TRUE | B84: Хлеб и булочные изделия из пшеничной муки различных сортов, кг | C84: Хлеб и булочные изделия из пшеничной муки различных сортов, кг | D84: 10 | E84: =IF(D84=20,1,0) -> 0
A85: =EXACT(B85,C85) -> TRUE | B85: Булочные изделия сдобные из муки высшего сорта штучные, кг | C85: Булочные изделия сдобные из муки высшего сорта штучные, кг | D85: 10 | E85: =IF(D85=20,1,0) -> 0
A86: =EXACT(B86,C86) -> TRUE | B86: Бараночные изделия, кг | C86: Бараночные изделия, кг | D86: 10 | E86: =IF(D86=20,1,0) -> 0
A87: =EXACT(B87,C87) -> TRUE | B87: Хлопья из злаков (сухие завтраки), кг | C87: Хлопья из злаков (сухие завтраки), кг | D87: 10 | E87: =IF(D87=20,1,0) -> 0
A88: =EXACT(B88,C88) -> TRUE | B88: Крупа манная, кг | C88: Крупа манная, кг | D88: 10 | E88: =IF(D88=20,1,0) -> 0
A89: =EXACT(B89,C89) -> TRUE | B89: Горох и фасоль, кг | C89: Горох и фасоль, кг | D89: 10 | E89: =IF(D89=20,1,0) -> 0 | F89: https://base.garant.ru/12138471/#block_1000
A90: =EXACT(B90,C90) -> TRUE | B90: Крупы овсяная и перловая, кг | C90: Крупы овсяная и перловая, кг | D90: 10 | E90: =IF(D90=20,1,0) -> 0
A91: =EXACT(B91,C91) -> TRUE | B91: Овсяные хлопья "Геркулес", кг | C91: Овсяные хлопья "Геркулес", кг | D91: 10 | E91: =IF(D91=20,1,0) -> 0 | F91: https://normativ.kontur.ru/document?moduleId=8&documentId=18705
A92: =EXACT(B92,C92) -> TRUE | B92: Вермишель, кг | C92: Вермишель, кг | D92: 10 | E92: =IF(D92=20,1,0) -> 0
A93: =EXACT(B93,C93) -> TRUE | B93: Макаронные изделия из пшеничной муки высшего сорта, кг | C93: Макаронные изделия из пшеничной муки высшего сорта, кг | D93: 10 | E93: =IF(D93=20,1,0) -> 0
A94: =EXACT(B94,C94) -> TRUE | B94: Овощи замороженные, кг | C94: Овощи замороженные, кг | D94: 20 | E94: =IF(D94=20,1,0) -> 1 | F94: https://www.glavbukh.ru/art/33429-stavka-nds-pri-realizatsii-zamorojennyh-ovoshchey | G94: Был чек
A95: =EXACT(B95,C95) -> TRUE | B95: Сухофрукты, кг | C95: Сухофрукты, кг | D95: 20 | E95: =IF(D95=20,1,0) -> 1 | F95: https://www.alta.ru/tnved/code/0813501900/ https://www.glavbukh.ru/hl/313569-nds-na-realizatsiyu-suhofruktov
A96: =EXACT(B96,C96) -> TRUE | B96: Орехи, кг | C96: Орехи, кг | D96: 20 | E96: =IF(D96=20,1,0) -> 1 | F96: https://www.alta.ru/tnved/code/0802320000/
A97: =EXACT(B97,C97) -> TRUE | B97: Ягоды замороженные, кг | C97: Ягоды замороженные, кг | D97: 10 | E97: =IF(D97=20,1,0) -> 0 | F97: https://www.alta.ru/tamdoc/19a89192/
A98: =EXACT(B98,C98) -> TRUE | B98: Пиво, л | C98: Пиво, л | D98: 20 | E98: =IF(D98=20,1,0) -> 1 | F98: https://www.bfm.ru/news/585794
A99: =EXACT(B99,C99) -> TRUE | B99: Вода минеральная и питьевая, л | C99: Вода минеральная и питьевая, л | D99: 20 | E99: =IF(D99=20,1,0) -> 1 | F99: https://www.consultant.ru/law/podborki/mineralnaya_voda_stavka_nds/
A100: =EXACT(B100,C100) -> TRUE | B100: Напитки газированные, л | C100: Напитки газированные, л | D100: 20 | E100: =IF(D100=20,1,0) -> 1
A101: =EXACT(B101,C101) -> TRUE | B101: Мороженое сливочное, кг | C101: Мороженое сливочное, кг | D101: 10 | E101: =IF(D101=20,1,0) -> 0 | F101: https://base.garant.ru/12138471/
A102: =EXACT(B102,C102) -> TRUE | B102: Кофе в организациях быстрого обслуживания, 200 г | C102: Кофе в организациях быстрого обслуживания, 200 г | D102: 20 | E102: =IF(D102=20,1,0) -> 1
A103: =EXACT(B103,C103) -> TRUE | B103: Продукция предприятий общественного питания быстрого обслуживания, шт. | C103: Продукция предприятий общественного питания быстрого обслуживания, шт. | D103: 20 | E103: =IF(D103=20,1,0) -> 1
A104: =EXACT(B104,C104) -> TRUE | B104: Обед в столовой, кафе, закусочной (кроме столовой в организации), на 1 человека | C104: Обед в столовой, кафе, закусочной (кроме столовой в организации), на 1 человека | D104: 20 | E104: =IF(D104=20,1,0) -> 1
A105: =EXACT(B105,C105) -> TRUE | B105: Обед в ресторане, на 1 человека | C105: Обед в ресторане, на 1 человека | D105: 20 | E105: =IF(D105=20,1,0) -> 1
A106: =EXACT(B106,C106) -> TRUE | B106: Ужин в ресторане, на 1 человека | C106: Ужин в ресторане, на 1 человека | D106: 20 | E106: =IF(D106=20,1,0) -> 1
A107: =EXACT(B107,C107) -> TRUE | B107: Ткани хлопчатобумажные бельевые, м | C107: Ткани хлопчатобумажные бельевые, м | D107: 20 | E107: =IF(D107=20,1,0) -> 1 | F107: https://kodtnved.ru/ts/5208420000.html
A108: =EXACT(B108,C108) -> TRUE | B108: Ткань костюмная шерстяная и полушерстяная, м | C108: Ткань костюмная шерстяная и полушерстяная, м | D108: 20 | E108: =IF(D108=20,1,0) -> 1
A109: =EXACT(B109,C109) -> TRUE | B109: Ткань платьевая из искусственного или синтетического шелка, м | C109: Ткань платьевая из искусственного или синтетического шелка, м | D109: 20 | E109: =IF(D109=20,1,0) -> 1
A110: =EXACT(B110,C110) -> TRUE | B110: Ткани декоративные для изготовления штор и занавесей, м | C110: Ткани декоративные для изготовления штор и занавесей, м | D110: 20 | E110: =IF(D110=20,1,0) -> 1
A111: =EXACT(B111,C111) -> TRUE | B111: Полотенце личное, шт. | C111: Полотенце личное, шт. | D111: 20 | E111: =IF(D111=20,1,0) -> 1
A112: =EXACT(B112,C112) -> TRUE | B112: Полотенце кухонное, шт. | C112: Полотенце кухонное, шт. | D112: 20 | E112: =IF(D112=20,1,0) -> 1
A113: =EXACT(B113,C113) -> TRUE | B113: Куртка мужская с верхом из плащевых тканей утепленная, шт. | C113: Куртка мужская с верхом из плащевых тканей утепленная, шт. | D113: 20 | E113: =IF(D113=20,1,0) -> 1
A114: =EXACT(B114,C114) -> TRUE | B114: Куртка мужская без утеплителя (ветровка), шт. | C114: Куртка мужская без утеплителя (ветровка), шт. | D114: 20 | E114: =IF(D114=20,1,0) -> 1
A115: =EXACT(B115,C115) -> TRUE | B115: Куртка мужская из натуральной кожи, шт. | C115: Куртка мужская из натуральной кожи, шт. | D115: 20 | E115: =IF(D115=20,1,0) -> 1
A116: =EXACT(B116,C116) -> FALSE | B116: Костюм-двойка мужской, шт. | C116: Костюм-двойка мужской из шерстяных, полушерстяных или смесовых тканей, шт. | D116: 20 | E116: =IF(D116=20,1,0) -> 1
A117: =EXACT(B117,C117) -> TRUE | B117: Брюки мужские из полушерстяных или смесовых тканей, шт. | C117: Брюки мужские из полушерстяных или смесовых тканей, шт. | D117: 20 | E117: =IF(D117=20,1,0) -> 1
A118: =EXACT(B118,C118) -> TRUE | B118: Брюки мужские из джинсовой ткани (джинсы), шт. | C118: Брюки мужские из джинсовой ткани (джинсы), шт. | D118: 20 | E118: =IF(D118=20,1,0) -> 1
A119: =EXACT(B119,C119) -> FALSE | B119: Рубашка верхняя мужская, шт. | C119: Рубашка верхняя мужская из хлопчатобумажных или смесовых тканей, шт. | D119: 20 | E119: =IF(D119=20,1,0) -> 1
... A153: =EXACT(B153,C153) -> TRUE | B153: Костюм спортивный для взрослых, шт. | C153: Костюм спортивный для взрослых, шт. | D153: 20 | E153: =IF(D153=20,1,0) -> 1
A154: =EXACT(B154,C154) -> TRUE | B154: Костюм спортивный для детей школьного возраста, шт. | C154: Костюм спортивный для детей школьного возраста, шт. | D154: 10 | E154: =IF(D154=20,1,0) -> 0 | F154: https://normativ.kontur.ru/document?moduleId=1&documentId=503427
A155: =EXACT(B155,C155) -> TRUE | B155: Костюм трикотажный для детей ясельного возраста, шт. | C155: Костюм трикотажный для детей ясельного возраста, шт. | D155: 10 | E155: =IF(D155=20,1,0) -> 0
...

Sheet Структура
A1: Новое название | B1: Название для поиска 2026 | C1: Название для поиска 2025 | D1: Название для поиска ИПЦ | E1: НДС | F1: Тип | G1: БИПЦ 2026 | H1: БИПЦ 2025 | I1: Туризм и общепит | J1: Вес янв26 | K1: Вес янв25 | L1: ИПЦ 2026 | M1: ИПЦ 2025 | N1: Учитывать | P1: ИПЦ янв25 | Q1: ИПЦ фев25 | R1: ИПЦ мар25 | S1: ИПЦ апр25 | T1: ИПЦ май25 | U1: ИПЦ июн25 | V1: ИПЦ июл25 | W1: ИПЦ авг25 | X1: ИПЦ сен25 | Y1: ИПЦ окт25 | Z1: ИПЦ ноя25 | AA1: ИПЦ дек25 | AB1: ИПЦ янв26 | AC1: ИПЦ фев26 | AD1: ИПЦ мар26 | AE1: ИПЦ апр26 | AG1: Вес янв25 | AH1: Вес фев25 | AI1: Вес мар25 | AJ1: Вес апр25 | AK1: Вес май25 | AL1: Вес июн25 | AM1: Вес июл25 | AN1: Вес авг25 | AO1: Вес сен25 | AP1: Вес окт25 | AQ1: Вес ноя25 | AR1: Вес дек25 | AS1: Вес янв26 | AT1: Вес фев26 | AU1: Вес мар26 | AV1: Вес апр26 | AW1: Вес май26
A2: Говядина (кроме бескостного мяса), кг | B2: =A2 -> Говядина (кроме бескостного мяса), кг | C2: =A2 -> Говядина (кроме бескостного мяса), кг | D2: =C2 -> Говядина (кроме бескостного мяса), кг | E2: =INDEX(БИПЦ_НДС!$D:$D,MATCH(Структура!A2,БИПЦ_НДС!$B:$B,0)) -> 10 | F2: Проды | G2: 1 | H2: 1 | I2: 0 | J2: =INDEX('2026'!$C:$C,MATCH(Структура!B2,'2026'!$B:$B,0)) -> 0.638 | K2: =INDEX('2025'!$C:$C,MATCH(Структура!C2,'2025'!$B:$B,0)) -> 0.627 | L2: 1 | M2: 1 | N2: 0 | P2: =INDEX('ИПЦ raw'!AA:AA, MATCH(Структура!$D2,'ИПЦ raw'!$A:$A,0)) -> 101.77 | Q2: =INDEX('ИПЦ raw'!AB:AB, MATCH(Структура!$D2,'ИПЦ raw'!$A:$A,0)) -> 101.57 | R2: =INDEX('ИПЦ raw'!AC:AC, MATCH(Структура!$D2,'ИПЦ raw'!$A:$A,0)) -> 102.06 | S2: =INDEX('ИПЦ raw'!AD:AD, MATCH(Структура!$D2,'ИПЦ raw'!$A:$A,0)) -> 101.45 | T2: =INDEX('ИПЦ raw'!AE:AE, MATCH(Структура!$D2,'ИПЦ raw'!$A:$A,0)) -> 100.69 | U2: =INDEX('ИПЦ raw'!AF:AF, MATCH(Структура!$D2,'ИПЦ raw'!$A:$A,0)) -> 100.66 | V2: =INDEX('ИПЦ raw'!AG:AG, MATCH(Структура!$D2,'ИПЦ raw'!$A:$A,0)) -> 100.5 | W2: =INDEX('ИПЦ raw'!AH:AH, MATCH(Структура!$D2,'ИПЦ raw'!$A:$A,0)) -> 100.54 | X2: =INDEX('ИПЦ raw'!AI:AI, MATCH(Структура!$D2,'ИПЦ raw'!$A:$A,0)) -> 101.34 | Y2: =INDEX('ИПЦ raw'!AJ:AJ, MATCH(Структура!$D2,'ИПЦ raw'!$A:$A,0)) -> 100.79 | Z2: =INDEX('ИПЦ raw'!AK:AK, MATCH(Структура!$D2,'ИПЦ raw'!$A:$A,0)) -> 100.64 | AA2: =INDEX('ИПЦ raw'!AL:AL, MATCH(Структура!$D2,'ИПЦ raw'!$A:$A,0)) -> 100.96 | AB2: =INDEX('ИПЦ raw'!AM:AM, MATCH(Структура!$D2,'ИПЦ raw'!$A:$A,0)) -> 102.13 | AC2: =INDEX('ИПЦ raw'!AN:AN, MATCH(Структура!$D2,'ИПЦ raw'!$A:$A,0)) -> 101.9 | AD2: =INDEX('ИПЦ raw'!AO:AO, MATCH(Структура!$D2,'ИПЦ raw'!$A:$A,0)) -> 102.33 | AE2: =INDEX('ИПЦ raw'!AP:AP, MATCH(Структура!$D2,'ИПЦ raw'!$A:$A,0)) -> 100.91 | AG2: =INDEX('2025'!$C:$C,MATCH(Структура!C2,'2025'!$B:$B,0)) -> 0.627 | AH2: =AG2*P2/100 -> 0.6380979 | AI2: =AH2*Q2/100 -> 0.64811604 | AJ2: =AI2*R2/100 -> 0.66146723 | AK2: =AJ2*S2/100 -> 0.6710585 | AL2: =AK2*T2/100 -> 0.67568881 | AM2: =AL2*U2/100 -> 0.68014835 | AN2: =AM2*V2/100 -> 0.68354909 | AO2: =AN2*W2/100 -> 0.68724026 | ... AR2: =AQ2*Z2/100 -> 0.70644372 | AS2: =J2 -> 0.638 | AT2: =AS2*AB2/100 -> 0.6515894 | AU2: =AT2*AC2/100 -> 0.6639696 | AV2: =AU2*AD2/100 -> 0.67944009 | AW2: =AV2*AE2/100 -> 0.685623
A3: Говядина бескостная, кг | B3: =A3 -> Говядина бескостная, кг | C3: =A3 -> Говядина бескостная, кг | D3: =C3 -> Говядина бескостная, кг | E3: =INDEX(БИПЦ_НДС!$D:$D,MATCH(Структура!A3,БИПЦ_НДС!$B:$B,0)) -> 10 | F3: Проды | G3: 1 | H3: 1 | I3: 0 | J3: =INDEX('2026'!$C:$C,MATCH(Структура!B3,'2026'!$B:$B,0)) -> 0.429 | K3: =INDEX('2025'!$C:$C,MATCH(Структура!C3,'2025'!$B:$B,0)) -> 0.396 | L3: 1 | M3: 1 | N3: =INDEX(MoM!B:B,MATCH(Структура!A3,MoM!J:J,0)) -> 1 | P3: =INDEX('ИПЦ raw'!AA:AA, MATCH(Структура!$D3,'ИПЦ raw'!$A:$A,0)) -> 101.49 | Q3: =INDEX('ИПЦ raw'!AB:AB, MATCH(Структура!$D3,'ИПЦ raw'!$A:$A,0)) -> 101.77 | R3: =INDEX('ИПЦ raw'!AC:AC, MATCH(Структура!$D3,'ИПЦ raw'!$A:$A,0)) -> 101.99 | S3: =INDEX('ИПЦ raw'!AD:AD, MATCH(Структура!$D3,'ИПЦ raw'!$A:$A,0)) -> 101.01 | T3: =INDEX('ИПЦ raw'!AE:AE, MATCH(Структура!$D3,'ИПЦ raw'!$A:$A,0)) -> 101.27 | U3: =INDEX('ИПЦ raw'!AF:AF, MATCH(Структура!$D3,'ИПЦ raw'!$A:$A,0)) -> 100.66 | V3: =INDEX('ИПЦ raw'!AG:AG, MATCH(Структура!$D3,'ИПЦ raw'!$A:$A,0)) -> 100.54 | W3: =INDEX('ИПЦ raw'!AH:AH, MATCH(Структура!$D3,'ИПЦ raw'!$A:$A,0)) -> 100.45 | X3: =INDEX('ИПЦ raw'!AI:AI, MATCH(Структура!$D3,'ИПЦ raw'!$A:$A,0)) -> 100.76 | Y3: =INDEX('ИПЦ raw'!AJ:AJ, MATCH(Структура!$D3,'ИПЦ raw'!$A:$A,0)) -> 100.53 | Z3: =INDEX('ИПЦ raw'!AK:AK, MATCH(Структура!$D3,'ИПЦ raw'!$A:$A,0)) -> 100.37 | AA3: =INDEX('ИПЦ raw'!AL:AL, MATCH(Структура!$D3,'ИПЦ raw'!$A:$A,0)) -> 100.72 | AB3: =INDEX('ИПЦ raw'!AM:AM, MATCH(Структура!$D3,'ИПЦ raw'!$A:$A,0)) -> 101.47 | AC3: =INDEX('ИПЦ raw'!AN:AN, MATCH(Структура!$D3,'ИПЦ raw'!$A:$A,0)) -> 101.56 | AD3: =INDEX('ИПЦ raw'!AO:AO, MATCH(Структура!$D3,'ИПЦ raw'!$A:$A,0)) -> 101.05 | AE3: =INDEX('ИПЦ raw'!AP:AP, MATCH(Структура!$D3,'ИПЦ raw'!$A:$A,0)) -> 101.05 | AG3: =INDEX('2025'!$C:$C,MATCH(Структура!C3,'2025'!$B:$B,0)) -> 0.396 | AH3: =AG3*P3/100 -> 0.4019004 | AI3: =AH3*Q3/100 -> 0.40901404 | AJ3: =AI3*R3/100 -> 0.41715342 | AK3: =AJ3*S3/100 -> 0.42136667 | AL3: =AK3*T3/100 -> 0.42671802 | AM3: =AL3*U3/100 -> 0.42953436 | AN3: =AM3*V3/100 -> 0.43185385 | AO3: =AN3*W3/100 -> 0.43379719 | ... AR3: =AQ3*Z3/100 -> 0.44103647 | AS3: =J3 -> 0.429 | AT3: =AS3*AB3/100 -> 0.4353063 | AU3: =AT3*AC3/100 -> 0.44209708 | AV3: =AU3*AD3/100 -> 0.4467391 | AW3: =AV3*AE3/100 -> 0.45142986
A4: Свинина (кроме бескостного мяса), кг | B4: =A4 -> Свинина (кроме бескостного мяса), кг | C4: =A4 -> Свинина (кроме бескостного мяса), кг | D4: =C4 -> Свинина (кроме бескостного мяса), кг | E4: =INDEX(БИПЦ_НДС!$D:$D,MATCH(Структура!A4,БИПЦ_НДС!$B:$B,0)) -> 10 | F4: Проды | G4: 1 | H4: 1 | I4: 0 | J4: =INDEX('2026'!$C:$C,MATCH(Структура!B4,'2026'!$B:$B,0)) -> 0.684 | K4: =INDEX('2025'!$C:$C,MATCH(Структура!C4,'2025'!$B:$B,0)) -> 0.726 | L4: 1 | M4: 1 | N4: =INDEX(MoM!B:B,MATCH(Структура!A4,MoM!J:J,0)) -> 1 | P4: =INDEX('ИПЦ raw'!AA:AA, MATCH(Структура!$D4,'ИПЦ raw'!$A:$A,0)) -> 101 | Q4: =INDEX('ИПЦ raw'!AB:AB, MATCH(Структура!$D4,'ИПЦ raw'!$A:$A,0)) -> 100.06 | R4: =INDEX('ИПЦ raw'!AC:AC, MATCH(Структура!$D4,'ИПЦ raw'!$A:$A,0)) -> 100.5 | S4: =INDEX('ИПЦ raw'!AD:AD, MATCH(Структура!$D4,'ИПЦ raw'!$A:$A,0)) -> 101.27 | T4: =INDEX('ИПЦ raw'!AE:AE, MATCH(Структура!$D4,'ИПЦ raw'!$A:$A,0)) -> 101.63 | U4: =INDEX('ИПЦ raw'!AF:AF, MATCH(Структура!$D4,'ИПЦ raw'!$A:$A,0)) -> 100.52 | V4: =INDEX('ИПЦ raw'!AG:AG, MATCH(Структура!$D4,'ИПЦ raw'!$A:$A,0)) -> 101.27 | W4: =INDEX('ИПЦ raw'!AH:AH, MATCH(Структура!$D4,'ИПЦ raw'!$A:$A,0)) -> 101.77 | X4: =INDEX('ИПЦ raw'!AI:AI, MATCH(Структура!$D4,'ИПЦ raw'!$A:$A,0)) -> 100.95 | Y4: =INDEX('ИПЦ raw'!AJ:AJ, MATCH(Структура!$D4,'ИПЦ raw'!$A:$A,0)) -> 100.28 | Z4: =INDEX('ИПЦ raw'!AK:AK, MATCH(Структура!$D4,'ИПЦ raw'!$A:$A,0)) -> 99.93 | AA4: =INDEX('ИПЦ raw'!AL:AL, MATCH(Структура!$D4,'ИПЦ raw'!$A:$A,0)) -> 98.96 | AB4: =INDEX('ИПЦ raw'!AM:AM, MATCH(Структура!$D4,'ИПЦ raw'!$A:$A,0)) -> 100.72 | AC4: =INDEX('ИПЦ raw'!AN:AN, MATCH(Структура!$D4,'ИПЦ raw'!$A:$A,0)) -> 98.67 | AD4: =INDEX('ИПЦ raw'!AO:AO, MATCH(Структура!$D4,'ИПЦ raw'!$A:$A,0)) -> 100.15 | AE4: =INDEX('ИПЦ raw'!AP:AP, MATCH(Структура!$D4,'ИПЦ raw'!$A:$A,0)) -> 100.89 | AG4: =INDEX('2025'!$C:$C,MATCH(Структура!C4,'2025'!$B:$B,0)) -> 0.726 | AH4: =AG4*P4/100 -> 0.73326 | AI4: =AH4*Q4/100 -> 0.73369996 | AJ4: =AI4*R4/100 -> 0.73736846 | AK4: =AJ4*S4/100 -> 0.74673304 | AL4: =AK4*T4/100 -> 0.75890478 | AM4: =AL4*U4/100 -> 0.76285109 | AN4: =AM4*V4/100 -> 0.7725393 | AO4: =AN4*W4/100 -> 0.78621324 | ... AR4: =AQ4*Z4/100 -> 0.79534745 | AS4: =J4 -> 0.684 | AT4: =AS4*AB4/100 -> 0.6889248 | AU4: =AT4*AC4/100 -> 0.6797621 | AV4: =AU4*AD4/100 -> 0.68078174 | AW4: =AV4*AE4/100 -> 0.6868407
A5: Свинина бескостная, кг | B5: =A5 -> Свинина бескостная, кг | C5: =A5 -> Свинина бескостная, кг | D5: =C5 -> Свинина бескостная, кг | E5: =INDEX(БИПЦ_НДС!$D:$D,MATCH(Структура!A5,БИПЦ_НДС!$B:$B,0)) -> 10 | F5: Проды | G5: 1 | H5: 1 | I5: 0 | J5: =INDEX('2026'!$C:$C,MATCH(Структура!B5,'2026'!$B:$B,0)) -> 0.713 | K5: =INDEX('2025'!$C:$C,MATCH(Структура!C5,'2025'!$B:$B,0)) -> 0.714 | L5: 1 | M5: 1 | N5: =INDEX(MoM!B:B,MATCH(Структура!A5,MoM!J:J,0)) -> 1 | P5: =INDEX('ИПЦ raw'!AA:AA, MATCH(Структура!$D5,'ИПЦ raw'!$A:$A,0)) -> 100.25 | Q5: =INDEX('ИПЦ raw'!AB:AB, MATCH(Структура!$D5,'ИПЦ raw'!$A:$A,0)) -> 99.66 | R5: =INDEX('ИПЦ raw'!AC:AC, MATCH(Структура!$D5,'ИПЦ raw'!$A:$A,0)) -> 100.2 | S5: =INDEX('ИПЦ raw'!AD:AD, MATCH(Структура!$D5,'ИПЦ raw'!$A:$A,0)) -> 100.99 | T5: =INDEX('ИПЦ raw'!AE:AE, MATCH(Структура!$D5,'ИПЦ raw'!$A:$A,0)) -> 102.09 | U5: =INDEX('ИПЦ raw'!AF:AF, MATCH(Структура!$D5,'ИПЦ raw'!$A:$A,0)) -> 100.29 | V5: =INDEX('ИПЦ raw'!AG:AG, MATCH(Структура!$D5,'ИПЦ raw'!$A:$A,0)) -> 101.45 | W5: =INDEX('ИПЦ raw'!AH:AH, MATCH(Структура!$D5,'ИПЦ raw'!$A:$A,0)) -> 102.15 | X5: =INDEX('ИПЦ raw'!AI:AI, MATCH(Структура!$D5,'ИПЦ raw'!$A:$A,0)) -> 100.99 | Y5: =INDEX('ИПЦ raw'!AJ:AJ, MATCH(Структура!$D5,'ИПЦ raw'!$A:$A,0)) -> 100.11 | Z5: =INDEX('ИПЦ raw'!AK:AK, MATCH(Структура!$D5,'ИПЦ raw'!$A:$A,0)) -> 99.53 | AA5: =INDEX('ИПЦ raw'!AL:AL, MATCH(Структура!$D5,'ИПЦ raw'!$A:$A,0)) -> 98.75 | AB5: =INDEX('ИПЦ raw'!AM:AM, MATCH(Структура!$D5,'ИПЦ raw'!$A:$A,0)) -> 100.32 | AC5: =INDEX('ИПЦ raw'!AN:AN, MATCH(Структура!$D5,'ИПЦ raw'!$A:$A,0)) -> 98.17 | AD5: =INDEX('ИПЦ raw'!AO:AO, MATCH(Структура!$D5,'ИПЦ raw'!$A:$A,0)) -> 99.28 | AE5: =INDEX('ИПЦ raw'!AP:AP, MATCH(Структура!$D5,'ИПЦ raw'!$A:$A,0)) -> 100.18 | AG5: =INDEX('2025'!$C:$C,MATCH(Структура!C5,'2025'!$B:$B,0)) -> 0.714 | AH5: =AG5*P5/100 -> 0.715785 | AI5: =AH5*Q5/100 -> 0.71335133 | AJ5: =AI5*R5/100 -> 0.71477803 | AK5: =AJ5*S5/100 -> 0.72185434 | AL5: =AK5*T5/100 -> 0.73694109 | AM5: =AL5*U5/100 -> 0.73907822 | AN5: =AM5*V5/100 -> 0.74979486 | AO5: =AN5*W5/100 -> 0.76591544 | ... AR5: =AQ5*Z5/100 -> 0.77070942 | AS5: =J5 -> 0.713 | AT5: =AS5*AB5/100 -> 0.7152816 | AU5: =AT5*AC5/100 -> 0.70219195 | AV5: =AU5*AD5/100 -> 0.69713616 | AW5: =AV5*AE5/100 -> 0.69839101
A6: Баранина (кроме бескостного мяса), кг | B6: =A6 -> Баранина (кроме бескостного мяса), кг | C6: =A6 -> Баранина (кроме бескостного мяса), кг | D6: =C6 -> Баранина (кроме бескостного мяса), кг | E6: =INDEX(БИПЦ_НДС!$D:$D,MATCH(Структура!A6,БИПЦ_НДС!$B:$B,0)) -> 10 | F6: Проды | G6: 1 | H6: 1 | I6: 0 | J6: =INDEX('2026'!$C:$C,MATCH(Структура!B6,'2026'!$B:$B,0)) -> 0.148 | K6: =INDEX('2025'!$C:$C,MATCH(Структура!C6,'2025'!$B:$B,0)) -> 0.145 | L6: 1 | M6: 1 | N6: =INDEX(MoM!B:B,MATCH(Структура!A6,MoM!J:J,0)) -> 1 | P6: =INDEX('ИПЦ raw'!AA:AA, MATCH(Структура!$D6,'ИПЦ raw'!$A:$A,0)) -> 100.21 | Q6: =INDEX('ИПЦ raw'!AB:AB, MATCH(Структура!$D6,'ИПЦ raw'!$A:$A,0)) -> 100.84 | R6: =INDEX('ИПЦ raw'!AC:AC, MATCH(Структура!$D6,'ИПЦ raw'!$A:$A,0)) -> 100.38 | S6: =INDEX('ИПЦ raw'!AD:AD, MATCH(Структура!$D6,'ИПЦ raw'!$A:$A,0)) -> 98.69 | T6: =INDEX('ИПЦ raw'!AE:AE, MATCH(Структура!$D6,'ИПЦ raw'!$A:$A,0)) -> 100.74 | U6: =INDEX('ИПЦ raw'!AF:AF, MATCH(Структура!$D6,'ИПЦ raw'!$A:$A,0)) -> 99.66 | V6: =INDEX('ИПЦ raw'!AG:AG, MATCH(Структура!$D6,'ИПЦ raw'!$A:$A,0)) -> 99.93 | W6: =INDEX('ИПЦ raw'!AH:AH, MATCH(Структура!$D6,'ИПЦ raw'!$A:$A,0)) -> 100.45 | X6: =INDEX('ИПЦ raw'!AI:AI, MATCH(Структура!$D6,'ИПЦ raw'!$A:$A,0)) -> 99.72 | Y6: =INDEX('ИПЦ raw'!AJ:AJ, MATCH(Структура!$D6,'ИПЦ raw'!$A:$A,0)) -> 100.01 | Z6: =INDEX('ИПЦ raw'!AK:AK, MATCH(Структура!$D6,'ИПЦ raw'!$A:$A,0)) -> 98.54 | AA6: =INDEX('ИПЦ raw'!AL:AL, MATCH(Структура!$D6,'ИПЦ raw'!$A:$A,0)) -> 100.32 | AB6: =INDEX('ИПЦ raw'!AM:AM, MATCH(Структура!$D6,'ИПЦ raw'!$A:$A,0)) -> 100.44 | AC6: =INDEX('ИПЦ raw'!AN:AN, MATCH(Структура!$D6,'ИПЦ raw'!$A:$A,0)) -> 102.05 | AD6: =INDEX('ИПЦ raw'!AO:AO, MATCH(Структура!$D6,'ИПЦ raw'!$A:$A,0)) -> 100.69 | AE6: =INDEX('ИПЦ raw'!AP:AP, MATCH(Структура!$D6,'ИПЦ raw'!$A:$A,0)) -> 100.69 | AG6: =INDEX('2025'!$C:$C,MATCH(Структура!C6,'2025'!$B:$B,0)) -> 0.145 | AH6: =AG6*P6/100 -> 0.1453045 | AI6: =AH6*Q6/100 -> 0.14652506 | AJ6: =AI6*R6/100 -> 0.14708185 | AK6: =AJ6*S6/100 -> 0.14515508 | AL6: =AK6*T6/100 -> 0.14622923 | AM6: =AL6*U6/100 -> 0.14573205 | AN6: =AM6*V6/100 -> 0.14563004 | AO6: =AN6*W6/100 -> 0.14628537 | ... AR6: =AQ6*Z6/100 -> 0.14376036 | AS6: =J6 -> 0.148 | AT6: =AS6*AB6/100 -> 0.1486512 | AU6: =AT6*AC6/100 -> 0.15169855 | AV6: =AU6*AD6/100 -> 0.15274527 | AW6: =AV6*AE6/100 -> 0.15379921
A7: Куры охлажденные и мороженые, кг | B7: =A7 -> Куры охлажденные и мороженые, кг | C7: =A7 -> Куры охлажденные и мороженые, кг | D7: =C7 -> Куры охлажденные и мороженые, кг | E7: =INDEX(БИПЦ_НДС!$D:$D,MATCH(Структура!A7,БИПЦ_НДС!$B:$B,0)) -> 10 | F7: Проды | G7: 1 | H7: 1 | I7: 0 | J7: =INDEX('2026'!$C:$C,MATCH(Структура!B7,'2026'!$B:$B,0)) -> 0.925 | K7: =INDEX('2025'!$C:$C,MATCH(Структура!C7,'2025'!$B:$B,0)) -> 0.965 | L7: 1 | M7: 1 | N7: =INDEX(MoM!B:B,MATCH(Структура!A7,MoM!J:J,0)) -> 1 | P7: =INDEX('ИПЦ raw'!AA:AA, MATCH(Структура!$D7,'ИПЦ raw'!$A:$A,0)) -> 100.7 | Q7: =INDEX('ИПЦ raw'!AB:AB, MATCH(Структура!$D7,'ИПЦ raw'!$A:$A,0)) -> 98.97 | R7: =INDEX('ИПЦ raw'!AC:AC, MATCH(Структура!$D7,'ИПЦ raw'!$A:$A,0)) -> 98.35 | S7: =INDEX('ИПЦ raw'!AD:AD, MATCH(Структура!$D7,'ИПЦ raw'!$A:$A,0)) -> 97.99 | T7: =INDEX('ИПЦ raw'!AE:AE, MATCH(Структура!$D7,'ИПЦ raw'!$A:$A,0)) -> 103.95 | U7: =INDEX('ИПЦ raw'!AF:AF, MATCH(Структура!$D7,'ИПЦ raw'!$A:$A,0)) -> 101.26 | V7: =INDEX('ИПЦ raw'!AG:AG, MATCH(Структура!$D7,'ИПЦ raw'!$A:$A,0)) -> 100.13 | W7: =INDEX('ИПЦ raw'!AH:AH, MATCH(Структура!$D7,'ИПЦ raw'!$A:$A,0)) -> 100.05 | X7: =INDEX('ИПЦ raw'!AI:AI, MATCH(Структура!$D7,'ИПЦ raw'!$A:$A,0)) -> 101.56 | Y7: =INDEX('ИПЦ raw'!AJ:AJ, MATCH(Структура!$D7,'ИПЦ raw'!$A:$A,0)) -> 102.34 | Z7: =INDEX('ИПЦ raw'!AK:AK, MATCH(Структура!$D7,'ИПЦ raw'!$A:$A,0)) -> 99.77 | AA7: =INDEX('ИПЦ raw'!AL:AL, MATCH(Структура!$D7,'ИПЦ raw'!$A:$A,0)) -> 100.22 | AB7: =INDEX('ИПЦ raw'!AM:AM, MATCH(Структура!$D7,'ИПЦ raw'!$A:$A,0)) -> 99.87 | AC7: =INDEX('ИПЦ raw'!AN:AN, MATCH(Структура!$D7,'ИПЦ raw'!$A:$A,0)) -> 98.97 | AD7: =INDEX('ИПЦ raw'!AO:AO, MATCH(Структура!$D7,'ИПЦ raw'!$A:$A,0)) -> 98 | AE7: =INDEX('ИПЦ raw'!AP:AP, MATCH(Структура!$D7,'ИПЦ raw'!$A:$A,0)) -> 99.89 | AG7: =INDEX('2025'!$C:$C,MATCH(Структура!C7,'2025'!$B:$B,0)) -> 0.965 | AH7: =AG7*P7/100 -> 0.971755 | AI7: =AH7*Q7/100 -> 0.96174592 | AJ7: =AI7*R7/100 -> 0.94587712 | AK7: =AJ7*S7/100 -> 0.92686499 | AL7: =AK7*T7/100 -> 0.96347615 | AM7: =AL7*U7/100 -> 0.97561595 | AN7: =AM7*V7/100 -> 0.97688425 | AO7: =AN7*W7/100 -> 0.9773727 | ... AR7: =AQ7*Z7/100 -> 1.0135106 | AS7: =J7 -> 0.925 | AT7: =AS7*AB7/100 -> 0.9237975 | AU7: =AT7*AC7/100 -> 0.91428239 | AV7: =AU7*AD7/100 -> 0.89599674 | AW7: =AV7*AE7/100 -> 0.89501114
A8: Окорочка куриные, кг | B8: =A8 -> Окорочка куриные, кг | C8: =A8 -> Окорочка куриные, кг | D8: =C8 -> Окорочка куриные, кг | E8: =INDEX(БИПЦ_НДС!$D:$D,MATCH(Структура!A8,БИПЦ_НДС!$B:$B,0)) -> 10 | F8: Проды | G8: 1 | H8: 1 | I8: 0 | J8: =INDEX('2026'!$C:$C,MATCH(Структура!B8,'2026'!$B:$B,0)) -> 0.44 | K8: =INDEX('2025'!$C:$C,MATCH(Структура!C8,'2025'!$B:$B,0)) -> 0.474 | L8: 1 | M8: 1 | N8: =INDEX(MoM!B:B,MATCH(Структура!A8,MoM!J:J,0)) -> 1 | P8: =INDEX('ИПЦ raw'!AA:AA, MATCH(Структура!$D8,'ИПЦ raw'!$A:$A,0)) -> 100.75 | Q8: =INDEX('ИПЦ raw'!AB:AB, MATCH(Структура!$D8,'ИПЦ raw'!$A:$A,0)) -> 100.16 | R8: =INDEX('ИПЦ raw'!AC:AC, MATCH(Структура!$D8,'ИПЦ raw'!$A:$A,0)) -> 99.89 | S8: =INDEX('ИПЦ raw'!AD:AD, MATCH(Структура!$D8,'ИПЦ raw'!$A:$A,0)) -> 99.54 | T8: =INDEX('ИПЦ raw'!AE:AE, MATCH(Структура!$D8,'ИПЦ raw'!$A:$A,0)) -> 101.37 | U8: =INDEX('ИПЦ raw'!AF:AF, MATCH(Структура!$D8,'ИПЦ raw'!$A:$A,0)) -> 100.45 | V8: =INDEX('ИПЦ raw'!AG:AG, MATCH(Структура!$D8,'ИПЦ raw'!$A:$A,0)) -> 100.45 | W8: =INDEX('ИПЦ raw'!AH:AH, MATCH(Структура!$D8,'ИПЦ raw'!$A:$A,0)) -> 100.52 | X8: =INDEX('ИПЦ raw'!AI:AI, MATCH(Структура!$D8,'ИПЦ raw'!$A:$A,0)) -> 100.68 | Y8: =INDEX('ИПЦ raw'!AJ:AJ, MATCH(Структура!$D8,'ИПЦ raw'!$A:$A,0)) -> 101.39 | Z8: =INDEX('ИПЦ raw'!AK:AK, MATCH(Структура!$D8,'ИПЦ raw'!$A:$A,0)) -> 99.92 | AA8: =INDEX('ИПЦ raw'!AL:AL, MATCH(Структура!$D8,'ИПЦ raw'!$A:$A,0)) -> 100.44 | AB8: =INDEX('ИПЦ raw'!AM:AM, MATCH(Структура!$D8,'ИПЦ raw'!$A:$A,0)) -> 99.94 | AC8: =INDEX('ИПЦ raw'!AN:AN, MATCH(Структура!$D8,'ИПЦ raw'!$A:$A,0)) -> 99.2 | AD8: =INDEX('ИПЦ raw'!AO:AO, MATCH(Структура!$D8,'ИПЦ raw'!$A:$A,0)) -> 99.47 | AE8: =INDEX('ИПЦ raw'!AP:AP, MATCH(Структура!$D8,'ИПЦ raw'!$A:$A,0)) -> 100.53 | AG8: =INDEX('2025'!$C:$C,MATCH(Структура!C8,'2025'!$B:$B,0)) -> 0.474 | AH8: =AG8*P8/100 -> 0.477555 | AI8: =AH8*Q8/100 -> 0.47831909 | AJ8: =AI8*R8/100 -> 0.47779294 | AK8: =AJ8*S8/100 -> 0.47559509 | AL8: =AK8*T8/100 -> 0.48211074 | AM8: =AL8*U8/100 -> 0.48428024 | AN8: =AM8*V8/100 -> 0.4864595 | AO8: =AN8*W8/100 -> 0.48898909 | ... AR8: =AQ8*Z8/100 -> 0.49875806 | AS8: =J8 -> 0.44 | AT8: =AS8*AB8/100 -> 0.439736 | AU8: =AT8*AC8/100 -> 0.43621811 | AV8: =AU8*AD8/100 -> 0.43390616 | AW8: =AV8*AE8/100 -> 0.43620586
A9: Мясо индейки, кг | B9: =A9 -> Мясо индейки, кг | C9: =A9 -> Мясо индейки, кг | D9: Мясо индейки, кг | E9: =INDEX(БИПЦ_НДС!$D:$D,MATCH(Структура!A9,БИПЦ_НДС!$B:$B,0)) -> 10 | F9: Проды | G9: 1 | H9: 1 | I9: 0 | J9: =INDEX('2026'!$C:$C,MATCH(Структура!B9,'2026'!$B:$B,0)) -> 0.235 | K9: =INDEX('2025'!$C:$C,MATCH(Структура!C9,'2025'!$B:$B,0)) -> 0.268 | L9: 1 | M9: 1 | N9: =INDEX(MoM!B:B,MATCH(Структура!A9,MoM!J:J,0)) -> 1 | P9: =INDEX('ИПЦ raw'!AA:AA, MATCH(Структура!$D9,'ИПЦ raw'!$A:$A,0)) -> 101.5 | Q9: =INDEX('ИПЦ raw'!AB:AB, MATCH(Структура!$D9,'ИПЦ raw'!$A:$A,0)) -> 100.62 | R9: =INDEX('ИПЦ raw'!AC:AC, MATCH(Структура!$D9,'ИПЦ raw'!$A:$A,0)) -> 99.8 | S9: =INDEX('ИПЦ raw'!AD:AD, MATCH(Структура!$D9,'ИПЦ raw'!$A:$A,0)) -> 99.79 | T9: =INDEX('ИПЦ raw'!AE:AE, MATCH(Структура!$D9,'ИПЦ raw'!$A:$A,0)) -> 99.13 | U9: =INDEX('ИПЦ raw'!AF:AF, MATCH(Структура!$D9,'ИПЦ raw'!$A:$A,0)) -> 99.06 | V9: =INDEX('ИПЦ raw'!AG:AG, MATCH(Структура!$D9,'ИПЦ raw'!$A:$A,0)) -> 99.48 | W9: =INDEX('ИПЦ raw'!AH:AH, MATCH(Структура!$D9,'ИПЦ raw'!$A:$A,0)) -> 99.69 | X9: =INDEX('ИПЦ raw'!AI:AI, MATCH(Структура!$D9,'ИПЦ raw'!$A:$A,0)) -> 99.58 | Y9: =INDEX('ИПЦ raw'!AJ:AJ, MATCH(Структура!$D9,'ИПЦ raw'!$A:$A,0)) -> 101.38 | Z9: =INDEX('ИПЦ raw'!AK:AK, MATCH(Структура!$D9,'ИПЦ raw'!$A:$A,0)) -> 102.75 | AA9: =INDEX('ИПЦ raw'!AL:AL, MATCH(Структура!$D9,'ИПЦ raw'!$A:$A,0)) -> 101.54 | AB9: =INDEX('ИПЦ raw'!AM:AM, MATCH(Структура!$D9,'ИПЦ raw'!$A:$A,0)) -> 101.2 | AC9: =INDEX('ИПЦ raw'!AN:AN, MATCH(Структура!$D9,'ИПЦ raw'!$A:$A,0)) -> 100.47 | AD9: =INDEX('ИПЦ raw'!AO:AO, MATCH(Структура!$D9,'ИПЦ raw'!$A:$A,0)) -> 100.72 | AE9: =INDEX('ИПЦ raw'!AP:AP, MATCH(Структура!$D9,'ИПЦ raw'!$A:$A,0)) -> 100.69 | AG9: =INDEX('2025'!$C:$C,MATCH(Структура!C9,'2025'!$B:$B,0)) -> 0.268 | AH9: =AG9*P9/100 -> 0.27202 | AI9: =AH9*Q9/100 -> 0.27370652 | AJ9: =AI9*R9/100 -> 0.27315911 | AK9: =AJ9*S9/100 -> 0.27258548 | AL9: =AK9*T9/100 -> 0.27021398 | AM9: =AL9*U9/100 -> 0.26767397 | AN9: =AM9*V9/100 -> 0.26628207 | AO9: =AN9*W9/100 -> 0.26545659 | ... AR9: =AQ9*Z9/100 -> 0.2753593 | AS9: =J9 -> 0.235 | AT9: =AS9*AB9/100 -> 0.23782 | AU9: =AT9*AC9/100 -> 0.23893775 | AV9: =AU9*AD9/100 -> 0.24065811 | AW9: =AV9*AE9/100 -> 0.24231865
A10: Печень говяжья, свиная, кг | B10: =A10 -> Печень говяжья, свиная, кг | C10: =A10 -> Печень говяжья, свиная, кг | D10: =C10 -> Печень говяжья, свиная, кг | E10: =INDEX(БИПЦ_НДС!$D:$D,MATCH(Структура!A10,БИПЦ_НДС!$B:$B,0)) -> 10 | F10: Проды | G10: 1 | H10: 1 | I10: 0 | J10: =INDEX('2026'!$C:$C,MATCH(Структура!B10,'2026'!$B:$B,0)) -> 0.151 | K10: =INDEX('2025'!$C:$C,MATCH(Структура!C10,'2025'!$B:$B,0)) -> 0.168 | L10: 1 | M10: 1 | N10: =INDEX(MoM!B:B,MATCH(Структура!A10,MoM!J:J,0)) -> 1 | P10: =INDEX('ИПЦ raw'!AA:AA, MATCH(Структура!$D10,'ИПЦ raw'!$A:$A,0)) -> 100.28 | Q10: =INDEX('ИПЦ raw'!AB:AB, MATCH(Структура!$D10,'ИПЦ raw'!$A:$A,0)) -> 100.32 | R10: =INDEX('ИПЦ raw'!AC:AC, MATCH(Структура!$D10,'ИПЦ raw'!$A:$A,0)) -> 100.86 | S10: =INDEX('ИПЦ raw'!AD:AD, MATCH(Структура!$D10,'ИПЦ raw'!$A:$A,0)) -> 100.79 | T10: =INDEX('ИПЦ raw'!AE:AE, MATCH(Структура!$D10,'ИПЦ raw'!$A:$A,0)) -> 100.78 | U10: =INDEX('ИПЦ raw'!AF:AF, MATCH(Структура!$D10,'ИПЦ raw'!$A:$A,0)) -> 100.6 | V10: =INDEX('ИПЦ raw'!AG:AG, MATCH(Структура!$D10,'ИПЦ raw'!$A:$A,0)) -> 101.08 | W10: =INDEX('ИПЦ raw'!AH:AH, MATCH(Структура!$D10,'ИПЦ raw'!$A:$A,0)) -> 101.24 | X10: =INDEX('ИПЦ raw'!AI:AI, MATCH(Структура!$D10,'ИПЦ raw'!$A:$A,0)) -> 101.65 | Y10: =INDEX('ИПЦ raw'!AJ:AJ, MATCH(Структура!$D10,'ИПЦ raw'!$A:$A,0)) -> 101.33 | Z10: =INDEX('ИПЦ raw'!AK:AK, MATCH(Структура!$D10,'ИПЦ raw'!$A:$A,0)) -> 101.5 | AA10: =INDEX('ИПЦ raw'!AL:AL, MATCH(Структура!$D10,'ИПЦ raw'!$A:$A,0)) -> 101.99 | AB10: =INDEX('ИПЦ raw'!AM:AM, MATCH(Структура!$D10,'ИПЦ raw'!$A:$A,0)) -> 101.29 | AC10: =INDEX('ИПЦ raw'!AN:AN, MATCH(Структура!$D10,'ИПЦ raw'!$A:$A,0)) -> 101.75 | AD10: =INDEX('ИПЦ raw'!AO:AO, MATCH(Структура!$D10,'ИПЦ raw'!$A:$A,0)) -> 100.77 | AE10: =INDEX('ИПЦ raw'!AP:AP, MATCH(Структура!$D10,'ИПЦ raw'!$A:$A,0)) -> 101.16 | AG10: =INDEX('2025'!$C:$C,MATCH(Структура!C10,'2025'!$B:$B,0)) -> 0.168 | AH10: =AG10*P10/100 -> 0.1684704 | AI10: =AH10*Q10/100 -> 0.16900951 | AJ10: =AI10*R10/100 -> 0.17046299 | AK10: =AJ10*S10/100 -> 0.17180964 | AL10: =AK10*T10/100 -> 0.17314976 | AM10: =AL10*U10/100 -> 0.17418866 | AN10: =AM10*V10/100 -> 0.1760699 | AO10: =AN10*W10/100 -> 0.17825316 | ... AR10: =AQ10*Z10/100 -> 0.18635829 | AS10: =J10 -> 0.151 | AT10: =AS10*AB10/100 -> 0.1529479 | AU10: =AT10*AC10/100 -> 0.15562449 | AV10: =AU10*AD10/100 -> 0.1568228 | AW10: =AV10*AE10/100 -> 0.15864194
A11: Фарш мясной, кг | B11: =A11 -> Фарш мясной, кг | C11: =A11 -> Фарш мясной, кг | D11: =C11 -> Фарш мясной, кг | E11: =INDEX(БИПЦ_НДС!$D:$D,MATCH(Структура!A11,БИПЦ_НДС!$B:$B,0)) -> 10 | F11: Проды | G11: 1 | H11: 1 | I11: 0 | J11: =INDEX('2026'!$C:$C,MATCH(Структура!B11,'2026'!$B:$B,0)) -> 0.892 | K11: =INDEX('2025'!$C:$C,MATCH(Структура!C11,'2025'!$B:$B,0)) -> 0.88 | L11: 1 | M11: 1 | N11: =INDEX(MoM!B:B,MATCH(Структура!A11,MoM!J:J,0)) -> 1 | P11: =INDEX('ИПЦ raw'!AA:AA, MATCH(Структура!$D11,'ИПЦ raw'!$A:$A,0)) -> 101.09 | Q11: =INDEX('ИПЦ raw'!AB:AB, MATCH(Структура!$D11,'ИПЦ raw'!$A:$A,0)) -> 101.09 | R11: =INDEX('ИПЦ raw'!AC:AC, MATCH(Структура!$D11,'ИПЦ raw'!$A:$A,0)) -> 100.81 | S11: =INDEX('ИПЦ raw'!AD:AD, MATCH(Структура!$D11,'ИПЦ raw'!$A:$A,0)) -> 101.25 | T11: =INDEX('ИПЦ raw'!AE:AE, MATCH(Структура!$D11,'ИПЦ raw'!$A:$A,0)) -> 100.78 | U11: =INDEX('ИПЦ raw'!AF:AF, MATCH(Структура!$D11,'ИПЦ raw'!$A:$A,0)) -> 100.75 | V11: =INDEX('ИПЦ raw'!AG:AG, MATCH(Структура!$D11,'ИПЦ raw'!$A:$A,0)) -> 100.33 | W11: =INDEX('ИПЦ raw'!AH:AH, MATCH(Структура!$D11,'ИПЦ raw'!$A:$A,0)) -> 101.32 | X11: =INDEX('ИПЦ raw'!AI:AI, MATCH(Структура!$D11,'ИПЦ raw'!$A:$A,0)) -> 100.86 | Y11: =INDEX('ИПЦ raw'!AJ:AJ, MATCH(Структура!$D11,'ИПЦ raw'!$A:$A,0)) -> 100.96 | Z11: =INDEX('ИПЦ raw'!AK:AK, MATCH(Структура!$D11,'ИПЦ raw'!$A:$A,0)) -> 100.14 | AA11: =INDEX('ИПЦ raw'!AL:AL, MATCH(Структура!$D11,'ИПЦ raw'!$A:$A,0)) -> 100.48 | AB11: =INDEX('ИПЦ raw'!AM:AM, MATCH(Структура!$D11,'ИПЦ raw'!$A:$A,0)) -> 100.33 | AC11: =INDEX('ИПЦ raw'!AN:AN, MATCH(Структура!$D11,'ИПЦ raw'!$A:$A,0)) -> 100.22 | AD11: =INDEX('ИПЦ raw'!AO:AO, MATCH(Структура!$D11,'ИПЦ raw'!$A:$A,0)) -> 100.77 | AE11: =INDEX('ИПЦ raw'!AP:AP, MATCH(Структура!$D11,'ИПЦ raw'!$A:$A,0)) -> 100.27 | AG11: =INDEX('2025'!$C:$C,MATCH(Структура!C11,'2025'!$B:$B,0)) -> 0.88 | AH11: =AG11*P11/100 -> 0.889592 | AI11: =AH11*Q11/100 -> 0.89928855 | AJ11: =AI11*R11/100 -> 0.90657279 | AK11: =AJ11*S11/100 -> 0.91790495 | AL11: =AK11*T11/100 -> 0.92506461 | AM11: =AL11*U11/100 -> 0.93200259 | AN11: =AM11*V11/100 -> 0.9350782 | AO11: =AN11*W11/100 -> 0.94742123 | ... AR11: =AQ11*Z11/100 -> 0.96609316 | AS11: =J11 -> 0.892 | AT11: =AS11*AB11/100 -> 0.8949436 | AU11: =AT11*AC11/100 -> 0.89691248 | AV11: =AU11*AD11/100 -> 0.9038187 | AW11: =AV11*AE11/100 -> 0.90625901
A12: Пельмени, манты, равиоли, кг | B12: =A12 -> Пельмени, манты, равиоли, кг | C12: =A12 -> Пельмени, манты, равиоли, кг | D12: =C12 -> Пельмени, манты, равиоли, кг | E12: =INDEX(БИПЦ_НДС!$D:$D,MATCH(Структура!A12,БИПЦ_НДС!$B:$B,0)) -> 10 | F12: Проды | G12: 1 | H12: 1 | I12: 0 | J12: =INDEX('2026'!$C:$C,MATCH(Структура!B12,'2026'!$B:$B,0)) -> 0.765 | K12: =INDEX('2025'!$C:$C,MATCH(Структура!C12,'2025'!$B:$B,0)) -> 0.757 | L12: 1 | M12: 1 | N12: =INDEX(MoM!B:B,MATCH(Структура!A12,MoM!J:J,0)) -> 1 | P12: =INDEX('ИПЦ raw'!AA:AA, MATCH(Структура!$D12,'ИПЦ raw'!$A:$A,0)) -> 100.36 | Q12: =INDEX('ИПЦ raw'!AB:AB, MATCH(Структура!$D12,'ИПЦ raw'!$A:$A,0)) -> 100.39 | R12: =INDEX('ИПЦ raw'!AC:AC, MATCH(Структура!$D12,'ИПЦ raw'!$A:$A,0)) -> 100.06 | S12: =INDEX('ИПЦ raw'!AD:AD, MATCH(Структура!$D12,'ИПЦ raw'!$A:$A,0)) -> 100.38 | T12: =INDEX('ИПЦ raw'!AE:AE, MATCH(Структура!$D12,'ИПЦ raw'!$A:$A,0)) -> 100.46 | U12: =INDEX('ИПЦ raw'!AF:AF, MATCH(Структура!$D12,'ИПЦ raw'!$A:$A,0)) -> 100.08 | V12: =INDEX('ИПЦ raw'!AG:AG, MATCH(Структура!$D12,'ИПЦ raw'!$A:$A,0)) -> 99.75 | W12: =INDEX('ИПЦ raw'!AH:AH, MATCH(Структура!$D12,'ИПЦ raw'!$A:$A,0)) -> 100.2 | X12: =INDEX('ИПЦ raw'!AI:AI, MATCH(Структура!$D12,'ИПЦ raw'!$A:$A,0)) -> 100.05 | Y12: =INDEX('ИПЦ raw'!AJ:AJ, MATCH(Структура!$D12,'ИПЦ raw'!$A:$A,0)) -> 100.4 | Z12: =INDEX('ИПЦ raw'!AK:AK, MATCH(Структура!$D12,'ИПЦ raw'!$A:$A,0)) -> 100.9 | AA12: =INDEX('ИПЦ raw'!AL:AL, MATCH(Структура!$D12,'ИПЦ raw'!$A:$A,0)) -> 100.74 | AB12: =INDEX('ИПЦ raw'!AM:AM, MATCH(Структура!$D12,'ИПЦ raw'!$A:$A,0)) -> 100.75 | AC12: =INDEX('ИПЦ raw'!AN:AN, MATCH(Структура!$D12,'ИПЦ raw'!$A:$A,0)) -> 100.13 | AD12: =INDEX('ИПЦ raw'!AO:AO, MATCH(Структура!$D12,'ИПЦ raw'!$A:$A,0)) -> 99.71 | AE12: =INDEX('ИПЦ raw'!AP:AP, MATCH(Структура!$D12,'ИПЦ raw'!$A:$A,0)) -> 99.52 | AG12: =INDEX('2025'!$C:$C,MATCH(Структура!C12,'2025'!$B:$B,0)) -> 0.757 | AH12: =AG12*P12/100 -> 0.7597252 | AI12: =AH12*Q12/100 -> 0.76268813 | AJ12: =AI12*R12/100 -> 0.76314574 | AK12: =AJ12*S12/100 -> 0.76604569 | AL12: =AK12*T12/100 -> 0.76956951 | AM12: =AL12*U12/100 -> 0.77018516 | AN12: =AM12*V12/100 -> 0.7682597 | AO12: =AN12*W12/100 -> 0.76979622 | ... AR12: =AQ12*Z12/100 -> 0.7802212 | AS12: =J12 -> 0.765 | AT12: =AS12*AB12/100 -> 0.7707375 | AU12: =AT12*AC12/100 -> 0.77173946 | AV12: =AU12*AD12/100 -> 0.76950141 | AW12: =AV12*AE12/100 -> 0.76580781
A13: Сосиски, сардельки, кг | B13: =A13 -> Сосиски, сардельки, кг | C13: =A13 -> Сосиски, сардельки, кг | D13: =C13 -> Сосиски, сардельки, кг | E13: =INDEX(БИПЦ_НДС!$D:$D,MATCH(Структура!A13,БИПЦ_НДС!$B:$B,0)) -> 10 | F13: Проды | G13: 1 | H13: 1 | I13: 0 | J13: =INDEX('2026'!$C:$C,MATCH(Структура!B13,'2026'!$B:$B,0)) -> 0.647 | K13: =INDEX('2025'!$C:$C,MATCH(Структура!C13,'2025'!$B:$B,0)) -> 0.68 | L13: 1 | M13: 1 | N13: =INDEX(MoM!B:B,MATCH(Структура!A13,MoM!J:J,0)) -> 1 | P13: =INDEX('ИПЦ raw'!AA:AA, MATCH(Структура!$D13,'ИПЦ raw'!$A:$A,0)) -> 99.7 | Q13: =INDEX('ИПЦ raw'!AB:AB, MATCH(Структура!$D13,'ИПЦ raw'!$A:$A,0)) -> 100.33 | R13: =INDEX('ИПЦ raw'!AC:AC, MATCH(Структура!$D13,'ИПЦ raw'!$A:$A,0)) -> 100.4 | S13: =INDEX('ИПЦ raw'!AD:AD, MATCH(Структура!$D13,'ИПЦ raw'!$A:$A,0)) -> 100.04 | T13: =INDEX('ИПЦ raw'!AE:AE, MATCH(Структура!$D13,'ИПЦ raw'!$A:$A,0)) -> 100.69 | U13: =INDEX('ИПЦ raw'!AF:AF, MATCH(Структура!$D13,'ИПЦ raw'!$A:$A,0)) -> 100.02 | V13: =INDEX('ИПЦ raw'!AG:AG, MATCH(Структура!$D13,'ИПЦ raw'!$A:$A,0)) -> 99.8 | W13: =INDEX('ИПЦ raw'!AH:AH, MATCH(Структура!$D13,'ИПЦ raw'!$A:$A,0)) -> 100.41 | X13: =INDEX('ИПЦ raw'!AI:AI, MATCH(Структура!$D13,'ИПЦ raw'!$A:$A,0)) -> 100.7 | Y13: =INDEX('ИПЦ raw'!AJ:AJ, MATCH(Структура!$D13,'ИПЦ raw'!$A:$A,0)) -> 100.71 | Z13: =INDEX('ИПЦ raw'!AK:AK, MATCH(Структура!$D13,'ИПЦ raw'!$A:$A,0)) -> 100.55 | AA13: =INDEX('ИПЦ raw'!AL:AL, MATCH(Структура!$D13,'ИПЦ raw'!$A:$A,0)) -> 100.56 | AB13: =INDEX('ИПЦ raw'!AM:AM, MATCH(Структура!$D13,'ИПЦ raw'!$A:$A,0)) -> 100.64 | AC13: =INDEX('ИПЦ raw'!AN:AN, MATCH(Структура!$D13,'ИПЦ raw'!$A:$A,0)) -> 99.86 | AD13: =INDEX('ИПЦ raw'!AO:AO, MATCH(Структура!$D13,'ИПЦ raw'!$A:$A,0)) -> 99.72 | AE13: =INDEX('ИПЦ raw'!AP:AP, MATCH(Структура!$D13,'ИПЦ raw'!$A:$A,0)) -> 99.47 | AG13: =INDEX('2025'!$C:$C,MATCH(Структура!C13,'2025'!$B:$B,0)) -> 0.68 | AH13: =AG13*P13/100 -> 0.67796 | AI13: =AH13*Q13/100 -> 0.68019727 | AJ13: =AI13*R13/100 -> 0.68291806 | AK13: =AJ13*S13/100 -> 0.68319122 | AL13: =AK13*T13/100 -> 0.68790524 | AM13: =AL13*U13/100 -> 0.68804282 | AN13: =AM13*V13/100 -> 0.68666674 | AO13: =AN13*W13/100 -> 0.68948207 | ... AR13: =AQ13*Z13/100 -> 0.70308385 | AS13: =J13 -> 0.647 | AT13: =AS13*AB13/100 -> 0.6511408 | AU13: =AT13*AC13/100 -> 0.6502292 | AV13: =AU13*AD13/100 -> 0.64840856 | AW13: =AV13*AE13/100 -> 0.644972
A14: Колбаса полукопченая и варено-копченая, кг | B14: =A14 -> Колбаса полукопченая и варено-копченая, кг | C14: =A14 -> Колбаса полукопченая и варено-копченая, кг | D14: =C14 -> Колбаса полукопченая и варено-копченая, кг | E14: =INDEX(БИПЦ_НДС!$D:$D,MATCH(Структура!A14,БИПЦ_НДС!$B:$B,0)) -> 10 | F14: Проды | G14: 1 | H14: 1 | I14: 0 | J14: =INDEX('2026'!$C:$C,MATCH(Структура!B14,'2026'!$B:$B,0)) -> 0.507 | K14: =INDEX('2025'!$C:$C,MATCH(Структура!C14,'2025'!$B:$B,0)) -> 0.501 | L14: 1 | M14: 1 | N14: =INDEX(MoM!B:B,MATCH(Структура!A14,MoM!J:J,0)) -> 1 | P14: =INDEX('ИПЦ raw'!AA:AA, MATCH(Структура!$D14,'ИПЦ raw'!$A:$A,0)) -> 100.28 | Q14: =INDEX('ИПЦ raw'!AB:AB, MATCH(Структура!$D14,'ИПЦ raw'!$A:$A,0)) -> 100.53 | R14: =INDEX('ИПЦ raw'!AC:AC, MATCH(Структура!$D14,'ИПЦ raw'!$A:$A,0)) -> 101.22 | S14: =INDEX('ИПЦ raw'!AD:AD, MATCH(Структура!$D14,'ИПЦ raw'!$A:$A,0)) -> 100.25 | T14: =INDEX('ИПЦ raw'!AE:AE, MATCH(Структура!$D14,'ИПЦ raw'!$A:$A,0)) -> 100.34 | U14: =INDEX('ИПЦ raw'!AF:AF, MATCH(Структура!$D14,'ИПЦ raw'!$A:$A,0)) -> 99.82 | V14: =INDEX('ИПЦ raw'!AG:AG, MATCH(Структура!$D14,'ИПЦ raw'!$A:$A,0)) -> 100.35 | W14: =INDEX('ИПЦ raw'!AH:AH, MATCH(Структура!$D14,'ИПЦ raw'!$A:$A,0)) -> 100.59 | X14: =INDEX('ИПЦ raw'!AI:AI, MATCH(Структура!$D14,'ИПЦ raw'!$A:$A,0)) -> 100.5 | Y14: =INDEX('ИПЦ raw'!AJ:AJ, MATCH(Структура!$D14,'ИПЦ raw'!$A:$A,0)) -> 100.8 | Z14: =INDEX('ИПЦ raw'!AK:AK, MATCH(Структура!$D14,'ИПЦ raw'!$A:$A,0)) -> 100.73 | AA14: =INDEX('ИПЦ raw'!AL:AL, MATCH(Структура!$D14,'ИПЦ raw'!$A:$A,0)) -> 100.1 | AB14: =INDEX('ИПЦ raw'!AM:AM, MATCH(Структура!$D14,'ИПЦ raw'!$A:$A,0)) -> 100.33 | AC14: =INDEX('ИПЦ raw'!AN:AN, MATCH(Структура!$D14,'ИПЦ raw'!$A:$A,0)) -> 100.1 | AD14: =INDEX('ИПЦ raw'!AO:AO, MATCH(Структура!$D14,'ИПЦ raw'!$A:$A,0)) -> 99.76 | AE14: =INDEX('ИПЦ raw'!AP:AP, MATCH(Структура!$D14,'ИПЦ raw'!$A:$A,0)) -> 99.6 | AG14: =INDEX('2025'!$C:$C,MATCH(Структура!C14,'2025'!$B:$B,0)) -> 0.501 | AH14: =AG14*P14/100 -> 0.5024028 | AI14: =AH14*Q14/100 -> 0.50506553 | AJ14: =AI14*R14/100 -> 0.51122733 | AK14: =AJ14*S14/100 -> 0.5125054 | AL14: =AK14*T14/100 -> 0.51424792 | AM14: =AL14*U14/100 -> 0.51332227 | AN14: =AM14*V14/100 -> 0.5151189 | AO14: =AN14*W14/100 -> 0.5181581 | ... AR14: =AQ14*Z14/100 -> 0.52874676 | AS14: =J14 -> 0.507 | AT14: =AS14*AB14/100 -> 0.5086731 | AU14: =AT14*AC14/100 -> 0.50918177 | AV14: =AU14*AD14/100 -> 0.50795974 | AW14: =AV14*AE14/100 -> 0.5059279
A15: Колбаса сырокопченая, кг | B15: =A15 -> Колбаса сырокопченая, кг | C15: =A15 -> Колбаса сырокопченая, кг | D15: =C15 -> Колбаса сырокопченая, кг | E15: =INDEX(БИПЦ_НДС!$D:$D,MATCH(Структура!A15,БИПЦ_НДС!$B:$B,0)) -> 10 | F15: Проды | G15: 1 | H15: 1 | I15: 0 | J15: =INDEX('2026'!$C:$C,MATCH(Структура!B15,'2026'!$B:$B,0)) -> 0.204 | K15: =INDEX('2025'!$C:$C,MATCH(Структура!C15,'2025'!$B:$B,0)) -> 0.195 | L15: 1 | M15: 1 | N15: =INDEX(MoM!B:B,MATCH(Структура!A15,MoM!J:J,0)) -> 1 | P15: =INDEX('ИПЦ raw'!AA:AA, MATCH(Структура!$D15,'ИПЦ raw'!$A:$A,0)) -> 99.68 | Q15: =INDEX('ИПЦ raw'!AB:AB, MATCH(Структура!$D15,'ИПЦ raw'!$A:$A,0)) -> 100.44 | R15: =INDEX('ИПЦ raw'!AC:AC, MATCH(Структура!$D15,'ИПЦ raw'!$A:$A,0)) -> 99.88 | S15: =INDEX('ИПЦ raw'!AD:AD, MATCH(Структура!$D15,'ИПЦ raw'!$A:$A,0)) -> 100.2 | T15: =INDEX('ИПЦ raw'!AE:AE, MATCH(Структура!$D15,'ИПЦ raw'!$A:$A,0)) -> 100.09 | U15: =INDEX('ИПЦ raw'!AF:AF, MATCH(Структура!$D15,'ИПЦ raw'!$A:$A,0)) -> 100.39 | V15: =INDEX('ИПЦ raw'!AG:AG, MATCH(Структура!$D15,'ИПЦ raw'!$A:$A,0)) -> 99.22 | W15: =INDEX('ИПЦ raw'!AH:AH, MATCH(Структура!$D15,'ИПЦ raw'!$A:$A,0)) -> 100.63 | X15: =INDEX('ИПЦ raw'!AI:AI, MATCH(Структура!$D15,'ИПЦ raw'!$A:$A,0)) -> 100.3 | Y15: =INDEX('ИПЦ raw'!AJ:AJ, MATCH(Структура!$D15,'ИПЦ raw'!$A:$A,0)) -> 101.1 | Z15: =INDEX('ИПЦ raw'!AK:AK, MATCH(Структура!$D15,'ИПЦ raw'!$A:$A,0)) -> 99.54 | AA15: =INDEX('ИПЦ raw'!AL:AL, MATCH(Структура!$D15,'ИПЦ raw'!$A:$A,0)) -> 99.65 | AB15: =INDEX('ИПЦ raw'!AM:AM, MATCH(Структура!$D15,'ИПЦ raw'!$A:$A,0)) -> 100.65 | AC15: =INDEX('ИПЦ raw'!AN:AN, MATCH(Структура!$D15,'ИПЦ raw'!$A:$A,0)) -> 100.69 | AD15: =INDEX('ИПЦ raw'!AO:AO, MATCH(Структура!$D15,'ИПЦ raw'!$A:$A,0)) -> 100.53 | AE15: =INDEX('ИПЦ raw'!AP:AP, MATCH(Структура!$D15,'ИПЦ raw'!$A:$A,0)) -> 99.05 | AG15: =INDEX('2025'!$C:$C,MATCH(Структура!C15,'2025'!$B:$B,0)) -> 0.195 | AH15: =AG15*P15/100 -> 0.194376 | AI15: =AH15*Q15/100 -> 0.19523125 | AJ15: =AI15*R15/100 -> 0.19499698 | AK15: =AJ15*S15/100 -> 0.19538697 | AL15: =AK15*T15/100 -> 0.19556282 | AM15: =AL15*U15/100 -> 0.19632551 | AN15: =AM15*V15/100 -> 0.19479418 | AO15: =AN15*W15/100 -> 0.19602138 | ... AR15: =AQ15*Z15/100 -> 0.19785779 | AS15: =J15 -> 0.204 | AT15: =AS15*AB15/100 -> 0.205326 | AU15: =AT15*AC15/100 -> 0.20674275 | AV15: =AU15*AD15/100 -> 0.20783849 | AW15: =AV15*AE15/100 -> 0.20586402
A16: Колбаса вареная, кг | B16: =A16 -> Колбаса вареная, кг | C16: =A16 -> Колбаса вареная, кг | D16: =C16 -> Колбаса вареная, кг | E16: =INDEX(БИПЦ_НДС!$D:$D,MATCH(Структура!A16,БИПЦ_НДС!$B:$B,0)) -> 10 | F16: Проды | G16: 1 | H16: 1 | I16: 0 | J16: =INDEX('2026'!$C:$C,MATCH(Структура!B16,'2026'!$B:$B,0)) -> 0.604 | K16: =INDEX('2025'!$C:$C,MATCH(Структура!C16,'2025'!$B:$B,0)) -> 0.602 | L16: 1 | M16: 1 | N16: =INDEX(MoM!B:B,MATCH(Структура!A16,MoM!J:J,0)) -> 1 | P16: =INDEX('ИПЦ raw'!AA:AA, MATCH(Структура!$D16,'ИПЦ raw'!$A:$A,0)) -> 99.7 | Q16: =INDEX('ИПЦ raw'!AB:AB, MATCH(Структура!$D16,'ИПЦ raw'!$A:$A,0)) -> 100.42 | R16: =INDEX('ИПЦ raw'!AC:AC, MATCH(Структура!$D16,'ИПЦ raw'!$A:$A,0)) -> 100.24 | S16: =INDEX('ИПЦ raw'!AD:AD, MATCH(Структура!$D16,'ИПЦ raw'!$A:$A,0)) -> 100.12 | T16: =INDEX('ИПЦ raw'!AE:AE, MATCH(Структура!$D16,'ИПЦ raw'!$A:$A,0)) -> 100.2 | U16: =INDEX('ИПЦ raw'!AF:AF, MATCH(Структура!$D16,'ИПЦ raw'!$A:$A,0)) -> 100.55 | V16: =INDEX('ИПЦ raw'!AG:AG, MATCH(Структура!$D16,'ИПЦ raw'!$A:$A,0)) -> 100.19 | W16: =INDEX('ИПЦ raw'!AH:AH, MATCH(Структура!$D16,'ИПЦ raw'!$A:$A,0)) -> 99.82 | X16: =INDEX('ИПЦ raw'!AI:AI, MATCH(Структура!$D16,'ИПЦ raw'!$A:$A,0)) -> 100.71 | Y16: =INDEX('ИПЦ raw'!AJ:AJ, MATCH(Структура!$D16,'ИПЦ raw'!$A:$A,0)) -> 100.59 | Z16: =INDEX('ИПЦ raw'!AK:AK, MATCH(Структура!$D16,'ИПЦ raw'!$A:$A,0)) -> 100.84 | AA16: =INDEX('ИПЦ raw'!AL:AL, MATCH(Структура!$D16,'ИПЦ raw'!$A:$A,0)) -> 99.85 | AB16: =INDEX('ИПЦ raw'!AM:AM, MATCH(Структура!$D16,'ИПЦ raw'!$A:$A,0)) -> 100.44 | AC16: =INDEX('ИПЦ raw'!AN:AN, MATCH(Структура!$D16,'ИПЦ raw'!$A:$A,0)) -> 100.28 | AD16: =INDEX('ИПЦ raw'!AO:AO, MATCH(Структура!$D16,'ИПЦ raw'!$A:$A,0)) -> 99.93 | AE16: =INDEX('ИПЦ raw'!AP:AP, MATCH(Структура!$D16,'ИПЦ raw'!$A:$A,0)) -> 99.74 | AG16: =INDEX('2025'!$C:$C,MATCH(Структура!C16,'2025'!$B:$B,0)) -> 0.602 | AH16: =AG16*P16/100 -> 0.600194 | AI16: =AH16*Q16/100 -> 0.60271481 | AJ16: =AI16*R16/100 -> 0.60416133 | AK16: =AJ16*S16/100 -> 0.60488632 | AL16: =AK16*T16/100 -> 0.6060961 | AM16: =AL16*U16/100 -> 0.60942963 | AN16: =AM16*V16/100 -> 0.61058754 | AO16: =AN16*W16/100 -> 0.60948848 | ... AR16: =AQ16*Z16/100 -> 0.62262384 | AS16: =J16 -> 0.604 | AT16: =AS16*AB16/100 -> 0.6066576 | AU16: =AT16*AC16/100 -> 0.60835624 | AV16: =AU16*AD16/100 -> 0.60793039 | AW16: =AV16*AE16/100 -> 0.60634977
A17: Мясокопчености, кг | B17: =A17 -> Мясокопчености, кг | C17: =A17 -> Мясокопчености, кг | D17: =C17 -> Мясокопчености, кг | E17: =INDEX(БИПЦ_НДС!$D:$D,MATCH(Структура!A17,БИПЦ_НДС!$B:$B,0)) -> 20 | F17: Проды | G17: 1 | H17: 1 | I17: 0 | J17: =INDEX('2026'!$C:$C,MATCH(Структура!B17,'2026'!$B:$B,0)) -> 0.402 | K17: =INDEX('2025'!$C:$C,MATCH(Структура!C17,'2025'!$B:$B,0)) -> 0.394 | L17: 1 | M17: 1 | N17: =INDEX(MoM!B:B,MATCH(Структура!A17,MoM!J:J,0)) -> 1 | P17: =INDEX('ИПЦ raw'!AA:AA, MATCH(Структура!$D17,'ИПЦ raw'!$A:$A,0)) -> 100.62 | Q17: =INDEX('ИПЦ raw'!AB:AB, MATCH(Структура!$D17,'ИПЦ raw'!$A:$A,0)) -> 100.58 | R17: =INDEX('ИПЦ raw'!AC:AC, MATCH(Структура!$D17,'ИПЦ raw'!$A:$A,0)) -> 100.96 | S17: =INDEX('ИПЦ raw'!AD:AD, MATCH(Структура!$D17,'ИПЦ raw'!$A:$A,0)) -> 100.15 | T17: =INDEX('ИПЦ raw'!AE:AE, MATCH(Структура!$D17,'ИПЦ raw'!$A:$A,0)) -> 100.45 | U17: =INDEX('ИПЦ raw'!AF:AF, MATCH(Структура!$D17,'ИПЦ raw'!$A:$A,0)) -> 100.28 | V17: =INDEX('ИПЦ raw'!AG:AG, MATCH(Структура!$D17,'ИПЦ raw'!$A:$A,0)) -> 100.42 | W17: =INDEX('ИПЦ raw'!AH:AH, MATCH(Структура!$D17,'ИПЦ raw'!$A:$A,0)) -> 100.47 | X17: =INDEX('ИПЦ raw'!AI:AI, MATCH(Структура!$D17,'ИПЦ raw'!$A:$A,0)) -> 100.84 | Y17: =INDEX('ИПЦ raw'!AJ:AJ, MATCH(Структура!$D17,'ИПЦ raw'!$A:$A,0)) -> 101.1 | Z17: =INDEX('ИПЦ raw'!AK:AK, MATCH(Структура!$D17,'ИПЦ raw'!$A:$A,0)) -> 100.4 | AA17: =INDEX('ИПЦ raw'!AL:AL, MATCH(Структура!$D17,'ИПЦ raw'!$A:$A,0)) -> 100.57 | AB17: =INDEX('ИПЦ raw'!AM:AM, MATCH(Структура!$D17,'ИПЦ raw'!$A:$A,0)) -> 100.59 | AC17: =INDEX('ИПЦ raw'!AN:AN, MATCH(Структура!$D17,'ИПЦ raw'!$A:$A,0)) -> 100.2 | AD17: =INDEX('ИПЦ raw'!AO:AO, MATCH(Структура!$D17,'ИПЦ raw'!$A:$A,0)) -> 100.07 | AE17: =INDEX('ИПЦ raw'!AP:AP, MATCH(Структура!$D17,'ИПЦ raw'!$A:$A,0)) -> 99.69 | AG17: =INDEX('2025'!$C:$C,MATCH(Структура!C17,'2025'!$B:$B,0)) -> 0.394 | AH17: =AG17*P17/100 -> 0.3964428 | AI17: =AH17*Q17/100 -> 0.39874217 | AJ17: =AI17*R17/100 -> 0.40257009 | AK17: =AJ17*S17/100 -> 0.40317395 | AL17: =AK17*T17/100 -> 0.40498823 | AM17: =AL17*U17/100 -> 0.4061222 | AN17: =AM17*V17/100 -> 0.40782791 | AO17: =AN17*W17/100 -> 0.4097447 | ... AR17: =AQ17*Z17/100 -> 0.41940254 | AS17: =J17 -> 0.402 | AT17: =AS17*AB17/100 -> 0.4043718 | AU17: =AT17*AC17/100 -> 0.40518054 | AV17: =AU17*AD17/100 -> 0.40546417 | AW17: =AV17*AE17/100 -> 0.40420723
A18: Кулинарные изделия из птицы, кг | B18: =A18 -> Кулинарные изделия из птицы, кг | C18: =A18 -> Кулинарные изделия из птицы, кг | D18: =C18 -> Кулинарные изделия из птицы, кг | E18: =INDEX(БИПЦ_НДС!$D:$D,MATCH(Структура!A18,БИПЦ_НДС!$B:$B,0)) -> 10 | F18: Проды | G18: 1 | H18: 1 | I18: 0 | J18: =INDEX('2026'!$C:$C,MATCH(Структура!B18,'2026'!$B:$B,0)) -> 0.17 | K18: =INDEX('2025'!$C:$C,MATCH(Структура!C18,'2025'!$B:$B,0)) -> 0.185 | L18: 1 | M18: 1 | N18: =INDEX(MoM!B:B,MATCH(Структура!A18,MoM!J:J,0)) -> 1 | P18: =INDEX('ИПЦ raw'!AA:AA, MATCH(Структура!$D18,'ИПЦ raw'!$A:$A,0)) -> 101.17 | Q18: =INDEX('ИПЦ raw'!AB:AB, MATCH(Структура!$D18,'ИПЦ raw'!$A:$A,0)) -> 101.09 | R18: =INDEX('ИПЦ raw'!AC:AC, MATCH(Структура!$D18,'ИПЦ raw'!$A:$A,0)) -> 100.66 | S18: =INDEX('ИПЦ raw'!AD:AD, MATCH(Структура!$D18,'ИПЦ raw'!$A:$A,0)) -> 100.5 | T18: =INDEX('ИПЦ raw'!AE:AE, MATCH(Структура!$D18,'ИПЦ raw'!$A:$A,0)) -> 100.91 | U18: =INDEX('ИПЦ raw'!AF:AF, MATCH(Структура!$D18,'ИПЦ raw'!$A:$A,0)) -> 100.36 | V18: =INDEX('ИПЦ raw'!AG:AG, MATCH(Структура!$D18,'ИПЦ raw'!$A:$A,0)) -> 100.51 | W18: =INDEX('ИПЦ raw'!AH:AH, MATCH(Структура!$D18,'ИПЦ raw'!$A:$A,0)) -> 100.05 | X18: =INDEX('ИПЦ raw'!AI:AI, MATCH(Структура!$D18,'ИПЦ raw'!$A:$A,0)) -> 100.52 | Y18: =INDEX('ИПЦ raw'!AJ:AJ, MATCH(Структура!$D18,'ИПЦ raw'!$A:$A,0)) -> 100.61 | Z18: =INDEX('ИПЦ raw'!AK:AK, MATCH(Структура!$D18,'ИПЦ raw'!$A:$A,0)) -> 100.71 | AA18: =INDEX('ИПЦ raw'!AL:AL, MATCH(Структура!$D18,'ИПЦ raw'!$A:$A,0)) -> 100.64 | AB18: =INDEX('ИПЦ raw'!AM:AM, MATCH(Структура!$D18,'ИПЦ raw'!$A:$A,0)) -> 100.28 | AC18: =INDEX('ИПЦ raw'!AN:AN, MATCH(Структура!$D18,'ИПЦ raw'!$A:$A,0)) -> 100.26 | AD18: =INDEX('ИПЦ raw'!AO:AO, MATCH(Структура!$D18,'ИПЦ raw'!$A:$A,0)) -> 100.36 | AE18: =INDEX('ИПЦ raw'!AP:AP, MATCH(Структура!$D18,'ИПЦ raw'!$A:$A,0)) -> 100.21 | AG18: =INDEX('2025'!$C:$C,MATCH(Структура!C18,'2025'!$B:$B,0)) -> 0.185 | AH18: =AG18*P18/100 -> 0.1871645 | AI18: =AH18*Q18/100 -> 0.18920459 | AJ18: =AI18*R18/100 -> 0.19045334 | AK18: =AJ18*S18/100 -> 0.19140561 | AL18: =AK18*T18/100 -> 0.1931474 | AM18: =AL18*U18/100 -> 0.19384273 | AN18: =AM18*V18/100 -> 0.19483133 | AO18: =AN18*W18/100 -> 0.19492875 | ... AR18: =AQ18*Z18/100 -> 0.1985373 | AS18: =J18 -> 0.17 | AT18: =AS18*AB18/100 -> 0.170476 | AU18: =AT18*AC18/100 -> 0.17091924 | AV18: =AU18*AD18/100 -> 0.17153455 | AW18: =AV18*AE18/100 -> 0.17189477
A19: Консервы мясные, кг | B19: =A19 -> Консервы мясные, кг | C19: =A19 -> Консервы мясные, кг | D19: =C19 -> Консервы мясные, кг | E19: =INDEX(БИПЦ_НДС!$D:$D,MATCH(Структура!A19,БИПЦ_НДС!$B:$B,0)) -> 10 | F19: Проды | G19: 1 | H19: 1 | I19: 0 | J19: =INDEX('2026'!$C:$C,MATCH(Структура!B19,'2026'!$B:$B,0)) -> 0.129 | K19: =INDEX('2025'!$C:$C,MATCH(Структура!C19,'2025'!$B:$B,0)) -> 0.129 | L19: 1 | M19: 1 | N19: =INDEX(MoM!B:B,MATCH(Структура!A19,MoM!J:J,0)) -> 1 | P19: =INDEX('ИПЦ raw'!AA:AA, MATCH(Структура!$D19,'ИПЦ raw'!$A:$A,0)) -> 100.67 | Q19: =INDEX('ИПЦ raw'!AB:AB, MATCH(Структура!$D19,'ИПЦ raw'!$A:$A,0)) -> 100.29 | R19: =INDEX('ИПЦ raw'!AC:AC, MATCH(Структура!$D19,'ИПЦ raw'!$A:$A,0)) -> 100.58 | S19: =INDEX('ИПЦ raw'!AD:AD, MATCH(Структура!$D19,'ИПЦ raw'!$A:$A,0)) -> 100.8 | T19: =INDEX('ИПЦ raw'!AE:AE, MATCH(Структура!$D19,'ИПЦ raw'!$A:$A,0)) -> 100.74 | U19: =INDEX('ИПЦ raw'!AF:AF, MATCH(Структура!$D19,'ИПЦ raw'!$A:$A,0)) -> 100.73 | V19: =INDEX('ИПЦ raw'!AG:AG, MATCH(Структура!$D19,'ИПЦ raw'!$A:$A,0)) -> 101 | W19: =INDEX('ИПЦ raw'!AH:AH, MATCH(Структура!$D19,'ИПЦ raw'!$A:$A,0)) -> 100.34 | X19: =INDEX('ИПЦ raw'!AI:AI, MATCH(Структура!$D19,'ИПЦ raw'!$A:$A,0)) -> 100.89 | Y19: =INDEX('ИПЦ raw'!AJ:AJ, MATCH(Структура!$D19,'ИПЦ raw'!$A:$A,0)) -> 100.19 | Z19: =INDEX('ИПЦ raw'!AK:AK, MATCH(Структура!$D19,'ИПЦ raw'!$A:$A,0)) -> 100.51 | AA19: =INDEX('ИПЦ raw'!AL:AL, MATCH(Структура!$D19,'ИПЦ raw'!$A:$A,0)) -> 100.53 | AB19: =INDEX('ИПЦ raw'!AM:AM, MATCH(Структура!$D19,'ИПЦ raw'!$A:$A,0)) -> 100.45 | AC19: =INDEX('ИПЦ raw'!AN:AN, MATCH(Структура!$D19,'ИПЦ raw'!$A:$A,0)) -> 100.23 | AD19: =INDEX('ИПЦ raw'!AO:AO, MATCH(Структура!$D19,'ИПЦ raw'!$A:$A,0)) -> 100.31 | AE19: =INDEX('ИПЦ raw'!AP:AP, MATCH(Структура!$D19,'ИПЦ raw'!$A:$A,0)) -> 100.56 | AG19: =INDEX('2025'!$C:$C,MATCH(Структура!C19,'2025'!$B:$B,0)) -> 0.129 | AH19: =AG19*P19/100 -> 0.1298643 | AI19: =AH19*Q19/100 -> 0.13024091 | AJ19: =AI19*R19/100 -> 0.1309963 | AK19: =AJ19*S19/100 -> 0.13204427 | AL19: =AK19*T19/100 -> 0.1330214 | AM19: =AL19*U19/100 -> 0.13399246 | AN19: =AM19*V19/100 -> 0.13533238 | AO19: =AN19*W19/100 -> 0.13579251 | ... AR19: =AQ19*Z19/100 -> 0.1379614 | AS19: =J19 -> 0.129 | AT19: =AS19*AB19/100 -> 0.1295805 | AU19: =AT19*AC19/100 -> 0.12987854 | AV19: =AU19*AD19/100 -> 0.13028116 | AW19: =AV19*AE19/100 -> 0.13101073
A20: Консервы мясные для детского питания, кг | B20: =A20 -> Консервы мясные для детского питания, кг | C20: =A20 -> Консервы мясные для детского питания, кг | D20: =C20 -> Консервы мясные для детского питания, кг | E20: =INDEX(БИПЦ_НДС!$D:$D,MATCH(Структура!A20,БИПЦ_НДС!$B:$B,0)) -> 10 | F20: Проды | G20: 1 | H20: 1 | I20: 0 | J20: =INDEX('2026'!$C:$C,MATCH(Структура!B20,'2026'!$B:$B,0)) -> 0.019 | K20: =INDEX('2025'!$C:$C,MATCH(Структура!C20,'2025'!$B:$B,0)) -> 0.016 | L20: 1 | M20: 1 | N20: =INDEX(MoM!B:B,MATCH(Структура!A20,MoM!J:J,0)) -> 1 | P20: =INDEX('ИПЦ raw'!AA:AA, MATCH(Структура!$D20,'ИПЦ raw'!$A:$A,0)) -> 99.88 | Q20: =INDEX('ИПЦ raw'!AB:AB, MATCH(Структура!$D20,'ИПЦ raw'!$A:$A,0)) -> 102.69 | R20: =INDEX('ИПЦ raw'!AC:AC, MATCH(Структура!$D20,'ИПЦ raw'!$A:$A,0)) -> 100.59 | S20: =INDEX('ИПЦ raw'!AD:AD, MATCH(Структура!$D20,'ИПЦ raw'!$A:$A,0)) -> 100.2 | T20: =INDEX('ИПЦ raw'!AE:AE, MATCH(Структура!$D20,'ИПЦ raw'!$A:$A,0)) -> 99.07 | U20: =INDEX('ИПЦ raw'!AF:AF, MATCH(Структура!$D20,'ИПЦ raw'!$A:$A,0)) -> 99.47 | V20: =INDEX('ИПЦ raw'!AG:AG, MATCH(Структура!$D20,'ИПЦ raw'!$A:$A,0)) -> 99.52 | W20: =INDEX('ИПЦ raw'!AH:AH, MATCH(Структура!$D20,'ИПЦ raw'!$A:$A,0)) -> 101.46 | X20: =INDEX('ИПЦ raw'!AI:AI, MATCH(Структура!$D20,'ИПЦ raw'!$A:$A,0)) -> 100.55 | Y20: =INDEX('ИПЦ raw'!AJ:AJ, MATCH(Структура!$D20,'ИПЦ raw'!$A:$A,0)) -> 99.87 | Z20: =INDEX('ИПЦ raw'!AK:AK, MATCH(Структура!$D20,'ИПЦ raw'!$A:$A,0)) -> 100.84 | AA20: =INDEX('ИПЦ raw'!AL:AL, MATCH(Структура!$D20,'ИПЦ raw'!$A:$A,0)) -> 100.14 | AB20: =INDEX('ИПЦ raw'!AM:AM, MATCH(Структура!$D20,'ИПЦ raw'!$A:$A,0)) -> 101.8 | AC20: =INDEX('ИПЦ raw'!AN:AN, MATCH(Структура!$D20,'ИПЦ raw'!$A:$A,0)) -> 100.36 | AD20: =INDEX('ИПЦ raw'!AO:AO, MATCH(Структура!$D20,'ИПЦ raw'!$A:$A,0)) -> 100.23 | AE20: =INDEX('ИПЦ raw'!AP:AP, MATCH(Структура!$D20,'ИПЦ raw'!$A:$A,0)) -> 100.99 | AG20: =INDEX('2025'!$C:$C,MATCH(Структура!C20,'2025'!$B:$B,0)) -> 0.016 | AH20: =AG20*P20/100 -> 0.0159808 | AI20: =AH20*Q20/100 -> 0.016410684 | AJ20: =AI20*R20/100 -> 0.016507507 | AK20: =AJ20*S20/100 -> 0.016540522 | AL20: =AK20*T20/100 -> 0.016386695 | AM20: =AL20*U20/100 -> 0.016299845 | AN20: =AM20*V20/100 -> 0.016221606 | AO20: =AN20*W20/100 -> 0.016458441 | ... AR20: =AQ20*Z20/100 -> 0.01666628 | AS20: =J20 -> 0.019 | AT20: =AS20*AB20/100 -> 0.019342 | AU20: =AT20*AC20/100 -> 0.019411631 | AV20: =AU20*AD20/100 -> 0.019456278 | AW20: =AV20*AE20/100 -> 0.019648895
A21: Рыба живая и охлажденная, кг | B21: =A21 -> Рыба живая и охлажденная, кг | C21: =A21 -> Рыба живая и охлажденная, кг | D21: =C21 -> Рыба живая и охлажденная, кг | E21: =INDEX(БИПЦ_НДС!$D:$D,MATCH(Структура!A21,БИПЦ_НДС!$B:$B,0)) -> 10 | F21: Проды | G21: 1 | H21: 1 | I21: 0 | J21: =INDEX('2026'!$C:$C,MATCH(Структура!B21,'2026'!$B:$B,0)) -> 0.133 | K21: =INDEX('2025'!$C:$C,MATCH(Структура!C21,'2025'!$B:$B,0)) -> 0.134 | L21: 1 | M21: 1 | N21: =INDEX(MoM!B:B,MATCH(Структура!A21,MoM!J:J,0)) -> 1 | P21: =INDEX('ИПЦ raw'!AA:AA, MATCH(Структура!$D21,'ИПЦ raw'!$A:$A,0)) -> 100.99 | Q21: =INDEX('ИПЦ raw'!AB:AB, MATCH(Структура!$D21,'ИПЦ raw'!$A:$A,0)) -> 101.69 | R21: =INDEX('ИПЦ raw'!AC:AC, MATCH(Структура!$D21,'ИПЦ raw'!$A:$A,0)) -> 100.14 | S21: =INDEX('ИПЦ raw'!AD:AD, MATCH(Структура!$D21,'ИПЦ raw'!$A:$A,0)) -> 101.78 | T21: =INDEX('ИПЦ raw'!AE:AE, MATCH(Структура!$D21,'ИПЦ raw'!$A:$A,0)) -> 101.25 | U21: =INDEX('ИПЦ raw'!AF:AF, MATCH(Структура!$D21,'ИПЦ raw'!$A:$A,0)) -> 101.63 | V21: =INDEX('ИПЦ raw'!AG:AG, MATCH(Структура!$D21,'ИПЦ raw'!$A:$A,0)) -> 101.33 | W21: =INDEX('ИПЦ raw'!AH:AH, MATCH(Структура!$D21,'ИПЦ raw'!$A:$A,0)) -> 100.96 | X21: =INDEX('ИПЦ raw'!AI:AI, MATCH(Структура!$D21,'ИПЦ raw'!$A:$A,0)) -> 100.07 | Y21: =INDEX('ИПЦ raw'!AJ:AJ, MATCH(Структура!$D21,'ИПЦ raw'!$A:$A,0)) -> 100.87 | Z21: =INDEX('ИПЦ raw'!AK:AK, MATCH(Структура!$D21,'ИПЦ raw'!$A:$A,0)) -> 100.23 | AA21: =INDEX('ИПЦ raw'!AL:AL, MATCH(Структура!$D21,'ИПЦ raw'!$A:$A,0)) -> 100.64 | AB21: =INDEX('ИПЦ raw'!AM:AM, MATCH(Структура!$D21,'ИПЦ raw'!$A:$A,0)) -> 100.2 | AC21: =INDEX('ИПЦ raw'!AN:AN, MATCH(Структура!$D21,'ИПЦ raw'!$A:$A,0)) -> 101.16 | AD21: =INDEX('ИПЦ raw'!AO:AO, MATCH(Структура!$D21,'ИПЦ raw'!$A:$A,0)) -> 100.98 | AE21: =INDEX('ИПЦ raw'!AP:AP, MATCH(Структура!$D21,'ИПЦ raw'!$A:$A,0)) -> 100.51 | AG21: =INDEX('2025'!$C:$C,MATCH(Структура!C21,'2025'!$B:$B,0)) -> 0.134 | AH21: =AG21*P21/100 -> 0.1353266 | AI21: =AH21*Q21/100 -> 0.13761362 | AJ21: =AI21*R21/100 -> 0.13780628 | AK21: =AJ21*S21/100 -> 0.14025923 | AL21: =AK21*T21/100 -> 0.14201247 | AM21: =AL21*U21/100 -> 0.14432727 | AN21: =AM21*V21/100 -> 0.14624683 | AO21: =AN21*W21/100 -> 0.1476508 | ... AR21: =AQ21*Z21/100 -> 0.1493824 | AS21: =J21 -> 0.133 | AT21: =AS21*AB21/100 -> 0.133266 | AU21: =AT21*AC21/100 -> 0.13481189 | AV21: =AU21*AD21/100 -> 0.13613304 | AW21: =AV21*AE21/100 -> 0.13682732
... A23: Соленые и копченые деликатесные продукты из рыбы, кг | B23: =A23 -> Соленые и копченые деликатесные продукты из рыбы, кг | C23: =A23 -> Соленые и копченые деликатесные продукты из рыбы, кг | D23: =C23 -> Соленые и копченые деликатесные продукты из рыбы, кг | E23: =INDEX(БИПЦ_НДС!$D:$D,MATCH(Структура!A23,БИПЦ_НДС!$B:$B,0)) -> 20 | F23: Проды | G23: 1 | H23: 1 | I23: 0 | J23: =INDEX('2026'!$C:$C,MATCH(Структура!B23,'2026'!$B:$B,0)) -> 0.159 | K23: =INDEX('2025'!$C:$C,MATCH(Структура!C23,'2025'!$B:$B,0)) -> 0.147 | L23: 1 | M23: 1 | N23: =INDEX(MoM!B:B,MATCH(Структура!A23,MoM!J:J,0)) -> 1 | P23: =INDEX('ИПЦ raw'!AA:AA, MATCH(Структура!$D23,'ИПЦ raw'!$A:$A,0)) -> 101.2 | Q23: =INDEX('ИПЦ raw'!AB:AB, MATCH(Структура!$D23,'ИПЦ raw'!$A:$A,0)) -> 101.44 | R23: =INDEX('ИПЦ raw'!AC:AC, MATCH(Структура!$D23,'ИПЦ raw'!$A:$A,0)) -> 101.39 | S23: =INDEX('ИПЦ raw'!AD:AD, MATCH(Структура!$D23,'ИПЦ raw'!$A:$A,0)) -> 100.63 | T23: =INDEX('ИПЦ raw'!AE:AE, MATCH(Структура!$D23,'ИПЦ raw'!$A:$A,0)) -> 100.38 | U23: =INDEX('ИПЦ raw'!AF:AF, MATCH(Структура!$D23,'ИПЦ raw'!$A:$A,0)) -> 100.02 | V23: =INDEX('ИПЦ raw'!AG:AG, MATCH(Структура!$D23,'ИПЦ raw'!$A:$A,0)) -> 100.3 | W23: =INDEX('ИПЦ raw'!AH:AH, MATCH(Структура!$D23,'ИПЦ raw'!$A:$A,0)) -> 100.08 | X23: =INDEX('ИПЦ raw'!AI:AI, MATCH(Структура!$D23,'ИПЦ raw'!$A:$A,0)) -> 100.15 | Y23: =INDEX('ИПЦ raw'!AJ:AJ, MATCH(Структура!$D23,'ИПЦ raw'!$A:$A,0)) -> 100.05 | Z23: =INDEX('ИПЦ raw'!AK:AK, MATCH(Структура!$D23,'ИПЦ raw'!$A:$A,0)) -> 99.79 | AA23: =INDEX('ИПЦ raw'!AL:AL, MATCH(Структура!$D23,'ИПЦ raw'!$A:$A,0)) -> 99.85 | AB23: =INDEX('ИПЦ raw'!AM:AM, MATCH(Структура!$D23,'ИПЦ raw'!$A:$A,0)) -> 100.38 | AC23: =INDEX('ИПЦ raw'!AN:AN, MATCH(Структура!$D23,'ИПЦ raw'!$A:$A,0)) -> 100.21 | AD23: =INDEX('ИПЦ raw'!AO:AO, MATCH(Структура!$D23,'ИПЦ raw'!$A:$A,0)) -> 99.98 | AE23: =INDEX('ИПЦ raw'!AP:AP, MATCH(Структура!$D23,'ИПЦ raw'!$A:$A,0)) -> 100.6 | AG23: =INDEX('2025'!$C:$C,MATCH(Структура!C23,'2025'!$B:$B,0)) -> 0.147 | AH23: =AG23*P23/100 -> 0.148764 | AI23: =AH23*Q23/100 -> 0.1509062 | AJ23: =AI23*R23/100 -> 0.1530038 | AK23: =AJ23*S23/100 -> 0.15396772 | AL23: =AK23*T23/100 -> 0.1545528 | AM23: =AL23*U23/100 -> 0.15458371 | AN23: =AM23*V23/100 -> 0.15504746 | AO23: =AN23*W23/100 -> 0.1551715 | ... AR23: =AQ23*Z23/100 -> 0.15515545 | AS23: =J23 -> 0.159 | AT23: =AS23*AB23/100 -> 0.1596042 | AU23: =AT23*AC23/100 -> 0.15993937 | AV23: =AU23*AD23/100 -> 0.15990738 | AW23: =AV23*AE23/100 -> 0.16086683
A24: Икра лососевых рыб отечественная, кг | B24: =A24 -> Икра лососевых рыб отечественная, кг | C24: Икра лососевых рыб, отечественная, кг | D24: Икра лососевых рыб отечественная, кг | E24: =INDEX(БИПЦ_НДС!$D:$D,MATCH(Структура!A24,БИПЦ_НДС!$B:$B,0)) -> 20 | F24: Проды | G24: 1 | H24: 1 | I24: 0 | J24: =INDEX('2026'!$C:$C,MATCH(Структура!B24,'2026'!$B:$B,0)) -> 0.161 | K24: =INDEX('2025'!$C:$C,MATCH(Структура!C24,'2025'!$B:$B,0)) -> 0.142 | L24: 1 | M24: 1 | N24: =INDEX(MoM!B:B,MATCH(Структура!A24,MoM!J:J,0)) -> 1 | P24: =INDEX('ИПЦ raw'!AA:AA, MATCH(Структура!$D24,'ИПЦ raw'!$A:$A,0)) -> 100.92 | Q24: =INDEX('ИПЦ raw'!AB:AB, MATCH(Структура!$D24,'ИПЦ raw'!$A:$A,0)) -> 100.08 | R24: =INDEX('ИПЦ raw'!AC:AC, MATCH(Структура!$D24,'ИПЦ raw'!$A:$A,0)) -> 100.63 | S24: =INDEX('ИПЦ raw'!AD:AD, MATCH(Структура!$D24,'ИПЦ raw'!$A:$A,0)) -> 100.14 | T24: =INDEX('ИПЦ raw'!AE:AE, MATCH(Структура!$D24,'ИПЦ raw'!$A:$A,0)) -> 100.08 | U24: =INDEX('ИПЦ raw'!AF:AF, MATCH(Структура!$D24,'ИПЦ raw'!$A:$A,0)) -> 99.64 | V24: =INDEX('ИПЦ raw'!AG:AG, MATCH(Структура!$D24,'ИПЦ raw'!$A:$A,0)) -> 100.4 | W24: =INDEX('ИПЦ raw'!AH:AH, MATCH(Структура!$D24,'ИПЦ raw'!$A:$A,0)) -> 99.14 | X24: =INDEX('ИПЦ raw'!AI:AI, MATCH(Структура!$D24,'ИПЦ raw'!$A:$A,0)) -> 98.77 | Y24: =INDEX('ИПЦ raw'!AJ:AJ, MATCH(Структура!$D24,'ИПЦ raw'!$A:$A,0)) -> 98.87 | Z24: =INDEX('ИПЦ raw'!AK:AK, MATCH(Структура!$D24,'ИПЦ raw'!$A:$A,0)) -> 100.04 | AA24: =INDEX('ИПЦ raw'!AL:AL, MATCH(Структура!$D24,'ИПЦ raw'!$A:$A,0)) -> 99.52 | AB24: =INDEX('ИПЦ raw'!AM:AM, MATCH(Структура!$D24,'ИПЦ raw'!$A:$A,0)) -> 100.1 | AC24: =INDEX('ИПЦ raw'!AN:AN, MATCH(Структура!$D24,'ИПЦ raw'!$A:$A,0)) -> 99.78 | AD24: =INDEX('ИПЦ raw'!AO:AO, MATCH(Структура!$D24,'ИПЦ raw'!$A:$A,0)) -> 100.24 | AE24: =INDEX('ИПЦ raw'!AP:AP, MATCH(Структура!$D24,'ИПЦ raw'!$A:$A,0)) -> 99.81 | AG24: =INDEX('2025'!$C:$C,MATCH(Структура!C24,'2025'!$B:$B,0)) -> 0.142 | AH24: =AG24*P24/100 -> 0.1433064 | AI24: =AH24*Q24/100 -> 0.14342105 | AJ24: =AI24*R24/100 -> 0.1443246 | AK24: =AJ24*S24/100 -> 0.14452665 | AL24: =AK24*T24/100 -> 0.14464227 | AM24: =AL24*U24/100 -> 0.14412156 | AN24: =AM24*V24/100 -> 0.14469805 | AO24: =AN24*W24/100 -> 0.14345364 | ... AR24: =AQ24*Z24/100 -> 0.14014411 | AS24: =J24 -> 0.161 | AT24: =AS24*AB24/100 -> 0.161161 | AU24: =AT24*AC24/100 -> 0.16080645 | AV24: =AU24*AD24/100 -> 0.16119238 | AW24: =AV24*AE24/100 -> 0.16088612
A25: Рыба мороженая разделанная (кроме лососевых пород), кг | B25: =A25 -> Рыба мороженая разделанная (кроме лососевых пород), кг | C25: =A25 -> Рыба мороженая разделанная (кроме лососевых пород), кг | D25: =C25 -> Рыба мороженая разделанная (кроме лососевых пород), кг | E25: =INDEX(БИПЦ_НДС!$D:$D,MATCH(Структура!A25,БИПЦ_НДС!$B:$B,0)) -> 10 | F25: Проды | G25: 1 | H25: 1 | I25: 0 | J25: =INDEX('2026'!$C:$C,MATCH(Структура!B25,'2026'!$B:$B,0)) -> 0.438 | K25: =INDEX('2025'!$C:$C,MATCH(Структура!C25,'2025'!$B:$B,0)) -> 0.413 | L25: 1 | M25: 1 | N25: =INDEX(MoM!B:B,MATCH(Структура!A25,MoM!J:J,0)) -> 1 | P25: =INDEX('ИПЦ raw'!AA:AA, MATCH(Структура!$D25,'ИПЦ raw'!$A:$A,0)) -> 102.41 | Q25: =INDEX('ИПЦ raw'!AB:AB, MATCH(Структура!$D25,'ИПЦ raw'!$A:$A,0)) -> 103.24 | R25: =INDEX('ИПЦ raw'!AC:AC, MATCH(Структура!$D25,'ИПЦ raw'!$A:$A,0)) -> 102.44 | S25: =INDEX('ИПЦ raw'!AD:AD, MATCH(Структура!$D25,'ИПЦ raw'!$A:$A,0)) -> 101.49 | T25: =INDEX('ИПЦ raw'!AE:AE, MATCH(Структура!$D25,'ИПЦ raw'!$A:$A,0)) -> 100.75 | U25: =INDEX('ИПЦ raw'!AF:AF, MATCH(Структура!$D25,'ИПЦ raw'!$A:$A,0)) -> 100.82 | V25: =INDEX('ИПЦ raw'!AG:AG, MATCH(Структура!$D25,'ИПЦ raw'!$A:$A,0)) -> 100.15 | W25: =INDEX('ИПЦ raw'!AH:AH, MATCH(Структура!$D25,'ИПЦ raw'!$A:$A,0)) -> 100.3 | X25: =INDEX('ИПЦ raw'!AI:AI, MATCH(Структура!$D25,'ИПЦ raw'!$A:$A,0)) -> 100.62 | Y25: =INDEX('ИПЦ raw'!AJ:AJ, MATCH(Структура!$D25,'ИПЦ raw'!$A:$A,0)) -> 100.32 | Z25: =INDEX('ИПЦ raw'!AK:AK, MATCH(Структура!$D25,'ИПЦ raw'!$A:$A,0)) -> 100.91 | AA25: =INDEX('ИПЦ raw'!AL:AL, MATCH(Структура!$D25,'ИПЦ raw'!$A:$A,0)) -> 100.46 | AB25: =INDEX('ИПЦ raw'!AM:AM, MATCH(Структура!$D25,'ИПЦ raw'!$A:$A,0)) -> 100.82 | AC25: =INDEX('ИПЦ raw'!AN:AN, MATCH(Структура!$D25,'ИПЦ raw'!$A:$A,0)) -> 100.5 | AD25: =INDEX('ИПЦ raw'!AO:AO, MATCH(Структура!$D25,'ИПЦ raw'!$A:$A,0)) -> 100.63 | AE25: =INDEX('ИПЦ raw'!AP:AP, MATCH(Структура!$D25,'ИПЦ raw'!$A:$A,0)) -> 101.15 | AG25: =INDEX('2025'!$C:$C,MATCH(Структура!C25,'2025'!$B:$B,0)) -> 0.413 | AH25: =AG25*P25/100 -> 0.4229533 | AI25: =AH25*Q25/100 -> 0.43665699 | AJ25: =AI25*R25/100 -> 0.44731142 | AK25: =AJ25*S25/100 -> 0.45397636 | AL25: =AK25*T25/100 -> 0.45738118 | AM25: =AL25*U25/100 -> 0.46113171 | AN25: =AM25*V25/100 -> 0.4618234 | AO25: =AN25*W25/100 -> 0.46320887 | ... AR25: =AQ25*Z25/100 -> 0.47182713 | AS25: =J25 -> 0.438 | AT25: =AS25*AB25/100 -> 0.4415916 | AU25: =AT25*AC25/100 -> 0.44379956 | AV25: =AU25*AD25/100 -> 0.4465955 | AW25: =AV25*AE25/100 -> 0.45173134
A26: Рыба охлажденная и мороженая разделанная лососевых пород, кг | B26: =A26 -> Рыба охлажденная и мороженая разделанная лососевых пород, кг | C26: =A26 -> Рыба охлажденная и мороженая разделанная лососевых пород, кг | D26: =C26 -> Рыба охлажденная и мороженая разделанная лососевых пород, кг | E26: =INDEX(БИПЦ_НДС!$D:$D,MATCH(Структура!A26,БИПЦ_НДС!$B:$B,0)) -> 20 | F26: Проды | G26: 1 | H26: 1 | I26: 0 | J26: =INDEX('2026'!$C:$C,MATCH(Структура!B26,'2026'!$B:$B,0)) -> 0.117 | K26: =INDEX('2025'!$C:$C,MATCH(Структура!C26,'2025'!$B:$B,0)) -> 0.115 | L26: 1 | M26: 1 | N26: =INDEX(MoM!B:B,MATCH(Структура!A26,MoM!J:J,0)) -> 1 | P26: =INDEX('ИПЦ raw'!AA:AA, MATCH(Структура!$D26,'ИПЦ raw'!$A:$A,0)) -> 102.05 | Q26: =INDEX('ИПЦ raw'!AB:AB, MATCH(Структура!$D26,'ИПЦ raw'!$A:$A,0)) -> 101.03 | R26: =INDEX('ИПЦ raw'!AC:AC, MATCH(Структура!$D26,'ИПЦ raw'!$A:$A,0)) -> 101.33 | S26: =INDEX('ИПЦ raw'!AD:AD, MATCH(Структура!$D26,'ИПЦ raw'!$A:$A,0)) -> 101.11 | T26: =INDEX('ИПЦ raw'!AE:AE, MATCH(Структура!$D26,'ИПЦ raw'!$A:$A,0)) -> 99.95 | U26: =INDEX('ИПЦ raw'!AF:AF, MATCH(Структура!$D26,'ИПЦ raw'!$A:$A,0)) -> 99.85 | V26: =INDEX('ИПЦ raw'!AG:AG, MATCH(Структура!$D26,'ИПЦ raw'!$A:$A,0)) -> 99.77 | W26: =INDEX('ИПЦ raw'!AH:AH, MATCH(Структура!$D26,'ИПЦ raw'!$A:$A,0)) -> 100.05 | X26: =INDEX('ИПЦ raw'!AI:AI, MATCH(Структура!$D26,'ИПЦ raw'!$A:$A,0)) -> 100.19 | Y26: =INDEX('ИПЦ raw'!AJ:AJ, MATCH(Структура!$D26,'ИПЦ raw'!$A:$A,0)) -> 100.23 | Z26: =INDEX('ИПЦ raw'!AK:AK, MATCH(Структура!$D26,'ИПЦ raw'!$A:$A,0)) -> 99.96 | AA26: =INDEX('ИПЦ raw'!AL:AL, MATCH(Структура!$D26,'ИПЦ raw'!$A:$A,0)) -> 100.19 | AB26: =INDEX('ИПЦ raw'!AM:AM, MATCH(Структура!$D26,'ИПЦ raw'!$A:$A,0)) -> 100.56 | AC26: =INDEX('ИПЦ raw'!AN:AN, MATCH(Структура!$D26,'ИПЦ raw'!$A:$A,0)) -> 99.93 | AD26: =INDEX('ИПЦ raw'!AO:AO, MATCH(Структура!$D26,'ИПЦ raw'!$A:$A,0)) -> 100.57 | AE26: =INDEX('ИПЦ raw'!AP:AP, MATCH(Структура!$D26,'ИПЦ raw'!$A:$A,0)) -> 99.89 | AG26: =INDEX('2025'!$C:$C,MATCH(Структура!C26,'2025'!$B:$B,0)) -> 0.115 | AH26: =AG26*P26/100 -> 0.1173575 | AI26: =AH26*Q26/100 -> 0.11856628 | AJ26: =AI26*R26/100 -> 0.12014321 | AK26: =AJ26*S26/100 -> 0.1214768 | AL26: =AK26*T26/100 -> 0.12141607 | AM26: =AL26*U26/100 -> 0.12123394 | AN26: =AM26*V26/100 -> 0.1209551 | AO26: =AN26*W26/100 -> 0.12101558 | ... AR26: =AQ26*Z26/100 -> 0.12147576 | AS26: =J26 -> 0.117 | AT26: =AS26*AB26/100 -> 0.1176552 | AU26: =AT26*AC26/100 -> 0.11757284 | AV26: =AU26*AD26/100 -> 0.11824301 | AW26: =AV26*AE26/100 -> 0.11811294
A27: Рыба мороженая неразделанная, кг | B27: =A27 -> Рыба мороженая неразделанная, кг | C27: =A27 -> Рыба мороженая неразделанная, кг | D27: =C27 -> Рыба мороженая неразделанная, кг | E27: =INDEX(БИПЦ_НДС!$D:$D,MATCH(Структура!A27,БИПЦ_НДС!$B:$B,0)) -> 10 | F27: Проды | G27: 1 | H27: 1 | I27: 0 | J27: =INDEX('2026'!$C:$C,MATCH(Структура!B27,'2026'!$B:$B,0)) -> 0.276 | K27: =INDEX('2025'!$C:$C,MATCH(Структура!C27,'2025'!$B:$B,0)) -> 0.262 | L27: 1 | M27: 1 | N27: =INDEX(MoM!B:B,MATCH(Структура!A27,MoM!J:J,0)) -> 1 | P27: =INDEX('ИПЦ raw'!AA:AA, MATCH(Структура!$D27,'ИПЦ raw'!$A:$A,0)) -> 102.52 | Q27: =INDEX('ИПЦ raw'!AB:AB, MATCH(Структура!$D27,'ИПЦ raw'!$A:$A,0)) -> 103.23 | R27: =INDEX('ИПЦ raw'!AC:AC, MATCH(Структура!$D27,'ИПЦ raw'!$A:$A,0)) -> 103 | S27: =INDEX('ИПЦ raw'!AD:AD, MATCH(Структура!$D27,'ИПЦ raw'!$A:$A,0)) -> 101.24 | T27: =INDEX('ИПЦ raw'!AE:AE, MATCH(Структура!$D27,'ИПЦ raw'!$A:$A,0)) -> 101.34 | U27: =INDEX('ИПЦ raw'!AF:AF, MATCH(Структура!$D27,'ИПЦ raw'!$A:$A,0)) -> 101.12 | V27: =INDEX('ИПЦ raw'!AG:AG, MATCH(Структура!$D27,'ИПЦ raw'!$A:$A,0)) -> 100.63 | W27: =INDEX('ИПЦ raw'!AH:AH, MATCH(Структура!$D27,'ИПЦ raw'!$A:$A,0)) -> 100.63 | X27: =INDEX('ИПЦ raw'!AI:AI, MATCH(Структура!$D27,'ИПЦ raw'!$A:$A,0)) -> 100.34 | Y27: =INDEX('ИПЦ raw'!AJ:AJ, MATCH(Структура!$D27,'ИПЦ raw'!$A:$A,0)) -> 100.68 | Z27: =INDEX('ИПЦ raw'!AK:AK, MATCH(Структура!$D27,'ИПЦ raw'!$A:$A,0)) -> 100.53 | AA27: =INDEX('ИПЦ raw'!AL:AL, MATCH(Структура!$D27,'ИПЦ raw'!$A:$A,0)) -> 100.59 | AB27: =INDEX('ИПЦ raw'!AM:AM, MATCH(Структура!$D27,'ИПЦ raw'!$A:$A,0)) -> 101.26 | AC27: =INDEX('ИПЦ raw'!AN:AN, MATCH(Структура!$D27,'ИПЦ raw'!$A:$A,0)) -> 101.13 | AD27: =INDEX('ИПЦ raw'!AO:AO, MATCH(Структура!$D27,'ИПЦ raw'!$A:$A,0)) -> 101.22 | AE27: =INDEX('ИПЦ raw'!AP:AP, MATCH(Структура!$D27,'ИПЦ raw'!$A:$A,0)) -> 101.46 | AG27: =INDEX('2025'!$C:$C,MATCH(Структура!C27,'2025'!$B:$B,0)) -> 0.262 | AH27: =AG27*P27/100 -> 0.2686024 | AI27: =AH27*Q27/100 -> 0.27727826 | AJ27: =AI27*R27/100 -> 0.28559661 | AK27: =AJ27*S27/100 -> 0.289138 | AL27: =AK27*T27/100 -> 0.29301245 | AM27: =AL27*U27/100 -> 0.29629419 | AN27: =AM27*V27/100 -> 0.29816085 | AO27: =AN27*W27/100 -> 0.30003926 | ... AR27: =AQ27*Z27/100 -> 0.30471306 | AS27: =J27 -> 0.276 | AT27: =AS27*AB27/100 -> 0.2794776 | AU27: =AT27*AC27/100 -> 0.2826357 | AV27: =AU27*AD27/100 -> 0.28608385 | AW27: =AV27*AE27/100 -> 0.29026068
A28: Филе рыбное, кг | B28: =A28 -> Филе рыбное, кг | C28: =A28 -> Филе рыбное, кг | D28: =C28 -> Филе рыбное, кг | E28: =INDEX(БИПЦ_НДС!$D:$D,MATCH(Структура!A28,БИПЦ_НДС!$B:$B,0)) -> 10 | F28: Проды | G28: 1 | H28: 1 | I28: 0 | J28: =INDEX('2026'!$C:$C,MATCH(Структура!B28,'2026'!$B:$B,0)) -> 0.261 | K28: =INDEX('2025'!$C:$C,MATCH(Структура!C28,'2025'!$B:$B,0)) -> 0.245 | L28: 1 | M28: 1 | N28: =INDEX(MoM!B:B,MATCH(Структура!A28,MoM!J:J,0)) -> 1 | P28: =INDEX('ИПЦ raw'!AA:AA, MATCH(Структура!$D28,'ИПЦ raw'!$A:$A,0)) -> 101.93 | Q28: =INDEX('ИПЦ raw'!AB:AB, MATCH(Структура!$D28,'ИПЦ raw'!$A:$A,0)) -> 102.26 | R28: =INDEX('ИПЦ raw'!AC:AC, MATCH(Структура!$D28,'ИПЦ raw'!$A:$A,0)) -> 101.62 | S28: =INDEX('ИПЦ raw'!AD:AD, MATCH(Структура!$D28,'ИПЦ raw'!$A:$A,0)) -> 101.42 | T28: =INDEX('ИПЦ raw'!AE:AE, MATCH(Структура!$D28,'ИПЦ raw'!$A:$A,0)) -> 100.81 | U28: =INDEX('ИПЦ raw'!AF:AF, MATCH(Структура!$D28,'ИПЦ raw'!$A:$A,0)) -> 100.59 | V28: =INDEX('ИПЦ raw'!AG:AG, MATCH(Структура!$D28,'ИПЦ raw'!$A:$A,0)) -> 100.55 | W28: =INDEX('ИПЦ raw'!AH:AH, MATCH(Структура!$D28,'ИПЦ raw'!$A:$A,0)) -> 100.45 | X28: =INDEX('ИПЦ raw'!AI:AI, MATCH(Структура!$D28,'ИПЦ raw'!$A:$A,0)) -> 100.01 | Y28: =INDEX('ИПЦ raw'!AJ:AJ, MATCH(Структура!$D28,'ИПЦ raw'!$A:$A,0)) -> 100.07 | Z28: =INDEX('ИПЦ raw'!AK:AK, MATCH(Структура!$D28,'ИПЦ raw'!$A:$A,0)) -> 99.72 | AA28: =INDEX('ИПЦ raw'!AL:AL, MATCH(Структура!$D28,'ИПЦ raw'!$A:$A,0)) -> 100.25 | AB28: =INDEX('ИПЦ raw'!AM:AM, MATCH(Структура!$D28,'ИПЦ raw'!$A:$A,0)) -> 100.02 | AC28: =INDEX('ИПЦ raw'!AN:AN, MATCH(Структура!$D28,'ИПЦ raw'!$A:$A,0)) -> 100.06 | AD28: =INDEX('ИПЦ raw'!AO:AO, MATCH(Структура!$D28,'ИПЦ raw'!$A:$A,0)) -> 99.74 | AE28: =INDEX('ИПЦ raw'!AP:AP, MATCH(Структура!$D28,'ИПЦ raw'!$A:$A,0)) -> 100.47 | AG28: =INDEX('2025'!$C:$C,MATCH(Структура!C28,'2025'!$B:$B,0)) -> 0.245 | AH28: =AG28*P28/100 -> 0.2497285 | AI28: =AH28*Q28/100 -> 0.25537236 | AJ28: =AI28*R28/100 -> 0.2595094 | AK28: =AJ28*S28/100 -> 0.26319443 | AL28: =AK28*T28/100 -> 0.2653263 | AM28: =AL28*U28/100 -> 0.26689173 | AN28: =AM28*V28/100 -> 0.26835963 | AO28: =AN28*W28/100 -> 0.26956725 | ... AR28: =AQ28*Z28/100 -> 0.26902753 | AS28: =J28 -> 0.261 | AT28: =AS28*AB28/100 -> 0.2610522 | AU28: =AT28*AC28/100 -> 0.26120883 | AV28: =AU28*AD28/100 -> 0.26052969 | AW28: =AV28*AE28/100 -> 0.26175418
A29: Креветки мороженые, неразделанные, кг | B29: =A29 -> Креветки мороженые, неразделанные, кг | C29: Креветки мороженые неразделанные, кг | D29: Креветки мороженые, неразделанные, кг | E29: =INDEX(БИПЦ_НДС!$D:$D,MATCH(Структура!A29,БИПЦ_НДС!$B:$B,0)) -> 10 | F29: Проды | G29: 1 | H29: 1 | I29: 0 | J29: =INDEX('2026'!$C:$C,MATCH(Структура!B29,'2026'!$B:$B,0)) -> 0.126 | K29: =INDEX('2025'!$C:$C,MATCH(Структура!C29,'2025'!$B:$B,0)) -> 0.12 | L29: 1 | M29: 1 | N29: =INDEX(MoM!B:B,MATCH(Структура!A29,MoM!J:J,0)) -> 1 | P29: =INDEX('ИПЦ raw'!AA:AA, MATCH(Структура!$D29,'ИПЦ raw'!$A:$A,0)) -> 100.69 | Q29: =INDEX('ИПЦ raw'!AB:AB, MATCH(Структура!$D29,'ИПЦ raw'!$A:$A,0)) -> 100.19 | R29: =INDEX('ИПЦ raw'!AC:AC, MATCH(Структура!$D29,'ИПЦ raw'!$A:$A,0)) -> 100.34 | S29: =INDEX('ИПЦ raw'!AD:AD, MATCH(Структура!$D29,'ИПЦ raw'!$A:$A,0)) -> 100.46 | T29: =INDEX('ИПЦ raw'!AE:AE, MATCH(Структура!$D29,'ИПЦ raw'!$A:$A,0)) -> 100.33 | U29: =INDEX('ИПЦ raw'!AF:AF, MATCH(Структура!$D29,'ИПЦ raw'!$A:$A,0)) -> 100 | V29: =INDEX('ИПЦ raw'!AG:AG, MATCH(Структура!$D29,'ИПЦ raw'!$A:$A,0)) -> 99.72 | W29: =INDEX('ИПЦ raw'!AH:AH, MATCH(Структура!$D29,'ИПЦ raw'!$A:$A,0)) -> 100.25 | X29: =INDEX('ИПЦ raw'!AI:AI, MATCH(Структура!$D29,'ИПЦ raw'!$A:$A,0)) -> 99.88 | Y29: =INDEX('ИПЦ raw'!AJ:AJ, MATCH(Структура!$D29,'ИПЦ raw'!$A:$A,0)) -> 100.59 | Z29: =INDEX('ИПЦ raw'!AK:AK, MATCH(Структура!$D29,'ИПЦ raw'!$A:$A,0)) -> 99.63 | AA29: =INDEX('ИПЦ raw'!AL:AL, MATCH(Структура!$D29,'ИПЦ raw'!$A:$A,0)) -> 99.78 | AB29: =INDEX('ИПЦ raw'!AM:AM, MATCH(Структура!$D29,'ИПЦ raw'!$A:$A,0)) -> 100.09 | AC29: =INDEX('ИПЦ raw'!AN:AN, MATCH(Структура!$D29,'ИПЦ raw'!$A:$A,0)) -> 99.86 | AD29: =INDEX('ИПЦ raw'!AO:AO, MATCH(Структура!$D29,'ИПЦ raw'!$A:$A,0)) -> 99.68 | AE29: =INDEX('ИПЦ raw'!AP:AP, MATCH(Структура!$D29,'ИПЦ raw'!$A:$A,0)) -> 99.72 | AG29: =INDEX('2025'!$C:$C,MATCH(Структура!C29,'2025'!$B:$B,0)) -> 0.12 | AH29: =AG29*P29/100 -> 0.120828 | AI29: =AH29*Q29/100 -> 0.12105757 | AJ29: =AI29*R29/100 -> 0.12146917 | AK29: =AJ29*S29/100 -> 0.12202793 | AL29: =AK29*T29/100 -> 0.12243062 | AM29: =AL29*U29/100 -> 0.12243062 | AN29: =AM29*V29/100 -> 0.12208781 | AO29: =AN29*W29/100 -> 0.12239303 | ... AR29: =AQ29*Z29/100 -> 0.12251243 | AS29: =J29 -> 0.126 | AT29: =AS29*AB29/100 -> 0.1261134 | AU29: =AT29*AC29/100 -> 0.12593684 | AV29: =AU29*AD29/100 -> 0.12553384 | AW29: =AV29*AE29/100 -> 0.12518235
A30: Кальмары мороженые, кг | B30: =A30 -> Кальмары мороженые, кг | C30: Кальмары мороженые,кг | D30: Кальмары мороженые, кг | E30: =INDEX(БИПЦ_НДС!$D:$D,MATCH(Структура!A30,БИПЦ_НДС!$B:$B,0)) -> 10 | F30: Проды | G30: 1 | H30: 1 | I30: 0 | J30: =INDEX('2026'!$C:$C,MATCH(Структура!B30,'2026'!$B:$B,0)) -> 0.093 | K30: =INDEX('2025'!$C:$C,MATCH(Структура!C30,'2025'!$B:$B,0)) -> 0.087 | L30: 1 | M30: 1 | N30: =INDEX(MoM!B:B,MATCH(Структура!A30,MoM!J:J,0)) -> 1 | P30: =INDEX('ИПЦ raw'!AA:AA, MATCH(Структура!$D30,'ИПЦ raw'!$A:$A,0)) -> 101.44 | Q30: =INDEX('ИПЦ raw'!AB:AB, MATCH(Структура!$D30,'ИПЦ raw'!$A:$A,0)) -> 101.93 | R30: =INDEX('ИПЦ raw'!AC:AC, MATCH(Структура!$D30,'ИПЦ raw'!$A:$A,0)) -> 101.14 | S30: =INDEX('ИПЦ raw'!AD:AD, MATCH(Структура!$D30,'ИПЦ raw'!$A:$A,0)) -> 102.53 | T30: =INDEX('ИПЦ raw'!AE:AE, MATCH(Структура!$D30,'ИПЦ raw'!$A:$A,0)) -> 102.38 | U30: =INDEX('ИПЦ raw'!AF:AF, MATCH(Структура!$D30,'ИПЦ raw'!$A:$A,0)) -> 102.06 | V30: =INDEX('ИПЦ raw'!AG:AG, MATCH(Структура!$D30,'ИПЦ raw'!$A:$A,0)) -> 101.71 | W30: =INDEX('ИПЦ raw'!AH:AH, MATCH(Структура!$D30,'ИПЦ raw'!$A:$A,0)) -> 101.83 | X30: =INDEX('ИПЦ raw'!AI:AI, MATCH(Структура!$D30,'ИПЦ raw'!$A:$A,0)) -> 101.24 | Y30: =INDEX('ИПЦ raw'!AJ:AJ, MATCH(Структура!$D30,'ИПЦ raw'!$A:$A,0)) -> 100.17 | Z30: =INDEX('ИПЦ raw'!AK:AK, MATCH(Структура!$D30,'ИПЦ raw'!$A:$A,0)) -> 100.57 | AA30: =INDEX('ИПЦ raw'!AL:AL, MATCH(Структура!$D30,'ИПЦ raw'!$A:$A,0)) -> 99.87 | AB30: =INDEX('ИПЦ raw'!AM:AM, MATCH(Структура!$D30,'ИПЦ raw'!$A:$A,0)) -> 101.22 | AC30: =INDEX('ИПЦ raw'!AN:AN, MATCH(Структура!$D30,'ИПЦ raw'!$A:$A,0)) -> 100.98 | AD30: =INDEX('ИПЦ raw'!AO:AO, MATCH(Структура!$D30,'ИПЦ raw'!$A:$A,0)) -> 101.02 | AE30: =INDEX('ИПЦ raw'!AP:AP, MATCH(Структура!$D30,'ИПЦ raw'!$A:$A,0)) -> 101.45 | AG30: =INDEX('2025'!$C:$C,MATCH(Структура!C30,'2025'!$B:$B,0)) -> 0.087 | AH30: =AG30*P30/100 -> 0.0882528 | AI30: =AH30*Q30/100 -> 0.089956079 | AJ30: =AI30*R30/100 -> 0.090981578 | AK30: =AJ30*S30/100 -> 0.093283412 | AL30: =AK30*T30/100 -> 0.095503557 | AM30: =AL30*U30/100 -> 0.097470931 | AN30: =AM30*V30/100 -> 0.099137684 | AO30: =AN30*W30/100 -> 0.1009519 | ... AR30: =AQ30*Z30/100 -> 0.102961 | AS30: =J30 -> 0.093 | AT30: =AS30*AB30/100 -> 0.0941346 | AU30: =AT30*AC30/100 -> 0.095057119 | AV30: =AU30*AD30/100 -> 0.096026702 | AW30: =AV30*AE30/100 -> 0.097419089
A31: Сельдь соленая, кг | B31: =A31 -> Сельдь соленая, кг | C31: =A31 -> Сельдь соленая, кг | D31: =C31 -> Сельдь соленая, кг | E31: =INDEX(БИПЦ_НДС!$D:$D,MATCH(Структура!A31,БИПЦ_НДС!$B:$B,0)) -> 10 | F31: Проды | G31: 1 | H31: 1 | I31: 0 | J31: =INDEX('2026'!$C:$C,MATCH(Структура!B31,'2026'!$B:$B,0)) -> 0.119 | K31: =INDEX('2025'!$C:$C,MATCH(Структура!C31,'2025'!$B:$B,0)) -> 0.127 | L31: 1 | M31: 1 | N31: =INDEX(MoM!B:B,MATCH(Структура!A31,MoM!J:J,0)) -> 1 | P31: =INDEX('ИПЦ raw'!AA:AA, MATCH(Структура!$D31,'ИПЦ raw'!$A:$A,0)) -> 103.51 | Q31: =INDEX('ИПЦ raw'!AB:AB, MATCH(Структура!$D31,'ИПЦ raw'!$A:$A,0)) -> 102.02 | R31: =INDEX('ИПЦ raw'!AC:AC, MATCH(Структура!$D31,'ИПЦ raw'!$A:$A,0)) -> 101.36 | S31: =INDEX('ИПЦ raw'!AD:AD, MATCH(Структура!$D31,'ИПЦ raw'!$A:$A,0)) -> 101.48 | T31: =INDEX('ИПЦ raw'!AE:AE, MATCH(Структура!$D31,'ИПЦ raw'!$A:$A,0)) -> 101 | U31: =INDEX('ИПЦ raw'!AF:AF, MATCH(Структура!$D31,'ИПЦ raw'!$A:$A,0)) -> 100.51 | V31: =INDEX('ИПЦ raw'!AG:AG, MATCH(Структура!$D31,'ИПЦ raw'!$A:$A,0)) -> 100.7 | W31: =INDEX('ИПЦ raw'!AH:AH, MATCH(Структура!$D31,'ИПЦ raw'!$A:$A,0)) -> 100.32 | X31: =INDEX('ИПЦ raw'!AI:AI, MATCH(Структура!$D31,'ИПЦ raw'!$A:$A,0)) -> 100.3 | Y31: =INDEX('ИПЦ raw'!AJ:AJ, MATCH(Структура!$D31,'ИПЦ raw'!$A:$A,0)) -> 100.53 | Z31: =INDEX('ИПЦ raw'!AK:AK, MATCH(Структура!$D31,'ИПЦ raw'!$A:$A,0)) -> 100.39 | AA31: =INDEX('ИПЦ raw'!AL:AL, MATCH(Структура!$D31,'ИПЦ raw'!$A:$A,0)) -> 99.86 | AB31: =INDEX('ИПЦ raw'!AM:AM, MATCH(Структура!$D31,'ИПЦ raw'!$A:$A,0)) -> 100.7 | AC31: =INDEX('ИПЦ raw'!AN:AN, MATCH(Структура!$D31,'ИПЦ raw'!$A:$A,0)) -> 100.35 | AD31: =INDEX('ИПЦ raw'!AO:AO, MATCH(Структура!$D31,'ИПЦ raw'!$A:$A,0)) -> 100.13 | AE31: =INDEX('ИПЦ raw'!AP:AP, MATCH(Структура!$D31,'ИПЦ raw'!$A:$A,0)) -> 99.97 | AG31: =INDEX('2025'!$C:$C,MATCH(Структура!C31,'2025'!$B:$B,0)) -> 0.127 | AH31: =AG31*P31/100 -> 0.1314577 | AI31: =AH31*Q31/100 -> 0.13411315 | AJ31: =AI31*R31/100 -> 0.13593708 | AK31: =AJ31*S31/100 -> 0.13794895 | AL31: =AK31*T31/100 -> 0.13932844 | AM31: =AL31*U31/100 -> 0.14003902 | AN31: =AM31*V31/100 -> 0.14101929 | AO31: =AN31*W31/100 -> 0.14147055 | ... AR31: =AQ31*Z31/100 -> 0.14320333 | AS31: =J31 -> 0.119 | AT31: =AS31*AB31/100 -> 0.119833 | AU31: =AT31*AC31/100 -> 0.12025242 | AV31: =AU31*AD31/100 -> 0.12040874 | AW31: =AV31*AE31/100 -> 0.12037262
A32: Филе сельди соленое, кг | B32: =A32 -> Филе сельди соленое, кг | C32: =A32 -> Филе сельди соленое, кг | D32: =C32 -> Филе сельди соленое, кг | E32: =INDEX(БИПЦ_НДС!$D:$D,MATCH(Структура!A32,БИПЦ_НДС!$B:$B,0)) -> 10 | F32: Проды | G32: 1 | H32: 1 | I32: 0 | J32: =INDEX('2026'!$C:$C,MATCH(Структура!B32,'2026'!$B:$B,0)) -> 0.088 | K32: =INDEX('2025'!$C:$C,MATCH(Структура!C32,'2025'!$B:$B,0)) -> 0.082 | L32: 1 | M32: 1 | N32: =INDEX(MoM!B:B,MATCH(Структура!A32,MoM!J:J,0)) -> 1 | P32: =INDEX('ИПЦ raw'!AA:AA, MATCH(Структура!$D32,'ИПЦ raw'!$A:$A,0)) -> 101.79 | Q32: =INDEX('ИПЦ raw'!AB:AB, MATCH(Структура!$D32,'ИПЦ raw'!$A:$A,0)) -> 101.11 | R32: =INDEX('ИПЦ raw'!AC:AC, MATCH(Структура!$D32,'ИПЦ raw'!$A:$A,0)) -> 101.25 | S32: =INDEX('ИПЦ raw'!AD:AD, MATCH(Структура!$D32,'ИПЦ raw'!$A:$A,0)) -> 100.67 | T32: =INDEX('ИПЦ raw'!AE:AE, MATCH(Структура!$D32,'ИПЦ raw'!$A:$A,0)) -> 100.83 | U32: =INDEX('ИПЦ raw'!AF:AF, MATCH(Структура!$D32,'ИПЦ raw'!$A:$A,0)) -> 100.83 | V32: =INDEX('ИПЦ raw'!AG:AG, MATCH(Структура!$D32,'ИПЦ raw'!$A:$A,0)) -> 100.21 | W32: =INDEX('ИПЦ raw'!AH:AH, MATCH(Структура!$D32,'ИПЦ raw'!$A:$A,0)) -> 100.15 | X32: =INDEX('ИПЦ raw'!AI:AI, MATCH(Структура!$D32,'ИПЦ raw'!$A:$A,0)) -> 99.58 | Y32: =INDEX('ИПЦ raw'!AJ:AJ, MATCH(Структура!$D32,'ИПЦ raw'!$A:$A,0)) -> 99.95 | Z32: =INDEX('ИПЦ raw'!AK:AK, MATCH(Структура!$D32,'ИПЦ raw'!$A:$A,0)) -> 100.15 | AA32: =INDEX('ИПЦ raw'!AL:AL, MATCH(Структура!$D32,'ИПЦ raw'!$A:$A,0)) -> 100.12 | AB32: =INDEX('ИПЦ raw'!AM:AM, MATCH(Структура!$D32,'ИПЦ raw'!$A:$A,0)) -> 100.49 | AC32: =INDEX('ИПЦ raw'!AN:AN, MATCH(Структура!$D32,'ИПЦ raw'!$A:$A,0)) -> 99.96 | AD32: =INDEX('ИПЦ raw'!AO:AO, MATCH(Структура!$D32,'ИПЦ raw'!$A:$A,0)) -> 99.66 | AE32: =INDEX('ИПЦ raw'!AP:AP, MATCH(Структура!$D32,'ИПЦ raw'!$A:$A,0)) -> 99.52 | AG32: =INDEX('2025'!$C:$C,MATCH(Структура!C32,'2025'!$B:$B,0)) -> 0.082 | AH32: =AG32*P32/100 -> 0.0834678 | AI32: =AH32*Q32/100 -> 0.084394293 | AJ32: =AI32*R32/100 -> 0.085449221 | AK32: =AJ32*S32/100 -> 0.086021731 | AL32: =AK32*T32/100 -> 0.086735711 | AM32: =AL32*U32/100 -> 0.087455618 | AN32: =AM32*V32/100 -> 0.087639275 | AO32: =AN32*W32/100 -> 0.087770734 | ... AR32: =AQ32*Z32/100 -> 0.087489433 | AS32: =J32 -> 0.088 | AT32: =AS32*AB32/100 -> 0.0884312 | AU32: =AT32*AC32/100 -> 0.088395828 | AV32: =AU32*AD32/100 -> 0.088095282 | AW32: =AV32*AE32/100 -> 0.087672424
A33: Консервы рыбные натуральные и с добавлением масла, кг | B33: =A33 -> Консервы рыбные натуральные и с добавлением масла, кг | C33: =A33 -> Консервы рыбные натуральные и с добавлением масла, кг | D33: =C33 -> Консервы рыбные натуральные и с добавлением масла, кг | E33: =INDEX(БИПЦ_НДС!$D:$D,MATCH(Структура!A33,БИПЦ_НДС!$B:$B,0)) -> 10 | F33: Проды | G33: 1 | H33: 1 | I33: 0 | J33: =INDEX('2026'!$C:$C,MATCH(Структура!B33,'2026'!$B:$B,0)) -> 0.228 | K33: =INDEX('2025'!$C:$C,MATCH(Структура!C33,'2025'!$B:$B,0)) -> 0.216 | L33: 1 | M33: 1 | N33: =INDEX(MoM!B:B,MATCH(Структура!A33,MoM!J:J,0)) -> 1 | P33: =INDEX('ИПЦ raw'!AA:AA, MATCH(Структура!$D33,'ИПЦ raw'!$A:$A,0)) -> 101.2 | Q33: =INDEX('ИПЦ raw'!AB:AB, MATCH(Структура!$D33,'ИПЦ raw'!$A:$A,0)) -> 101.84 | R33: =INDEX('ИПЦ raw'!AC:AC, MATCH(Структура!$D33,'ИПЦ raw'!$A:$A,0)) -> 101.22 | S33: =INDEX('ИПЦ raw'!AD:AD, MATCH(Структура!$D33,'ИПЦ raw'!$A:$A,0)) -> 100.96 | T33: =INDEX('ИПЦ raw'!AE:AE, MATCH(Структура!$D33,'ИПЦ raw'!$A:$A,0)) -> 100.94 | U33: =INDEX('ИПЦ raw'!AF:AF, MATCH(Структура!$D33,'ИПЦ raw'!$A:$A,0)) -> 100.59 | V33: =INDEX('ИПЦ raw'!AG:AG, MATCH(Структура!$D33,'ИПЦ raw'!$A:$A,0)) -> 100.97 | W33: =INDEX('ИПЦ raw'!AH:AH, MATCH(Структура!$D33,'ИПЦ raw'!$A:$A,0)) -> 100.53 | X33: =INDEX('ИПЦ raw'!AI:AI, MATCH(Структура!$D33,'ИПЦ raw'!$A:$A,0)) -> 100.45 | Y33: =INDEX('ИПЦ raw'!AJ:AJ, MATCH(Структура!$D33,'ИПЦ raw'!$A:$A,0)) -> 100.66 | Z33: =INDEX('ИПЦ raw'!AK:AK, MATCH(Структура!$D33,'ИПЦ raw'!$A:$A,0)) -> 100.22 | AA33: =INDEX('ИПЦ raw'!AL:AL, MATCH(Структура!$D33,'ИПЦ raw'!$A:$A,0)) -> 101.01 | AB33: =INDEX('ИПЦ raw'!AM:AM, MATCH(Структура!$D33,'ИПЦ raw'!$A:$A,0)) -> 100.52 | AC33: =INDEX('ИПЦ raw'!AN:AN, MATCH(Структура!$D33,'ИПЦ raw'!$A:$A,0)) -> 100.46 | AD33: =INDEX('ИПЦ raw'!AO:AO, MATCH(Структура!$D33,'ИПЦ raw'!$A:$A,0)) -> 100.84 | AE33: =INDEX('ИПЦ raw'!AP:AP, MATCH(Структура!$D33,'ИПЦ raw'!$A:$A,0)) -> 99.85 | AG33: =INDEX('2025'!$C:$C,MATCH(Структура!C33,'2025'!$B:$B,0)) -> 0.216 | AH33: =AG33*P33/100 -> 0.218592 | AI33: =AH33*Q33/100 -> 0.22261409 | AJ33: =AI33*R33/100 -> 0.22532998 | AK33: =AJ33*S33/100 -> 0.22749315 | AL33: =AK33*T33/100 -> 0.22963159 | AM33: =AL33*U33/100 -> 0.23098641 | AN33: =AM33*V33/100 -> 0.23322698 | AO33: =AN33*W33/100 -> 0.23446309 | ... AR33: =AQ33*Z33/100 -> 0.23759415 | AS33: =J33 -> 0.228 | AT33: =AS33*AB33/100 -> 0.2291856 | AU33: =AT33*AC33/100 -> 0.23023985 | AV33: =AU33*AD33/100 -> 0.23217387 | AW33: =AV33*AE33/100 -> 0.23182561
A34: Консервы рыбные в томатном соусе, кг | B34: =A34 -> Консервы рыбные в томатном соусе, кг | C34: =A34 -> Консервы рыбные в томатном соусе, кг | D34: =C34 -> Консервы рыбные в томатном соусе, кг | E34: =INDEX(БИПЦ_НДС!$D:$D,MATCH(Структура!A34,БИПЦ_НДС!$B:$B,0)) -> 10 | F34: Проды | G34: 1 | H34: 1 | I34: 0 | J34: =INDEX('2026'!$C:$C,MATCH(Структура!B34,'2026'!$B:$B,0)) -> 0.048 | K34: =INDEX('2025'!$C:$C,MATCH(Структура!C34,'2025'!$B:$B,0)) -> 0.046 | L34: 1 | M34: 1 | N34: =INDEX(MoM!B:B,MATCH(Структура!A34,MoM!J:J,0)) -> 1 | P34: =INDEX('ИПЦ raw'!AA:AA, MATCH(Структура!$D34,'ИПЦ raw'!$A:$A,0)) -> 101.49 | Q34: =INDEX('ИПЦ raw'!AB:AB, MATCH(Структура!$D34,'ИПЦ raw'!$A:$A,0)) -> 101.13 | R34: =INDEX('ИПЦ raw'!AC:AC, MATCH(Структура!$D34,'ИПЦ raw'!$A:$A,0)) -> 101.53 | S34: =INDEX('ИПЦ raw'!AD:AD, MATCH(Структура!$D34,'ИПЦ raw'!$A:$A,0)) -> 101.44 | T34: =INDEX('ИПЦ raw'!AE:AE, MATCH(Структура!$D34,'ИПЦ raw'!$A:$A,0)) -> 100.54 | U34: =INDEX('ИПЦ raw'!AF:AF, MATCH(Структура!$D34,'ИПЦ raw'!$A:$A,0)) -> 100.69 | V34: =INDEX('ИПЦ raw'!AG:AG, MATCH(Структура!$D34,'ИПЦ raw'!$A:$A,0)) -> 101.15 | W34: =INDEX('ИПЦ raw'!AH:AH, MATCH(Структура!$D34,'ИПЦ raw'!$A:$A,0)) -> 100.32 | X34: =INDEX('ИПЦ raw'!AI:AI, MATCH(Структура!$D34,'ИПЦ raw'!$A:$A,0)) -> 100.29 | Y34: =INDEX('ИПЦ raw'!AJ:AJ, MATCH(Структура!$D34,'ИПЦ raw'!$A:$A,0)) -> 101.12 | Z34: =INDEX('ИПЦ raw'!AK:AK, MATCH(Структура!$D34,'ИПЦ raw'!$A:$A,0)) -> 99.93 | AA34: =INDEX('ИПЦ raw'!AL:AL, MATCH(Структура!$D34,'ИПЦ raw'!$A:$A,0)) -> 100.99 | AB34: =INDEX('ИПЦ raw'!AM:AM, MATCH(Структура!$D34,'ИПЦ raw'!$A:$A,0)) -> 100.59 | AC34: =INDEX('ИПЦ raw'!AN:AN, MATCH(Структура!$D34,'ИПЦ raw'!$A:$A,0)) -> 100.32 | AD34: =INDEX('ИПЦ raw'!AO:AO, MATCH(Структура!$D34,'ИПЦ raw'!$A:$A,0)) -> 99.66 | AE34: =INDEX('ИПЦ raw'!AP:AP, MATCH(Структура!$D34,'ИПЦ raw'!$A:$A,0)) -> 100.13 | AG34: =INDEX('2025'!$C:$C,MATCH(Структура!C34,'2025'!$B:$B,0)) -> 0.046 | AH34: =AG34*P34/100 -> 0.0466854 | AI34: =AH34*Q34/100 -> 0.047212945 | AJ34: =AI34*R34/100 -> 0.047935303 | AK34: =AJ34*S34/100 -> 0.048625571 | AL34: =AK34*T34/100 -> 0.04888815 | AM34: =AL34*U34/100 -> 0.049225478 | AN34: =AM34*V34/100 -> 0.049791571 | AO34: =AN34*W34/100 -> 0.049950904 | ... AR34: =AQ34*Z34/100 -> 0.050621374 | AS34: =J34 -> 0.048 | AT34: =AS34*AB34/100 -> 0.0482832 | AU34: =AT34*AC34/100 -> 0.048437706 | AV34: =AU34*AD34/100 -> 0.048273018 | AW34: =AV34*AE34/100 -> 0.048335773
A35: Масло сливочное, кг | B35: =A35 -> Масло сливочное, кг | C35: =A35 -> Масло сливочное, кг | D35: =C35 -> Масло сливочное, кг | E35: =INDEX(БИПЦ_НДС!$D:$D,MATCH(Структура!A35,БИПЦ_НДС!$B:$B,0)) -> 10 | F35: Проды | G35: 1 | H35: 1 | I35: 0 | J35: =INDEX('2026'!$C:$C,MATCH(Структура!B35,'2026'!$B:$B,0)) -> 0.813 | K35: =INDEX('2025'!$C:$C,MATCH(Структура!C35,'2025'!$B:$B,0)) -> 0.853 | L35: 1 | M35: 1 | N35: =INDEX(MoM!B:B,MATCH(Структура!A35,MoM!J:J,0)) -> 1 | P35: =INDEX('ИПЦ raw'!AA:AA, MATCH(Структура!$D35,'ИПЦ raw'!$A:$A,0)) -> 101.25 | Q35: =INDEX('ИПЦ raw'!AB:AB, MATCH(Структура!$D35,'ИПЦ raw'!$A:$A,0)) -> 100.59 | R35: =INDEX('ИПЦ raw'!AC:AC, MATCH(Структура!$D35,'ИПЦ raw'!$A:$A,0)) -> 100.17 | S35: =INDEX('ИПЦ raw'!AD:AD, MATCH(Структура!$D35,'ИПЦ raw'!$A:$A,0)) -> 99.5 | T35: =INDEX('ИПЦ raw'!AE:AE, MATCH(Структура!$D35,'ИПЦ raw'!$A:$A,0)) -> 99.21 | U35: =INDEX('ИПЦ raw'!AF:AF, MATCH(Структура!$D35,'ИПЦ raw'!$A:$A,0)) -> 98.96 | V35: =INDEX('ИПЦ raw'!AG:AG, MATCH(Структура!$D35,'ИПЦ raw'!$A:$A,0)) -> 99.52 | W35: =INDEX('ИПЦ raw'!AH:AH, MATCH(Структура!$D35,'ИПЦ raw'!$A:$A,0)) -> 99.63 | X35: =INDEX('ИПЦ raw'!AI:AI, MATCH(Структура!$D35,'ИПЦ raw'!$A:$A,0)) -> 99.69 | Y35: =INDEX('ИПЦ raw'!AJ:AJ, MATCH(Структура!$D35,'ИПЦ raw'!$A:$A,0)) -> 99.86 | Z35: =INDEX('ИПЦ raw'!AK:AK, MATCH(Структура!$D35,'ИПЦ raw'!$A:$A,0)) -> 99.3 | AA35: =INDEX('ИПЦ raw'!AL:AL, MATCH(Структура!$D35,'ИПЦ raw'!$A:$A,0)) -> 99.29 | AB35: =INDEX('ИПЦ raw'!AM:AM, MATCH(Структура!$D35,'ИПЦ raw'!$A:$A,0)) -> 99.86 | AC35: =INDEX('ИПЦ raw'!AN:AN, MATCH(Структура!$D35,'ИПЦ raw'!$A:$A,0)) -> 98.63 | AD35: =INDEX('ИПЦ raw'!AO:AO, MATCH(Структура!$D35,'ИПЦ raw'!$A:$A,0)) -> 98.87 | AE35: =INDEX('ИПЦ raw'!AP:AP, MATCH(Структура!$D35,'ИПЦ raw'!$A:$A,0)) -> 99.1 | AG35: =INDEX('2025'!$C:$C,MATCH(Структура!C35,'2025'!$B:$B,0)) -> 0.853 | AH35: =AG35*P35/100 -> 0.8636625 | AI35: =AH35*Q35/100 -> 0.86875811 | AJ35: =AI35*R35/100 -> 0.870235 | AK35: =AJ35*S35/100 -> 0.86588382 | AL35: =AK35*T35/100 -> 0.85904334 | AM35: =AL35*U35/100 -> 0.85010929 | AN35: =AM35*V35/100 -> 0.84602877 | AO35: =AN35*W35/100 -> 0.84289846 | ... AR35: =AQ35*Z35/100 -> 0.83323531 | AS35: =J35 -> 0.813 | AT35: =AS35*AB35/100 -> 0.8118618 | AU35: =AT35*AC35/100 -> 0.80073929 | AV35: =AU35*AD35/100 -> 0.79169094 | AW35: =AV35*AE35/100 -> 0.78456572
A36: Масло подсолнечное, л | B36: =A36 -> Масло подсолнечное, л | C36: =A36 -> Масло подсолнечное, л | D36: =C36 -> Масло подсолнечное, л | E36: =INDEX(БИПЦ_НДС!$D:$D,MATCH(Структура!A36,БИПЦ_НДС!$B:$B,0)) -> 10 | F36: Проды | G36: 1 | H36: 1 | I36: 0 | J36: =INDEX('2026'!$C:$C,MATCH(Структура!B36,'2026'!$B:$B,0)) -> 0.306 | K36: =INDEX('2025'!$C:$C,MATCH(Структура!C36,'2025'!$B:$B,0)) -> 0.331 | L36: 1 | M36: 1 | N36: =INDEX(MoM!B:B,MATCH(Структура!A36,MoM!J:J,0)) -> 1 | P36: =INDEX('ИПЦ raw'!AA:AA, MATCH(Структура!$D36,'ИПЦ raw'!$A:$A,0)) -> 102.01 | Q36: =INDEX('ИПЦ raw'!AB:AB, MATCH(Структура!$D36,'ИПЦ raw'!$A:$A,0)) -> 100.71 | R36: =INDEX('ИПЦ raw'!AC:AC, MATCH(Структура!$D36,'ИПЦ raw'!$A:$A,0)) -> 99.95 | S36: =INDEX('ИПЦ raw'!AD:AD, MATCH(Структура!$D36,'ИПЦ raw'!$A:$A,0)) -> 100.01 | T36: =INDEX('ИПЦ raw'!AE:AE, MATCH(Структура!$D36,'ИПЦ raw'!$A:$A,0)) -> 99.84 | U36: =INDEX('ИПЦ raw'!AF:AF, MATCH(Структура!$D36,'ИПЦ raw'!$A:$A,0)) -> 100.24 | V36: =INDEX('ИПЦ raw'!AG:AG, MATCH(Структура!$D36,'ИПЦ raw'!$A:$A,0)) -> 99.75 | W36: =INDEX('ИПЦ raw'!AH:AH, MATCH(Структура!$D36,'ИПЦ raw'!$A:$A,0)) -> 99.45 | X36: =INDEX('ИПЦ raw'!AI:AI, MATCH(Структура!$D36,'ИПЦ raw'!$A:$A,0)) -> 99.78 | Y36: =INDEX('ИПЦ raw'!AJ:AJ, MATCH(Структура!$D36,'ИПЦ raw'!$A:$A,0)) -> 100.66 | Z36: =INDEX('ИПЦ raw'!AK:AK, MATCH(Структура!$D36,'ИПЦ raw'!$A:$A,0)) -> 100.56 | AA36: =INDEX('ИПЦ raw'!AL:AL, MATCH(Структура!$D36,'ИПЦ raw'!$A:$A,0)) -> 100.32 | AB36: =INDEX('ИПЦ raw'!AM:AM, MATCH(Структура!$D36,'ИПЦ raw'!$A:$A,0)) -> 100.2 | AC36: =INDEX('ИПЦ raw'!AN:AN, MATCH(Структура!$D36,'ИПЦ raw'!$A:$A,0)) -> 99.66 | AD36: =INDEX('ИПЦ raw'!AO:AO, MATCH(Структура!$D36,'ИПЦ raw'!$A:$A,0)) -> 100.17 | AE36: =INDEX('ИПЦ raw'!AP:AP, MATCH(Структура!$D36,'ИПЦ raw'!$A:$A,0)) -> 100.89 | AG36: =INDEX('2025'!$C:$C,MATCH(Структура!C36,'2025'!$B:$B,0)) -> 0.331 | AH36: =AG36*P36/100 -> 0.3376531 | AI36: =AH36*Q36/100 -> 0.34005044 | AJ36: =AI36*R36/100 -> 0.33988041 | AK36: =AJ36*S36/100 -> 0.3399144 | AL36: =AK36*T36/100 -> 0.33937054 | AM36: =AL36*U36/100 -> 0.34018503 | AN36: =AM36*V36/100 -> 0.33933456 | AO36: =AN36*W36/100 -> 0.33746822 | ... AR36: =AQ36*Z36/100 -> 0.34084629 | AS36: =J36 -> 0.306 | AT36: =AS36*AB36/100 -> 0.306612 | AU36: =AT36*AC36/100 -> 0.30556952 | AV36: =AU36*AD36/100 -> 0.30608899 | AW36: =AV36*AE36/100 -> 0.30881318
A37: Масло оливковое, л | B37: =A37 -> Масло оливковое, л | C37: =A37 -> Масло оливковое, л | D37: =C37 -> Масло оливковое, л | E37: =INDEX(БИПЦ_НДС!$D:$D,MATCH(Структура!A37,БИПЦ_НДС!$B:$B,0)) -> 10 | F37: Проды | G37: 1 | H37: 1 | I37: 0 | J37: =INDEX('2026'!$C:$C,MATCH(Структура!B37,'2026'!$B:$B,0)) -> 0.067 | K37: =INDEX('2025'!$C:$C,MATCH(Структура!C37,'2025'!$B:$B,0)) -> 0.085 | L37: 1 | M37: 1 | N37: =INDEX(MoM!B:B,MATCH(Структура!A37,MoM!J:J,0)) -> 1 | P37: =INDEX('ИПЦ raw'!AA:AA, MATCH(Структура!$D37,'ИПЦ raw'!$A:$A,0)) -> 100.22 | Q37: =INDEX('ИПЦ raw'!AB:AB, MATCH(Структура!$D37,'ИПЦ raw'!$A:$A,0)) -> 101 | R37: =INDEX('ИПЦ raw'!AC:AC, MATCH(Структура!$D37,'ИПЦ raw'!$A:$A,0)) -> 99.61 | S37: =INDEX('ИПЦ raw'!AD:AD, MATCH(Структура!$D37,'ИПЦ raw'!$A:$A,0)) -> 99.59 | T37: =INDEX('ИПЦ raw'!AE:AE, MATCH(Структура!$D37,'ИПЦ raw'!$A:$A,0)) -> 98.52 | U37: =INDEX('ИПЦ raw'!AF:AF, MATCH(Структура!$D37,'ИПЦ raw'!$A:$A,0)) -> 98.98 | V37: =INDEX('ИПЦ raw'!AG:AG, MATCH(Структура!$D37,'ИПЦ raw'!$A:$A,0)) -> 98.17 | W37: =INDEX('ИПЦ raw'!AH:AH, MATCH(Структура!$D37,'ИПЦ raw'!$A:$A,0)) -> 97.94 | X37: =INDEX('ИПЦ raw'!AI:AI, MATCH(Структура!$D37,'ИПЦ raw'!$A:$A,0)) -> 97.21 | Y37: =INDEX('ИПЦ raw'!AJ:AJ, MATCH(Структура!$D37,'ИПЦ raw'!$A:$A,0)) -> 99.3 | Z37: =INDEX('ИПЦ raw'!AK:AK, MATCH(Структура!$D37,'ИПЦ raw'!$A:$A,0)) -> 98.31 | AA37: =INDEX('ИПЦ raw'!AL:AL, MATCH(Структура!$D37,'ИПЦ raw'!$A:$A,0)) -> 99.57 | AB37: =INDEX('ИПЦ raw'!AM:AM, MATCH(Структура!$D37,'ИПЦ raw'!$A:$A,0)) -> 98.3 | AC37: =INDEX('ИПЦ raw'!AN:AN, MATCH(Структура!$D37,'ИПЦ raw'!$A:$A,0)) -> 99.19 | AD37: =INDEX('ИПЦ raw'!AO:AO, MATCH(Структура!$D37,'ИПЦ raw'!$A:$A,0)) -> 97.94 | AE37: =INDEX('ИПЦ raw'!AP:AP, MATCH(Структура!$D37,'ИПЦ raw'!$A:$A,0)) -> 99.48 | AG37: =INDEX('2025'!$C:$C,MATCH(Структура!C37,'2025'!$B:$B,0)) -> 0.085 | AH37: =AG37*P37/100 -> 0.085187 | AI37: =AH37*Q37/100 -> 0.08603887 | AJ37: =AI37*R37/100 -> 0.085703318 | AK37: =AJ37*S37/100 -> 0.085351935 | AL37: =AK37*T37/100 -> 0.084088726 | AM37: =AL37*U37/100 -> 0.083231021 | AN37: =AM37*V37/100 -> 0.081707893 | AO37: =AN37*W37/100 -> 0.080024711 | ... AR37: =AQ37*Z37/100 -> 0.075941995 | AS37: =J37 -> 0.067 | AT37: =AS37*AB37/100 -> 0.065861 | AU37: =AT37*AC37/100 -> 0.065327526 | AV37: =AU37*AD37/100 -> 0.063981779 | AW37: =AV37*AE37/100 -> 0.063649074
A38: Маргарин, кг | B38: =A38 -> Маргарин, кг | C38: =A38 -> Маргарин, кг | D38: =C38 -> Маргарин, кг | E38: =INDEX(БИПЦ_НДС!$D:$D,MATCH(Структура!A38,БИПЦ_НДС!$B:$B,0)) -> 10 | F38: Проды | G38: 1 | H38: 1 | I38: 0 | J38: =INDEX('2026'!$C:$C,MATCH(Структура!B38,'2026'!$B:$B,0)) -> 0.027 | K38: =INDEX('2025'!$C:$C,MATCH(Структура!C38,'2025'!$B:$B,0)) -> 0.033 | L38: 1 | M38: 1 | N38: =INDEX(MoM!B:B,MATCH(Структура!A38,MoM!J:J,0)) -> 1 | P38: =INDEX('ИПЦ raw'!AA:AA, MATCH(Структура!$D38,'ИПЦ raw'!$A:$A,0)) -> 101.07 | Q38: =INDEX('ИПЦ raw'!AB:AB, MATCH(Структура!$D38,'ИПЦ raw'!$A:$A,0)) -> 101.72 | R38: =INDEX('ИПЦ raw'!AC:AC, MATCH(Структура!$D38,'ИПЦ raw'!$A:$A,0)) -> 101.63 | S38: =INDEX('ИПЦ raw'!AD:AD, MATCH(Структура!$D38,'ИПЦ raw'!$A:$A,0)) -> 100.8 | T38: =INDEX('ИПЦ raw'!AE:AE, MATCH(Структура!$D38,'ИПЦ raw'!$A:$A,0)) -> 101.15 | U38: =INDEX('ИПЦ raw'!AF:AF, MATCH(Структура!$D38,'ИПЦ raw'!$A:$A,0)) -> 100.26 | V38: =INDEX('ИПЦ raw'!AG:AG, MATCH(Структура!$D38,'ИПЦ raw'!$A:$A,0)) -> 100.84 | W38: =INDEX('ИПЦ raw'!AH:AH, MATCH(Структура!$D38,'ИПЦ raw'!$A:$A,0)) -> 100.17 | X38: =INDEX('ИПЦ raw'!AI:AI, MATCH(Структура!$D38,'ИПЦ raw'!$A:$A,0)) -> 100.45 | Y38: =INDEX('ИПЦ raw'!AJ:AJ, MATCH(Структура!$D38,'ИПЦ raw'!$A:$A,0)) -> 99.95 | Z38: =INDEX('ИПЦ raw'!AK:AK, MATCH(Структура!$D38,'ИПЦ raw'!$A:$A,0)) -> 100.84 | AA38: =INDEX('ИПЦ raw'!AL:AL, MATCH(Структура!$D38,'ИПЦ raw'!$A:$A,0)) -> 100.32 | AB38: =INDEX('ИПЦ raw'!AM:AM, MATCH(Структура!$D38,'ИПЦ raw'!$A:$A,0)) -> 102.77 | AC38: =INDEX('ИПЦ raw'!AN:AN, MATCH(Структура!$D38,'ИПЦ raw'!$A:$A,0)) -> 99.49 | AD38: =INDEX('ИПЦ raw'!AO:AO, MATCH(Структура!$D38,'ИПЦ raw'!$A:$A,0)) -> 99.45 | AE38: =INDEX('ИПЦ raw'!AP:AP, MATCH(Структура!$D38,'ИПЦ raw'!$A:$A,0)) -> 100.26 | AG38: =INDEX('2025'!$C:$C,MATCH(Структура!C38,'2025'!$B:$B,0)) -> 0.033 | AH38: =AG38*P38/100 -> 0.0333531 | AI38: =AH38*Q38/100 -> 0.033926773 | AJ38: =AI38*R38/100 -> 0.03447978 | AK38: =AJ38*S38/100 -> 0.034755618 | AL38: =AK38*T38/100 -> 0.035155308 | AM38: =AL38*U38/100 -> 0.035246711 | AN38: =AM38*V38/100 -> 0.035542784 | AO38: =AN38*W38/100 -> 0.035603206 | ... AR38: =AQ38*Z38/100 -> 0.036045802 | AS38: =J38 -> 0.027 | AT38: =AS38*AB38/100 -> 0.0277479 | AU38: =AT38*AC38/100 -> 0.027606386 | AV38: =AU38*AD38/100 -> 0.027454551 | AW38: =AV38*AE38/100 -> 0.027525932
A39: Молоко питьевое цельное пастеризованное 2,5-3,2% жирности, л | B39: =A39 -> Молоко питьевое цельное пастеризованное 2,5-3,2% жирности, л | C39: =A39 -> Молоко питьевое цельное пастеризованное 2,5-3,2% жирности, л | D39: =C39 -> Молоко питьевое цельное пастеризованное 2,5-3,2% жирности, л | E39: =INDEX(БИПЦ_НДС!$D:$D,MATCH(Структура!A39,БИПЦ_НДС!$B:$B,0)) -> 10 | F39: Проды | G39: 1 | H39: 1 | I39: 0 | J39: =INDEX('2026'!$C:$C,MATCH(Структура!B39,'2026'!$B:$B,0)) -> 0.459 | K39: =INDEX('2025'!$C:$C,MATCH(Структура!C39,'2025'!$B:$B,0)) -> 0.459 | L39: 1 | M39: 1 | N39: =INDEX(MoM!B:B,MATCH(Структура!A39,MoM!J:J,0)) -> 1 | P39: =INDEX('ИПЦ raw'!AA:AA, MATCH(Структура!$D39,'ИПЦ raw'!$A:$A,0)) -> 101.48 | Q39: =INDEX('ИПЦ raw'!AB:AB, MATCH(Структура!$D39,'ИПЦ raw'!$A:$A,0)) -> 102.17 | R39: =INDEX('ИПЦ raw'!AC:AC, MATCH(Структура!$D39,'ИПЦ raw'!$A:$A,0)) -> 101.37 | S39: =INDEX('ИПЦ raw'!AD:AD, MATCH(Структура!$D39,'ИПЦ raw'!$A:$A,0)) -> 100.78 | T39: =INDEX('ИПЦ raw'!AE:AE, MATCH(Структура!$D39,'ИПЦ raw'!$A:$A,0)) -> 100.19 | U39: =INDEX('ИПЦ raw'!AF:AF, MATCH(Структура!$D39,'ИПЦ raw'!$A:$A,0)) -> 100.23 | V39: =INDEX('ИПЦ raw'!AG:AG, MATCH(Структура!$D39,'ИПЦ raw'!$A:$A,0)) -> 99.79 | W39: =INDEX('ИПЦ raw'!AH:AH, MATCH(Структура!$D39,'ИПЦ raw'!$A:$A,0)) -> 100.16 | X39: =INDEX('ИПЦ raw'!AI:AI, MATCH(Структура!$D39,'ИПЦ raw'!$A:$A,0)) -> 100.45 | Y39: =INDEX('ИПЦ raw'!AJ:AJ, MATCH(Структура!$D39,'ИПЦ raw'!$A:$A,0)) -> 100.25 | Z39: =INDEX('ИПЦ raw'!AK:AK, MATCH(Структура!$D39,'ИПЦ raw'!$A:$A,0)) -> 100.32 | AA39: =INDEX('ИПЦ raw'!AL:AL, MATCH(Структура!$D39,'ИПЦ raw'!$A:$A,0)) -> 100.36 | AB39: =INDEX('ИПЦ raw'!AM:AM, MATCH(Структура!$D39,'ИПЦ raw'!$A:$A,0)) -> 100.55 | AC39: =INDEX('ИПЦ raw'!AN:AN, MATCH(Структура!$D39,'ИПЦ raw'!$A:$A,0)) -> 99.75 | AD39: =INDEX('ИПЦ raw'!AO:AO, MATCH(Структура!$D39,'ИПЦ raw'!$A:$A,0)) -> 99.65 | AE39: =INDEX('ИПЦ raw'!AP:AP, MATCH(Структура!$D39,'ИПЦ raw'!$A:$A,0)) -> 99.46 | AG39: =INDEX('2025'!$C:$C,MATCH(Структура!C39,'2025'!$B:$B,0)) -> 0.459 | AH39: =AG39*P39/100 -> 0.4657932 | AI39: =AH39*Q39/100 -> 0.47590091 | AJ39: =AI39*R39/100 -> 0.48242075 | AK39: =AJ39*S39/100 -> 0.48618364 | AL39: =AK39*T39/100 -> 0.48710739 | AM39: =AL39*U39/100 -> 0.48822773 | AN39: =AM39*V39/100 -> 0.48720245 | AO39: =AN39*W39/100 -> 0.48798198 | ... AR39: =AQ39*Z39/100 -> 0.49297583 | AS39: =J39 -> 0.459 | AT39: =AS39*AB39/100 -> 0.4615245 | AU39: =AT39*AC39/100 -> 0.46037069 | AV39: =AU39*AD39/100 -> 0.45875939 | AW39: =AV39*AE39/100 -> 0.45628209
A40: Молоко питьевое цельное ультрапастеризованное 2,5-3,2% жирности, л | B40: =A40 -> Молоко питьевое цельное ультрапастеризованное 2,5-3,2% жирности, л | C40: =A40 -> Молоко питьевое цельное ультрапастеризованное 2,5-3,2% жирности, л | D40: =C40 -> Молоко питьевое цельное ультрапастеризованное 2,5-3,2% жирности, л | E40: =INDEX(БИПЦ_НДС!$D:$D,MATCH(Структура!A40,БИПЦ_НДС!$B:$B,0)) -> 10 | F40: Проды | G40: 1 | H40: 1 | I40: 0 | J40: =INDEX('2026'!$C:$C,MATCH(Структура!B40,'2026'!$B:$B,0)) -> 0.332 | K40: =INDEX('2025'!$C:$C,MATCH(Структура!C40,'2025'!$B:$B,0)) -> 0.345 | L40: 1 | M40: 1 | N40: =INDEX(MoM!B:B,MATCH(Структура!A40,MoM!J:J,0)) -> 0 | P40: =INDEX('ИПЦ raw'!AA:AA, MATCH(Структура!$D40,'ИПЦ raw'!$A:$A,0)) -> 101.57 | Q40: =INDEX('ИПЦ raw'!AB:AB, MATCH(Структура!$D40,'ИПЦ raw'!$A:$A,0)) -> 101.37 | R40: =INDEX('ИПЦ raw'!AC:AC, MATCH(Структура!$D40,'ИПЦ raw'!$A:$A,0)) -> 101.14 | S40: =INDEX('ИПЦ raw'!AD:AD, MATCH(Структура!$D40,'ИПЦ raw'!$A:$A,0)) -> 99.95 | T40: =INDEX('ИПЦ raw'!AE:AE, MATCH(Структура!$D40,'ИПЦ raw'!$A:$A,0)) -> 99.83 | U40: =INDEX('ИПЦ raw'!AF:AF, MATCH(Структура!$D40,'ИПЦ raw'!$A:$A,0)) -> 99.69 | V40: =INDEX('ИПЦ raw'!AG:AG, MATCH(Структура!$D40,'ИПЦ raw'!$A:$A,0)) -> 99.72 | W40: =INDEX('ИПЦ raw'!AH:AH, MATCH(Структура!$D40,'ИПЦ raw'!$A:$A,0)) -> 100.09 | X40: =INDEX('ИПЦ raw'!AI:AI, MATCH(Структура!$D40,'ИПЦ raw'!$A:$A,0)) -> 100.56 | Y40: =INDEX('ИПЦ raw'!AJ:AJ, MATCH(Структура!$D40,'ИПЦ raw'!$A:$A,0)) -> 100.74 | Z40: =INDEX('ИПЦ raw'!AK:AK, MATCH(Структура!$D40,'ИПЦ raw'!$A:$A,0)) -> 100.66 | AA40: =INDEX('ИПЦ raw'!AL:AL, MATCH(Структура!$D40,'ИПЦ raw'!$A:$A,0)) -> 100.33 | AB40: =INDEX('ИПЦ raw'!AM:AM, MATCH(Структура!$D40,'ИПЦ raw'!$A:$A,0)) -> 100.69 | AC40: =INDEX('ИПЦ raw'!AN:AN, MATCH(Структура!$D40,'ИПЦ raw'!$A:$A,0)) -> 98.97 | AD40: =INDEX('ИПЦ raw'!AO:AO, MATCH(Структура!$D40,'ИПЦ raw'!$A:$A,0)) -> 99.82 | AE40: =INDEX('ИПЦ raw'!AP:AP, MATCH(Структура!$D40,'ИПЦ raw'!$A:$A,0)) -> 99.4 | AG40: =INDEX('2025'!$C:$C,MATCH(Структура!C40,'2025'!$B:$B,0)) -> 0.345 | AH40: =AG40*P40/100 -> 0.3504165 | AI40: =AH40*Q40/100 -> 0.35521721 | AJ40: =AI40*R40/100 -> 0.35926668 | AK40: =AJ40*S40/100 -> 0.35908705 | AL40: =AK40*T40/100 -> 0.3584766 | AM40: =AL40*U40/100 -> 0.35736532 | AN40: =AM40*V40/100 -> 0.3563647 | AO40: =AN40*W40/100 -> 0.35668543 | ... AR40: =AQ40*Z40/100 -> 0.36372195 | AS40: =J40 -> 0.332 | AT40: =AS40*AB40/100 -> 0.3342908 | AU40: =AT40*AC40/100 -> 0.3308476 | AV40: =AU40*AD40/100 -> 0.33025208 | AW40: =AV40*AE40/100 -> 0.32827057
A41: Молоко питьевое цельное пастеризованное более 3,2% жирности, л | B41: =A41 -> Молоко питьевое цельное пастеризованное более 3,2% жирности, л | C41: =A41 -> Молоко питьевое цельное пастеризованное более 3,2% жирности, л | D41: =C41 -> Молоко питьевое цельное пастеризованное более 3,2% жирности, л | E41: =INDEX(БИПЦ_НДС!$D:$D,MATCH(Структура!A41,БИПЦ_НДС!$B:$B,0)) -> 10 | F41: Проды | G41: 1 | H41: 1 | I41: 0 | J41: =INDEX('2026'!$C:$C,MATCH(Структура!B41,'2026'!$B:$B,0)) -> 0.2 | K41: =INDEX('2025'!$C:$C,MATCH(Структура!C41,'2025'!$B:$B,0)) -> 0.215 | L41: 1 | M41: 1 | N41: =INDEX(MoM!B:B,MATCH(Структура!A41,MoM!J:J,0)) -> 1 | P41: =INDEX('ИПЦ raw'!AA:AA, MATCH(Структура!$D41,'ИПЦ raw'!$A:$A,0)) -> 101.33 | Q41: =INDEX('ИПЦ raw'!AB:AB, MATCH(Структура!$D41,'ИПЦ raw'!$A:$A,0)) -> 101.92 | R41: =INDEX('ИПЦ raw'!AC:AC, MATCH(Структура!$D41,'ИПЦ raw'!$A:$A,0)) -> 101.54 | S41: =INDEX('ИПЦ raw'!AD:AD, MATCH(Структура!$D41,'ИПЦ raw'!$A:$A,0)) -> 101.03 | T41: =INDEX('ИПЦ raw'!AE:AE, MATCH(Структура!$D41,'ИПЦ raw'!$A:$A,0)) -> 100.41 | U41: =INDEX('ИПЦ raw'!AF:AF, MATCH(Структура!$D41,'ИПЦ raw'!$A:$A,0)) -> 100.62 | V41: =INDEX('ИПЦ raw'!AG:AG, MATCH(Структура!$D41,'ИПЦ raw'!$A:$A,0)) -> 100.24 | W41: =INDEX('ИПЦ raw'!AH:AH, MATCH(Структура!$D41,'ИПЦ raw'!$A:$A,0)) -> 99.71 | X41: =INDEX('ИПЦ raw'!AI:AI, MATCH(Структура!$D41,'ИПЦ raw'!$A:$A,0)) -> 100.05 | Y41: =INDEX('ИПЦ raw'!AJ:AJ, MATCH(Структура!$D41,'ИПЦ raw'!$A:$A,0)) -> 100.1 | Z41: =INDEX('ИПЦ raw'!AK:AK, MATCH(Структура!$D41,'ИПЦ raw'!$A:$A,0)) -> 100.13 | AA41: =INDEX('ИПЦ raw'!AL:AL, MATCH(Структура!$D41,'ИПЦ raw'!$A:$A,0)) -> 100.14 | AB41: =INDEX('ИПЦ raw'!AM:AM, MATCH(Структура!$D41,'ИПЦ raw'!$A:$A,0)) -> 100.24 | AC41: =INDEX('ИПЦ raw'!AN:AN, MATCH(Структура!$D41,'ИПЦ raw'!$A:$A,0)) -> 99.92 | AD41: =INDEX('ИПЦ raw'!AO:AO, MATCH(Структура!$D41,'ИПЦ raw'!$A:$A,0)) -> 99.79 | AE41: =INDEX('ИПЦ raw'!AP:AP, MATCH(Структура!$D41,'ИПЦ raw'!$A:$A,0)) -> 99.62 | AG41: =INDEX('2025'!$C:$C,MATCH(Структура!C41,'2025'!$B:$B,0)) -> 0.215 | AH41: =AG41*P41/100 -> 0.2178595 | AI41: =AH41*Q41/100 -> 0.2220424 | AJ41: =AI41*R41/100 -> 0.22546186 | AK41: =AJ41*S41/100 -> 0.22778411 | AL41: =AK41*T41/100 -> 0.22871803 | AM41: =AL41*U41/100 -> 0.23013608 | AN41: =AM41*V41/100 -> 0.23068841 | AO41: =AN41*W41/100 -> 0.23001941 | ... AR41: =AQ41*Z41/100 -> 0.23066403 | AS41: =J41 -> 0.2 | AT41: =AS41*AB41/100 -> 0.20048 | AU41: =AT41*AC41/100 -> 0.20031962 | AV41: =AU41*AD41/100 -> 0.19989894 | AW41: =AV41*AE41/100 -> 0.19913933
A42: Сметана, кг | B42: =A42 -> Сметана, кг | C42: =A42 -> Сметана, кг | D42: =C42 -> Сметана, кг | E42: =INDEX(БИПЦ_НДС!$D:$D,MATCH(Структура!A42,БИПЦ_НДС!$B:$B,0)) -> 10 | F42: Проды | G42: 1 | H42: 1 | I42: 0 | J42: =INDEX('2026'!$C:$C,MATCH(Структура!B42,'2026'!$B:$B,0)) -> 0.453 | K42: =INDEX('2025'!$C:$C,MATCH(Структура!C42,'2025'!$B:$B,0)) -> 0.474 | L42: 1 | M42: 1 | N42: =INDEX(MoM!B:B,MATCH(Структура!A42,MoM!J:J,0)) -> 1 | P42: =INDEX('ИПЦ raw'!AA:AA, MATCH(Структура!$D42,'ИПЦ raw'!$A:$A,0)) -> 101.37 | Q42: =INDEX('ИПЦ raw'!AB:AB, MATCH(Структура!$D42,'ИПЦ raw'!$A:$A,0)) -> 101.99 | R42: =INDEX('ИПЦ raw'!AC:AC, MATCH(Структура!$D42,'ИПЦ raw'!$A:$A,0)) -> 101.54 | S42: =INDEX('ИПЦ raw'!AD:AD, MATCH(Структура!$D42,'ИПЦ raw'!$A:$A,0)) -> 100.25 | T42: =INDEX('ИПЦ raw'!AE:AE, MATCH(Структура!$D42,'ИПЦ raw'!$A:$A,0)) -> 100.28 | U42: =INDEX('ИПЦ raw'!AF:AF, MATCH(Структура!$D42,'ИПЦ raw'!$A:$A,0)) -> 100.76 | V42: =INDEX('ИПЦ raw'!AG:AG, MATCH(Структура!$D42,'ИПЦ raw'!$A:$A,0)) -> 99.69 | W42: =INDEX('ИПЦ raw'!AH:AH, MATCH(Структура!$D42,'ИПЦ raw'!$A:$A,0)) -> 100.16 | X42: =INDEX('ИПЦ raw'!AI:AI, MATCH(Структура!$D42,'ИПЦ raw'!$A:$A,0)) -> 99.7 | Y42: =INDEX('ИПЦ raw'!AJ:AJ, MATCH(Структура!$D42,'ИПЦ raw'!$A:$A,0)) -> 100.63 | Z42: =INDEX('ИПЦ raw'!AK:AK, MATCH(Структура!$D42,'ИПЦ raw'!$A:$A,0)) -> 100.24 | AA42: =INDEX('ИПЦ raw'!AL:AL, MATCH(Структура!$D42,'ИПЦ raw'!$A:$A,0)) -> 99.81 | AB42: =INDEX('ИПЦ raw'!AM:AM, MATCH(Структура!$D42,'ИПЦ raw'!$A:$A,0)) -> 100.4 | AC42: =INDEX('ИПЦ raw'!AN:AN, MATCH(Структура!$D42,'ИПЦ raw'!$A:$A,0)) -> 99.03 | AD42: =INDEX('ИПЦ raw'!AO:AO, MATCH(Структура!$D42,'ИПЦ raw'!$A:$A,0)) -> 99.68 | AE42: =INDEX('ИПЦ raw'!AP:AP, MATCH(Структура!$D42,'ИПЦ raw'!$A:$A,0)) -> 99.65 | AG42: =INDEX('2025'!$C:$C,MATCH(Структура!C42,'2025'!$B:$B,0)) -> 0.474 | AH42: =AG42*P42/100 -> 0.4804938 | AI42: =AH42*Q42/100 -> 0.49005563 | AJ42: =AI42*R42/100 -> 0.49760248 | AK42: =AJ42*S42/100 -> 0.49884649 | AL42: =AK42*T42/100 -> 0.50024326 | AM42: =AL42*U42/100 -> 0.50404511 | AN42: =AM42*V42/100 -> 0.50248257 | AO42: =AN42*W42/100 -> 0.50328654 | ... AR42: =AQ42*Z42/100 -> 0.50614973 | AS42: =J42 -> 0.453 | AT42: =AS42*AB42/100 -> 0.454812 | AU42: =AT42*AC42/100 -> 0.45040032 | AV42: =AU42*AD42/100 -> 0.44895904 | AW42: =AV42*AE42/100 -> 0.44738769
... A46: Творог, кг | B46: =A46 -> Творог, кг | C46: =A46 -> Творог, кг | D46: =C46 -> Творог, кг | E46: =INDEX(БИПЦ_НДС!$D:$D,MATCH(Структура!A46,БИПЦ_НДС!$B:$B,0)) -> 10 | F46: Проды | G46: 1 | H46: 1 | I46: 0 | J46: =INDEX('2026'!$C:$C,MATCH(Структура!B46,'2026'!$B:$B,0)) -> 0.537 | K46: =INDEX('2025'!$C:$C,MATCH(Структура!C46,'2025'!$B:$B,0)) -> 0.533 | L46: 1 | M46: 1 | N46: =INDEX(MoM!B:B,MATCH(Структура!A46,MoM!J:J,0)) -> 1 | P46: =INDEX('ИПЦ raw'!AA:AA, MATCH(Структура!$D46,'ИПЦ raw'!$A:$A,0)) -> 100.92 | Q46: =INDEX('ИПЦ raw'!AB:AB, MATCH(Структура!$D46,'ИПЦ raw'!$A:$A,0)) -> 101.71 | R46: =INDEX('ИПЦ raw'!AC:AC, MATCH(Структура!$D46,'ИПЦ raw'!$A:$A,0)) -> 100.9 | S46: =INDEX('ИПЦ raw'!AD:AD, MATCH(Структура!$D46,'ИПЦ raw'!$A:$A,0)) -> 100.16 | T46: =INDEX('ИПЦ raw'!AE:AE, MATCH(Структура!$D46,'ИПЦ raw'!$A:$A,0)) -> 100.43 | U46: =INDEX('ИПЦ raw'!AF:AF, MATCH(Структура!$D46,'ИПЦ raw'!$A:$A,0)) -> 100.47 | V46: =INDEX('ИПЦ raw'!AG:AG, MATCH(Структура!$D46,'ИПЦ raw'!$A:$A,0)) -> 99.74 | W46: =INDEX('ИПЦ raw'!AH:AH, MATCH(Структура!$D46,'ИПЦ raw'!$A:$A,0)) -> 99.99 | X46: =INDEX('ИПЦ raw'!AI:AI, MATCH(Структура!$D46,'ИПЦ raw'!$A:$A,0)) -> 100.29 | Y46: =INDEX('ИПЦ raw'!AJ:AJ, MATCH(Структура!$D46,'ИПЦ raw'!$A:$A,0)) -> 100.65 | Z46: =INDEX('ИПЦ raw'!AK:AK, MATCH(Структура!$D46,'ИПЦ raw'!$A:$A,0)) -> 100.35 | AA46: =INDEX('ИПЦ raw'!AL:AL, MATCH(Структура!$D46,'ИПЦ raw'!$A:$A,0)) -> 100.14 | AB46: =INDEX('ИПЦ raw'!AM:AM, MATCH(Структура!$D46,'ИПЦ raw'!$A:$A,0)) -> 100.27 | AC46: =INDEX('ИПЦ raw'!AN:AN, MATCH(Структура!$D46,'ИПЦ raw'!$A:$A,0)) -> 99.47 | AD46: =INDEX('ИПЦ raw'!AO:AO, MATCH(Структура!$D46,'ИПЦ raw'!$A:$A,0)) -> 100.07 | AE46: =INDEX('ИПЦ raw'!AP:AP, MATCH(Структура!$D46,'ИПЦ raw'!$A:$A,0)) -> 99.56 | AG46: =INDEX('2025'!$C:$C,MATCH(Структура!C46,'2025'!$B:$B,0)) -> 0.533 | AH46: =AG46*P46/100 -> 0.5379036 | AI46: =AH46*Q46/100 -> 0.54710175 | AJ46: =AI46*R46/100 -> 0.55202567 | AK46: =AJ46*S46/100 -> 0.55290891 | AL46: =AK46*T46/100 -> 0.55528642 | AM46: =AL46*U46/100 -> 0.55789626 | AN46: =AM46*V46/100 -> 0.55644573 | AO46: =AN46*W46/100 -> 0.55639009 | ... AR46: =AQ46*Z46/100 -> 0.56359635 | AS46: =J46 -> 0.537 | AT46: =AS46*AB46/100 -> 0.5384499 | AU46: =AT46*AC46/100 -> 0.53559612 | AV46: =AU46*AD46/100 -> 0.53597103 | AW46: =AV46*AE46/100 -> 0.53361276
A47: Сырки творожные, глазированные, кг | B47: =A47 -> Сырки творожные, глазированные, кг | C47: Сырки творожные, глазированные шоколадом, кг | D47: Сырки творожные, глазированные, кг | E47: =INDEX(БИПЦ_НДС!$D:$D,MATCH(Структура!A47,БИПЦ_НДС!$B:$B,0)) -> 10 | F47: Проды | G47: 1 | H47: 1 | I47: 0 | J47: =INDEX('2026'!$C:$C,MATCH(Структура!B47,'2026'!$B:$B,0)) -> 0.18 | K47: =INDEX('2025'!$C:$C,MATCH(Структура!C47,'2025'!$B:$B,0)) -> 0.196 | L47: 1 | M47: 1 | N47: =INDEX(MoM!B:B,MATCH(Структура!A47,MoM!J:J,0)) -> 0 | P47: =INDEX('ИПЦ raw'!AA:AA, MATCH(Структура!$C47,'ИПЦ raw'!$A:$A,0)) -> 100.75 | Q47: =INDEX('ИПЦ raw'!AB:AB, MATCH(Структура!$C47,'ИПЦ raw'!$A:$A,0)) -> 101.05 | R47: =INDEX('ИПЦ raw'!AC:AC, MATCH(Структура!$C47,'ИПЦ raw'!$A:$A,0)) -> 100.59 | S47: =INDEX('ИПЦ raw'!AD:AD, MATCH(Структура!$C47,'ИПЦ raw'!$A:$A,0)) -> 100.65 | T47: =INDEX('ИПЦ raw'!AE:AE, MATCH(Структура!$C47,'ИПЦ raw'!$A:$A,0)) -> 99.99 | U47: =INDEX('ИПЦ raw'!AF:AF, MATCH(Структура!$C47,'ИПЦ raw'!$A:$A,0)) -> 101.3 | V47: =INDEX('ИПЦ raw'!AG:AG, MATCH(Структура!$C47,'ИПЦ raw'!$A:$A,0)) -> 99.34 | W47: =INDEX('ИПЦ raw'!AH:AH, MATCH(Структура!$C47,'ИПЦ raw'!$A:$A,0)) -> 99.95 | X47: =INDEX('ИПЦ raw'!AI:AI, MATCH(Структура!$C47,'ИПЦ raw'!$A:$A,0)) -> 99.81 | Y47: =INDEX('ИПЦ raw'!AJ:AJ, MATCH(Структура!$C47,'ИПЦ raw'!$A:$A,0)) -> 100.34 | Z47: =INDEX('ИПЦ raw'!AK:AK, MATCH(Структура!$C47,'ИПЦ raw'!$A:$A,0)) -> 99.93 | AA47: =INDEX('ИПЦ raw'!AL:AL, MATCH(Структура!$C47,'ИПЦ raw'!$A:$A,0)) -> 100.11 | AB47: =INDEX('ИПЦ raw'!AM:AM, MATCH(Структура!$D47,'ИПЦ raw'!$A:$A,0)) -> 100.17 | AC47: =INDEX('ИПЦ raw'!AN:AN, MATCH(Структура!$D47,'ИПЦ raw'!$A:$A,0)) -> 100.53 | AD47: =INDEX('ИПЦ raw'!AO:AO, MATCH(Структура!$D47,'ИПЦ raw'!$A:$A,0)) -> 100.05 | AE47: =INDEX('ИПЦ raw'!AP:AP, MATCH(Структура!$D47,'ИПЦ raw'!$A:$A,0)) -> 99.89 | AG47: =INDEX('2025'!$C:$C,MATCH(Структура!C47,'2025'!$B:$B,0)) -> 0.196 | AH47: =AG47*P47/100 -> 0.19747 | AI47: =AH47*Q47/100 -> 0.19954343 | AJ47: =AI47*R47/100 -> 0.20072074 | AK47: =AJ47*S47/100 -> 0.20202543 | AL47: =AK47*T47/100 -> 0.20200522 | AM47: =AL47*U47/100 -> 0.20463129 | AN47: =AM47*V47/100 -> 0.20328072 | AO47: =AN47*W47/100 -> 0.20317908 | ... AR47: =AQ47*Z47/100 -> 0.2033401 | AS47: =J47 -> 0.18 | AT47: =AS47*AB47/100 -> 0.180306 | AU47: =AT47*AC47/100 -> 0.18126162 | AV47: =AU47*AD47/100 -> 0.18135225 | AW47: =AV47*AE47/100 -> 0.18115277
A48: Молоко сгущенное с сахаром, кг | B48: =A48 -> Молоко сгущенное с сахаром, кг | C48: =A48 -> Молоко сгущенное с сахаром, кг | D48: =C48 -> Молоко сгущенное с сахаром, кг | E48: =INDEX(БИПЦ_НДС!$D:$D,MATCH(Структура!A48,БИПЦ_НДС!$B:$B,0)) -> 10 | F48: Проды | G48: 1 | H48: 1 | I48: 0 | J48: =INDEX('2026'!$C:$C,MATCH(Структура!B48,'2026'!$B:$B,0)) -> 0.101 | K48: =INDEX('2025'!$C:$C,MATCH(Структура!C48,'2025'!$B:$B,0)) -> 0.101 | L48: 1 | M48: 1 | N48: =INDEX(MoM!B:B,MATCH(Структура!A48,MoM!J:J,0)) -> 1 | P48: =INDEX('ИПЦ raw'!AA:AA, MATCH(Структура!$D48,'ИПЦ raw'!$A:$A,0)) -> 101.08 | Q48: =INDEX('ИПЦ raw'!AB:AB, MATCH(Структура!$D48,'ИПЦ raw'!$A:$A,0)) -> 101.39 | R48: =INDEX('ИПЦ raw'!AC:AC, MATCH(Структура!$D48,'ИПЦ raw'!$A:$A,0)) -> 101.67 | S48: =INDEX('ИПЦ raw'!AD:AD, MATCH(Структура!$D48,'ИПЦ raw'!$A:$A,0)) -> 100.3 | T48: =INDEX('ИПЦ raw'!AE:AE, MATCH(Структура!$D48,'ИПЦ raw'!$A:$A,0)) -> 100.58 | U48: =INDEX('ИПЦ raw'!AF:AF, MATCH(Структура!$D48,'ИПЦ raw'!$A:$A,0)) -> 100.2 | V48: =INDEX('ИПЦ raw'!AG:AG, MATCH(Структура!$D48,'ИПЦ raw'!$A:$A,0)) -> 100.11 | W48: =INDEX('ИПЦ raw'!AH:AH, MATCH(Структура!$D48,'ИПЦ raw'!$A:$A,0)) -> 100.15 | X48: =INDEX('ИПЦ raw'!AI:AI, MATCH(Структура!$D48,'ИПЦ raw'!$A:$A,0)) -> 99.26 | Y48: =INDEX('ИПЦ raw'!AJ:AJ, MATCH(Структура!$D48,'ИПЦ raw'!$A:$A,0)) -> 100.5 | Z48: =INDEX('ИПЦ raw'!AK:AK, MATCH(Структура!$D48,'ИПЦ raw'!$A:$A,0)) -> 100.18 | AA48: =INDEX('ИПЦ raw'!AL:AL, MATCH(Структура!$D48,'ИПЦ raw'!$A:$A,0)) -> 100.36 | AB48: =INDEX('ИПЦ raw'!AM:AM, MATCH(Структура!$D48,'ИПЦ raw'!$A:$A,0)) -> 100.85 | AC48: =INDEX('ИПЦ raw'!AN:AN, MATCH(Структура!$D48,'ИПЦ raw'!$A:$A,0)) -> 99.56 | AD48: =INDEX('ИПЦ raw'!AO:AO, MATCH(Структура!$D48,'ИПЦ raw'!$A:$A,0)) -> 99.99 | AE48: =INDEX('ИПЦ raw'!AP:AP, MATCH(Структура!$D48,'ИПЦ raw'!$A:$A,0)) -> 99.91 | AG48: =INDEX('2025'!$C:$C,MATCH(Структура!C48,'2025'!$B:$B,0)) -> 0.101 | AH48: =AG48*P48/100 -> 0.1020908 | AI48: =AH48*Q48/100 -> 0.10350986 | AJ48: =AI48*R48/100 -> 0.10523848 | AK48: =AJ48*S48/100 -> 0.10555419 | AL48: =AK48*T48/100 -> 0.10616641 | AM48: =AL48*U48/100 -> 0.10637874 | AN48: =AM48*V48/100 -> 0.10649576 | AO48: =AN48*W48/100 -> 0.1066555 | ... AR48: =AQ48*Z48/100 -> 0.10658709 | AS48: =J48 -> 0.101 | AT48: =AS48*AB48/100 -> 0.1018585 | AU48: =AT48*AC48/100 -> 0.10141032 | AV48: =AU48*AD48/100 -> 0.10140018 | AW48: =AV48*AE48/100 -> 0.10130892
A49: Молоко для детей, л | B49: =A49 -> Молоко для детей, л | C49: =A49 -> Молоко для детей, л | D49: =C49 -> Молоко для детей, л | E49: =INDEX(БИПЦ_НДС!$D:$D,MATCH(Структура!A49,БИПЦ_НДС!$B:$B,0)) -> 10 | F49: Проды | G49: 1 | H49: 1 | I49: 0 | J49: =INDEX('2026'!$C:$C,MATCH(Структура!B49,'2026'!$B:$B,0)) -> 0.012 | K49: =INDEX('2025'!$C:$C,MATCH(Структура!C49,'2025'!$B:$B,0)) -> 0.012 | L49: 1 | M49: 1 | N49: =INDEX(MoM!B:B,MATCH(Структура!A49,MoM!J:J,0)) -> 1 | P49: =INDEX('ИПЦ raw'!AA:AA, MATCH(Структура!$D49,'ИПЦ raw'!$A:$A,0)) -> 101.39 | Q49: =INDEX('ИПЦ raw'!AB:AB, MATCH(Структура!$D49,'ИПЦ raw'!$A:$A,0)) -> 102.22 | R49: =INDEX('ИПЦ raw'!AC:AC, MATCH(Структура!$D49,'ИПЦ raw'!$A:$A,0)) -> 101.64 | S49: =INDEX('ИПЦ raw'!AD:AD, MATCH(Структура!$D49,'ИПЦ raw'!$A:$A,0)) -> 100.89 | T49: =INDEX('ИПЦ raw'!AE:AE, MATCH(Структура!$D49,'ИПЦ raw'!$A:$A,0)) -> 100.22 | U49: =INDEX('ИПЦ raw'!AF:AF, MATCH(Структура!$D49,'ИПЦ raw'!$A:$A,0)) -> 100.35 | V49: =INDEX('ИПЦ raw'!AG:AG, MATCH(Структура!$D49,'ИПЦ raw'!$A:$A,0)) -> 101.12 | W49: =INDEX('ИПЦ raw'!AH:AH, MATCH(Структура!$D49,'ИПЦ raw'!$A:$A,0)) -> 100.05 | X49: =INDEX('ИПЦ raw'!AI:AI, MATCH(Структура!$D49,'ИПЦ raw'!$A:$A,0)) -> 100.26 | Y49: =INDEX('ИПЦ raw'!AJ:AJ, MATCH(Структура!$D49,'ИПЦ raw'!$A:$A,0)) -> 100.67 | Z49: =INDEX('ИПЦ raw'!AK:AK, MATCH(Структура!$D49,'ИПЦ raw'!$A:$A,0)) -> 100.3 | AA49: =INDEX('ИПЦ raw'!AL:AL, MATCH(Структура!$D49,'ИПЦ raw'!$A:$A,0)) -> 99.92 | AB49: =INDEX('ИПЦ raw'!AM:AM, MATCH(Структура!$D49,'ИПЦ raw'!$A:$A,0)) -> 100.37 | AC49: =INDEX('ИПЦ raw'!AN:AN, MATCH(Структура!$D49,'ИПЦ raw'!$A:$A,0)) -> 99.03 | AD49: =INDEX('ИПЦ raw'!AO:AO, MATCH(Структура!$D49,'ИПЦ raw'!$A:$A,0)) -> 99.66 | AE49: =INDEX('ИПЦ raw'!AP:AP, MATCH(Структура!$D49,'ИПЦ raw'!$A:$A,0)) -> 99.81 | AG49: =INDEX('2025'!$C:$C,MATCH(Структура!C49,'2025'!$B:$B,0)) -> 0.012 | AH49: =AG49*P49/100 -> 0.0121668 | AI49: =AH49*Q49/100 -> 0.012436903 | AJ49: =AI49*R49/100 -> 0.012640868 | AK49: =AJ49*S49/100 -> 0.012753372 | AL49: =AK49*T49/100 -> 0.012781429 | AM49: =AL49*U49/100 -> 0.012826164 | AN49: =AM49*V49/100 -> 0.012969817 | AO49: =AN49*W49/100 -> 0.012976302 | ... AR49: =AQ49*Z49/100 -> 0.0131365 | AS49: =J49 -> 0.012 | AT49: =AS49*AB49/100 -> 0.0120444 | AU49: =AT49*AC49/100 -> 0.011927569 | AV49: =AU49*AD49/100 -> 0.011887016 | AW49: =AV49*AE49/100 -> 0.01186443
A50: Творожок детский, кг | B50: =A50 -> Творожок детский, кг | C50: =A50 -> Творожок детский, кг | D50: =C50 -> Творожок детский, кг | E50: =INDEX(БИПЦ_НДС!$D:$D,MATCH(Структура!A50,БИПЦ_НДС!$B:$B,0)) -> 10 | F50: Проды | G50: 1 | H50: 1 | I50: 0 | J50: =INDEX('2026'!$C:$C,MATCH(Структура!B50,'2026'!$B:$B,0)) -> 0.015 | K50: =INDEX('2025'!$C:$C,MATCH(Структура!C50,'2025'!$B:$B,0)) -> 0.015 | L50: 1 | M50: 1 | N50: =INDEX(MoM!B:B,MATCH(Структура!A50,MoM!J:J,0)) -> 1 | P50: =INDEX('ИПЦ raw'!AA:AA, MATCH(Структура!$D50,'ИПЦ raw'!$A:$A,0)) -> 100.6 | Q50: =INDEX('ИПЦ raw'!AB:AB, MATCH(Структура!$D50,'ИПЦ raw'!$A:$A,0)) -> 101.49 | R50: =INDEX('ИПЦ raw'!AC:AC, MATCH(Структура!$D50,'ИПЦ raw'!$A:$A,0)) -> 100.68 | S50: =INDEX('ИПЦ raw'!AD:AD, MATCH(Структура!$D50,'ИПЦ raw'!$A:$A,0)) -> 102.3 | T50: =INDEX('ИПЦ raw'!AE:AE, MATCH(Структура!$D50,'ИПЦ raw'!$A:$A,0)) -> 100.55 | U50: =INDEX('ИПЦ raw'!AF:AF, MATCH(Структура!$D50,'ИПЦ raw'!$A:$A,0)) -> 100.62 | V50: =INDEX('ИПЦ raw'!AG:AG, MATCH(Структура!$D50,'ИПЦ raw'!$A:$A,0)) -> 101.03 | W50: =INDEX('ИПЦ raw'!AH:AH, MATCH(Структура!$D50,'ИПЦ raw'!$A:$A,0)) -> 100.23 | X50: =INDEX('ИПЦ raw'!AI:AI, MATCH(Структура!$D50,'ИПЦ raw'!$A:$A,0)) -> 100.05 | Y50: =INDEX('ИПЦ raw'!AJ:AJ, MATCH(Структура!$D50,'ИПЦ raw'!$A:$A,0)) -> 100.43 | Z50: =INDEX('ИПЦ raw'!AK:AK, MATCH(Структура!$D50,'ИПЦ raw'!$A:$A,0)) -> 100.2 | AA50: =INDEX('ИПЦ raw'!AL:AL, MATCH(Структура!$D50,'ИПЦ raw'!$A:$A,0)) -> 99.98 | AB50: =INDEX('ИПЦ raw'!AM:AM, MATCH(Структура!$D50,'ИПЦ raw'!$A:$A,0)) -> 100.13 | AC50: =INDEX('ИПЦ raw'!AN:AN, MATCH(Структура!$D50,'ИПЦ raw'!$A:$A,0)) -> 99.65 | AD50: =INDEX('ИПЦ raw'!AO:AO, MATCH(Структура!$D50,'ИПЦ raw'!$A:$A,0)) -> 100.69 | AE50: =INDEX('ИПЦ raw'!AP:AP, MATCH(Структура!$D50,'ИПЦ raw'!$A:$A,0)) -> 99.94 | AG50: =INDEX('2025'!$C:$C,MATCH(Структура!C50,'2025'!$B:$B,0)) -> 0.015 | AH50: =AG50*P50/100 -> 0.01509 | AI50: =AH50*Q50/100 -> 0.015314841 | AJ50: =AI50*R50/100 -> 0.015418982 | AK50: =AJ50*S50/100 -> 0.015773619 | AL50: =AK50*T50/100 -> 0.015860373 | AM50: =AL50*U50/100 -> 0.015958708 | AN50: =AM50*V50/100 -> 0.016123082 | AO50: =AN50*W50/100 -> 0.016160165 | ... AR50: =AQ50*Z50/100 -> 0.016270245 | AS50: =J50 -> 0.015 | AT50: =AS50*AB50/100 -> 0.0150195 | AU50: =AT50*AC50/100 -> 0.014966932 | AV50: =AU50*AD50/100 -> 0.015070204 | AW50: =AV50*AE50/100 -> 0.015061161
A51: Смеси сухие молочные для детского питания, кг | B51: =A51 -> Смеси сухие молочные для детского питания, кг | C51: =A51 -> Смеси сухие молочные для детского питания, кг | D51: =C51 -> Смеси сухие молочные для детского питания, кг | E51: =INDEX(БИПЦ_НДС!$D:$D,MATCH(Структура!A51,БИПЦ_НДС!$B:$B,0)) -> 10 | F51: Проды | G51: 1 | H51: 1 | I51: 0 | J51: =INDEX('2026'!$C:$C,MATCH(Структура!B51,'2026'!$B:$B,0)) -> 0.043 | K51: =INDEX('2025'!$C:$C,MATCH(Структура!C51,'2025'!$B:$B,0)) -> 0.045 | L51: 1 | M51: 1 | N51: =INDEX(MoM!B:B,MATCH(Структура!A51,MoM!J:J,0)) -> 1 | P51: =INDEX('ИПЦ raw'!AA:AA, MATCH(Структура!$D51,'ИПЦ raw'!$A:$A,0)) -> 100.06 | Q51: =INDEX('ИПЦ raw'!AB:AB, MATCH(Структура!$D51,'ИПЦ raw'!$A:$A,0)) -> 101.41 | R51: =INDEX('ИПЦ raw'!AC:AC, MATCH(Структура!$D51,'ИПЦ raw'!$A:$A,0)) -> 100.29 | S51: =INDEX('ИПЦ raw'!AD:AD, MATCH(Структура!$D51,'ИПЦ raw'!$A:$A,0)) -> 101.28 | T51: =INDEX('ИПЦ raw'!AE:AE, MATCH(Структура!$D51,'ИПЦ raw'!$A:$A,0)) -> 100.55 | U51: =INDEX('ИПЦ raw'!AF:AF, MATCH(Структура!$D51,'ИПЦ raw'!$A:$A,0)) -> 101.26 | V51: =INDEX('ИПЦ raw'!AG:AG, MATCH(Структура!$D51,'ИПЦ raw'!$A:$A,0)) -> 100.37 | W51: =INDEX('ИПЦ raw'!AH:AH, MATCH(Структура!$D51,'ИПЦ raw'!$A:$A,0)) -> 100.69 | X51: =INDEX('ИПЦ raw'!AI:AI, MATCH(Структура!$D51,'ИПЦ raw'!$A:$A,0)) -> 99.99 | Y51: =INDEX('ИПЦ raw'!AJ:AJ, MATCH(Структура!$D51,'ИПЦ raw'!$A:$A,0)) -> 100.57 | Z51: =INDEX('ИПЦ raw'!AK:AK, MATCH(Структура!$D51,'ИПЦ raw'!$A:$A,0)) -> 100.77 | AA51: =INDEX('ИПЦ raw'!AL:AL, MATCH(Структура!$D51,'ИПЦ raw'!$A:$A,0)) -> 100.72 | AB51: =INDEX('ИПЦ raw'!AM:AM, MATCH(Структура!$D51,'ИПЦ raw'!$A:$A,0)) -> 99.86 | AC51: =INDEX('ИПЦ raw'!AN:AN, MATCH(Структура!$D51,'ИПЦ raw'!$A:$A,0)) -> 100.08 | AD51: =INDEX('ИПЦ raw'!AO:AO, MATCH(Структура!$D51,'ИПЦ raw'!$A:$A,0)) -> 99.94 | AE51: =INDEX('ИПЦ raw'!AP:AP, MATCH(Структура!$D51,'ИПЦ raw'!$A:$A,0)) -> 100.38 | AG51: =INDEX('2025'!$C:$C,MATCH(Структура!C51,'2025'!$B:$B,0)) -> 0.045 | AH51: =AG51*P51/100 -> 0.045027 | AI51: =AH51*Q51/100 -> 0.045661881 | AJ51: =AI51*R51/100 -> 0.0457943 | AK51: =AJ51*S51/100 -> 0.046380467 | AL51: =AK51*T51/100 -> 0.04663556 | AM51: =AL51*U51/100 -> 0.047223168 | AN51: =AM51*V51/100 -> 0.047397894 | AO51: =AN51*W51/100 -> 0.047724939 | ... AR51: =AQ51*Z51/100 -> 0.048361711 | AS51: =J51 -> 0.043 | AT51: =AS51*AB51/100 -> 0.0429398 | AU51: =AT51*AC51/100 -> 0.042974152 | AV51: =AU51*AD51/100 -> 0.042948367 | AW51: =AV51*AE51/100 -> 0.043111571
A52: Национальные сыры и брынза, кг | B52: =A52 -> Национальные сыры и брынза, кг | C52: =A52 -> Национальные сыры и брынза, кг | D52: =C52 -> Национальные сыры и брынза, кг | E52: =INDEX(БИПЦ_НДС!$D:$D,MATCH(Структура!A52,БИПЦ_НДС!$B:$B,0)) -> 10 | F52: Проды | G52: 1 | H52: 1 | I52: 0 | J52: =INDEX('2026'!$C:$C,MATCH(Структура!B52,'2026'!$B:$B,0)) -> 0.199 | K52: =INDEX('2025'!$C:$C,MATCH(Структура!C52,'2025'!$B:$B,0)) -> 0.194 | L52: 1 | M52: 1 | N52: =INDEX(MoM!B:B,MATCH(Структура!A52,MoM!J:J,0)) -> 1 | P52: =INDEX('ИПЦ raw'!AA:AA, MATCH(Структура!$D52,'ИПЦ raw'!$A:$A,0)) -> 101.38 | Q52: =INDEX('ИПЦ raw'!AB:AB, MATCH(Структура!$D52,'ИПЦ raw'!$A:$A,0)) -> 101.85 | R52: =INDEX('ИПЦ raw'!AC:AC, MATCH(Структура!$D52,'ИПЦ raw'!$A:$A,0)) -> 100.3 | S52: =INDEX('ИПЦ raw'!AD:AD, MATCH(Структура!$D52,'ИПЦ raw'!$A:$A,0)) -> 100.22 | T52: =INDEX('ИПЦ raw'!AE:AE, MATCH(Структура!$D52,'ИПЦ raw'!$A:$A,0)) -> 99.9 | U52: =INDEX('ИПЦ raw'!AF:AF, MATCH(Структура!$D52,'ИПЦ raw'!$A:$A,0)) -> 99.97 | V52: =INDEX('ИПЦ raw'!AG:AG, MATCH(Структура!$D52,'ИПЦ raw'!$A:$A,0)) -> 99.87 | W52: =INDEX('ИПЦ raw'!AH:AH, MATCH(Структура!$D52,'ИПЦ raw'!$A:$A,0)) -> 100.47 | X52: =INDEX('ИПЦ raw'!AI:AI, MATCH(Структура!$D52,'ИПЦ raw'!$A:$A,0)) -> 100.7 | Y52: =INDEX('ИПЦ raw'!AJ:AJ, MATCH(Структура!$D52,'ИПЦ raw'!$A:$A,0)) -> 101.2 | Z52: =INDEX('ИПЦ raw'!AK:AK, MATCH(Структура!$D52,'ИПЦ raw'!$A:$A,0)) -> 100.47 | AA52: =INDEX('ИПЦ raw'!AL:AL, MATCH(Структура!$D52,'ИПЦ raw'!$A:$A,0)) -> 100.47 | AB52: =INDEX('ИПЦ raw'!AM:AM, MATCH(Структура!$D52,'ИПЦ raw'!$A:$A,0)) -> 100.59 | AC52: =INDEX('ИПЦ raw'!AN:AN, MATCH(Структура!$D52,'ИПЦ raw'!$A:$A,0)) -> 99.79 | AD52: =INDEX('ИПЦ raw'!AO:AO, MATCH(Структура!$D52,'ИПЦ raw'!$A:$A,0)) -> 99.57 | AE52: =INDEX('ИПЦ raw'!AP:AP, MATCH(Структура!$D52,'ИПЦ raw'!$A:$A,0)) -> 99.17 | AG52: =INDEX('2025'!$C:$C,MATCH(Структура!C52,'2025'!$B:$B,0)) -> 0.194 | AH52: =AG52*P52/100 -> 0.1966772 | AI52: =AH52*Q52/100 -> 0.20031573 | AJ52: =AI52*R52/100 -> 0.20091668 | AK52: =AJ52*S52/100 -> 0.20135869 | AL52: =AK52*T52/100 -> 0.20115733 | AM52: =AL52*U52/100 -> 0.20109699 | AN52: =AM52*V52/100 -> 0.20083556 | AO52: =AN52*W52/100 -> 0.20177949 | ... AR52: =AQ52*Z52/100 -> 0.20659671 | AS52: =J52 -> 0.199 | AT52: =AS52*AB52/100 -> 0.2001741 | AU52: =AT52*AC52/100 -> 0.19975373 | AV52: =AU52*AD52/100 -> 0.19889479 | AW52: =AV52*AE52/100 -> 0.19724397
A53: Овощи натуральные консервированные, маринованные, кг | B53: =A53 -> Овощи натуральные консервированные, маринованные, кг | C53: =A53 -> Овощи натуральные консервированные, маринованные, кг | D53: =C53 -> Овощи натуральные консервированные, маринованные, кг | E53: =INDEX(БИПЦ_НДС!$D:$D,MATCH(Структура!A53,БИПЦ_НДС!$B:$B,0)) -> 20 | F53: Проды | G53: 1 | H53: 1 | I53: 0 | J53: =INDEX('2026'!$C:$C,MATCH(Структура!B53,'2026'!$B:$B,0)) -> 0.245 | K53: =INDEX('2025'!$C:$C,MATCH(Структура!C53,'2025'!$B:$B,0)) -> 0.251 | L53: 1 | M53: 1 | N53: =INDEX(MoM!B:B,MATCH(Структура!A53,MoM!J:J,0)) -> 1 | P53: =INDEX('ИПЦ raw'!AA:AA, MATCH(Структура!$D53,'ИПЦ raw'!$A:$A,0)) -> 100.83 | Q53: =INDEX('ИПЦ raw'!AB:AB, MATCH(Структура!$D53,'ИПЦ raw'!$A:$A,0)) -> 100.52 | R53: =INDEX('ИПЦ raw'!AC:AC, MATCH(Структура!$D53,'ИПЦ raw'!$A:$A,0)) -> 100.64 | S53: =INDEX('ИПЦ raw'!AD:AD, MATCH(Структура!$D53,'ИПЦ raw'!$A:$A,0)) -> 100.53 | T53: =INDEX('ИПЦ raw'!AE:AE, MATCH(Структура!$D53,'ИПЦ raw'!$A:$A,0)) -> 100.82 | U53: =INDEX('ИПЦ raw'!AF:AF, MATCH(Структура!$D53,'ИПЦ raw'!$A:$A,0)) -> 100.17 | V53: =INDEX('ИПЦ raw'!AG:AG, MATCH(Структура!$D53,'ИПЦ raw'!$A:$A,0)) -> 101.07 | W53: =INDEX('ИПЦ raw'!AH:AH, MATCH(Структура!$D53,'ИПЦ raw'!$A:$A,0)) -> 100.39 | X53: =INDEX('ИПЦ raw'!AI:AI, MATCH(Структура!$D53,'ИПЦ raw'!$A:$A,0)) -> 100.25 | Y53: =INDEX('ИПЦ raw'!AJ:AJ, MATCH(Структура!$D53,'ИПЦ raw'!$A:$A,0)) -> 100.54 | Z53: =INDEX('ИПЦ raw'!AK:AK, MATCH(Структура!$D53,'ИПЦ raw'!$A:$A,0)) -> 100.38 | AA53: =INDEX('ИПЦ raw'!AL:AL, MATCH(Структура!$D53,'ИПЦ raw'!$A:$A,0)) -> 100.66 | AB53: =INDEX('ИПЦ raw'!AM:AM, MATCH(Структура!$D53,'ИПЦ raw'!$A:$A,0)) -> 101.89 | AC53: =INDEX('ИПЦ raw'!AN:AN, MATCH(Структура!$D53,'ИПЦ raw'!$A:$A,0)) -> 100.46 | AD53: =INDEX('ИПЦ raw'!AO:AO, MATCH(Структура!$D53,'ИПЦ raw'!$A:$A,0)) -> 99.92 | AE53: =INDEX('ИПЦ raw'!AP:AP, MATCH(Структура!$D53,'ИПЦ raw'!$A:$A,0)) -> 100.28 | AG53: =INDEX('2025'!$C:$C,MATCH(Структура!C53,'2025'!$B:$B,0)) -> 0.251 | AH53: =AG53*P53/100 -> 0.2530833 | AI53: =AH53*Q53/100 -> 0.25439933 | AJ53: =AI53*R53/100 -> 0.25602749 | AK53: =AJ53*S53/100 -> 0.25738443 | AL53: =AK53*T53/100 -> 0.25949499 | AM53: =AL53*U53/100 -> 0.25993613 | AN53: =AM53*V53/100 -> 0.26271744 | AO53: =AN53*W53/100 -> 0.26374204 | ... AR53: =AQ53*Z53/100 -> 0.26683932 | AS53: =J53 -> 0.245 | AT53: =AS53*AB53/100 -> 0.2496305 | AU53: =AT53*AC53/100 -> 0.2507788 | AV53: =AU53*AD53/100 -> 0.25057818 | AW53: =AV53*AE53/100 -> 0.2512798
A54: Горошек зеленый консервированный, кг | B54: =A54 -> Горошек зеленый консервированный, кг | C54: =A54 -> Горошек зеленый консервированный, кг | D54: =C54 -> Горошек зеленый консервированный, кг | E54: =INDEX(БИПЦ_НДС!$D:$D,MATCH(Структура!A54,БИПЦ_НДС!$B:$B,0)) -> 20 | F54: Проды | G54: 1 | H54: 1 | I54: 0 | J54: =INDEX('2026'!$C:$C,MATCH(Структура!B54,'2026'!$B:$B,0)) -> 0.102 | K54: =INDEX('2025'!$C:$C,MATCH(Структура!C54,'2025'!$B:$B,0)) -> 0.101 | L54: 1 | M54: 1 | N54: =INDEX(MoM!B:B,MATCH(Структура!A54,MoM!J:J,0)) -> 0 | P54: =INDEX('ИПЦ raw'!AA:AA, MATCH(Структура!$D54,'ИПЦ raw'!$A:$A,0)) -> 99.76 | Q54: =INDEX('ИПЦ raw'!AB:AB, MATCH(Структура!$D54,'ИПЦ raw'!$A:$A,0)) -> 100.33 | R54: =INDEX('ИПЦ raw'!AC:AC, MATCH(Структура!$D54,'ИПЦ raw'!$A:$A,0)) -> 100.18 | S54: =INDEX('ИПЦ raw'!AD:AD, MATCH(Структура!$D54,'ИПЦ raw'!$A:$A,0)) -> 101.14 | T54: =INDEX('ИПЦ raw'!AE:AE, MATCH(Структура!$D54,'ИПЦ raw'!$A:$A,0)) -> 100.16 | U54: =INDEX('ИПЦ raw'!AF:AF, MATCH(Структура!$D54,'ИПЦ raw'!$A:$A,0)) -> 100.69 | V54: =INDEX('ИПЦ raw'!AG:AG, MATCH(Структура!$D54,'ИПЦ raw'!$A:$A,0)) -> 100.18 | W54: =INDEX('ИПЦ raw'!AH:AH, MATCH(Структура!$D54,'ИПЦ raw'!$A:$A,0)) -> 100.25 | X54: =INDEX('ИПЦ raw'!AI:AI, MATCH(Структура!$D54,'ИПЦ raw'!$A:$A,0)) -> 100.24 | Y54: =INDEX('ИПЦ raw'!AJ:AJ, MATCH(Структура!$D54,'ИПЦ raw'!$A:$A,0)) -> 101.37 | Z54: =INDEX('ИПЦ raw'!AK:AK, MATCH(Структура!$D54,'ИПЦ raw'!$A:$A,0)) -> 100.79 | AA54: =INDEX('ИПЦ raw'!AL:AL, MATCH(Структура!$D54,'ИПЦ raw'!$A:$A,0)) -> 99.63 | AB54: =INDEX('ИПЦ raw'!AM:AM, MATCH(Структура!$D54,'ИПЦ raw'!$A:$A,0)) -> 102.52 | AC54: =INDEX('ИПЦ raw'!AN:AN, MATCH(Структура!$D54,'ИПЦ raw'!$A:$A,0)) -> 100.8 | AD54: =INDEX('ИПЦ raw'!AO:AO, MATCH(Структура!$D54,'ИПЦ raw'!$A:$A,0)) -> 99.74 | AE54: =INDEX('ИПЦ raw'!AP:AP, MATCH(Структура!$D54,'ИПЦ raw'!$A:$A,0)) -> 100.91 | AG54: =INDEX('2025'!$C:$C,MATCH(Структура!C54,'2025'!$B:$B,0)) -> 0.101 | AH54: =AG54*P54/100 -> 0.1007576 | AI54: =AH54*Q54/100 -> 0.1010901 | AJ54: =AI54*R54/100 -> 0.10127206 | AK54: =AJ54*S54/100 -> 0.10242656 | AL54: =AK54*T54/100 -> 0.10259045 | AM54: =AL54*U54/100 -> 0.10329832 | AN54: =AM54*V54/100 -> 0.10348426 | AO54: =AN54*W54/100 -> 0.10374297 | ... AR54: =AQ54*Z54/100 -> 0.10624943 | AS54: =J54 -> 0.102 | AT54: =AS54*AB54/100 -> 0.1045704 | AU54: =AT54*AC54/100 -> 0.10540696 | AV54: =AU54*AD54/100 -> 0.10513291 | AW54: =AV54*AE54/100 -> 0.10608961
A55: Консервы овощные для детского питания, кг | B55: =A55 -> Консервы овощные для детского питания, кг | C55: =A55 -> Консервы овощные для детского питания, кг | D55: =C55 -> Консервы овощные для детского питания, кг | E55: =INDEX(БИПЦ_НДС!$D:$D,MATCH(Структура!A55,БИПЦ_НДС!$B:$B,0)) -> 10 | F55: Проды | G55: 1 | H55: 1 | I55: 0 | J55: =INDEX('2026'!$C:$C,MATCH(Структура!B55,'2026'!$B:$B,0)) -> 0.016 | K55: =INDEX('2025'!$C:$C,MATCH(Структура!C55,'2025'!$B:$B,0)) -> 0.015 | L55: 1 | M55: 1 | N55: =INDEX(MoM!B:B,MATCH(Структура!A55,MoM!J:J,0)) -> 1 | P55: =INDEX('ИПЦ raw'!AA:AA, MATCH(Структура!$D55,'ИПЦ raw'!$A:$A,0)) -> 99.91 | Q55: =INDEX('ИПЦ raw'!AB:AB, MATCH(Структура!$D55,'ИПЦ raw'!$A:$A,0)) -> 101.51 | R55: =INDEX('ИПЦ raw'!AC:AC, MATCH(Структура!$D55,'ИПЦ raw'!$A:$A,0)) -> 101.75 | S55: =INDEX('ИПЦ raw'!AD:AD, MATCH(Структура!$D55,'ИПЦ raw'!$A:$A,0)) -> 101.11 | T55: =INDEX('ИПЦ raw'!AE:AE, MATCH(Структура!$D55,'ИПЦ raw'!$A:$A,0)) -> 100.61 | U55: =INDEX('ИПЦ raw'!AF:AF, MATCH(Структура!$D55,'ИПЦ raw'!$A:$A,0)) -> 99.96 | V55: =INDEX('ИПЦ raw'!AG:AG, MATCH(Структура!$D55,'ИПЦ raw'!$A:$A,0)) -> 100.25 | W55: =INDEX('ИПЦ raw'!AH:AH, MATCH(Структура!$D55,'ИПЦ raw'!$A:$A,0)) -> 100.87 | X55: =INDEX('ИПЦ raw'!AI:AI, MATCH(Структура!$D55,'ИПЦ raw'!$A:$A,0)) -> 100 | Y55: =INDEX('ИПЦ raw'!AJ:AJ, MATCH(Структура!$D55,'ИПЦ raw'!$A:$A,0)) -> 100.76 | Z55: =INDEX('ИПЦ raw'!AK:AK, MATCH(Структура!$D55,'ИПЦ raw'!$A:$A,0)) -> 100.1 | AA55: =INDEX('ИПЦ raw'!AL:AL, MATCH(Структура!$D55,'ИПЦ raw'!$A:$A,0)) -> 99.76 | AB55: =INDEX('ИПЦ raw'!AM:AM, MATCH(Структура!$D55,'ИПЦ raw'!$A:$A,0)) -> 100.99 | AC55: =INDEX('ИПЦ raw'!AN:AN, MATCH(Структура!$D55,'ИПЦ raw'!$A:$A,0)) -> 100.08 | AD55: =INDEX('ИПЦ raw'!AO:AO, MATCH(Структура!$D55,'ИПЦ raw'!$A:$A,0)) -> 101.09 | AE55: =INDEX('ИПЦ raw'!AP:AP, MATCH(Структура!$D55,'ИПЦ raw'!$A:$A,0)) -> 100.42 | AG55: =INDEX('2025'!$C:$C,MATCH(Структура!C55,'2025'!$B:$B,0)) -> 0.015 | AH55: =AG55*P55/100 -> 0.0149865 | AI55: =AH55*Q55/100 -> 0.015212796 | AJ55: =AI55*R55/100 -> 0.01547902 | AK55: =AJ55*S55/100 -> 0.015650837 | AL55: =AK55*T55/100 -> 0.015746307 | AM55: =AL55*U55/100 -> 0.015740009 | AN55: =AM55*V55/100 -> 0.015779359 | AO55: =AN55*W55/100 -> 0.015916639 | ... AR55: =AQ55*Z55/100 -> 0.016053643 | AS55: =J55 -> 0.016 | AT55: =AS55*AB55/100 -> 0.0161584 | AU55: =AT55*AC55/100 -> 0.016171327 | AV55: =AU55*AD55/100 -> 0.016347594 | AW55: =AV55*AE55/100 -> 0.016416254
A56: Консервы томатные, кг | B56: =A56 -> Консервы томатные, кг | C56: =A56 -> Консервы томатные, кг | D56: =C56 -> Консервы томатные, кг | E56: =INDEX(БИПЦ_НДС!$D:$D,MATCH(Структура!A56,БИПЦ_НДС!$B:$B,0)) -> 20 | F56: Проды | G56: 1 | H56: 1 | I56: 0 | J56: =INDEX('2026'!$C:$C,MATCH(Структура!B56,'2026'!$B:$B,0)) -> 0.135 | K56: =INDEX('2025'!$C:$C,MATCH(Структура!C56,'2025'!$B:$B,0)) -> 0.138 | L56: 1 | M56: 1 | N56: =INDEX(MoM!B:B,MATCH(Структура!A56,MoM!J:J,0)) -> 1 | P56: =INDEX('ИПЦ raw'!AA:AA, MATCH(Структура!$D56,'ИПЦ raw'!$A:$A,0)) -> 100.19 | Q56: =INDEX('ИПЦ raw'!AB:AB, MATCH(Структура!$D56,'ИПЦ raw'!$A:$A,0)) -> 100.02 | R56: =INDEX('ИПЦ raw'!AC:AC, MATCH(Структура!$D56,'ИПЦ raw'!$A:$A,0)) -> 100.17 | S56: =INDEX('ИПЦ raw'!AD:AD, MATCH(Структура!$D56,'ИПЦ raw'!$A:$A,0)) -> 100.09 | T56: =INDEX('ИПЦ raw'!AE:AE, MATCH(Структура!$D56,'ИПЦ raw'!$A:$A,0)) -> 100.22 | U56: =INDEX('ИПЦ raw'!AF:AF, MATCH(Структура!$D56,'ИПЦ raw'!$A:$A,0)) -> 99.52 | V56: =INDEX('ИПЦ raw'!AG:AG, MATCH(Структура!$D56,'ИПЦ raw'!$A:$A,0)) -> 100.04 | W56: =INDEX('ИПЦ raw'!AH:AH, MATCH(Структура!$D56,'ИПЦ raw'!$A:$A,0)) -> 100.35 | X56: =INDEX('ИПЦ raw'!AI:AI, MATCH(Структура!$D56,'ИПЦ raw'!$A:$A,0)) -> 99.8 | Y56: =INDEX('ИПЦ raw'!AJ:AJ, MATCH(Структура!$D56,'ИПЦ raw'!$A:$A,0)) -> 100.59 | Z56: =INDEX('ИПЦ raw'!AK:AK, MATCH(Структура!$D56,'ИПЦ raw'!$A:$A,0)) -> 100.18 | AA56: =INDEX('ИПЦ raw'!AL:AL, MATCH(Структура!$D56,'ИПЦ raw'!$A:$A,0)) -> 100.43 | AB56: =INDEX('ИПЦ raw'!AM:AM, MATCH(Структура!$D56,'ИПЦ raw'!$A:$A,0)) -> 100.78 | AC56: =INDEX('ИПЦ raw'!AN:AN, MATCH(Структура!$D56,'ИПЦ raw'!$A:$A,0)) -> 99.68 | AD56: =INDEX('ИПЦ raw'!AO:AO, MATCH(Структура!$D56,'ИПЦ raw'!$A:$A,0)) -> 100.03 | AE56: =INDEX('ИПЦ raw'!AP:AP, MATCH(Структура!$D56,'ИПЦ raw'!$A:$A,0)) -> 100.31 | AG56: =INDEX('2025'!$C:$C,MATCH(Структура!C56,'2025'!$B:$B,0)) -> 0.138 | AH56: =AG56*P56/100 -> 0.1382622 | AI56: =AH56*Q56/100 -> 0.13828985 | AJ56: =AI56*R56/100 -> 0.13852495 | AK56: =AJ56*S56/100 -> 0.13864962 | AL56: =AK56*T56/100 -> 0.13895465 | AM56: =AL56*U56/100 -> 0.13828766 | AN56: =AM56*V56/100 -> 0.13834298 | AO56: =AN56*W56/100 -> 0.13882718 | ... AR56: =AQ56*Z56/100 -> 0.13961783 | AS56: =J56 -> 0.135 | AT56: =AS56*AB56/100 -> 0.136053 | AU56: =AT56*AC56/100 -> 0.13561763 | AV56: =AU56*AD56/100 -> 0.13565832 | AW56: =AV56*AE56/100 -> 0.13607886
A57: Соки фруктовые, л | B57: =A57 -> Соки фруктовые, л | C57: =A57 -> Соки фруктовые, л | D57: =C57 -> Соки фруктовые, л | E57: =INDEX(БИПЦ_НДС!$D:$D,MATCH(Структура!A57,БИПЦ_НДС!$B:$B,0)) -> 10 | F57: Проды | G57: 1 | H57: 1 | I57: 0 | J57: =INDEX('2026'!$C:$C,MATCH(Структура!B57,'2026'!$B:$B,0)) -> 0.286 | K57: =INDEX('2025'!$C:$C,MATCH(Структура!C57,'2025'!$B:$B,0)) -> 0.281 | L57: 1 | M57: 1 | N57: =INDEX(MoM!B:B,MATCH(Структура!A57,MoM!J:J,0)) -> 1 | P57: =INDEX('ИПЦ raw'!AA:AA, MATCH(Структура!$D57,'ИПЦ raw'!$A:$A,0)) -> 101.13 | Q57: =INDEX('ИПЦ raw'!AB:AB, MATCH(Структура!$D57,'ИПЦ raw'!$A:$A,0)) -> 102.26 | R57: =INDEX('ИПЦ raw'!AC:AC, MATCH(Структура!$D57,'ИПЦ raw'!$A:$A,0)) -> 101.92 | S57: =INDEX('ИПЦ raw'!AD:AD, MATCH(Структура!$D57,'ИПЦ raw'!$A:$A,0)) -> 100.58 | T57: =INDEX('ИПЦ raw'!AE:AE, MATCH(Структура!$D57,'ИПЦ raw'!$A:$A,0)) -> 100.1 | U57: =INDEX('ИПЦ raw'!AF:AF, MATCH(Структура!$D57,'ИПЦ raw'!$A:$A,0)) -> 100.15 | V57: =INDEX('ИПЦ raw'!AG:AG, MATCH(Структура!$D57,'ИПЦ raw'!$A:$A,0)) -> 99.94 | W57: =INDEX('ИПЦ raw'!AH:AH, MATCH(Структура!$D57,'ИПЦ raw'!$A:$A,0)) -> 99.77 | X57: =INDEX('ИПЦ raw'!AI:AI, MATCH(Структура!$D57,'ИПЦ raw'!$A:$A,0)) -> 99.67 | Y57: =INDEX('ИПЦ raw'!AJ:AJ, MATCH(Структура!$D57,'ИПЦ raw'!$A:$A,0)) -> 99.96 | Z57: =INDEX('ИПЦ raw'!AK:AK, MATCH(Структура!$D57,'ИПЦ raw'!$A:$A,0)) -> 99.53 | AA57: =INDEX('ИПЦ raw'!AL:AL, MATCH(Структура!$D57,'ИПЦ raw'!$A:$A,0)) -> 99.58 | AB57: =INDEX('ИПЦ raw'!AM:AM, MATCH(Структура!$D57,'ИПЦ raw'!$A:$A,0)) -> 100.54 | AC57: =INDEX('ИПЦ raw'!AN:AN, MATCH(Структура!$D57,'ИПЦ raw'!$A:$A,0)) -> 99.62 | AD57: =INDEX('ИПЦ raw'!AO:AO, MATCH(Структура!$D57,'ИПЦ raw'!$A:$A,0)) -> 100.32 | AE57: =INDEX('ИПЦ raw'!AP:AP, MATCH(Структура!$D57,'ИПЦ raw'!$A:$A,0)) -> 99.86 | AG57: =INDEX('2025'!$C:$C,MATCH(Структура!C57,'2025'!$B:$B,0)) -> 0.281 | AH57: =AG57*P57/100 -> 0.2841753 | AI57: =AH57*Q57/100 -> 0.29059766 | AJ57: =AI57*R57/100 -> 0.29617714 | AK57: =AJ57*S57/100 -> 0.29789496 | AL57: =AK57*T57/100 -> 0.29819286 | AM57: =AL57*U57/100 -> 0.29864015 | AN57: =AM57*V57/100 -> 0.29846096 | AO57: =AN57*W57/100 -> 0.2977745 | ... AR57: =AQ57*Z57/100 -> 0.29527877 | AS57: =J57 -> 0.286 | AT57: =AS57*AB57/100 -> 0.2875444 | AU57: =AT57*AC57/100 -> 0.28645173 | AV57: =AU57*AD57/100 -> 0.28736838 | AW57: =AV57*AE57/100 -> 0.28696606
A58: Консервы фруктово-ягодные для детского питания, кг | B58: =A58 -> Консервы фруктово-ягодные для детского питания, кг | C58: =A58 -> Консервы фруктово-ягодные для детского питания, кг | D58: =C58 -> Консервы фруктово-ягодные для детского питания, кг | E58: =INDEX(БИПЦ_НДС!$D:$D,MATCH(Структура!A58,БИПЦ_НДС!$B:$B,0)) -> 10 | F58: Проды | G58: 1 | H58: 1 | I58: 0 | J58: =INDEX('2026'!$C:$C,MATCH(Структура!B58,'2026'!$B:$B,0)) -> 0.03 | K58: =INDEX('2025'!$C:$C,MATCH(Структура!C58,'2025'!$B:$B,0)) -> 0.03 | L58: 1 | M58: 1 | N58: =INDEX(MoM!B:B,MATCH(Структура!A58,MoM!J:J,0)) -> 1 | P58: =INDEX('ИПЦ raw'!AA:AA, MATCH(Структура!$D58,'ИПЦ raw'!$A:$A,0)) -> 100.61 | Q58: =INDEX('ИПЦ raw'!AB:AB, MATCH(Структура!$D58,'ИПЦ raw'!$A:$A,0)) -> 101.67 | R58: =INDEX('ИПЦ raw'!AC:AC, MATCH(Структура!$D58,'ИПЦ raw'!$A:$A,0)) -> 99.92 | S58: =INDEX('ИПЦ raw'!AD:AD, MATCH(Структура!$D58,'ИПЦ raw'!$A:$A,0)) -> 101.15 | T58: =INDEX('ИПЦ raw'!AE:AE, MATCH(Структура!$D58,'ИПЦ raw'!$A:$A,0)) -> 99.35 | U58: =INDEX('ИПЦ raw'!AF:AF, MATCH(Структура!$D58,'ИПЦ raw'!$A:$A,0)) -> 101.11 | V58: =INDEX('ИПЦ raw'!AG:AG, MATCH(Структура!$D58,'ИПЦ raw'!$A:$A,0)) -> 100.33 | W58: =INDEX('ИПЦ raw'!AH:AH, MATCH(Структура!$D58,'ИПЦ raw'!$A:$A,0)) -> 99.87 | X58: =INDEX('ИПЦ raw'!AI:AI, MATCH(Структура!$D58,'ИПЦ raw'!$A:$A,0)) -> 100.31 | Y58: =INDEX('ИПЦ raw'!AJ:AJ, MATCH(Структура!$D58,'ИПЦ raw'!$A:$A,0)) -> 100.97 | Z58: =INDEX('ИПЦ raw'!AK:AK, MATCH(Структура!$D58,'ИПЦ raw'!$A:$A,0)) -> 99.47 | AA58: =INDEX('ИПЦ raw'!AL:AL, MATCH(Структура!$D58,'ИПЦ raw'!$A:$A,0)) -> 100.34 | AB58: =INDEX('ИПЦ raw'!AM:AM, MATCH(Структура!$D58,'ИПЦ raw'!$A:$A,0)) -> 101.81 | AC58: =INDEX('ИПЦ raw'!AN:AN, MATCH(Структура!$D58,'ИПЦ raw'!$A:$A,0)) -> 100.04 | AD58: =INDEX('ИПЦ raw'!AO:AO, MATCH(Структура!$D58,'ИПЦ raw'!$A:$A,0)) -> 100.31 | AE58: =INDEX('ИПЦ raw'!AP:AP, MATCH(Структура!$D58,'ИПЦ raw'!$A:$A,0)) -> 100.62 | AG58: =INDEX('2025'!$C:$C,MATCH(Структура!C58,'2025'!$B:$B,0)) -> 0.03 | AH58: =AG58*P58/100 -> 0.030183 | AI58: =AH58*Q58/100 -> 0.030687056 | AJ58: =AI58*R58/100 -> 0.030662506 | AK58: =AJ58*S58/100 -> 0.031015125 | AL58: =AK58*T58/100 -> 0.030813527 | AM58: =AL58*U58/100 -> 0.031155557 | AN58: =AM58*V58/100 -> 0.03125837 | AO58: =AN58*W58/100 -> 0.031217735 | ... AR58: =AQ58*Z58/100 -> 0.031450684 | AS58: =J58 -> 0.03 | AT58: =AS58*AB58/100 -> 0.030543 | AU58: =AT58*AC58/100 -> 0.030555217 | AV58: =AU58*AD58/100 -> 0.030649938 | AW58: =AV58*AE58/100 -> 0.030839968
A59: Зефир, пастила, кг | B59: =A59 -> Зефир, пастила, кг | C59: =A59 -> Зефир, пастила, кг | D59: =C59 -> Зефир, пастила, кг | E59: =INDEX(БИПЦ_НДС!$D:$D,MATCH(Структура!A59,БИПЦ_НДС!$B:$B,0)) -> 20 | F59: Проды | G59: 1 | H59: 1 | I59: 0 | J59: =INDEX('2026'!$C:$C,MATCH(Структура!B59,'2026'!$B:$B,0)) -> 0.164 | K59: =INDEX('2025'!$C:$C,MATCH(Структура!C59,'2025'!$B:$B,0)) -> 0.144 | L59: 1 | M59: 1 | N59: =INDEX(MoM!B:B,MATCH(Структура!A59,MoM!J:J,0)) -> 1 | P59: =INDEX('ИПЦ raw'!AA:AA, MATCH(Структура!$D59,'ИПЦ raw'!$A:$A,0)) -> 100.18 | Q59: =INDEX('ИПЦ raw'!AB:AB, MATCH(Структура!$D59,'ИПЦ raw'!$A:$A,0)) -> 101.28 | R59: =INDEX('ИПЦ raw'!AC:AC, MATCH(Структура!$D59,'ИПЦ raw'!$A:$A,0)) -> 100.63 | S59: =INDEX('ИПЦ raw'!AD:AD, MATCH(Структура!$D59,'ИПЦ raw'!$A:$A,0)) -> 101.37 | T59: =INDEX('ИПЦ raw'!AE:AE, MATCH(Структура!$D59,'ИПЦ raw'!$A:$A,0)) -> 100.52 | U59: =INDEX('ИПЦ raw'!AF:AF, MATCH(Структура!$D59,'ИПЦ raw'!$A:$A,0)) -> 100.76 | V59: =INDEX('ИПЦ raw'!AG:AG, MATCH(Структура!$D59,'ИПЦ raw'!$A:$A,0)) -> 100.74 | W59: =INDEX('ИПЦ raw'!AH:AH, MATCH(Структура!$D59,'ИПЦ raw'!$A:$A,0)) -> 99.73 | X59: =INDEX('ИПЦ raw'!AI:AI, MATCH(Структура!$D59,'ИПЦ raw'!$A:$A,0)) -> 100.49 | Y59: =INDEX('ИПЦ raw'!AJ:AJ, MATCH(Структура!$D59,'ИПЦ raw'!$A:$A,0)) -> 100.65 | Z59: =INDEX('ИПЦ raw'!AK:AK, MATCH(Структура!$D59,'ИПЦ raw'!$A:$A,0)) -> 100.29 | AA59: =INDEX('ИПЦ raw'!AL:AL, MATCH(Структура!$D59,'ИПЦ raw'!$A:$A,0)) -> 100.18 | AB59: =INDEX('ИПЦ raw'!AM:AM, MATCH(Структура!$D59,'ИПЦ raw'!$A:$A,0)) -> 101.18 | AC59: =INDEX('ИПЦ raw'!AN:AN, MATCH(Структура!$D59,'ИПЦ raw'!$A:$A,0)) -> 100.54 | AD59: =INDEX('ИПЦ raw'!AO:AO, MATCH(Структура!$D59,'ИПЦ raw'!$A:$A,0)) -> 100.85 | AE59: =INDEX('ИПЦ raw'!AP:AP, MATCH(Структура!$D59,'ИПЦ raw'!$A:$A,0)) -> 99.97 | AG59: =INDEX('2025'!$C:$C,MATCH(Структура!C59,'2025'!$B:$B,0)) -> 0.144 | AH59: =AG59*P59/100 -> 0.1442592 | AI59: =AH59*Q59/100 -> 0.14610572 | AJ59: =AI59*R59/100 -> 0.14702618 | AK59: =AJ59*S59/100 -> 0.14904044 | AL59: =AK59*T59/100 -> 0.14981545 | AM59: =AL59*U59/100 -> 0.15095405 | AN59: =AM59*V59/100 -> 0.15207111 | AO59: =AN59*W59/100 -> 0.15166052 | ... AR59: =AQ59*Z59/100 -> 0.15383912 | AS59: =J59 -> 0.164 | AT59: =AS59*AB59/100 -> 0.1659352 | AU59: =AT59*AC59/100 -> 0.16683125 | AV59: =AU59*AD59/100 -> 0.16824932 | AW59: =AV59*AE59/100 -> 0.16819884
... A98: Пиво, л | B98: =A98 -> Пиво, л | C98: =A98 -> Пиво, л | D98: =C98 -> Пиво, л | E98: =INDEX(БИПЦ_НДС!$D:$D,MATCH(Структура!A98,БИПЦ_НДС!$B:$B,0)) -> 20 | F98: Проды | G98: 1 | H98: 1 | I98: 0 | J98: =INDEX('2026'!$C:$C,MATCH(Структура!B98,'2026'!$B:$B,0)) -> 1.202 | K98: =INDEX('2025'!$C:$C,MATCH(Структура!C98,'2025'!$B:$B,0)) -> 1.09 | L98: 1 | M98: 1 | N98: =INDEX(MoM!B:B,MATCH(Структура!A98,MoM!J:J,0)) -> 1 | P98: =INDEX('ИПЦ raw'!AA:AA, MATCH(Структура!$D98,'ИПЦ raw'!$A:$A,0)) -> 101.33 | Q98: =INDEX('ИПЦ raw'!AB:AB, MATCH(Структура!$D98,'ИПЦ raw'!$A:$A,0)) -> 103.02 | R98: =INDEX('ИПЦ raw'!AC:AC, MATCH(Структура!$D98,'ИПЦ raw'!$A:$A,0)) -> 101.89 | S98: =INDEX('ИПЦ raw'!AD:AD, MATCH(Структура!$D98,'ИПЦ raw'!$A:$A,0)) -> 101.79 | T98: =INDEX('ИПЦ raw'!AE:AE, MATCH(Структура!$D98,'ИПЦ raw'!$A:$A,0)) -> 101.04 | U98: =INDEX('ИПЦ raw'!AF:AF, MATCH(Структура!$D98,'ИПЦ raw'!$A:$A,0)) -> 102.03 | V98: =INDEX('ИПЦ raw'!AG:AG, MATCH(Структура!$D98,'ИПЦ raw'!$A:$A,0)) -> 100.68 | W98: =INDEX('ИПЦ raw'!AH:AH, MATCH(Структура!$D98,'ИПЦ raw'!$A:$A,0)) -> 100.16 | X98: =INDEX('ИПЦ raw'!AI:AI, MATCH(Структура!$D98,'ИПЦ raw'!$A:$A,0)) -> 100.32 | Y98: =INDEX('ИПЦ raw'!AJ:AJ, MATCH(Структура!$D98,'ИПЦ raw'!$A:$A,0)) -> 100.74 | Z98: =INDEX('ИПЦ raw'!AK:AK, MATCH(Структура!$D98,'ИПЦ raw'!$A:$A,0)) -> 100.05 | AA98: =INDEX('ИПЦ raw'!AL:AL, MATCH(Структура!$D98,'ИПЦ raw'!$A:$A,0)) -> 101.12 | AB98: =INDEX('ИПЦ raw'!AM:AM, MATCH(Структура!$D98,'ИПЦ raw'!$A:$A,0)) -> 101.53 | AC98: =INDEX('ИПЦ raw'!AN:AN, MATCH(Структура!$D98,'ИПЦ raw'!$A:$A,0)) -> 101.49 | AD98: =INDEX('ИПЦ raw'!AO:AO, MATCH(Структура!$D98,'ИПЦ raw'!$A:$A,0)) -> 100.65 | AE98: =INDEX('ИПЦ raw'!AP:AP, MATCH(Структура!$D98,'ИПЦ raw'!$A:$A,0)) -> 101.77 | AG98: =INDEX('2025'!$C:$C,MATCH(Структура!C98,'2025'!$B:$B,0)) -> 1.09 | AH98: =AG98*P98/100 -> 1.104497 | AI98: =AH98*Q98/100 -> 1.1378528 | AJ98: =AI98*R98/100 -> 1.1593582 | AK98: =AJ98*S98/100 -> 1.1801107 | AL98: =AK98*T98/100 -> 1.1923839 | AM98: =AL98*U98/100 -> 1.2165893 | AN98: =AM98*V98/100 -> 1.2248621 | AO98: =AN98*W98/100 -> 1.2268219 | ... AR98: =AQ98*Z98/100 -> 1.2404752 | AS98: =J98 -> 1.202 | AT98: =AS98*AB98/100 -> 1.2203906 | AU98: =AT98*AC98/100 -> 1.2385744 | AV98: =AU98*AD98/100 -> 1.2466252 | AW98: =AV98*AE98/100 -> 1.2686904
A99: Вода минеральная и питьевая, л | B99: =A99 -> Вода минеральная и питьевая, л | C99: =A99 -> Вода минеральная и питьевая, л | D99: =C99 -> Вода минеральная и питьевая, л | E99: =INDEX(БИПЦ_НДС!$D:$D,MATCH(Структура!A99,БИПЦ_НДС!$B:$B,0)) -> 20 | F99: Проды | G99: 1 | H99: 1 | I99: 0 | J99: ='2026'!C192+'2026'!C193 -> 0.163 | K99: =INDEX('2025'!$C:$C,MATCH(Структура!C99,'2025'!$B:$B,0)) -> 0.143 | L99: 1 | M99: 1 | N99: =INDEX(MoM!B:B,MATCH(Структура!A99,MoM!J:J,0)) -> 1 | P99: =INDEX('ИПЦ raw'!AA:AA, MATCH(Структура!$D99,'ИПЦ raw'!$A:$A,0)) -> 100.75 | Q99: =INDEX('ИПЦ raw'!AB:AB, MATCH(Структура!$D99,'ИПЦ raw'!$A:$A,0)) -> 101.94 | R99: =INDEX('ИПЦ raw'!AC:AC, MATCH(Структура!$D99,'ИПЦ raw'!$A:$A,0)) -> 101.59 | S99: =INDEX('ИПЦ raw'!AD:AD, MATCH(Структура!$D99,'ИПЦ raw'!$A:$A,0)) -> 101.09 | T99: =INDEX('ИПЦ raw'!AE:AE, MATCH(Структура!$D99,'ИПЦ raw'!$A:$A,0)) -> 100.8 | U99: =INDEX('ИПЦ raw'!AF:AF, MATCH(Структура!$D99,'ИПЦ raw'!$A:$A,0)) -> 100.83 | V99: =INDEX('ИПЦ raw'!AG:AG, MATCH(Структура!$D99,'ИПЦ raw'!$A:$A,0)) -> 100.84 | W99: =INDEX('ИПЦ raw'!AH:AH, MATCH(Структура!$D99,'ИПЦ raw'!$A:$A,0)) -> 100.55 | X99: =INDEX('ИПЦ raw'!AI:AI, MATCH(Структура!$D99,'ИПЦ raw'!$A:$A,0)) -> 100.17 | Y99: =INDEX('ИПЦ raw'!AJ:AJ, MATCH(Структура!$D99,'ИПЦ raw'!$A:$A,0)) -> 100.58 | Z99: =INDEX('ИПЦ raw'!AK:AK, MATCH(Структура!$D99,'ИПЦ raw'!$A:$A,0)) -> 100.16 | AA99: =INDEX('ИПЦ raw'!AL:AL, MATCH(Структура!$D99,'ИПЦ raw'!$A:$A,0)) -> 100.63 | AB99: ='ИПЦ raw'!AM172 -> 100.58 | AC99: ='ИПЦ raw'!AN172 -> 100.54 | AD99: ='ИПЦ raw'!AO172 -> 100.96 | AE99: ='ИПЦ raw'!AP172 -> 100.74 | AG99: =INDEX('2025'!$C:$C,MATCH(Структура!C99,'2025'!$B:$B,0)) -> 0.143 | AH99: =AG99*P99/100 -> 0.1440725 | AI99: =AH99*Q99/100 -> 0.14686751 | AJ99: =AI99*R99/100 -> 0.1492027 | AK99: =AJ99*S99/100 -> 0.15082901 | AL99: =AK99*T99/100 -> 0.15203564 | AM99: =AL99*U99/100 -> 0.15329754 | AN99: =AM99*V99/100 -> 0.15458524 | AO99: =AN99*W99/100 -> 0.15543546 | ... AR99: =AQ99*Z99/100 -> 0.15685332 | AS99: =J99 -> 0.163 | AT99: =AS99*AB99/100 -> 0.1639454 | AU99: =AT99*AC99/100 -> 0.16483071 | AV99: =AU99*AD99/100 -> 0.16641308 | AW99: =AV99*AE99/100 -> 0.16764454
A100: Напитки газированные, л | B100: =A100 -> Напитки газированные, л | C100: =A100 -> Напитки газированные, л | D100: =C100 -> Напитки газированные, л | E100: =INDEX(БИПЦ_НДС!$D:$D,MATCH(Структура!A100,БИПЦ_НДС!$B:$B,0)) -> 20 | F100: Проды | G100: 1 | H100: 1 | I100: 0 | J100: =INDEX('2026'!$C:$C,MATCH(Структура!B100,'2026'!$B:$B,0)) -> 0.241 | K100: =INDEX('2025'!$C:$C,MATCH(Структура!C100,'2025'!$B:$B,0)) -> 0.223 | L100: 1 | M100: 1 | N100: =INDEX(MoM!B:B,MATCH(Структура!A100,MoM!J:J,0)) -> 1 | P100: =INDEX('ИПЦ raw'!AA:AA, MATCH(Структура!$D100,'ИПЦ raw'!$A:$A,0)) -> 100.54 | Q100: =INDEX('ИПЦ raw'!AB:AB, MATCH(Структура!$D100,'ИПЦ raw'!$A:$A,0)) -> 102.35 | R100: =INDEX('ИПЦ raw'!AC:AC, MATCH(Структура!$D100,'ИПЦ raw'!$A:$A,0)) -> 101.55 | S100: =INDEX('ИПЦ raw'!AD:AD, MATCH(Структура!$D100,'ИПЦ raw'!$A:$A,0)) -> 100.6 | T100: =INDEX('ИПЦ raw'!AE:AE, MATCH(Структура!$D100,'ИПЦ raw'!$A:$A,0)) -> 100.95 | U100: =INDEX('ИПЦ raw'!AF:AF, MATCH(Структура!$D100,'ИПЦ raw'!$A:$A,0)) -> 100.66 | V100: =INDEX('ИПЦ raw'!AG:AG, MATCH(Структура!$D100,'ИПЦ raw'!$A:$A,0)) -> 100.38 | W100: =INDEX('ИПЦ raw'!AH:AH, MATCH(Структура!$D100,'ИПЦ raw'!$A:$A,0)) -> 100.39 | X100: =INDEX('ИПЦ raw'!AI:AI, MATCH(Структура!$D100,'ИПЦ raw'!$A:$A,0)) -> 100.29 | Y100: =INDEX('ИПЦ raw'!AJ:AJ, MATCH(Структура!$D100,'ИПЦ raw'!$A:$A,0)) -> 99.71 | Z100: =INDEX('ИПЦ raw'!AK:AK, MATCH(Структура!$D100,'ИПЦ raw'!$A:$A,0)) -> 99.94 | AA100: =INDEX('ИПЦ raw'!AL:AL, MATCH(Структура!$D100,'ИПЦ raw'!$A:$A,0)) -> 100.16 | AB100: =INDEX('ИПЦ raw'!AM:AM, MATCH(Структура!$D100,'ИПЦ raw'!$A:$A,0)) -> 101.3 | AC100: =INDEX('ИПЦ raw'!AN:AN, MATCH(Структура!$D100,'ИПЦ raw'!$A:$A,0)) -> 100.51 | AD100: =INDEX('ИПЦ raw'!AO:AO, MATCH(Структура!$D100,'ИПЦ raw'!$A:$A,0)) -> 101.17 | AE100: =INDEX('ИПЦ raw'!AP:AP, MATCH(Структура!$D100,'ИПЦ raw'!$A:$A,0)) -> 101.29 | AG100: =INDEX('2025'!$C:$C,MATCH(Структура!C100,'2025'!$B:$B,0)) -> 0.223 | AH100: =AG100*P100/100 -> 0.2242042 | AI100: =AH100*Q100/100 -> 0.229473 | AJ100: =AI100*R100/100 -> 0.23302983 | AK100: =AJ100*S100/100 -> 0.23442801 | AL100: =AK100*T100/100 -> 0.23665508 | AM100: =AL100*U100/100 -> 0.238217 | AN100: =AM100*V100/100 -> 0.23912222 | AO100: =AN100*W100/100 -> 0.2400548 | ... AR100: =AQ100*Z100/100 -> 0.23990875 | AS100: =J100 -> 0.241 | AT100: =AS100*AB100/100 -> 0.244133 | AU100: =AT100*AC100/100 -> 0.24537808 | AV100: =AU100*AD100/100 -> 0.248249 | AW100: =AV100*AE100/100 -> 0.25145141
A101: Мороженое сливочное, кг | B101: =A101 -> Мороженое сливочное, кг | C101: =A101 -> Мороженое сливочное, кг | D101: =C101 -> Мороженое сливочное, кг | E101: =INDEX(БИПЦ_НДС!$D:$D,MATCH(Структура!A101,БИПЦ_НДС!$B:$B,0)) -> 10 | F101: Проды | G101: 1 | H101: 1 | I101: 0 | J101: =INDEX('2026'!$C:$C,MATCH(Структура!B101,'2026'!$B:$B,0)) -> 0.366 | K101: =INDEX('2025'!$C:$C,MATCH(Структура!C101,'2025'!$B:$B,0)) -> 0.345 | L101: 1 | M101: 1 | N101: =INDEX(MoM!B:B,MATCH(Структура!A101,MoM!J:J,0)) -> 1 | P101: =INDEX('ИПЦ raw'!AA:AA, MATCH(Структура!$D101,'ИПЦ raw'!$A:$A,0)) -> 101.14 | Q101: =INDEX('ИПЦ raw'!AB:AB, MATCH(Структура!$D101,'ИПЦ raw'!$A:$A,0)) -> 101.4 | R101: =INDEX('ИПЦ raw'!AC:AC, MATCH(Структура!$D101,'ИПЦ raw'!$A:$A,0)) -> 102.03 | S101: =INDEX('ИПЦ raw'!AD:AD, MATCH(Структура!$D101,'ИПЦ raw'!$A:$A,0)) -> 101.66 | T101: =INDEX('ИПЦ raw'!AE:AE, MATCH(Структура!$D101,'ИПЦ raw'!$A:$A,0)) -> 100.95 | U101: =INDEX('ИПЦ raw'!AF:AF, MATCH(Структура!$D101,'ИПЦ raw'!$A:$A,0)) -> 101.45 | V101: =INDEX('ИПЦ raw'!AG:AG, MATCH(Структура!$D101,'ИПЦ raw'!$A:$A,0)) -> 100.74 | W101: =INDEX('ИПЦ raw'!AH:AH, MATCH(Структура!$D101,'ИПЦ raw'!$A:$A,0)) -> 100.27 | X101: =INDEX('ИПЦ raw'!AI:AI, MATCH(Структура!$D101,'ИПЦ raw'!$A:$A,0)) -> 100.48 | Y101: =INDEX('ИПЦ raw'!AJ:AJ, MATCH(Структура!$D101,'ИПЦ raw'!$A:$A,0)) -> 100.26 | Z101: =INDEX('ИПЦ raw'!AK:AK, MATCH(Структура!$D101,'ИПЦ raw'!$A:$A,0)) -> 100.19 | AA101: =INDEX('ИПЦ raw'!AL:AL, MATCH(Структура!$D101,'ИПЦ raw'!$A:$A,0)) -> 99.96 | AB101: =INDEX('ИПЦ raw'!AM:AM, MATCH(Структура!$D101,'ИПЦ raw'!$A:$A,0)) -> 100.47 | AC101: =INDEX('ИПЦ raw'!AN:AN, MATCH(Структура!$D101,'ИПЦ raw'!$A:$A,0)) -> 100.19 | AD101: =INDEX('ИПЦ raw'!AO:AO, MATCH(Структура!$D101,'ИПЦ raw'!$A:$A,0)) -> 100.08 | AE101: =INDEX('ИПЦ raw'!AP:AP, MATCH(Структура!$D101,'ИПЦ raw'!$A:$A,0)) -> 100.21 | AG101: =INDEX('2025'!$C:$C,MATCH(Структура!C101,'2025'!$B:$B,0)) -> 0.345 | AH101: =AG101*P101/100 -> 0.348933 | AI101: =AH101*Q101/100 -> 0.35381806 | AJ101: =AI101*R101/100 -> 0.36100057 | AK101: =AJ101*S101/100 -> 0.36699318 | AL101: =AK101*T101/100 -> 0.37047961 | AM101: =AL101*U101/100 -> 0.37585157 | AN101: =AM101*V101/100 -> 0.37863287 | AO101: =AN101*W101/100 -> 0.37965518 | ... AR101: =AQ101*Z101/100 -> 0.38319606 | AS101: =J101 -> 0.366 | AT101: =AS101*AB101/100 -> 0.3677202 | AU101: =AT101*AC101/100 -> 0.36841887 | AV101: =AU101*AD101/100 -> 0.3687136 | AW101: =AV101*AE101/100 -> 0.3694879
A102: Кофе в организациях быстрого обслуживания, 200 г | B102: =A102 -> Кофе в организациях быстрого обслуживания, 200 г | C102: =A102 -> Кофе в организациях быстрого обслуживания, 200 г | D102: =C102 -> Кофе в организациях быстрого обслуживания, 200 г | E102: =INDEX(БИПЦ_НДС!$D:$D,MATCH(Структура!A102,БИПЦ_НДС!$B:$B,0)) -> 20 | F102: Проды | G102: 1 | H102: 1 | I102: 1 | J102: =INDEX('2026'!$C:$C,MATCH(Структура!B102,'2026'!$B:$B,0)) -> 0.303 | K102: =INDEX('2025'!$C:$C,MATCH(Структура!C102,'2025'!$B:$B,0)) -> 0.221 | L102: 1 | M102: 1 | N102: =INDEX(MoM!B:B,MATCH(Структура!A102,MoM!J:J,0)) -> 0 | P102: =INDEX('ИПЦ raw'!AA:AA, MATCH(Структура!$D102,'ИПЦ raw'!$A:$A,0)) -> 101.2 | Q102: =INDEX('ИПЦ raw'!AB:AB, MATCH(Структура!$D102,'ИПЦ raw'!$A:$A,0)) -> 101.17 | R102: =INDEX('ИПЦ raw'!AC:AC, MATCH(Структура!$D102,'ИПЦ raw'!$A:$A,0)) -> 100.95 | S102: =INDEX('ИПЦ raw'!AD:AD, MATCH(Структура!$D102,'ИПЦ raw'!$A:$A,0)) -> 101.43 | T102: =INDEX('ИПЦ raw'!AE:AE, MATCH(Структура!$D102,'ИПЦ raw'!$A:$A,0)) -> 100.96 | U102: =INDEX('ИПЦ raw'!AF:AF, MATCH(Структура!$D102,'ИПЦ raw'!$A:$A,0)) -> 101.04 | V102: =INDEX('ИПЦ raw'!AG:AG, MATCH(Структура!$D102,'ИПЦ raw'!$A:$A,0)) -> 100.77 | W102: =INDEX('ИПЦ raw'!AH:AH, MATCH(Структура!$D102,'ИПЦ raw'!$A:$A,0)) -> 100.49 | X102: =INDEX('ИПЦ raw'!AI:AI, MATCH(Структура!$D102,'ИПЦ raw'!$A:$A,0)) -> 100.69 | Y102: =INDEX('ИПЦ raw'!AJ:AJ, MATCH(Структура!$D102,'ИПЦ raw'!$A:$A,0)) -> 100.75 | Z102: =INDEX('ИПЦ raw'!AK:AK, MATCH(Структура!$D102,'ИПЦ raw'!$A:$A,0)) -> 100.42 | AA102: =INDEX('ИПЦ raw'!AL:AL, MATCH(Структура!$D102,'ИПЦ raw'!$A:$A,0)) -> 100.99 | AB102: =INDEX('ИПЦ raw'!AM:AM, MATCH(Структура!$D102,'ИПЦ raw'!$A:$A,0)) -> 100.82 | AC102: =INDEX('ИПЦ raw'!AN:AN, MATCH(Структура!$D102,'ИПЦ raw'!$A:$A,0)) -> 100.83 | AD102: =INDEX('ИПЦ raw'!AO:AO, MATCH(Структура!$D102,'ИПЦ raw'!$A:$A,0)) -> 100.74 | AE102: =INDEX('ИПЦ raw'!AP:AP, MATCH(Структура!$D102,'ИПЦ raw'!$A:$A,0)) -> 99.46 | AG102: =INDEX('2025'!$C:$C,MATCH(Структура!C102,'2025'!$B:$B,0)) -> 0.221 | AH102: =AG102*P102/100 -> 0.223652 | AI102: =AH102*Q102/100 -> 0.22626873 | AJ102: =AI102*R102/100 -> 0.22841828 | AK102: =AJ102*S102/100 -> 0.23168466 | AL102: =AK102*T102/100 -> 0.23390884 | AM102: =AL102*U102/100 -> 0.23634149 | AN102: =AM102*V102/100 -> 0.23816132 | AO102: =AN102*W102/100 -> 0.23932831 | ... AR102: =AQ102*Z102/100 -> 0.24380673 | AS102: =J102 -> 0.303 | AT102: =AS102*AB102/100 -> 0.3054846 | AU102: =AT102*AC102/100 -> 0.30802012 | AV102: =AU102*AD102/100 -> 0.31029947 | AW102: =AV102*AE102/100 -> 0.30862385
A103: Продукция предприятий общественного питания быстрого обслуживания, шт. | B103: =A103 -> Продукция предприятий общественного питания быстрого обслуживания, шт. | C103: =A103 -> Продукция предприятий общественного питания быстрого обслуживания, шт. | D103: Продукция предприятий общественного питания быстрого обслуживания, шт. | E103: =INDEX(БИПЦ_НДС!$D:$D,MATCH(Структура!A103,БИПЦ_НДС!$B:$B,0)) -> 20 | F103: Проды | G103: 1 | H103: 1 | I103: 1 | J103: =INDEX('2026'!$C:$C,MATCH(Структура!B103,'2026'!$B:$B,0)) -> 0.409 | K103: =INDEX('2025'!$C:$C,MATCH(Структура!C103,'2025'!$B:$B,0)) -> 0.34 | L103: 1 | M103: 1 | N103: =INDEX(MoM!B:B,MATCH(Структура!A103,MoM!J:J,0)) -> 0 | P103: =INDEX('ИПЦ raw'!AA:AA, MATCH(Структура!$D103,'ИПЦ raw'!$A:$A,0)) -> 100.84 | Q103: =INDEX('ИПЦ raw'!AB:AB, MATCH(Структура!$D103,'ИПЦ raw'!$A:$A,0)) -> 100.68 | R103: =INDEX('ИПЦ raw'!AC:AC, MATCH(Структура!$D103,'ИПЦ raw'!$A:$A,0)) -> 100.3 | S103: =INDEX('ИПЦ raw'!AD:AD, MATCH(Структура!$D103,'ИПЦ raw'!$A:$A,0)) -> 101.3 | T103: =INDEX('ИПЦ raw'!AE:AE, MATCH(Структура!$D103,'ИПЦ raw'!$A:$A,0)) -> 100.99 | U103: =INDEX('ИПЦ raw'!AF:AF, MATCH(Структура!$D103,'ИПЦ raw'!$A:$A,0)) -> 99.91 | V103: =INDEX('ИПЦ raw'!AG:AG, MATCH(Структура!$D103,'ИПЦ raw'!$A:$A,0)) -> 101.85 | W103: =INDEX('ИПЦ raw'!AH:AH, MATCH(Структура!$D103,'ИПЦ raw'!$A:$A,0)) -> 100.66 | X103: =INDEX('ИПЦ raw'!AI:AI, MATCH(Структура!$D103,'ИПЦ raw'!$A:$A,0)) -> 100.77 | Y103: =INDEX('ИПЦ raw'!AJ:AJ, MATCH(Структура!$D103,'ИПЦ raw'!$A:$A,0)) -> 100.99 | Z103: =INDEX('ИПЦ raw'!AK:AK, MATCH(Структура!$D103,'ИПЦ raw'!$A:$A,0)) -> 100.62 | AA103: =INDEX('ИПЦ raw'!AL:AL, MATCH(Структура!$D103,'ИПЦ raw'!$A:$A,0)) -> 100.65 | AB103: =INDEX('ИПЦ raw'!AM:AM, MATCH(Структура!$D103,'ИПЦ raw'!$A:$A,0)) -> 101.7 | AC103: =INDEX('ИПЦ raw'!AN:AN, MATCH(Структура!$D103,'ИПЦ raw'!$A:$A,0)) -> 100.32 | AD103: =INDEX('ИПЦ raw'!AO:AO, MATCH(Структура!$D103,'ИПЦ raw'!$A:$A,0)) -> 101.27 | AE103: =INDEX('ИПЦ raw'!AP:AP, MATCH(Структура!$D103,'ИПЦ raw'!$A:$A,0)) -> 99.57 | AG103: =INDEX('2025'!$C:$C,MATCH(Структура!C103,'2025'!$B:$B,0)) -> 0.34 | AH103: =AG103*P103/100 -> 0.342856 | AI103: =AH103*Q103/100 -> 0.34518742 | AJ103: =AI103*R103/100 -> 0.34622298 | AK103: =AJ103*S103/100 -> 0.35072388 | AL103: =AK103*T103/100 -> 0.35419605 | AM103: =AL103*U103/100 -> 0.35387727 | AN103: =AM103*V103/100 -> 0.360424 | AO103: =AN103*W103/100 -> 0.3628028 | ... AR103: =AQ103*Z103/100 -> 0.37150492 | AS103: =J103 -> 0.409 | AT103: =AS103*AB103/100 -> 0.415953 | AU103: =AT103*AC103/100 -> 0.41728405 | AV103: =AU103*AD103/100 -> 0.42258356 | AW103: =AV103*AE103/100 -> 0.42076645
A104: Обед в столовой, кафе, закусочной (кроме столовой в организации), на 1 человека | B104: =A104 -> Обед в столовой, кафе, закусочной (кроме столовой в организации), на 1 человека | C104: =A104 -> Обед в столовой, кафе, закусочной (кроме столовой в организации), на 1 человека | D104: =C104 -> Обед в столовой, кафе, закусочной (кроме столовой в организации), на 1 человека | E104: =INDEX(БИПЦ_НДС!$D:$D,MATCH(Структура!A104,БИПЦ_НДС!$B:$B,0)) -> 20 | F104: Проды | G104: 1 | H104: 1 | I104: 1 | J104: =INDEX('2026'!$C:$C,MATCH(Структура!B104,'2026'!$B:$B,0)) -> 1.126 | K104: =INDEX('2025'!$C:$C,MATCH(Структура!C104,'2025'!$B:$B,0)) -> 1.139 | L104: 1 | M104: 1 | N104: =INDEX(MoM!B:B,MATCH(Структура!A104,MoM!J:J,0)) -> 0 | P104: =INDEX('ИПЦ raw'!AA:AA, MATCH(Структура!$D104,'ИПЦ raw'!$A:$A,0)) -> 101.35 | Q104: =INDEX('ИПЦ raw'!AB:AB, MATCH(Структура!$D104,'ИПЦ raw'!$A:$A,0)) -> 100.97 | R104: =INDEX('ИПЦ raw'!AC:AC, MATCH(Структура!$D104,'ИПЦ raw'!$A:$A,0)) -> 101.64 | S104: =INDEX('ИПЦ raw'!AD:AD, MATCH(Структура!$D104,'ИПЦ raw'!$A:$A,0)) -> 100.93 | T104: =INDEX('ИПЦ raw'!AE:AE, MATCH(Структура!$D104,'ИПЦ raw'!$A:$A,0)) -> 100.78 | U104: =INDEX('ИПЦ raw'!AF:AF, MATCH(Структура!$D104,'ИПЦ raw'!$A:$A,0)) -> 101.13 | V104: =INDEX('ИПЦ raw'!AG:AG, MATCH(Структура!$D104,'ИПЦ raw'!$A:$A,0)) -> 101.2 | W104: =INDEX('ИПЦ raw'!AH:AH, MATCH(Структура!$D104,'ИПЦ raw'!$A:$A,0)) -> 100.59 | X104: =INDEX('ИПЦ raw'!AI:AI, MATCH(Структура!$D104,'ИПЦ raw'!$A:$A,0)) -> 101.19 | Y104: =INDEX('ИПЦ raw'!AJ:AJ, MATCH(Структура!$D104,'ИПЦ raw'!$A:$A,0)) -> 100.89 | Z104: =INDEX('ИПЦ raw'!AK:AK, MATCH(Структура!$D104,'ИПЦ raw'!$A:$A,0)) -> 100.53 | AA104: =INDEX('ИПЦ raw'!AL:AL, MATCH(Структура!$D104,'ИПЦ raw'!$A:$A,0)) -> 100.71 | AB104: =INDEX('ИПЦ raw'!AM:AM, MATCH(Структура!$D104,'ИПЦ raw'!$A:$A,0)) -> 101.66 | AC104: =INDEX('ИПЦ raw'!AN:AN, MATCH(Структура!$D104,'ИПЦ raw'!$A:$A,0)) -> 100.95 | AD104: =INDEX('ИПЦ raw'!AO:AO, MATCH(Структура!$D104,'ИПЦ raw'!$A:$A,0)) -> 100.8 | AE104: =INDEX('ИПЦ raw'!AP:AP, MATCH(Структура!$D104,'ИПЦ raw'!$A:$A,0)) -> 100.49 | AG104: =INDEX('2025'!$C:$C,MATCH(Структура!C104,'2025'!$B:$B,0)) -> 1.139 | AH104: =AG104*P104/100 -> 1.1543765 | AI104: =AH104*Q104/100 -> 1.165574 | AJ104: =AI104*R104/100 -> 1.1846894 | AK104: =AJ104*S104/100 -> 1.195707 | AL104: =AK104*T104/100 -> 1.2050335 | AM104: =AL104*U104/100 -> 1.2186504 | AN104: =AM104*V104/100 -> 1.2332742 | AO104: =AN104*W104/100 -> 1.2405505 | ... AR104: =AQ104*Z104/100 -> 1.2731977 | AS104: =J104 -> 1.126 | AT104: =AS104*AB104/100 -> 1.1446916 | AU104: =AT104*AC104/100 -> 1.1555662 | AV104: =AU104*AD104/100 -> 1.1648107 | AW104: =AV104*AE104/100 -> 1.1705183
A105: Обед в ресторане, на 1 человека | B105: =A105 -> Обед в ресторане, на 1 человека | C105: =A105 -> Обед в ресторане, на 1 человека | D105: =C105 -> Обед в ресторане, на 1 человека | E105: =INDEX(БИПЦ_НДС!$D:$D,MATCH(Структура!A105,БИПЦ_НДС!$B:$B,0)) -> 20 | F105: Проды | G105: 1 | H105: 1 | I105: 1 | J105: =INDEX('2026'!$C:$C,MATCH(Структура!B105,'2026'!$B:$B,0)) -> 0.392 | K105: =INDEX('2025'!$C:$C,MATCH(Структура!C105,'2025'!$B:$B,0)) -> 0.331 | L105: 1 | M105: 1 | N105: =INDEX(MoM!B:B,MATCH(Структура!A105,MoM!J:J,0)) -> 0 | P105: =INDEX('ИПЦ raw'!AA:AA, MATCH(Структура!$D105,'ИПЦ raw'!$A:$A,0)) -> 101.18 | Q105: =INDEX('ИПЦ raw'!AB:AB, MATCH(Структура!$D105,'ИПЦ raw'!$A:$A,0)) -> 100.95 | R105: =INDEX('ИПЦ raw'!AC:AC, MATCH(Структура!$D105,'ИПЦ raw'!$A:$A,0)) -> 101.35 | S105: =INDEX('ИПЦ raw'!AD:AD, MATCH(Структура!$D105,'ИПЦ raw'!$A:$A,0)) -> 100.67 | T105: =INDEX('ИПЦ raw'!AE:AE, MATCH(Структура!$D105,'ИПЦ raw'!$A:$A,0)) -> 100.95 | U105: =INDEX('ИПЦ raw'!AF:AF, MATCH(Структура!$D105,'ИПЦ raw'!$A:$A,0)) -> 100.95 | V105: =INDEX('ИПЦ raw'!AG:AG, MATCH(Структура!$D105,'ИПЦ raw'!$A:$A,0)) -> 100.74 | W105: =INDEX('ИПЦ raw'!AH:AH, MATCH(Структура!$D105,'ИПЦ raw'!$A:$A,0)) -> 100.66 | X105: =INDEX('ИПЦ raw'!AI:AI, MATCH(Структура!$D105,'ИПЦ raw'!$A:$A,0)) -> 100.56 | Y105: =INDEX('ИПЦ raw'!AJ:AJ, MATCH(Структура!$D105,'ИПЦ raw'!$A:$A,0)) -> 100.95 | Z105: =INDEX('ИПЦ raw'!AK:AK, MATCH(Структура!$D105,'ИПЦ raw'!$A:$A,0)) -> 100.89 | AA105: =INDEX('ИПЦ raw'!AL:AL, MATCH(Структура!$D105,'ИПЦ raw'!$A:$A,0)) -> 100.56 | AB105: =INDEX('ИПЦ raw'!AM:AM, MATCH(Структура!$D105,'ИПЦ raw'!$A:$A,0)) -> 101.13 | AC105: =INDEX('ИПЦ raw'!AN:AN, MATCH(Структура!$D105,'ИПЦ raw'!$A:$A,0)) -> 100.79 | AD105: =INDEX('ИПЦ raw'!AO:AO, MATCH(Структура!$D105,'ИПЦ raw'!$A:$A,0)) -> 100.64 | AE105: =INDEX('ИПЦ raw'!AP:AP, MATCH(Структура!$D105,'ИПЦ raw'!$A:$A,0)) -> 100.36 | AG105: =INDEX('2025'!$C:$C,MATCH(Структура!C105,'2025'!$B:$B,0)) -> 0.331 | AH105: =AG105*P105/100 -> 0.3349058 | AI105: =AH105*Q105/100 -> 0.33808741 | AJ105: =AI105*R105/100 -> 0.34265159 | AK105: =AJ105*S105/100 -> 0.34494735 | AL105: =AK105*T105/100 -> 0.34822435 | AM105: =AL105*U105/100 -> 0.35153248 | AN105: =AM105*V105/100 -> 0.35413382 | AO105: =AN105*W105/100 -> 0.35647111 | ... AR105: =AQ105*Z105/100 -> 0.36509345 | AS105: =J105 -> 0.392 | AT105: =AS105*AB105/100 -> 0.3964296 | AU105: =AT105*AC105/100 -> 0.39956139 | AV105: =AU105*AD105/100 -> 0.40211859 | AW105: =AV105*AE105/100 -> 0.40356621
A106: Ужин в ресторане, на 1 человека | B106: =A106 -> Ужин в ресторане, на 1 человека | C106: =A106 -> Ужин в ресторане, на 1 человека | D106: =C106 -> Ужин в ресторане, на 1 человека | E106: =INDEX(БИПЦ_НДС!$D:$D,MATCH(Структура!A106,БИПЦ_НДС!$B:$B,0)) -> 20 | F106: Проды | G106: 1 | H106: 1 | I106: 1 | J106: =INDEX('2026'!$C:$C,MATCH(Структура!B106,'2026'!$B:$B,0)) -> 0.607 | K106: =INDEX('2025'!$C:$C,MATCH(Структура!C106,'2025'!$B:$B,0)) -> 0.521 | L106: 1 | M106: 1 | N106: =INDEX(MoM!B:B,MATCH(Структура!A106,MoM!J:J,0)) -> 0 | P106: =INDEX('ИПЦ raw'!AA:AA, MATCH(Структура!$D106,'ИПЦ raw'!$A:$A,0)) -> 101.08 | Q106: =INDEX('ИПЦ raw'!AB:AB, MATCH(Структура!$D106,'ИПЦ raw'!$A:$A,0)) -> 100.83 | R106: =INDEX('ИПЦ raw'!AC:AC, MATCH(Структура!$D106,'ИПЦ raw'!$A:$A,0)) -> 101.14 | S106: =INDEX('ИПЦ raw'!AD:AD, MATCH(Структура!$D106,'ИПЦ raw'!$A:$A,0)) -> 100.86 | T106: =INDEX('ИПЦ raw'!AE:AE, MATCH(Структура!$D106,'ИПЦ raw'!$A:$A,0)) -> 101.13 | U106: =INDEX('ИПЦ raw'!AF:AF, MATCH(Структура!$D106,'ИПЦ raw'!$A:$A,0)) -> 100.73 | V106: =INDEX('ИПЦ raw'!AG:AG, MATCH(Структура!$D106,'ИПЦ raw'!$A:$A,0)) -> 100.86 | W106: =INDEX('ИПЦ raw'!AH:AH, MATCH(Структура!$D106,'ИПЦ raw'!$A:$A,0)) -> 100.51 | X106: =INDEX('ИПЦ raw'!AI:AI, MATCH(Структура!$D106,'ИПЦ raw'!$A:$A,0)) -> 100.56 | Y106: =INDEX('ИПЦ raw'!AJ:AJ, MATCH(Структура!$D106,'ИПЦ raw'!$A:$A,0)) -> 100.78 | Z106: =INDEX('ИПЦ raw'!AK:AK, MATCH(Структура!$D106,'ИПЦ raw'!$A:$A,0)) -> 100.83 | AA106: =INDEX('ИПЦ raw'!AL:AL, MATCH(Структура!$D106,'ИПЦ raw'!$A:$A,0)) -> 100.59 | AB106: =INDEX('ИПЦ raw'!AM:AM, MATCH(Структура!$D106,'ИПЦ raw'!$A:$A,0)) -> 100.96 | AC106: =INDEX('ИПЦ raw'!AN:AN, MATCH(Структура!$D106,'ИПЦ raw'!$A:$A,0)) -> 100.57 | AD106: =INDEX('ИПЦ raw'!AO:AO, MATCH(Структура!$D106,'ИПЦ raw'!$A:$A,0)) -> 100.89 | AE106: =INDEX('ИПЦ raw'!AP:AP, MATCH(Структура!$D106,'ИПЦ raw'!$A:$A,0)) -> 100.46 | AG106: =INDEX('2025'!$C:$C,MATCH(Структура!C106,'2025'!$B:$B,0)) -> 0.521 | AH106: =AG106*P106/100 -> 0.5266268 | AI106: =AH106*Q106/100 -> 0.5309978 | AJ106: =AI106*R106/100 -> 0.53705118 | AK106: =AJ106*S106/100 -> 0.54166982 | AL106: =AK106*T106/100 -> 0.54779069 | AM106: =AL106*U106/100 -> 0.55178956 | AN106: =AM106*V106/100 -> 0.55653495 | AO106: =AN106*W106/100 -> 0.55937328 | ... AR106: =AQ106*Z106/100 -> 0.57159853 | AS106: =J106 -> 0.607 | AT106: =AS106*AB106/100 -> 0.6128272 | AU106: =AT106*AC106/100 -> 0.61632032 | AV106: =AU106*AD106/100 -> 0.62180557 | AW106: =AV106*AE106/100 -> 0.62466587
A107: Ткани хлопчатобумажные бельевые, м | B107: =A107 -> Ткани хлопчатобумажные бельевые, м | C107: =A107 -> Ткани хлопчатобумажные бельевые, м | D107: =C107 -> Ткани хлопчатобумажные бельевые, м | E107: =INDEX(БИПЦ_НДС!$D:$D,MATCH(Структура!A107,БИПЦ_НДС!$B:$B,0)) -> 20 | F107: Непроды | G107: 1 | H107: 1 | I107: 0 | J107: =INDEX('2026'!$C:$C,MATCH(Структура!B107,'2026'!$B:$B,0)) -> 0.007 | K107: =INDEX('2025'!$C:$C,MATCH(Структура!C107,'2025'!$B:$B,0)) -> 0.007 | L107: 1 | M107: 1 | N107: =INDEX(MoM!B:B,MATCH(Структура!A107,MoM!J:J,0)) -> 1 | P107: =INDEX('ИПЦ raw'!AA:AA, MATCH(Структура!$D107,'ИПЦ raw'!$A:$A,0)) -> 100.43 | Q107: =INDEX('ИПЦ raw'!AB:AB, MATCH(Структура!$D107,'ИПЦ raw'!$A:$A,0)) -> 100.6 | R107: =INDEX('ИПЦ raw'!AC:AC, MATCH(Структура!$D107,'ИПЦ raw'!$A:$A,0)) -> 100.33 | S107: =INDEX('ИПЦ raw'!AD:AD, MATCH(Структура!$D107,'ИПЦ raw'!$A:$A,0)) -> 99.86 | T107: =INDEX('ИПЦ raw'!AE:AE, MATCH(Структура!$D107,'ИПЦ raw'!$A:$A,0)) -> 99.93 | U107: =INDEX('ИПЦ raw'!AF:AF, MATCH(Структура!$D107,'ИПЦ raw'!$A:$A,0)) -> 100.25 | V107: =INDEX('ИПЦ raw'!AG:AG, MATCH(Структура!$D107,'ИПЦ raw'!$A:$A,0)) -> 100.19 | W107: =INDEX('ИПЦ raw'!AH:AH, MATCH(Структура!$D107,'ИПЦ raw'!$A:$A,0)) -> 100.24 | X107: =INDEX('ИПЦ raw'!AI:AI, MATCH(Структура!$D107,'ИПЦ raw'!$A:$A,0)) -> 100.29 | Y107: =INDEX('ИПЦ raw'!AJ:AJ, MATCH(Структура!$D107,'ИПЦ raw'!$A:$A,0)) -> 99.73 | Z107: =INDEX('ИПЦ raw'!AK:AK, MATCH(Структура!$D107,'ИПЦ raw'!$A:$A,0)) -> 100.15 | AA107: =INDEX('ИПЦ raw'!AL:AL, MATCH(Структура!$D107,'ИПЦ raw'!$A:$A,0)) -> 100.04 | AB107: =INDEX('ИПЦ raw'!AM:AM, MATCH(Структура!$D107,'ИПЦ raw'!$A:$A,0)) -> 100.2 | AC107: =INDEX('ИПЦ raw'!AN:AN, MATCH(Структура!$D107,'ИПЦ raw'!$A:$A,0)) -> 100.16 | AD107: =INDEX('ИПЦ raw'!AO:AO, MATCH(Структура!$D107,'ИПЦ raw'!$A:$A,0)) -> 100.23 | AE107: =INDEX('ИПЦ raw'!AP:AP, MATCH(Структура!$D107,'ИПЦ raw'!$A:$A,0)) -> 100.1 | AG107: =INDEX('2025'!$C:$C,MATCH(Структура!C107,'2025'!$B:$B,0)) -> 0.007 | AH107: =AG107*P107/100 -> 0.0070301 | AI107: =AH107*Q107/100 -> 0.0070722806 | AJ107: =AI107*R107/100 -> 0.0070956191 | AK107: =AJ107*S107/100 -> 0.0070856853 | AL107: =AK107*T107/100 -> 0.0070807253 | AM107: =AL107*U107/100 -> 0.0070984271 | AN107: =AM107*V107/100 -> 0.0071119141 | AO107: =AN107*W107/100 -> 0.0071289827 | ... AR107: =AQ107*Z107/100 -> 0.0071410482 | AS107: =J107 -> 0.007 | AT107: =AS107*AB107/100 -> 0.007014 | AU107: =AT107*AC107/100 -> 0.0070252224 | AV107: =AU107*AD107/100 -> 0.0070413804 | AW107: =AV107*AE107/100 -> 0.0070484218
A108: Ткань костюмная шерстяная и полушерстяная, м | B108: =A108 -> Ткань костюмная шерстяная и полушерстяная, м | C108: =A108 -> Ткань костюмная шерстяная и полушерстяная, м | D108: =C108 -> Ткань костюмная шерстяная и полушерстяная, м | E108: =INDEX(БИПЦ_НДС!$D:$D,MATCH(Структура!A108,БИПЦ_НДС!$B:$B,0)) -> 20 | F108: Непроды | G108: 1 | H108: 1 | I108: 0 | J108: =INDEX('2026'!$C:$C,MATCH(Структура!B108,'2026'!$B:$B,0)) -> 0.005 | K108: =INDEX('2025'!$C:$C,MATCH(Структура!C108,'2025'!$B:$B,0)) -> 0.005 | L108: 1 | M108: 1 | N108: =INDEX(MoM!B:B,MATCH(Структура!A108,MoM!J:J,0)) -> 1 | P108: =INDEX('ИПЦ raw'!AA:AA, MATCH(Структура!$D108,'ИПЦ raw'!$A:$A,0)) -> 100.19 | Q108: =INDEX('ИПЦ raw'!AB:AB, MATCH(Структура!$D108,'ИПЦ raw'!$A:$A,0)) -> 100.39 | R108: =INDEX('ИПЦ raw'!AC:AC, MATCH(Структура!$D108,'ИПЦ raw'!$A:$A,0)) -> 100.29 | S108: =INDEX('ИПЦ raw'!AD:AD, MATCH(Структура!$D108,'ИПЦ raw'!$A:$A,0)) -> 100.2 | T108: =INDEX('ИПЦ raw'!AE:AE, MATCH(Структура!$D108,'ИПЦ raw'!$A:$A,0)) -> 100.06 | U108: =INDEX('ИПЦ raw'!AF:AF, MATCH(Структура!$D108,'ИПЦ raw'!$A:$A,0)) -> 100.05 | V108: =INDEX('ИПЦ raw'!AG:AG, MATCH(Структура!$D108,'ИПЦ raw'!$A:$A,0)) -> 100.07 | W108: =INDEX('ИПЦ raw'!AH:AH, MATCH(Структура!$D108,'ИПЦ raw'!$A:$A,0)) -> 100.26 | X108: =INDEX('ИПЦ raw'!AI:AI, MATCH(Структура!$D108,'ИПЦ raw'!$A:$A,0)) -> 99.98 | Y108: =INDEX('ИПЦ raw'!AJ:AJ, MATCH(Структура!$D108,'ИПЦ raw'!$A:$A,0)) -> 99.93 | Z108: =INDEX('ИПЦ raw'!AK:AK, MATCH(Структура!$D108,'ИПЦ raw'!$A:$A,0)) -> 100.49 | AA108: =INDEX('ИПЦ raw'!AL:AL, MATCH(Структура!$D108,'ИПЦ raw'!$A:$A,0)) -> 100.4 | AB108: =INDEX('ИПЦ raw'!AM:AM, MATCH(Структура!$D108,'ИПЦ raw'!$A:$A,0)) -> 100.11 | AC108: =INDEX('ИПЦ raw'!AN:AN, MATCH(Структура!$D108,'ИПЦ raw'!$A:$A,0)) -> 100.18 | AD108: =INDEX('ИПЦ raw'!AO:AO, MATCH(Структура!$D108,'ИПЦ raw'!$A:$A,0)) -> 100.2 | AE108: =INDEX('ИПЦ raw'!AP:AP, MATCH(Структура!$D108,'ИПЦ raw'!$A:$A,0)) -> 100.14 | AG108: =INDEX('2025'!$C:$C,MATCH(Структура!C108,'2025'!$B:$B,0)) -> 0.005 | AH108: =AG108*P108/100 -> 0.0050095 | AI108: =AH108*Q108/100 -> 0.0050290371 | AJ108: =AI108*R108/100 -> 0.0050436213 | AK108: =AJ108*S108/100 -> 0.0050537085 | AL108: =AK108*T108/100 -> 0.0050567407 | AM108: =AL108*U108/100 -> 0.0050592691 | AN108: =AM108*V108/100 -> 0.0050628106 | AO108: =AN108*W108/100 -> 0.0050759739 | ... AR108: =AQ108*Z108/100 -> 0.0050962561 | AS108: =J108 -> 0.005 | AT108: =AS108*AB108/100 -> 0.0050055 | AU108: =AT108*AC108/100 -> 0.0050145099 | AV108: =AU108*AD108/100 -> 0.0050245389 | AW108: =AV108*AE108/100 -> 0.0050315733
A109: Ткань платьевая из искусственного или синтетического шелка, м | B109: =A109 -> Ткань платьевая из искусственного или синтетического шелка, м | C109: =A109 -> Ткань платьевая из искусственного или синтетического шелка, м | D109: =C109 -> Ткань платьевая из искусственного или синтетического шелка, м | E109: =INDEX(БИПЦ_НДС!$D:$D,MATCH(Структура!A109,БИПЦ_НДС!$B:$B,0)) -> 20 | F109: Непроды | G109: 1 | H109: 1 | I109: 0 | J109: =INDEX('2026'!$C:$C,MATCH(Структура!B109,'2026'!$B:$B,0)) -> 0.005 | K109: =INDEX('2025'!$C:$C,MATCH(Структура!C109,'2025'!$B:$B,0)) -> 0.006 | L109: 1 | M109: 1 | N109: =INDEX(MoM!B:B,MATCH(Структура!A109,MoM!J:J,0)) -> 1 | P109: =INDEX('ИПЦ raw'!AA:AA, MATCH(Структура!$D109,'ИПЦ raw'!$A:$A,0)) -> 100.28 | Q109: =INDEX('ИПЦ raw'!AB:AB, MATCH(Структура!$D109,'ИПЦ raw'!$A:$A,0)) -> 100.34 | R109: =INDEX('ИПЦ raw'!AC:AC, MATCH(Структура!$D109,'ИПЦ raw'!$A:$A,0)) -> 100.17 | S109: =INDEX('ИПЦ raw'!AD:AD, MATCH(Структура!$D109,'ИПЦ raw'!$A:$A,0)) -> 100.39 | T109: =INDEX('ИПЦ raw'!AE:AE, MATCH(Структура!$D109,'ИПЦ raw'!$A:$A,0)) -> 100.05 | U109: =INDEX('ИПЦ raw'!AF:AF, MATCH(Структура!$D109,'ИПЦ raw'!$A:$A,0)) -> 100.23 | V109: =INDEX('ИПЦ raw'!AG:AG, MATCH(Структура!$D109,'ИПЦ raw'!$A:$A,0)) -> 99.91 | W109: =INDEX('ИПЦ raw'!AH:AH, MATCH(Структура!$D109,'ИПЦ raw'!$A:$A,0)) -> 100.21 | X109: =INDEX('ИПЦ raw'!AI:AI, MATCH(Структура!$D109,'ИПЦ raw'!$A:$A,0)) -> 100.05 | Y109: =INDEX('ИПЦ raw'!AJ:AJ, MATCH(Структура!$D109,'ИПЦ raw'!$A:$A,0)) -> 100.11 | Z109: =INDEX('ИПЦ raw'!AK:AK, MATCH(Структура!$D109,'ИПЦ raw'!$A:$A,0)) -> 100.19 | AA109: =INDEX('ИПЦ raw'!AL:AL, MATCH(Структура!$D109,'ИПЦ raw'!$A:$A,0)) -> 100.08 | AB109: =INDEX('ИПЦ raw'!AM:AM, MATCH(Структура!$D109,'ИПЦ raw'!$A:$A,0)) -> 100.31 | AC109: =INDEX('ИПЦ raw'!AN:AN, MATCH(Структура!$D109,'ИПЦ raw'!$A:$A,0)) -> 100.2 | AD109: =INDEX('ИПЦ raw'!AO:AO, MATCH(Структура!$D109,'ИПЦ raw'!$A:$A,0)) -> 100.3 | AE109: =INDEX('ИПЦ raw'!AP:AP, MATCH(Структура!$D109,'ИПЦ raw'!$A:$A,0)) -> 100.03 | AG109: =INDEX('2025'!$C:$C,MATCH(Структура!C109,'2025'!$B:$B,0)) -> 0.006 | AH109: =AG109*P109/100 -> 0.0060168 | AI109: =AH109*Q109/100 -> 0.0060372571 | AJ109: =AI109*R109/100 -> 0.0060475205 | AK109: =AJ109*S109/100 -> 0.0060711058 | AL109: =AK109*T109/100 -> 0.0060741413 | AM109: =AL109*U109/100 -> 0.0060881119 | AN109: =AM109*V109/100 -> 0.0060826326 | AO109: =AN109*W109/100 -> 0.0060954061 | ... AR109: =AQ109*Z109/100 -> 0.0061167619 | AS109: =J109 -> 0.005 | AT109: =AS109*AB109/100 -> 0.0050155 | AU109: =AT109*AC109/100 -> 0.005025531 | AV109: =AU109*AD109/100 -> 0.0050406076 | AW109: =AV109*AE109/100 -> 0.0050421198
A110: Ткани декоративные для изготовления штор и занавесей, м | B110: =A110 -> Ткани декоративные для изготовления штор и занавесей, м | C110: =A110 -> Ткани декоративные для изготовления штор и занавесей, м | D110: =C110 -> Ткани декоративные для изготовления штор и занавесей, м | E110: =INDEX(БИПЦ_НДС!$D:$D,MATCH(Структура!A110,БИПЦ_НДС!$B:$B,0)) -> 20 | F110: Непроды | G110: 1 | H110: 1 | I110: 0 | J110: =INDEX('2026'!$C:$C,MATCH(Структура!B110,'2026'!$B:$B,0)) -> 0.031 | K110: =INDEX('2025'!$C:$C,MATCH(Структура!C110,'2025'!$B:$B,0)) -> 0.033 | L110: 1 | M110: 1 | N110: =INDEX(MoM!B:B,MATCH(Структура!A110,MoM!J:J,0)) -> 1 | P110: =INDEX('ИПЦ raw'!AA:AA, MATCH(Структура!$D110,'ИПЦ raw'!$A:$A,0)) -> 100.54 | Q110: =INDEX('ИПЦ raw'!AB:AB, MATCH(Структура!$D110,'ИПЦ raw'!$A:$A,0)) -> 100.27 | R110: =INDEX('ИПЦ raw'!AC:AC, MATCH(Структура!$D110,'ИПЦ raw'!$A:$A,0)) -> 100.24 | S110: =INDEX('ИПЦ raw'!AD:AD, MATCH(Структура!$D110,'ИПЦ raw'!$A:$A,0)) -> 100.17 | T110: =INDEX('ИПЦ raw'!AE:AE, MATCH(Структура!$D110,'ИПЦ raw'!$A:$A,0)) -> 100.06 | U110: =INDEX('ИПЦ raw'!AF:AF, MATCH(Структура!$D110,'ИПЦ raw'!$A:$A,0)) -> 100.12 | V110: =INDEX('ИПЦ raw'!AG:AG, MATCH(Структура!$D110,'ИПЦ raw'!$A:$A,0)) -> 100.07 | W110: =INDEX('ИПЦ raw'!AH:AH, MATCH(Структура!$D110,'ИПЦ raw'!$A:$A,0)) -> 100.19 | X110: =INDEX('ИПЦ raw'!AI:AI, MATCH(Структура!$D110,'ИПЦ raw'!$A:$A,0)) -> 100.1 | Y110: =INDEX('ИПЦ raw'!AJ:AJ, MATCH(Структура!$D110,'ИПЦ raw'!$A:$A,0)) -> 100.26 | Z110: =INDEX('ИПЦ raw'!AK:AK, MATCH(Структура!$D110,'ИПЦ raw'!$A:$A,0)) -> 100.14 | AA110: =INDEX('ИПЦ raw'!AL:AL, MATCH(Структура!$D110,'ИПЦ raw'!$A:$A,0)) -> 100.34 | AB110: =INDEX('ИПЦ raw'!AM:AM, MATCH(Структура!$D110,'ИПЦ raw'!$A:$A,0)) -> 100.24 | AC110: =INDEX('ИПЦ raw'!AN:AN, MATCH(Структура!$D110,'ИПЦ raw'!$A:$A,0)) -> 100.3 | AD110: =INDEX('ИПЦ raw'!AO:AO, MATCH(Структура!$D110,'ИПЦ raw'!$A:$A,0)) -> 100.65 | AE110: =INDEX('ИПЦ raw'!AP:AP, MATCH(Структура!$D110,'ИПЦ raw'!$A:$A,0)) -> 100.2 | AG110: =INDEX('2025'!$C:$C,MATCH(Структура!C110,'2025'!$B:$B,0)) -> 0.033 | AH110: =AG110*P110/100 -> 0.0331782 | AI110: =AH110*Q110/100 -> 0.033267781 | AJ110: =AI110*R110/100 -> 0.033347624 | AK110: =AJ110*S110/100 -> 0.033404315 | AL110: =AK110*T110/100 -> 0.033424357 | AM110: =AL110*U110/100 -> 0.033464467 | AN110: =AM110*V110/100 -> 0.033487892 | AO110: =AN110*W110/100 -> 0.033551519 | ... AR110: =AQ110*Z110/100 -> 0.033719533 | AS110: =J110 -> 0.031 | AT110: =AS110*AB110/100 -> 0.0310744 | AU110: =AT110*AC110/100 -> 0.031167623 | AV110: =AU110*AD110/100 -> 0.031370213 | AW110: =AV110*AE110/100 -> 0.031432953
A111: Полотенце личное, шт. | B111: =A111 -> Полотенце личное, шт. | C111: =A111 -> Полотенце личное, шт. | D111: =C111 -> Полотенце личное, шт. | E111: =INDEX(БИПЦ_НДС!$D:$D,MATCH(Структура!A111,БИПЦ_НДС!$B:$B,0)) -> 20 | F111: Непроды | G111: 1 | H111: 1 | I111: 0 | J111: =INDEX('2026'!$C:$C,MATCH(Структура!B111,'2026'!$B:$B,0)) -> 0.073 | K111: =INDEX('2025'!$C:$C,MATCH(Структура!C111,'2025'!$B:$B,0)) -> 0.073 | L111: 1 | M111: 1 | N111: =INDEX(MoM!B:B,MATCH(Структура!A111,MoM!J:J,0)) -> 1 | P111: =INDEX('ИПЦ raw'!AA:AA, MATCH(Структура!$D111,'ИПЦ raw'!$A:$A,0)) -> 100.62 | Q111: =INDEX('ИПЦ raw'!AB:AB, MATCH(Структура!$D111,'ИПЦ raw'!$A:$A,0)) -> 100.24 | R111: =INDEX('ИПЦ raw'!AC:AC, MATCH(Структура!$D111,'ИПЦ raw'!$A:$A,0)) -> 100.55 | S111: =INDEX('ИПЦ raw'!AD:AD, MATCH(Структура!$D111,'ИПЦ raw'!$A:$A,0)) -> 100.68 | T111: =INDEX('ИПЦ raw'!AE:AE, MATCH(Структура!$D111,'ИПЦ raw'!$A:$A,0)) -> 100.01 | U111: =INDEX('ИПЦ raw'!AF:AF, MATCH(Структура!$D111,'ИПЦ raw'!$A:$A,0)) -> 100.64 | V111: =INDEX('ИПЦ raw'!AG:AG, MATCH(Структура!$D111,'ИПЦ raw'!$A:$A,0)) -> 100.05 | W111: =INDEX('ИПЦ raw'!AH:AH, MATCH(Структура!$D111,'ИПЦ raw'!$A:$A,0)) -> 100.06 | X111: =INDEX('ИПЦ raw'!AI:AI, MATCH(Структура!$D111,'ИПЦ raw'!$A:$A,0)) -> 99.8 | Y111: =INDEX('ИПЦ raw'!AJ:AJ, MATCH(Структура!$D111,'ИПЦ raw'!$A:$A,0)) -> 100.22 | Z111: =INDEX('ИПЦ raw'!AK:AK, MATCH(Структура!$D111,'ИПЦ raw'!$A:$A,0)) -> 99.89 | AA111: =INDEX('ИПЦ raw'!AL:AL, MATCH(Структура!$D111,'ИПЦ raw'!$A:$A,0)) -> 100.2 | AB111: =INDEX('ИПЦ raw'!AM:AM, MATCH(Структура!$D111,'ИПЦ raw'!$A:$A,0)) -> 100.41 | AC111: =INDEX('ИПЦ raw'!AN:AN, MATCH(Структура!$D111,'ИПЦ raw'!$A:$A,0)) -> 100.22 | AD111: =INDEX('ИПЦ raw'!AO:AO, MATCH(Структура!$D111,'ИПЦ raw'!$A:$A,0)) -> 100.32 | AE111: =INDEX('ИПЦ raw'!AP:AP, MATCH(Структура!$D111,'ИПЦ raw'!$A:$A,0)) -> 100 | AG111: =INDEX('2025'!$C:$C,MATCH(Структура!C111,'2025'!$B:$B,0)) -> 0.073 | AH111: =AG111*P111/100 -> 0.0734526 | AI111: =AH111*Q111/100 -> 0.073628886 | AJ111: =AI111*R111/100 -> 0.074033845 | AK111: =AJ111*S111/100 -> 0.074537275 | AL111: =AK111*T111/100 -> 0.074544729 | AM111: =AL111*U111/100 -> 0.075021815 | AN111: =AM111*V111/100 -> 0.075059326 | AO111: =AN111*W111/100 -> 0.075104362 | ... AR111: =AQ111*Z111/100 -> 0.075036421 | AS111: =J111 -> 0.073 | AT111: =AS111*AB111/100 -> 0.0732993 | AU111: =AT111*AC111/100 -> 0.073460558 | AV111: =AU111*AD111/100 -> 0.073695632 | AW111: =AV111*AE111/100 -> 0.073695632
A112: Полотенце кухонное, шт. | B112: =A112 -> Полотенце кухонное, шт. | C112: =A112 -> Полотенце кухонное, шт. | D112: =C112 -> Полотенце кухонное, шт. | E112: =INDEX(БИПЦ_НДС!$D:$D,MATCH(Структура!A112,БИПЦ_НДС!$B:$B,0)) -> 20 | F112: Непроды | G112: 1 | H112: 1 | I112: 0 | J112: =INDEX('2026'!$C:$C,MATCH(Структура!B112,'2026'!$B:$B,0)) -> 0.029 | K112: =INDEX('2025'!$C:$C,MATCH(Структура!C112,'2025'!$B:$B,0)) -> 0.028 | L112: 1 | M112: 1 | N112: =INDEX(MoM!B:B,MATCH(Структура!A112,MoM!J:J,0)) -> 1 | P112: =INDEX('ИПЦ raw'!AA:AA, MATCH(Структура!$D112,'ИПЦ raw'!$A:$A,0)) -> 100.33 | Q112: =INDEX('ИПЦ raw'!AB:AB, MATCH(Структура!$D112,'ИПЦ raw'!$A:$A,0)) -> 100.09 | R112: =INDEX('ИПЦ raw'!AC:AC, MATCH(Структура!$D112,'ИПЦ raw'!$A:$A,0)) -> 100.55 | S112: =INDEX('ИПЦ raw'!AD:AD, MATCH(Структура!$D112,'ИПЦ raw'!$A:$A,0)) -> 100.26 | T112: =INDEX('ИПЦ raw'!AE:AE, MATCH(Структура!$D112,'ИПЦ raw'!$A:$A,0)) -> 100.35 | U112: =INDEX('ИПЦ raw'!AF:AF, MATCH(Структура!$D112,'ИПЦ raw'!$A:$A,0)) -> 100.73 | V112: =INDEX('ИПЦ raw'!AG:AG, MATCH(Структура!$D112,'ИПЦ raw'!$A:$A,0)) -> 99.96 | W112: =INDEX('ИПЦ raw'!AH:AH, MATCH(Структура!$D112,'ИПЦ raw'!$A:$A,0)) -> 100.14 | X112: =INDEX('ИПЦ raw'!AI:AI, MATCH(Структура!$D112,'ИПЦ raw'!$A:$A,0)) -> 100.09 | Y112: =INDEX('ИПЦ raw'!AJ:AJ, MATCH(Структура!$D112,'ИПЦ raw'!$A:$A,0)) -> 100.46 | Z112: =INDEX('ИПЦ raw'!AK:AK, MATCH(Структура!$D112,'ИПЦ raw'!$A:$A,0)) -> 100.19 | AA112: =INDEX('ИПЦ raw'!AL:AL, MATCH(Структура!$D112,'ИПЦ raw'!$A:$A,0)) -> 100.36 | AB112: =INDEX('ИПЦ raw'!AM:AM, MATCH(Структура!$D112,'ИПЦ raw'!$A:$A,0)) -> 100.11 | AC112: =INDEX('ИПЦ raw'!AN:AN, MATCH(Структура!$D112,'ИПЦ raw'!$A:$A,0)) -> 100.5 | AD112: =INDEX('ИПЦ raw'!AO:AO, MATCH(Структура!$D112,'ИПЦ raw'!$A:$A,0)) -> 100.34 | AE112: =INDEX('ИПЦ raw'!AP:AP, MATCH(Структура!$D112,'ИПЦ raw'!$A:$A,0)) -> 99.97 | AG112: =INDEX('2025'!$C:$C,MATCH(Структура!C112,'2025'!$B:$B,0)) -> 0.028 | AH112: =AG112*P112/100 -> 0.0280924 | AI112: =AH112*Q112/100 -> 0.028117683 | AJ112: =AI112*R112/100 -> 0.02827233 | AK112: =AJ112*S112/100 -> 0.028345838 | AL112: =AK112*T112/100 -> 0.028445049 | AM112: =AL112*U112/100 -> 0.028652698 | AN112: =AM112*V112/100 -> 0.028641237 | AO112: =AN112*W112/100 -> 0.028681334 | ... AR112: =AQ112*Z112/100 -> 0.028893995 | AS112: =J112 -> 0.029 | AT112: =AS112*AB112/100 -> 0.0290319 | AU112: =AT112*AC112/100 -> 0.029177059 | AV112: =AU112*AD112/100 -> 0.029276262 | AW112: =AV112*AE112/100 -> 0.029267479
A113: Куртка мужская с верхом из плащевых тканей утепленная, шт. | B113: =A113 -> Куртка мужская с верхом из плащевых тканей утепленная, шт. | C113: =A113 -> Куртка мужская с верхом из плащевых тканей утепленная, шт. | D113: =C113 -> Куртка мужская с верхом из плащевых тканей утепленная, шт. | E113: =INDEX(БИПЦ_НДС!$D:$D,MATCH(Структура!A113,БИПЦ_НДС!$B:$B,0)) -> 20 | F113: Непроды | G113: 1 | H113: 1 | I113: 0 | J113: =INDEX('2026'!$C:$C,MATCH(Структура!B113,'2026'!$B:$B,0)) -> 0.151 | K113: =INDEX('2025'!$C:$C,MATCH(Структура!C113,'2025'!$B:$B,0)) -> 0.16 | L113: 1 | M113: 1 | N113: =INDEX(MoM!B:B,MATCH(Структура!A113,MoM!J:J,0)) -> 1 | P113: =INDEX('ИПЦ raw'!AA:AA, MATCH(Структура!$D113,'ИПЦ raw'!$A:$A,0)) -> 98.45 | Q113: =INDEX('ИПЦ raw'!AB:AB, MATCH(Структура!$D113,'ИПЦ raw'!$A:$A,0)) -> 98.57 | R113: =INDEX('ИПЦ raw'!AC:AC, MATCH(Структура!$D113,'ИПЦ raw'!$A:$A,0)) -> 99.45 | S113: =INDEX('ИПЦ raw'!AD:AD, MATCH(Структура!$D113,'ИПЦ raw'!$A:$A,0)) -> 99.81 | T113: =INDEX('ИПЦ raw'!AE:AE, MATCH(Структура!$D113,'ИПЦ raw'!$A:$A,0)) -> 99.96 | U113: =INDEX('ИПЦ raw'!AF:AF, MATCH(Структура!$D113,'ИПЦ raw'!$A:$A,0)) -> 99.94 | V113: =INDEX('ИПЦ raw'!AG:AG, MATCH(Структура!$D113,'ИПЦ raw'!$A:$A,0)) -> 100.07 | W113: =INDEX('ИПЦ raw'!AH:AH, MATCH(Структура!$D113,'ИПЦ raw'!$A:$A,0)) -> 100.57 | X113: =INDEX('ИПЦ raw'!AI:AI, MATCH(Структура!$D113,'ИПЦ raw'!$A:$A,0)) -> 100.92 | Y113: =INDEX('ИПЦ raw'!AJ:AJ, MATCH(Структура!$D113,'ИПЦ raw'!$A:$A,0)) -> 101.55 | Z113: =INDEX('ИПЦ raw'!AK:AK, MATCH(Структура!$D113,'ИПЦ raw'!$A:$A,0)) -> 100.3 | AA113: =INDEX('ИПЦ raw'!AL:AL, MATCH(Структура!$D113,'ИПЦ raw'!$A:$A,0)) -> 99.63 | AB113: =INDEX('ИПЦ raw'!AM:AM, MATCH(Структура!$D113,'ИПЦ raw'!$A:$A,0)) -> 98.56 | AC113: =INDEX('ИПЦ raw'!AN:AN, MATCH(Структура!$D113,'ИПЦ raw'!$A:$A,0)) -> 98.76 | AD113: =INDEX('ИПЦ raw'!AO:AO, MATCH(Структура!$D113,'ИПЦ raw'!$A:$A,0)) -> 100.01 | AE113: =INDEX('ИПЦ raw'!AP:AP, MATCH(Структура!$D113,'ИПЦ raw'!$A:$A,0)) -> 99.59 | AG113: =INDEX('2025'!$C:$C,MATCH(Структура!C113,'2025'!$B:$B,0)) -> 0.16 | AH113: =AG113*P113/100 -> 0.15752 | AI113: =AH113*Q113/100 -> 0.15526746 | AJ113: =AI113*R113/100 -> 0.15441349 | AK113: =AJ113*S113/100 -> 0.15412011 | AL113: =AK113*T113/100 -> 0.15405846 | AM113: =AL113*U113/100 -> 0.15396602 | AN113: =AM113*V113/100 -> 0.1540738 | AO113: =AN113*W113/100 -> 0.15495202 | ... AR113: =AQ113*Z113/100 -> 0.15927784 | AS113: =J113 -> 0.151 | AT113: =AS113*AB113/100 -> 0.1488256 | AU113: =AT113*AC113/100 -> 0.14698016 | AV113: =AU113*AD113/100 -> 0.14699486 | AW113: =AV113*AE113/100 -> 0.14639218
A114: Куртка мужская без утеплителя (ветровка), шт. | B114: =A114 -> Куртка мужская без утеплителя (ветровка), шт. | C114: =A114 -> Куртка мужская без утеплителя (ветровка), шт. | D114: =C114 -> Куртка мужская без утеплителя (ветровка), шт. | E114: =INDEX(БИПЦ_НДС!$D:$D,MATCH(Структура!A114,БИПЦ_НДС!$B:$B,0)) -> 20 | F114: Непроды | G114: 1 | H114: 1 | I114: 0 | J114: =INDEX('2026'!$C:$C,MATCH(Структура!B114,'2026'!$B:$B,0)) -> 0.123 | K114: =INDEX('2025'!$C:$C,MATCH(Структура!C114,'2025'!$B:$B,0)) -> 0.115 | L114: 1 | M114: 1 | N114: =INDEX(MoM!B:B,MATCH(Структура!A114,MoM!J:J,0)) -> 1 | P114: =INDEX('ИПЦ raw'!AA:AA, MATCH(Структура!$D114,'ИПЦ raw'!$A:$A,0)) -> 100.37 | Q114: =INDEX('ИПЦ raw'!AB:AB, MATCH(Структура!$D114,'ИПЦ raw'!$A:$A,0)) -> 100.69 | R114: =INDEX('ИПЦ raw'!AC:AC, MATCH(Структура!$D114,'ИПЦ raw'!$A:$A,0)) -> 100.56 | S114: =INDEX('ИПЦ raw'!AD:AD, MATCH(Структура!$D114,'ИПЦ raw'!$A:$A,0)) -> 100.03 | T114: =INDEX('ИПЦ raw'!AE:AE, MATCH(Структура!$D114,'ИПЦ raw'!$A:$A,0)) -> 99.39 | U114: =INDEX('ИПЦ raw'!AF:AF, MATCH(Структура!$D114,'ИПЦ raw'!$A:$A,0)) -> 99.31 | V114: =INDEX('ИПЦ raw'!AG:AG, MATCH(Структура!$D114,'ИПЦ raw'!$A:$A,0)) -> 99.83 | W114: =INDEX('ИПЦ raw'!AH:AH, MATCH(Структура!$D114,'ИПЦ raw'!$A:$A,0)) -> 100.13 | X114: =INDEX('ИПЦ raw'!AI:AI, MATCH(Структура!$D114,'ИПЦ raw'!$A:$A,0)) -> 99.96 | Y114: =INDEX('ИПЦ raw'!AJ:AJ, MATCH(Структура!$D114,'ИПЦ raw'!$A:$A,0)) -> 99.94 | Z114: =INDEX('ИПЦ raw'!AK:AK, MATCH(Структура!$D114,'ИПЦ raw'!$A:$A,0)) -> 100.16 | AA114: =INDEX('ИПЦ raw'!AL:AL, MATCH(Структура!$D114,'ИПЦ raw'!$A:$A,0)) -> 99.96 | AB114: =INDEX('ИПЦ raw'!AM:AM, MATCH(Структура!$D114,'ИПЦ raw'!$A:$A,0)) -> 99.63 | AC114: =INDEX('ИПЦ raw'!AN:AN, MATCH(Структура!$D114,'ИПЦ raw'!$A:$A,0)) -> 99.93 | AD114: =INDEX('ИПЦ raw'!AO:AO, MATCH(Структура!$D114,'ИПЦ raw'!$A:$A,0)) -> 100.55 | AE114: =INDEX('ИПЦ raw'!AP:AP, MATCH(Структура!$D114,'ИПЦ raw'!$A:$A,0)) -> 99.77 | AG114: =INDEX('2025'!$C:$C,MATCH(Структура!C114,'2025'!$B:$B,0)) -> 0.115 | AH114: =AG114*P114/100 -> 0.1154255 | AI114: =AH114*Q114/100 -> 0.11622194 | AJ114: =AI114*R114/100 -> 0.11687278 | AK114: =AJ114*S114/100 -> 0.11690784 | AL114: =AK114*T114/100 -> 0.1161947 | AM114: =AL114*U114/100 -> 0.11539296 | AN114: =AM114*V114/100 -> 0.11519679 | AO114: =AN114*W114/100 -> 0.11534655 | ... AR114: =AQ114*Z114/100 -> 0.1154156 | AS114: =J114 -> 0.123 | AT114: =AS114*AB114/100 -> 0.1225449 | AU114: =AT114*AC114/100 -> 0.12245912 | AV114: =AU114*AD114/100 -> 0.12313264 | AW114: =AV114*AE114/100 -> 0.12284944
A115: Куртка мужская из натуральной кожи, шт. | B115: =A115 -> Куртка мужская из натуральной кожи, шт. | C115: =A115 -> Куртка мужская из натуральной кожи, шт. | D115: =C115 -> Куртка мужская из натуральной кожи, шт. | E115: =INDEX(БИПЦ_НДС!$D:$D,MATCH(Структура!A115,БИПЦ_НДС!$B:$B,0)) -> 20 | F115: Непроды | G115: 1 | H115: 1 | I115: 0 | J115: =INDEX('2026'!$C:$C,MATCH(Структура!B115,'2026'!$B:$B,0)) -> 0.047 | K115: =INDEX('2025'!$C:$C,MATCH(Структура!C115,'2025'!$B:$B,0)) -> 0.049 | L115: 1 | M115: 1 | N115: =INDEX(MoM!B:B,MATCH(Структура!A115,MoM!J:J,0)) -> 1 | P115: =INDEX('ИПЦ raw'!AA:AA, MATCH(Структура!$D115,'ИПЦ raw'!$A:$A,0)) -> 99.82 | Q115: =INDEX('ИПЦ raw'!AB:AB, MATCH(Структура!$D115,'ИПЦ raw'!$A:$A,0)) -> 100.69 | R115: =INDEX('ИПЦ raw'!AC:AC, MATCH(Структура!$D115,'ИПЦ raw'!$A:$A,0)) -> 100.09 | S115: =INDEX('ИПЦ raw'!AD:AD, MATCH(Структура!$D115,'ИПЦ raw'!$A:$A,0)) -> 99.39 | T115: =INDEX('ИПЦ raw'!AE:AE, MATCH(Структура!$D115,'ИПЦ raw'!$A:$A,0)) -> 98.27 | U115: =INDEX('ИПЦ raw'!AF:AF, MATCH(Структура!$D115,'ИПЦ raw'!$A:$A,0)) -> 99.44 | V115: =INDEX('ИПЦ raw'!AG:AG, MATCH(Структура!$D115,'ИПЦ raw'!$A:$A,0)) -> 100 | W115: =INDEX('ИПЦ raw'!AH:AH, MATCH(Структура!$D115,'ИПЦ raw'!$A:$A,0)) -> 100.91 | X115: =INDEX('ИПЦ raw'!AI:AI, MATCH(Структура!$D115,'ИПЦ raw'!$A:$A,0)) -> 100.5 | Y115: =INDEX('ИПЦ raw'!AJ:AJ, MATCH(Структура!$D115,'ИПЦ raw'!$A:$A,0)) -> 100.05 | Z115: =INDEX('ИПЦ raw'!AK:AK, MATCH(Структура!$D115,'ИПЦ raw'!$A:$A,0)) -> 100.27 | AA115: =INDEX('ИПЦ raw'!AL:AL, MATCH(Структура!$D115,'ИПЦ raw'!$A:$A,0)) -> 99.68 | AB115: =INDEX('ИПЦ raw'!AM:AM, MATCH(Структура!$D115,'ИПЦ raw'!$A:$A,0)) -> 99.45 | AC115: =INDEX('ИПЦ raw'!AN:AN, MATCH(Структура!$D115,'ИПЦ raw'!$A:$A,0)) -> 100.26 | AD115: =INDEX('ИПЦ raw'!AO:AO, MATCH(Структура!$D115,'ИПЦ raw'!$A:$A,0)) -> 100.66 | AE115: =INDEX('ИПЦ raw'!AP:AP, MATCH(Структура!$D115,'ИПЦ raw'!$A:$A,0)) -> 100.57 | AG115: =INDEX('2025'!$C:$C,MATCH(Структура!C115,'2025'!$B:$B,0)) -> 0.049 | AH115: =AG115*P115/100 -> 0.0489118 | AI115: =AH115*Q115/100 -> 0.049249291 | AJ115: =AI115*R115/100 -> 0.049293616 | AK115: =AJ115*S115/100 -> 0.048992925 | AL115: =AK115*T115/100 -> 0.048145347 | AM115: =AL115*U115/100 -> 0.047875733 | AN115: =AM115*V115/100 -> 0.047875733 | AO115: =AN115*W115/100 -> 0.048311402 | ... AR115: =AQ115*Z115/100 -> 0.048708394 | AS115: =J115 -> 0.047 | AT115: =AS115*AB115/100 -> 0.0467415 | AU115: =AT115*AC115/100 -> 0.046863028 | AV115: =AU115*AD115/100 -> 0.047172324 | AW115: =AV115*AE115/100 -> 0.047441206
A116: Костюм-двойка мужской, шт. | B116: =A116 -> Костюм-двойка мужской, шт. | C116: Костюм-двойка мужской из шерстяных, полушерстяных или смесовых тканей, шт. | D116: Костюм-двойка мужской, шт. | E116: =INDEX(БИПЦ_НДС!$D:$D,MATCH(Структура!A116,БИПЦ_НДС!$B:$B,0)) -> 20 | F116: Непроды | G116: 1 | H116: 1 | I116: 0 | J116: =INDEX('2026'!$C:$C,MATCH(Структура!B116,'2026'!$B:$B,0)) -> 0.1 | K116: =INDEX('2025'!$C:$C,MATCH(Структура!C116,'2025'!$B:$B,0)) -> 0.098 | L116: 1 | M116: 1 | N116: =INDEX(MoM!B:B,MATCH(Структура!A116,MoM!J:J,0)) -> 1 | P116: =INDEX('ИПЦ raw'!AA:AA, MATCH(Структура!$D116,'ИПЦ raw'!$A:$A,0)) -> 100.4 | Q116: =INDEX('ИПЦ raw'!AB:AB, MATCH(Структура!$D116,'ИПЦ raw'!$A:$A,0)) -> 100.86 | R116: =INDEX('ИПЦ raw'!AC:AC, MATCH(Структура!$D116,'ИПЦ raw'!$A:$A,0)) -> 100.31 | S116: =INDEX('ИПЦ raw'!AD:AD, MATCH(Структура!$D116,'ИПЦ raw'!$A:$A,0)) -> 100.29 | T116: =INDEX('ИПЦ raw'!AE:AE, MATCH(Структура!$D116,'ИПЦ raw'!$A:$A,0)) -> 100 | U116: =INDEX('ИПЦ raw'!AF:AF, MATCH(Структура!$D116,'ИПЦ raw'!$A:$A,0)) -> 100.56 | V116: =INDEX('ИПЦ raw'!AG:AG, MATCH(Структура!$D116,'ИПЦ raw'!$A:$A,0)) -> 100.45 | W116: =INDEX('ИПЦ raw'!AH:AH, MATCH(Структура!$D116,'ИПЦ raw'!$A:$A,0)) -> 100.64 | X116: =INDEX('ИПЦ raw'!AI:AI, MATCH(Структура!$D116,'ИПЦ raw'!$A:$A,0)) -> 99.29 | Y116: =INDEX('ИПЦ raw'!AJ:AJ, MATCH(Структура!$D116,'ИПЦ raw'!$A:$A,0)) -> 100.85 | Z116: =INDEX('ИПЦ raw'!AK:AK, MATCH(Структура!$D116,'ИПЦ raw'!$A:$A,0)) -> 100.85 | AA116: =INDEX('ИПЦ raw'!AL:AL, MATCH(Структура!$D116,'ИПЦ raw'!$A:$A,0)) -> 100.49 | AB116: =INDEX('ИПЦ raw'!AM:AM, MATCH(Структура!$D116,'ИПЦ raw'!$A:$A,0)) -> 100.02 | AC116: =INDEX('ИПЦ raw'!AN:AN, MATCH(Структура!$D116,'ИПЦ raw'!$A:$A,0)) -> 99.51 | AD116: =INDEX('ИПЦ raw'!AO:AO, MATCH(Структура!$D116,'ИПЦ raw'!$A:$A,0)) -> 99.89 | AE116: =INDEX('ИПЦ raw'!AP:AP, MATCH(Структура!$D116,'ИПЦ raw'!$A:$A,0)) -> 100.34 | AG116: =INDEX('2025'!$C:$C,MATCH(Структура!C116,'2025'!$B:$B,0)) -> 0.098 | AH116: =AG116*P116/100 -> 0.098392 | AI116: =AH116*Q116/100 -> 0.099238171 | AJ116: =AI116*R116/100 -> 0.09954581 | AK116: =AJ116*S116/100 -> 0.099834492 | AL116: =AK116*T116/100 -> 0.099834492 | AM116: =AL116*U116/100 -> 0.10039357 | AN116: =AM116*V116/100 -> 0.10084534 | AO116: =AN116*W116/100 -> 0.10149075 | ... AR116: =AQ116*Z116/100 -> 0.10249054 | AS116: =J116 -> 0.1 | AT116: =AS116*AB116/100 -> 0.10002 | AU116: =AT116*AC116/100 -> 0.099529902 | AV116: =AU116*AD116/100 -> 0.099420419 | AW116: =AV116*AE116/100 -> 0.099758449
A117: Брюки мужские из полушерстяных или смесовых тканей, шт. | B117: =A117 -> Брюки мужские из полушерстяных или смесовых тканей, шт. | C117: =A117 -> Брюки мужские из полушерстяных или смесовых тканей, шт. | D117: =C117 -> Брюки мужские из полушерстяных или смесовых тканей, шт. | E117: =INDEX(БИПЦ_НДС!$D:$D,MATCH(Структура!A117,БИПЦ_НДС!$B:$B,0)) -> 20 | F117: Непроды | G117: 1 | H117: 1 | I117: 0 | J117: =INDEX('2026'!$C:$C,MATCH(Структура!B117,'2026'!$B:$B,0)) -> 0.102 | K117: =INDEX('2025'!$C:$C,MATCH(Структура!C117,'2025'!$B:$B,0)) -> 0.117 | L117: 1 | M117: 1 | N117: =INDEX(MoM!B:B,MATCH(Структура!A117,MoM!J:J,0)) -> 1 | P117: =INDEX('ИПЦ raw'!AA:AA, MATCH(Структура!$D117,'ИПЦ raw'!$A:$A,0)) -> 100.16 | Q117: =INDEX('ИПЦ raw'!AB:AB, MATCH(Структура!$D117,'ИПЦ raw'!$A:$A,0)) -> 99.8 | R117: =INDEX('ИПЦ raw'!AC:AC, MATCH(Структура!$D117,'ИПЦ raw'!$A:$A,0)) -> 100.4 | S117: =INDEX('ИПЦ raw'!AD:AD, MATCH(Структура!$D117,'ИПЦ raw'!$A:$A,0)) -> 100.02 | T117: =INDEX('ИПЦ raw'!AE:AE, MATCH(Структура!$D117,'ИПЦ raw'!$A:$A,0)) -> 99.61 | U117: =INDEX('ИПЦ raw'!AF:AF, MATCH(Структура!$D117,'ИПЦ raw'!$A:$A,0)) -> 100.06 | V117: =INDEX('ИПЦ raw'!AG:AG, MATCH(Структура!$D117,'ИПЦ raw'!$A:$A,0)) -> 99.72 | W117: =INDEX('ИПЦ raw'!AH:AH, MATCH(Структура!$D117,'ИПЦ raw'!$A:$A,0)) -> 100.4 | X117: =INDEX('ИПЦ raw'!AI:AI, MATCH(Структура!$D117,'ИПЦ raw'!$A:$A,0)) -> 99.59 | Y117: =INDEX('ИПЦ raw'!AJ:AJ, MATCH(Структура!$D117,'ИПЦ raw'!$A:$A,0)) -> 99.99 | Z117: =INDEX('ИПЦ raw'!AK:AK, MATCH(Структура!$D117,'ИПЦ raw'!$A:$A,0)) -> 100.27 | AA117: =INDEX('ИПЦ raw'!AL:AL, MATCH(Структура!$D117,'ИПЦ raw'!$A:$A,0)) -> 100.19 | AB117: =INDEX('ИПЦ raw'!AM:AM, MATCH(Структура!$D117,'ИПЦ raw'!$A:$A,0)) -> 99.9 | AC117: =INDEX('ИПЦ raw'!AN:AN, MATCH(Структура!$D117,'ИПЦ raw'!$A:$A,0)) -> 100.19 | AD117: =INDEX('ИПЦ raw'!AO:AO, MATCH(Структура!$D117,'ИПЦ raw'!$A:$A,0)) -> 99.94 | AE117: =INDEX('ИПЦ raw'!AP:AP, MATCH(Структура!$D117,'ИПЦ raw'!$A:$A,0)) -> 100.07 | AG117: =INDEX('2025'!$C:$C,MATCH(Структура!C117,'2025'!$B:$B,0)) -> 0.117 | AH117: =AG117*P117/100 -> 0.1171872 | AI117: =AH117*Q117/100 -> 0.11695283 | AJ117: =AI117*R117/100 -> 0.11742064 | AK117: =AJ117*S117/100 -> 0.11744412 | AL117: =AK117*T117/100 -> 0.11698609 | AM117: =AL117*U117/100 -> 0.11705628 | AN117: =AM117*V117/100 -> 0.11672852 | AO117: =AN117*W117/100 -> 0.11719544 | ... AR117: =AQ117*Z117/100 -> 0.11701836 | AS117: =J117 -> 0.102 | AT117: =AS117*AB117/100 -> 0.101898 | AU117: =AT117*AC117/100 -> 0.10209161 | AV117: =AU117*AD117/100 -> 0.10203035 | AW117: =AV117*AE117/100 -> 0.10210177
A118: Брюки мужские из джинсовой ткани (джинсы), шт. | B118: =A118 -> Брюки мужские из джинсовой ткани (джинсы), шт. | C118: =A118 -> Брюки мужские из джинсовой ткани (джинсы), шт. | D118: =C118 -> Брюки мужские из джинсовой ткани (джинсы), шт. | E118: =INDEX(БИПЦ_НДС!$D:$D,MATCH(Структура!A118,БИПЦ_НДС!$B:$B,0)) -> 20 | F118: Непроды | G118: 1 | H118: 1 | I118: 0 | J118: =INDEX('2026'!$C:$C,MATCH(Структура!B118,'2026'!$B:$B,0)) -> 0.241 | K118: =INDEX('2025'!$C:$C,MATCH(Структура!C118,'2025'!$B:$B,0)) -> 0.226 | L118: 1 | M118: 1 | N118: =INDEX(MoM!B:B,MATCH(Структура!A118,MoM!J:J,0)) -> 1 | P118: =INDEX('ИПЦ raw'!AA:AA, MATCH(Структура!$D118,'ИПЦ raw'!$A:$A,0)) -> 100.4 | Q118: =INDEX('ИПЦ raw'!AB:AB, MATCH(Структура!$D118,'ИПЦ raw'!$A:$A,0)) -> 100.01 | R118: =INDEX('ИПЦ raw'!AC:AC, MATCH(Структура!$D118,'ИПЦ raw'!$A:$A,0)) -> 100.08 | S118: =INDEX('ИПЦ raw'!AD:AD, MATCH(Структура!$D118,'ИПЦ raw'!$A:$A,0)) -> 99.22 | T118: =INDEX('ИПЦ raw'!AE:AE, MATCH(Структура!$D118,'ИПЦ raw'!$A:$A,0)) -> 99.56 | U118: =INDEX('ИПЦ raw'!AF:AF, MATCH(Структура!$D118,'ИПЦ raw'!$A:$A,0)) -> 99.49 | V118: =INDEX('ИПЦ raw'!AG:AG, MATCH(Структура!$D118,'ИПЦ raw'!$A:$A,0)) -> 99.61 | W118: =INDEX('ИПЦ raw'!AH:AH, MATCH(Структура!$D118,'ИПЦ raw'!$A:$A,0)) -> 100.51 | X118: =INDEX('ИПЦ raw'!AI:AI, MATCH(Структура!$D118,'ИПЦ raw'!$A:$A,0)) -> 99.65 | Y118: =INDEX('ИПЦ raw'!AJ:AJ, MATCH(Структура!$D118,'ИПЦ raw'!$A:$A,0)) -> 100.06 | Z118: =INDEX('ИПЦ raw'!AK:AK, MATCH(Структура!$D118,'ИПЦ raw'!$A:$A,0)) -> 100.5 | AA118: =INDEX('ИПЦ raw'!AL:AL, MATCH(Структура!$D118,'ИПЦ raw'!$A:$A,0)) -> 100.25 | AB118: =INDEX('ИПЦ raw'!AM:AM, MATCH(Структура!$D118,'ИПЦ raw'!$A:$A,0)) -> 99.59 | AC118: =INDEX('ИПЦ raw'!AN:AN, MATCH(Структура!$D118,'ИПЦ raw'!$A:$A,0)) -> 99.43 | AD118: =INDEX('ИПЦ raw'!AO:AO, MATCH(Структура!$D118,'ИПЦ raw'!$A:$A,0)) -> 100.04 | AE118: =INDEX('ИПЦ raw'!AP:AP, MATCH(Структура!$D118,'ИПЦ raw'!$A:$A,0)) -> 100.2 | AG118: =INDEX('2025'!$C:$C,MATCH(Структура!C118,'2025'!$B:$B,0)) -> 0.226 | AH118: =AG118*P118/100 -> 0.226904 | AI118: =AH118*Q118/100 -> 0.22692669 | AJ118: =AI118*R118/100 -> 0.22710823 | AK118: =AJ118*S118/100 -> 0.22533679 | AL118: =AK118*T118/100 -> 0.22434531 | AM118: =AL118*U118/100 -> 0.22320114 | AN118: =AM118*V118/100 -> 0.22233066 | AO118: =AN118*W118/100 -> 0.22346455 | ... AR118: =AQ118*Z118/100 -> 0.22393011 | AS118: =J118 -> 0.241 | AT118: =AS118*AB118/100 -> 0.2400119 | AU118: =AT118*AC118/100 -> 0.23864383 | AV118: =AU118*AD118/100 -> 0.23873929 | AW118: =AV118*AE118/100 -> 0.23921677
