Workbook

Sheet БИПЦ_НДС
A1: Совпадение ключей названия | B1: Новое название | C1: Старое основное название | D1: Итог | E1: Базовая ставка
A2: =EXACT(B2,C2) -> TRUE | B2: Говядина (кроме бескостного мяса), кг | C2: Говядина (кроме бескостного мяса), кг | D2: 10 | E2: =IF(D2=20,1,0) -> 0
A3: =EXACT(B3,C3) -> TRUE | B3: Говядина бескостная, кг | C3: Говядина бескостная, кг | D3: 10 | E3: =IF(D3=20,1,0) -> 0
A4: =EXACT(B4,C4) -> TRUE | B4: Свинина (кроме бескостного мяса), кг | C4: Свинина (кроме бескостного мяса), кг | D4: 10 | E4: =IF(D4=20,1,0) -> 0
A5: =EXACT(B5,C5) -> TRUE | B5: Свинина бескостная, кг | C5: Свинина бескостная, кг | D5: 10 | E5: =IF(D5=20,1,0) -> 0
A6: =EXACT(B6,C6) -> TRUE | B6: Баранина (кроме бескостного мяса), кг | C6: Баранина (кроме бескостного мяса), кг | D6: 10 | E6: =IF(D6=20,1,0) -> 0
A7: =EXACT(B7,C7) -> TRUE | B7: Куры охлажденные и мороженые, кг | C7: Куры охлажденные и мороженые, кг | D7: 10 | E7: =IF(D7=20,1,0) -> 0
A8: =EXACT(B8,C8) -> TRUE | B8: Окорочка куриные, кг | C8: Окорочка куриные, кг | D8: 10 | E8: =IF(D8=20,1,0) -> 0
A9: =EXACT(B9,C9) -> TRUE | B9: Мясо индейки, кг | C9: Мясо индейки, кг | D9: 10 | E9: =IF(D9=20,1,0) -> 0
A10: =EXACT(B10,C10) -> TRUE | B10: Печень говяжья, свиная, кг | C10: Печень говяжья, свиная, кг | D10: 10 | E10: =IF(D10=20,1,0) -> 0
A11: =EXACT(B11,C11) -> TRUE | B11: Фарш мясной, кг | C11: Фарш мясной, кг | D11: 10 | E11: =IF(D11=20,1,0) -> 0
A12: =EXACT(B12,C12) -> TRUE | B12: Пельмени, манты, равиоли, кг | C12: Пельмени, манты, равиоли, кг | D12: 10 | E12: =IF(D12=20,1,0) -> 0
A13: =EXACT(B13,C13) -> TRUE | B13: Сосиски, сардельки, кг | C13: Сосиски, сардельки, кг | D13: 10 | E13: =IF(D13=20,1,0) -> 0
... A394: =EXACT(B394,C394) -> TRUE | B394: Музеи и выставки, билет | C394: Музеи и выставки, билет | D394: 0 | E394: =IF(D394=20,1,0) -> 0
A395: =EXACT(B395,C395) -> TRUE | B395: Поездка на отдых в Турцию, поездка | C395: Поездка на отдых в Турцию, поездка | E395: =IF(D395=20,1,0) -> 0
A396: =EXACT(B396,C396) -> TRUE | B396: Поездка на отдых в ОАЭ, поездка | C396: Поездка на отдых в ОАЭ, поездка | E396: =IF(D396=20,1,0) -> 0
A397: =EXACT(B397,C397) -> TRUE | B397: Поездка на отдых в Египет, поездка | C397: Поездка на отдых в Египет, поездка | E397: =IF(D397=20,1,0) -> 0
A398: =EXACT(B398,C398) -> TRUE | B398: Поездка в Беларусь, поездка | C398: Поездка в Беларусь, поездка | E398: =IF(D398=20,1,0) -> 0
A399: =EXACT(B399,C399) -> TRUE | B399: Поездки в страны Закавказья, поездка | C399: Поездки в страны Закавказья, поездка | E399: =IF(D399=20,1,0) -> 0
A400: =EXACT(B400,C400) -> TRUE | B400: Поездки в отдельные страны Средней Азии, поездка | C400: Поездки в отдельные страны Средней Азии, поездка | E400: =IF(D400=20,1,0) -> 0
A401: =EXACT(B401,C401) -> TRUE | B401: Поездки в отдельные страны Юго-Восточной Азии, поездка | C401: Поездки в отдельные страны Юго-Восточной Азии, поездка | E401: =IF(D401=20,1,0) -> 0
A402: =EXACT(B402,C402) -> TRUE | B402: Экскурсия автобусная, час | C402: Экскурсия автобусная, час | D402: 0 | E402: =IF(D402=20,1,0) -> 0
A403: =EXACT(B403,C403) -> FALSE | B403: Экскурсионные туры по России, экскурсия | C403: Экскурсионные туры по России, поездка | D403: 0 | E403: =IF(D403=20,1,0) -> 0
A404: =EXACT(B404,C404) -> TRUE | B404: Поездка на отдых на Черноморское побережье России, поездка | C404: Поездка на отдых на Черноморское побережье России, поездка | E404: =IF(D404=20,1,0) -> 0
A405: =EXACT(B405,C405) -> TRUE | B405: Санаторий, день | C405: Санаторий, день | E405: =IF(D405=20,1,0) -> 0
A406: =EXACT(B406,C406) -> TRUE | B406: Дом отдыха, пансионат, день | C406: Дом отдыха, пансионат, день | E406: =IF(D406=20,1,0) -> 0
A407: =EXACT(B407,C407) -> TRUE | B407: Первичный консультативный прием у врача специалиста, посещение | C407: Первичный консультативный прием у врача специалиста, посещение | D407: 0 | E407: =IF(D407=20,1,0) -> 0
A408: =EXACT(B408,C408) -> TRUE | B408: Ультразвуковое исследование брюшной полости, исследование | C408: Ультразвуковое исследование брюшной полости, исследование | D408: 0 | E408: =IF(D408=20,1,0) -> 0
A409: =EXACT(B409,C409) -> TRUE | B409: Диагностика на магнитно-резонансном или компьютерном томографе, услуга | C409: Диагностика на магнитно-резонансном или компьютерном томографе, услуга | D409: 0 | E409: =IF(D409=20,1,0) -> 0
A410: =EXACT(B410,C410) -> TRUE | B410: Гастроскопия (ФГДС, ЭГДС), услуга | C410: Гастроскопия (ФГДС, ЭГДС), услуга | D410: 0 | E410: =IF(D410=20,1,0) -> 0
A411: =EXACT(B411,C411) -> TRUE | B411: Физиотерапевтическое лечение, процедура | C411: Физиотерапевтическое лечение, процедура | D411: 0 | E411: =IF(D411=20,1,0) -> 0
A412: =EXACT(B412,C412) -> TRUE | B412: Общий анализ крови, анализ | C412: Общий анализ крови, анализ | D412: 0 | E412: =IF(D412=20,1,0) -> 0
A413: =EXACT(B413,C413) -> TRUE | B413: Пребывание пациента в круглосуточном стационаре, койко-день | C413: Пребывание пациента в круглосуточном стационаре, койко-день | D413: 0 | E413: =IF(D413=20,1,0) -> 0
A414: =EXACT(B414,C414) -> TRUE | B414: Первичный консультативный осмотр больного у стоматолога, посещение | C414: Первичный консультативный осмотр больного у стоматолога, посещение | D414: 0 | E414: =IF(D414=20,1,0) -> 0
A415: =EXACT(B415,C415) -> TRUE | B415: Удаление зуба под местным обезболиванием, удаление | C415: Удаление зуба под местным обезболиванием, удаление | D415: 0 | E415: =IF(D415=20,1,0) -> 0
A416: =EXACT(B416,C416) -> TRUE | B416: Восстановление зуба пломбой, услуга | C416: Восстановление зуба пломбой, услуга | D416: 0 | E416: =IF(D416=20,1,0) -> 0
A417: =EXACT(B417,C417) -> TRUE | B417: Изготовление съёмного зубного протеза, протез | C417: Изготовление съёмного зубного протеза, протез | D417: 0 | E417: =IF(D417=20,1,0) -> 0
A418: =EXACT(B418,C418) -> TRUE | B418: Изготовление коронки, шт. | C418: Изготовление коронки, шт. | D418: 0 | E418: =IF(D418=20,1,0) -> 0
... A433: =EXACT(B433,C433) -> TRUE | B433: Пользование общественным туалетом, посещение | C433: Пользование общественным туалетом, посещение | D433: 20 | E433: =IF(D433=20,1,0) -> 1
B437: Для маски: https://cntd.ru/news/read/vvoz-i-prodaja-tekstilnyh-masok-obschego-polzovaniya-daje-esli-oni-ispolzuutsya-v-kachestve-siz-dlya-borby-s-koronavirusnoy-infekciey-oblagautsya-nds-po-stavke-20

Sheet Структура
A1: Новое название | B1: Название для поиска 2026 | C1: Название для поиска 2025 | D1: Название для поиска ИПЦ | E1: НДС | F1: Тип | G1: БИПЦ 2026 | H1: БИПЦ 2025 | I1: Туризм и общепит | J1: ИПЦ 2026 | K1: ИПЦ 2025 | L1: Учитывать
A2: Говядина (кроме бескостного мяса), кг | B2: =A2 -> Говядина (кроме бескостного мяса), кг | C2: =A2 -> Говядина (кроме бескостного мяса), кг | D2: =C2 -> Говядина (кроме бескостного мяса), кг | E2: =INDEX(БИПЦ_НДС!$D:$D,MATCH(Структура!A2,БИПЦ_НДС!$B:$B,0)) -> 10 | F2: Проды | G2: 1 | H2: 1 | I2: 0 | J2: 1 | K2: 1 | L2: 0
A3: Говядина бескостная, кг | B3: =A3 -> Говядина бескостная, кг | C3: =A3 -> Говядина бескостная, кг | D3: =C3 -> Говядина бескостная, кг | E3: =INDEX(БИПЦ_НДС!$D:$D,MATCH(Структура!A3,БИПЦ_НДС!$B:$B,0)) -> 10 | F3: Проды | G3: 1 | H3: 1 | I3: 0 | J3: 1 | K3: 1 | L3: =INDEX(MoM!B:B,MATCH(Структура!A3,MoM!K:K,0)) -> 1
A4: Свинина (кроме бескостного мяса), кг | B4: =A4 -> Свинина (кроме бескостного мяса), кг | C4: =A4 -> Свинина (кроме бескостного мяса), кг | D4: =C4 -> Свинина (кроме бескостного мяса), кг | E4: =INDEX(БИПЦ_НДС!$D:$D,MATCH(Структура!A4,БИПЦ_НДС!$B:$B,0)) -> 10 | F4: Проды | G4: 1 | H4: 1 | I4: 0 | J4: 1 | K4: 1 | L4: =INDEX(MoM!B:B,MATCH(Структура!A4,MoM!K:K,0)) -> 1
A5: Свинина бескостная, кг | B5: =A5 -> Свинина бескостная, кг | C5: =A5 -> Свинина бескостная, кг | D5: =C5 -> Свинина бескостная, кг | E5: =INDEX(БИПЦ_НДС!$D:$D,MATCH(Структура!A5,БИПЦ_НДС!$B:$B,0)) -> 10 | F5: Проды | G5: 1 | H5: 1 | I5: 0 | J5: 1 | K5: 1 | L5: =INDEX(MoM!B:B,MATCH(Структура!A5,MoM!K:K,0)) -> 1
A6: Баранина (кроме бескостного мяса), кг | B6: =A6 -> Баранина (кроме бескостного мяса), кг | C6: =A6 -> Баранина (кроме бескостного мяса), кг | D6: =C6 -> Баранина (кроме бескостного мяса), кг | E6: =INDEX(БИПЦ_НДС!$D:$D,MATCH(Структура!A6,БИПЦ_НДС!$B:$B,0)) -> 10 | F6: Проды | G6: 1 | H6: 1 | I6: 0 | J6: 1 | K6: 1 | L6: =INDEX(MoM!B:B,MATCH(Структура!A6,MoM!K:K,0)) -> 1
A7: Куры охлажденные и мороженые, кг | B7: =A7 -> Куры охлажденные и мороженые, кг | C7: =A7 -> Куры охлажденные и мороженые, кг | D7: =C7 -> Куры охлажденные и мороженые, кг | E7: =INDEX(БИПЦ_НДС!$D:$D,MATCH(Структура!A7,БИПЦ_НДС!$B:$B,0)) -> 10 | F7: Проды | G7: 1 | H7: 1 | I7: 0 | J7: 1 | K7: 1 | L7: =INDEX(MoM!B:B,MATCH(Структура!A7,MoM!K:K,0)) -> 1
A8: Окорочка куриные, кг | B8: =A8 -> Окорочка куриные, кг | C8: =A8 -> Окорочка куриные, кг | D8: =C8 -> Окорочка куриные, кг | E8: =INDEX(БИПЦ_НДС!$D:$D,MATCH(Структура!A8,БИПЦ_НДС!$B:$B,0)) -> 10 | F8: Проды | G8: 1 | H8: 1 | I8: 0 | J8: 1 | K8: 1 | L8: =INDEX(MoM!B:B,MATCH(Структура!A8,MoM!K:K,0)) -> 1
A9: Мясо индейки, кг | B9: =A9 -> Мясо индейки, кг | C9: =A9 -> Мясо индейки, кг | D9: Мясо индейки, кг | E9: =INDEX(БИПЦ_НДС!$D:$D,MATCH(Структура!A9,БИПЦ_НДС!$B:$B,0)) -> 10 | F9: Проды | G9: 1 | H9: 1 | I9: 0 | J9: 1 | K9: 1 | L9: =INDEX(MoM!B:B,MATCH(Структура!A9,MoM!K:K,0)) -> 0
A10: Печень говяжья, свиная, кг | B10: =A10 -> Печень говяжья, свиная, кг | C10: =A10 -> Печень говяжья, свиная, кг | D10: =C10 -> Печень говяжья, свиная, кг | E10: =INDEX(БИПЦ_НДС!$D:$D,MATCH(Структура!A10,БИПЦ_НДС!$B:$B,0)) -> 10 | F10: Проды | G10: 1 | H10: 1 | I10: 0 | J10: 1 | K10: 1 | L10: =INDEX(MoM!B:B,MATCH(Структура!A10,MoM!K:K,0)) -> 1
A11: Фарш мясной, кг | B11: =A11 -> Фарш мясной, кг | C11: =A11 -> Фарш мясной, кг | D11: =C11 -> Фарш мясной, кг | E11: =INDEX(БИПЦ_НДС!$D:$D,MATCH(Структура!A11,БИПЦ_НДС!$B:$B,0)) -> 10 | F11: Проды | G11: 1 | H11: 1 | I11: 0 | J11: 1 | K11: 1 | L11: =INDEX(MoM!B:B,MATCH(Структура!A11,MoM!K:K,0)) -> 1
A12: Пельмени, манты, равиоли, кг | B12: =A12 -> Пельмени, манты, равиоли, кг | C12: =A12 -> Пельмени, манты, равиоли, кг | D12: =C12 -> Пельмени, манты, равиоли, кг | E12: =INDEX(БИПЦ_НДС!$D:$D,MATCH(Структура!A12,БИПЦ_НДС!$B:$B,0)) -> 10 | F12: Проды | G12: 1 | H12: 1 | I12: 0 | J12: 1 | K12: 1 | L12: =INDEX(MoM!B:B,MATCH(Структура!A12,MoM!K:K,0)) -> 1
A13: Сосиски, сардельки, кг | B13: =A13 -> Сосиски, сардельки, кг | C13: =A13 -> Сосиски, сардельки, кг | D13: =C13 -> Сосиски, сардельки, кг | E13: =INDEX(БИПЦ_НДС!$D:$D,MATCH(Структура!A13,БИПЦ_НДС!$B:$B,0)) -> 10 | F13: Проды | G13: 1 | H13: 1 | I13: 0 | J13: 1 | K13: 1 | L13: =INDEX(MoM!B:B,MATCH(Структура!A13,MoM!K:K,0)) -> 1
A14: Колбаса полукопченая и варено-копченая, кг | B14: =A14 -> Колбаса полукопченая и варено-копченая, кг | C14: =A14 -> Колбаса полукопченая и варено-копченая, кг | D14: =C14 -> Колбаса полукопченая и варено-копченая, кг | E14: =INDEX(БИПЦ_НДС!$D:$D,MATCH(Структура!A14,БИПЦ_НДС!$B:$B,0)) -> 10 | F14: Проды | G14: 1 | H14: 1 | I14: 0 | J14: 1 | K14: 1 | L14: =INDEX(MoM!B:B,MATCH(Структура!A14,MoM!K:K,0)) -> 1
A15: Колбаса сырокопченая, кг | B15: =A15 -> Колбаса сырокопченая, кг | C15: =A15 -> Колбаса сырокопченая, кг | D15: =C15 -> Колбаса сырокопченая, кг | E15: =INDEX(БИПЦ_НДС!$D:$D,MATCH(Структура!A15,БИПЦ_НДС!$B:$B,0)) -> 10 | F15: Проды | G15: 1 | H15: 1 | I15: 0 | J15: 1 | K15: 1 | L15: =INDEX(MoM!B:B,MATCH(Структура!A15,MoM!K:K,0)) -> 1
A16: Колбаса вареная, кг | B16: =A16 -> Колбаса вареная, кг | C16: =A16 -> Колбаса вареная, кг | D16: =C16 -> Колбаса вареная, кг | E16: =INDEX(БИПЦ_НДС!$D:$D,MATCH(Структура!A16,БИПЦ_НДС!$B:$B,0)) -> 10 | F16: Проды | G16: 1 | H16: 1 | I16: 0 | J16: 1 | K16: 1 | L16: =INDEX(MoM!B:B,MATCH(Структура!A16,MoM!K:K,0)) -> 1
A17: Мясокопчености, кг | B17: =A17 -> Мясокопчености, кг | C17: =A17 -> Мясокопчености, кг | D17: =C17 -> Мясокопчености, кг | E17: =INDEX(БИПЦ_НДС!$D:$D,MATCH(Структура!A17,БИПЦ_НДС!$B:$B,0)) -> 20 | F17: Проды | G17: 1 | H17: 1 | I17: 0 | J17: 1 | K17: 1 | L17: =INDEX(MoM!B:B,MATCH(Структура!A17,MoM!K:K,0)) -> 1
A18: Кулинарные изделия из птицы, кг | B18: =A18 -> Кулинарные изделия из птицы, кг | C18: =A18 -> Кулинарные изделия из птицы, кг | D18: =C18 -> Кулинарные изделия из птицы, кг | E18: =INDEX(БИПЦ_НДС!$D:$D,MATCH(Структура!A18,БИПЦ_НДС!$B:$B,0)) -> 10 | F18: Проды | G18: 1 | H18: 1 | I18: 0 | J18: 1 | K18: 1 | L18: =INDEX(MoM!B:B,MATCH(Структура!A18,MoM!K:K,0)) -> 1
A19: Консервы мясные, кг | B19: =A19 -> Консервы мясные, кг | C19: =A19 -> Консервы мясные, кг | D19: =C19 -> Консервы мясные, кг | E19: =INDEX(БИПЦ_НДС!$D:$D,MATCH(Структура!A19,БИПЦ_НДС!$B:$B,0)) -> 10 | F19: Проды | G19: 1 | H19: 1 | I19: 0 | J19: 1 | K19: 1 | L19: =INDEX(MoM!B:B,MATCH(Структура!A19,MoM!K:K,0)) -> 1
A20: Консервы мясные для детского питания, кг | B20: =A20 -> Консервы мясные для детского питания, кг | C20: =A20 -> Консервы мясные для детского питания, кг | D20: =C20 -> Консервы мясные для детского питания, кг | E20: =INDEX(БИПЦ_НДС!$D:$D,MATCH(Структура!A20,БИПЦ_НДС!$B:$B,0)) -> 10 | F20: Проды | G20: 1 | H20: 1 | I20: 0 | J20: 1 | K20: 1 | L20: =INDEX(MoM!B:B,MATCH(Структура!A20,MoM!K:K,0)) -> 0
A21: Рыба живая и охлажденная, кг | B21: =A21 -> Рыба живая и охлажденная, кг | C21: =A21 -> Рыба живая и охлажденная, кг | D21: =C21 -> Рыба живая и охлажденная, кг | E21: =INDEX(БИПЦ_НДС!$D:$D,MATCH(Структура!A21,БИПЦ_НДС!$B:$B,0)) -> 10 | F21: Проды | G21: 1 | H21: 1 | I21: 0 | J21: 1 | K21: 1 | L21: =INDEX(MoM!B:B,MATCH(Структура!A21,MoM!K:K,0)) -> 1
... A23: Соленые и копченые деликатесные продукты из рыбы, кг | B23: =A23 -> Соленые и копченые деликатесные продукты из рыбы, кг | C23: =A23 -> Соленые и копченые деликатесные продукты из рыбы, кг | D23: =C23 -> Соленые и копченые деликатесные продукты из рыбы, кг | E23: =INDEX(БИПЦ_НДС!$D:$D,MATCH(Структура!A23,БИПЦ_НДС!$B:$B,0)) -> 20 | F23: Проды | G23: 1 | H23: 1 | I23: 0 | J23: 1 | K23: 1 | L23: =INDEX(MoM!B:B,MATCH(Структура!A23,MoM!K:K,0)) -> 1
A24: Икра лососевых рыб отечественная, кг | B24: =A24 -> Икра лососевых рыб отечественная, кг | C24: Икра лососевых рыб, отечественная, кг | D24: Икра лососевых рыб отечественная, кг | E24: =INDEX(БИПЦ_НДС!$D:$D,MATCH(Структура!A24,БИПЦ_НДС!$B:$B,0)) -> 20 | F24: Проды | G24: 1 | H24: 1 | I24: 0 | J24: 1 | K24: 1 | L24: =INDEX(MoM!B:B,MATCH(Структура!A24,MoM!K:K,0)) -> 1
A25: Рыба мороженая разделанная (кроме лососевых пород), кг | B25: =A25 -> Рыба мороженая разделанная (кроме лососевых пород), кг | C25: =A25 -> Рыба мороженая разделанная (кроме лососевых пород), кг | D25: =C25 -> Рыба мороженая разделанная (кроме лососевых пород), кг | E25: =INDEX(БИПЦ_НДС!$D:$D,MATCH(Структура!A25,БИПЦ_НДС!$B:$B,0)) -> 10 | F25: Проды | G25: 1 | H25: 1 | I25: 0 | J25: 1 | K25: 1 | L25: =INDEX(MoM!B:B,MATCH(Структура!A25,MoM!K:K,0)) -> 1
A26: Рыба охлажденная и мороженая разделанная лососевых пород, кг | B26: =A26 -> Рыба охлажденная и мороженая разделанная лососевых пород, кг | C26: =A26 -> Рыба охлажденная и мороженая разделанная лососевых пород, кг | D26: =C26 -> Рыба охлажденная и мороженая разделанная лососевых пород, кг | E26: =INDEX(БИПЦ_НДС!$D:$D,MATCH(Структура!A26,БИПЦ_НДС!$B:$B,0)) -> 20 | F26: Проды | G26: 1 | H26: 1 | I26: 0 | J26: 1 | K26: 1 | L26: =INDEX(MoM!B:B,MATCH(Структура!A26,MoM!K:K,0)) -> 1
A27: Рыба мороженая неразделанная, кг | B27: =A27 -> Рыба мороженая неразделанная, кг | C27: =A27 -> Рыба мороженая неразделанная, кг | D27: =C27 -> Рыба мороженая неразделанная, кг | E27: =INDEX(БИПЦ_НДС!$D:$D,MATCH(Структура!A27,БИПЦ_НДС!$B:$B,0)) -> 10 | F27: Проды | G27: 1 | H27: 1 | I27: 0 | J27: 1 | K27: 1 | L27: =INDEX(MoM!B:B,MATCH(Структура!A27,MoM!K:K,0)) -> 1
A28: Филе рыбное, кг | B28: =A28 -> Филе рыбное, кг | C28: =A28 -> Филе рыбное, кг | D28: =C28 -> Филе рыбное, кг | E28: =INDEX(БИПЦ_НДС!$D:$D,MATCH(Структура!A28,БИПЦ_НДС!$B:$B,0)) -> 10 | F28: Проды | G28: 1 | H28: 1 | I28: 0 | J28: 1 | K28: 1 | L28: =INDEX(MoM!B:B,MATCH(Структура!A28,MoM!K:K,0)) -> 1
A29: Креветки мороженые, неразделанные, кг | B29: =A29 -> Креветки мороженые, неразделанные, кг | C29: Креветки мороженые неразделанные, кг | D29: Креветки мороженые, неразделанные, кг | E29: =INDEX(БИПЦ_НДС!$D:$D,MATCH(Структура!A29,БИПЦ_НДС!$B:$B,0)) -> 10 | F29: Проды | G29: 1 | H29: 1 | I29: 0 | J29: 1 | K29: 1 | L29: =INDEX(MoM!B:B,MATCH(Структура!A29,MoM!K:K,0)) -> 0
A30: Кальмары мороженые, кг | B30: =A30 -> Кальмары мороженые, кг | C30: Кальмары мороженые,кг | D30: Кальмары мороженые, кг | E30: =INDEX(БИПЦ_НДС!$D:$D,MATCH(Структура!A30,БИПЦ_НДС!$B:$B,0)) -> 10 | F30: Проды | G30: 1 | H30: 1 | I30: 0 | J30: 1 | K30: 1 | L30: =INDEX(MoM!B:B,MATCH(Структура!A30,MoM!K:K,0)) -> 0
A31: Сельдь соленая, кг | B31: =A31 -> Сельдь соленая, кг | C31: =A31 -> Сельдь соленая, кг | D31: =C31 -> Сельдь соленая, кг | E31: =INDEX(БИПЦ_НДС!$D:$D,MATCH(Структура!A31,БИПЦ_НДС!$B:$B,0)) -> 10 | F31: Проды | G31: 1 | H31: 1 | I31: 0 | J31: 1 | K31: 1 | L31: =INDEX(MoM!B:B,MATCH(Структура!A31,MoM!K:K,0)) -> 1
A32: Филе сельди соленое, кг | B32: =A32 -> Филе сельди соленое, кг | C32: =A32 -> Филе сельди соленое, кг | D32: =C32 -> Филе сельди соленое, кг | E32: =INDEX(БИПЦ_НДС!$D:$D,MATCH(Структура!A32,БИПЦ_НДС!$B:$B,0)) -> 10 | F32: Проды | G32: 1 | H32: 1 | I32: 0 | J32: 1 | K32: 1 | L32: =INDEX(MoM!B:B,MATCH(Структура!A32,MoM!K:K,0)) -> 1
A33: Консервы рыбные натуральные и с добавлением масла, кг | B33: =A33 -> Консервы рыбные натуральные и с добавлением масла, кг | C33: =A33 -> Консервы рыбные натуральные и с добавлением масла, кг | D33: =C33 -> Консервы рыбные натуральные и с добавлением масла, кг | E33: =INDEX(БИПЦ_НДС!$D:$D,MATCH(Структура!A33,БИПЦ_НДС!$B:$B,0)) -> 10 | F33: Проды | G33: 1 | H33: 1 | I33: 0 | J33: 1 | K33: 1 | L33: =INDEX(MoM!B:B,MATCH(Структура!A33,MoM!K:K,0)) -> 1
A34: Консервы рыбные в томатном соусе, кг | B34: =A34 -> Консервы рыбные в томатном соусе, кг | C34: =A34 -> Консервы рыбные в томатном соусе, кг | D34: =C34 -> Консервы рыбные в томатном соусе, кг | E34: =INDEX(БИПЦ_НДС!$D:$D,MATCH(Структура!A34,БИПЦ_НДС!$B:$B,0)) -> 10 | F34: Проды | G34: 1 | H34: 1 | I34: 0 | J34: 1 | K34: 1 | L34: =INDEX(MoM!B:B,MATCH(Структура!A34,MoM!K:K,0)) -> 1
A35: Масло сливочное, кг | B35: =A35 -> Масло сливочное, кг | C35: =A35 -> Масло сливочное, кг | D35: =C35 -> Масло сливочное, кг | E35: =INDEX(БИПЦ_НДС!$D:$D,MATCH(Структура!A35,БИПЦ_НДС!$B:$B,0)) -> 10 | F35: Проды | G35: 1 | H35: 1 | I35: 0 | J35: 1 | K35: 1 | L35: =INDEX(MoM!B:B,MATCH(Структура!A35,MoM!K:K,0)) -> 1
A36: Масло подсолнечное, л | B36: =A36 -> Масло подсолнечное, л | C36: =A36 -> Масло подсолнечное, л | D36: =C36 -> Масло подсолнечное, л | E36: =INDEX(БИПЦ_НДС!$D:$D,MATCH(Структура!A36,БИПЦ_НДС!$B:$B,0)) -> 10 | F36: Проды | G36: 1 | H36: 1 | I36: 0 | J36: 1 | K36: 1 | L36: =INDEX(MoM!B:B,MATCH(Структура!A36,MoM!K:K,0)) -> 1
A37: Масло оливковое, л | B37: =A37 -> Масло оливковое, л | C37: =A37 -> Масло оливковое, л | D37: =C37 -> Масло оливковое, л | E37: =INDEX(БИПЦ_НДС!$D:$D,MATCH(Структура!A37,БИПЦ_НДС!$B:$B,0)) -> 10 | F37: Проды | G37: 1 | H37: 1 | I37: 0 | J37: 1 | K37: 1 | L37: =INDEX(MoM!B:B,MATCH(Структура!A37,MoM!K:K,0)) -> 1
A38: Маргарин, кг | B38: =A38 -> Маргарин, кг | C38: =A38 -> Маргарин, кг | D38: =C38 -> Маргарин, кг | E38: =INDEX(БИПЦ_НДС!$D:$D,MATCH(Структура!A38,БИПЦ_НДС!$B:$B,0)) -> 10 | F38: Проды | G38: 1 | H38: 1 | I38: 0 | J38: 1 | K38: 1 | L38: =INDEX(MoM!B:B,MATCH(Структура!A38,MoM!K:K,0)) -> 1
A39: Молоко питьевое цельное пастеризованное 2,5-3,2% жирности, л | B39: =A39 -> Молоко питьевое цельное пастеризованное 2,5-3,2% жирности, л | C39: =A39 -> Молоко питьевое цельное пастеризованное 2,5-3,2% жирности, л | D39: =C39 -> Молоко питьевое цельное пастеризованное 2,5-3,2% жирности, л | E39: =INDEX(БИПЦ_НДС!$D:$D,MATCH(Структура!A39,БИПЦ_НДС!$B:$B,0)) -> 10 | F39: Проды | G39: 1 | H39: 1 | I39: 0 | J39: 1 | K39: 1 | L39: =INDEX(MoM!B:B,MATCH(Структура!A39,MoM!K:K,0)) -> 1
A40: Молоко питьевое цельное ультрапастеризованное 2,5-3,2% жирности, л | B40: =A40 -> Молоко питьевое цельное ультрапастеризованное 2,5-3,2% жирности, л | C40: =A40 -> Молоко питьевое цельное ультрапастеризованное 2,5-3,2% жирности, л | D40: =C40 -> Молоко питьевое цельное ультрапастеризованное 2,5-3,2% жирности, л | E40: =INDEX(БИПЦ_НДС!$D:$D,MATCH(Структура!A40,БИПЦ_НДС!$B:$B,0)) -> 10 | F40: Проды | G40: 1 | H40: 1 | I40: 0 | J40: 1 | K40: 1 | L40: =INDEX(MoM!B:B,MATCH(Структура!A40,MoM!K:K,0)) -> 0
A41: Молоко питьевое цельное пастеризованное более 3,2% жирности, л | B41: =A41 -> Молоко питьевое цельное пастеризованное более 3,2% жирности, л | C41: =A41 -> Молоко питьевое цельное пастеризованное более 3,2% жирности, л | D41: =C41 -> Молоко питьевое цельное пастеризованное более 3,2% жирности, л | E41: =INDEX(БИПЦ_НДС!$D:$D,MATCH(Структура!A41,БИПЦ_НДС!$B:$B,0)) -> 10 | F41: Проды | G41: 1 | H41: 1 | I41: 0 | J41: 1 | K41: 1 | L41: =INDEX(MoM!B:B,MATCH(Структура!A41,MoM!K:K,0)) -> 0
A42: Сметана, кг | B42: =A42 -> Сметана, кг | C42: =A42 -> Сметана, кг | D42: =C42 -> Сметана, кг | E42: =INDEX(БИПЦ_НДС!$D:$D,MATCH(Структура!A42,БИПЦ_НДС!$B:$B,0)) -> 10 | F42: Проды | G42: 1 | H42: 1 | I42: 0 | J42: 1 | K42: 1 | L42: =INDEX(MoM!B:B,MATCH(Структура!A42,MoM!K:K,0)) -> 1
... A46: Творог, кг | B46: =A46 -> Творог, кг | C46: =A46 -> Творог, кг | D46: =C46 -> Творог, кг | E46: =INDEX(БИПЦ_НДС!$D:$D,MATCH(Структура!A46,БИПЦ_НДС!$B:$B,0)) -> 10 | F46: Проды | G46: 1 | H46: 1 | I46: 0 | J46: 1 | K46: 1 | L46: =INDEX(MoM!B:B,MATCH(Структура!A46,MoM!K:K,0)) -> 1
A47: Сырки творожные, глазированные, кг | B47: =A47 -> Сырки творожные, глазированные, кг | C47: Сырки творожные, глазированные шоколадом, кг | D47: Сырки творожные, глазированные, кг | E47: =INDEX(БИПЦ_НДС!$D:$D,MATCH(Структура!A47,БИПЦ_НДС!$B:$B,0)) -> 10 | F47: Проды | G47: 1 | H47: 1 | I47: 0 | J47: 1 | K47: 1 | L47: =INDEX(MoM!B:B,MATCH(Структура!A47,MoM!K:K,0)) -> 0
A48: Молоко сгущенное с сахаром, кг | B48: =A48 -> Молоко сгущенное с сахаром, кг | C48: =A48 -> Молоко сгущенное с сахаром, кг | D48: =C48 -> Молоко сгущенное с сахаром, кг | E48: =INDEX(БИПЦ_НДС!$D:$D,MATCH(Структура!A48,БИПЦ_НДС!$B:$B,0)) -> 10 | F48: Проды | G48: 1 | H48: 1 | I48: 0 | J48: 1 | K48: 1 | L48: =INDEX(MoM!B:B,MATCH(Структура!A48,MoM!K:K,0)) -> 1
A49: Молоко для детей, л | B49: =A49 -> Молоко для детей, л | C49: =A49 -> Молоко для детей, л | D49: =C49 -> Молоко для детей, л | E49: =INDEX(БИПЦ_НДС!$D:$D,MATCH(Структура!A49,БИПЦ_НДС!$B:$B,0)) -> 10 | F49: Проды | G49: 1 | H49: 1 | I49: 0 | J49: 1 | K49: 1 | L49: =INDEX(MoM!B:B,MATCH(Структура!A49,MoM!K:K,0)) -> 0
A50: Творожок детский, кг | B50: =A50 -> Творожок детский, кг | C50: =A50 -> Творожок детский, кг | D50: =C50 -> Творожок детский, кг | E50: =INDEX(БИПЦ_НДС!$D:$D,MATCH(Структура!A50,БИПЦ_НДС!$B:$B,0)) -> 10 | F50: Проды | G50: 1 | H50: 1 | I50: 0 | J50: 1 | K50: 1 | L50: =INDEX(MoM!B:B,MATCH(Структура!A50,MoM!K:K,0)) -> 0
A51: Смеси сухие молочные для детского питания, кг | B51: =A51 -> Смеси сухие молочные для детского питания, кг | C51: =A51 -> Смеси сухие молочные для детского питания, кг | D51: =C51 -> Смеси сухие молочные для детского питания, кг | E51: =INDEX(БИПЦ_НДС!$D:$D,MATCH(Структура!A51,БИПЦ_НДС!$B:$B,0)) -> 10 | F51: Проды | G51: 1 | H51: 1 | I51: 0 | J51: 1 | K51: 1 | L51: =INDEX(MoM!B:B,MATCH(Структура!A51,MoM!K:K,0)) -> 1
A52: Национальные сыры и брынза, кг | B52: =A52 -> Национальные сыры и брынза, кг | C52: =A52 -> Национальные сыры и брынза, кг | D52: =C52 -> Национальные сыры и брынза, кг | E52: =INDEX(БИПЦ_НДС!$D:$D,MATCH(Структура!A52,БИПЦ_НДС!$B:$B,0)) -> 10 | F52: Проды | G52: 1 | H52: 1 | I52: 0 | J52: 1 | K52: 1 | L52: =INDEX(MoM!B:B,MATCH(Структура!A52,MoM!K:K,0)) -> 1
A53: Овощи натуральные консервированные, маринованные, кг | B53: =A53 -> Овощи натуральные консервированные, маринованные, кг | C53: =A53 -> Овощи натуральные консервированные, маринованные, кг | D53: =C53 -> Овощи натуральные консервированные, маринованные, кг | E53: =INDEX(БИПЦ_НДС!$D:$D,MATCH(Структура!A53,БИПЦ_НДС!$B:$B,0)) -> 20 | F53: Проды | G53: 1 | H53: 1 | I53: 0 | J53: 1 | K53: 1 | L53: =INDEX(MoM!B:B,MATCH(Структура!A53,MoM!K:K,0)) -> 1
A54: Горошек зеленый консервированный, кг | B54: =A54 -> Горошек зеленый консервированный, кг | C54: =A54 -> Горошек зеленый консервированный, кг | D54: =C54 -> Горошек зеленый консервированный, кг | E54: =INDEX(БИПЦ_НДС!$D:$D,MATCH(Структура!A54,БИПЦ_НДС!$B:$B,0)) -> 20 | F54: Проды | G54: 1 | H54: 1 | I54: 0 | J54: 1 | K54: 1 | L54: =INDEX(MoM!B:B,MATCH(Структура!A54,MoM!K:K,0)) -> 0
A55: Консервы овощные для детского питания, кг | B55: =A55 -> Консервы овощные для детского питания, кг | C55: =A55 -> Консервы овощные для детского питания, кг | D55: =C55 -> Консервы овощные для детского питания, кг | E55: =INDEX(БИПЦ_НДС!$D:$D,MATCH(Структура!A55,БИПЦ_НДС!$B:$B,0)) -> 10 | F55: Проды | G55: 1 | H55: 1 | I55: 0 | J55: 1 | K55: 1 | L55: =INDEX(MoM!B:B,MATCH(Структура!A55,MoM!K:K,0)) -> 1
A56: Консервы томатные, кг | B56: =A56 -> Консервы томатные, кг | C56: =A56 -> Консервы томатные, кг | D56: =C56 -> Консервы томатные, кг | E56: =INDEX(БИПЦ_НДС!$D:$D,MATCH(Структура!A56,БИПЦ_НДС!$B:$B,0)) -> 20 | F56: Проды | G56: 1 | H56: 1 | I56: 0 | J56: 1 | K56: 1 | L56: =INDEX(MoM!B:B,MATCH(Структура!A56,MoM!K:K,0)) -> 1
A57: Соки фруктовые, л | B57: =A57 -> Соки фруктовые, л | C57: =A57 -> Соки фруктовые, л | D57: =C57 -> Соки фруктовые, л | E57: =INDEX(БИПЦ_НДС!$D:$D,MATCH(Структура!A57,БИПЦ_НДС!$B:$B,0)) -> 10 | F57: Проды | G57: 1 | H57: 1 | I57: 0 | J57: 1 | K57: 1 | L57: =INDEX(MoM!B:B,MATCH(Структура!A57,MoM!K:K,0)) -> 1
A58: Консервы фруктово-ягодные для детского питания, кг | B58: =A58 -> Консервы фруктово-ягодные для детского питания, кг | C58: =A58 -> Консервы фруктово-ягодные для детского питания, кг | D58: =C58 -> Консервы фруктово-ягодные для детского питания, кг | E58: =INDEX(БИПЦ_НДС!$D:$D,MATCH(Структура!A58,БИПЦ_НДС!$B:$B,0)) -> 10 | F58: Проды | G58: 1 | H58: 1 | I58: 0 | J58: 1 | K58: 1 | L58: =INDEX(MoM!B:B,MATCH(Структура!A58,MoM!K:K,0)) -> 1
A59: Зефир, пастила, кг | B59: =A59 -> Зефир, пастила, кг | C59: =A59 -> Зефир, пастила, кг | D59: =C59 -> Зефир, пастила, кг | E59: =INDEX(БИПЦ_НДС!$D:$D,MATCH(Структура!A59,БИПЦ_НДС!$B:$B,0)) -> 20 | F59: Проды | G59: 1 | H59: 1 | I59: 0 | J59: 1 | K59: 1 | L59: =INDEX(MoM!B:B,MATCH(Структура!A59,MoM!K:K,0)) -> 1
... A102: Кофе в организациях быстрого обслуживания, 200 г | B102: =A102 -> Кофе в организациях быстрого обслуживания, 200 г | C102: =A102 -> Кофе в организациях быстрого обслуживания, 200 г | D102: =C102 -> Кофе в организациях быстрого обслуживания, 200 г | E102: =INDEX(БИПЦ_НДС!$D:$D,MATCH(Структура!A102,БИПЦ_НДС!$B:$B,0)) -> 20 | F102: Проды | G102: 1 | H102: 1 | I102: 1 | J102: 1 | K102: 1 | L102: =INDEX(MoM!B:B,MATCH(Структура!A102,MoM!K:K,0)) -> 0
A103: Продукция предприятий общественного питания быстрого обслуживания, шт. | B103: =A103 -> Продукция предприятий общественного питания быстрого обслуживания, шт. | C103: =A103 -> Продукция предприятий общественного питания быстрого обслуживания, шт. | D103: Продукция предприятий общественного питания быстрого обслуживания, шт. | E103: =INDEX(БИПЦ_НДС!$D:$D,MATCH(Структура!A103,БИПЦ_НДС!$B:$B,0)) -> 20 | F103: Проды | G103: 1 | H103: 1 | I103: 1 | J103: 1 | K103: 1 | L103: =INDEX(MoM!B:B,MATCH(Структура!A103,MoM!K:K,0)) -> 0
A104: Обед в столовой, кафе, закусочной (кроме столовой в организации), на 1 человека | B104: =A104 -> Обед в столовой, кафе, закусочной (кроме столовой в организации), на 1 человека | C104: =A104 -> Обед в столовой, кафе, закусочной (кроме столовой в организации), на 1 человека | D104: =C104 -> Обед в столовой, кафе, закусочной (кроме столовой в организации), на 1 человека | E104: =INDEX(БИПЦ_НДС!$D:$D,MATCH(Структура!A104,БИПЦ_НДС!$B:$B,0)) -> 20 | F104: Проды | G104: 1 | H104: 1 | I104: 1 | J104: 1 | K104: 1 | L104: =INDEX(MoM!B:B,MATCH(Структура!A104,MoM!K:K,0)) -> 0
A105: Обед в ресторане, на 1 человека | B105: =A105 -> Обед в ресторане, на 1 человека | C105: =A105 -> Обед в ресторане, на 1 человека | D105: =C105 -> Обед в ресторане, на 1 человека | E105: =INDEX(БИПЦ_НДС!$D:$D,MATCH(Структура!A105,БИПЦ_НДС!$B:$B,0)) -> 20 | F105: Проды | G105: 1 | H105: 1 | I105: 1 | J105: 1 | K105: 1 | L105: =INDEX(MoM!B:B,MATCH(Структура!A105,MoM!K:K,0)) -> 0
A106: Ужин в ресторане, на 1 человека | B106: =A106 -> Ужин в ресторане, на 1 человека | C106: =A106 -> Ужин в ресторане, на 1 человека | D106: =C106 -> Ужин в ресторане, на 1 человека | E106: =INDEX(БИПЦ_НДС!$D:$D,MATCH(Структура!A106,БИПЦ_НДС!$B:$B,0)) -> 20 | F106: Проды | G106: 1 | H106: 1 | I106: 1 | J106: 1 | K106: 1 | L106: =INDEX(MoM!B:B,MATCH(Структура!A106,MoM!K:K,0)) -> 0
A107: Ткани хлопчатобумажные бельевые, м | B107: =A107 -> Ткани хлопчатобумажные бельевые, м | C107: =A107 -> Ткани хлопчатобумажные бельевые, м | D107: =C107 -> Ткани хлопчатобумажные бельевые, м | E107: =INDEX(БИПЦ_НДС!$D:$D,MATCH(Структура!A107,БИПЦ_НДС!$B:$B,0)) -> 20 | F107: Непроды | G107: 1 | H107: 1 | I107: 0 | J107: 1 | K107: 1 | L107: =INDEX(MoM!B:B,MATCH(Структура!A107,MoM!K:K,0)) -> 1
A108: Ткань костюмная шерстяная и полушерстяная, м | B108: =A108 -> Ткань костюмная шерстяная и полушерстяная, м | C108: =A108 -> Ткань костюмная шерстяная и полушерстяная, м | D108: =C108 -> Ткань костюмная шерстяная и полушерстяная, м | E108: =INDEX(БИПЦ_НДС!$D:$D,MATCH(Структура!A108,БИПЦ_НДС!$B:$B,0)) -> 20 | F108: Непроды | G108: 1 | H108: 1 | I108: 0 | J108: 1 | K108: 1 | L108: =INDEX(MoM!B:B,MATCH(Структура!A108,MoM!K:K,0)) -> 1
A109: Ткань платьевая из искусственного или синтетического шелка, м | B109: =A109 -> Ткань платьевая из искусственного или синтетического шелка, м | C109: =A109 -> Ткань платьевая из искусственного или синтетического шелка, м | D109: =C109 -> Ткань платьевая из искусственного или синтетического шелка, м | E109: =INDEX(БИПЦ_НДС!$D:$D,MATCH(Структура!A109,БИПЦ_НДС!$B:$B,0)) -> 20 | F109: Непроды | G109: 1 | H109: 1 | I109: 0 | J109: 1 | K109: 1 | L109: =INDEX(MoM!B:B,MATCH(Структура!A109,MoM!K:K,0)) -> 1
A110: Ткани декоративные для изготовления штор и занавесей, м | B110: =A110 -> Ткани декоративные для изготовления штор и занавесей, м | C110: =A110 -> Ткани декоративные для изготовления штор и занавесей, м | D110: =C110 -> Ткани декоративные для изготовления штор и занавесей, м | E110: =INDEX(БИПЦ_НДС!$D:$D,MATCH(Структура!A110,БИПЦ_НДС!$B:$B,0)) -> 20 | F110: Непроды | G110: 1 | H110: 1 | I110: 0 | J110: 1 | K110: 1 | L110: =INDEX(MoM!B:B,MATCH(Структура!A110,MoM!K:K,0)) -> 1
A111: Полотенце личное, шт. | B111: =A111 -> Полотенце личное, шт. | C111: =A111 -> Полотенце личное, шт. | D111: =C111 -> Полотенце личное, шт. | E111: =INDEX(БИПЦ_НДС!$D:$D,MATCH(Структура!A111,БИПЦ_НДС!$B:$B,0)) -> 20 | F111: Непроды | G111: 1 | H111: 1 | I111: 0 | J111: 1 | K111: 1 | L111: =INDEX(MoM!B:B,MATCH(Структура!A111,MoM!K:K,0)) -> 1
A112: Полотенце кухонное, шт. | B112: =A112 -> Полотенце кухонное, шт. | C112: =A112 -> Полотенце кухонное, шт. | D112: =C112 -> Полотенце кухонное, шт. | E112: =INDEX(БИПЦ_НДС!$D:$D,MATCH(Структура!A112,БИПЦ_НДС!$B:$B,0)) -> 20 | F112: Непроды | G112: 1 | H112: 1 | I112: 0 | J112: 1 | K112: 1 | L112: =INDEX(MoM!B:B,MATCH(Структура!A112,MoM!K:K,0)) -> 1
A113: Куртка мужская с верхом из плащевых тканей утепленная, шт. | B113: =A113 -> Куртка мужская с верхом из плащевых тканей утепленная, шт. | C113: =A113 -> Куртка мужская с верхом из плащевых тканей утепленная, шт. | D113: =C113 -> Куртка мужская с верхом из плащевых тканей утепленная, шт. | E113: =INDEX(БИПЦ_НДС!$D:$D,MATCH(Структура!A113,БИПЦ_НДС!$B:$B,0)) -> 20 | F113: Непроды | G113: 1 | H113: 1 | I113: 0 | J113: 1 | K113: 1 | L113: =INDEX(MoM!B:B,MATCH(Структура!A113,MoM!K:K,0)) -> 1
A114: Куртка мужская без утеплителя (ветровка), шт. | B114: =A114 -> Куртка мужская без утеплителя (ветровка), шт. | C114: =A114 -> Куртка мужская без утеплителя (ветровка), шт. | D114: =C114 -> Куртка мужская без утеплителя (ветровка), шт. | E114: =INDEX(БИПЦ_НДС!$D:$D,MATCH(Структура!A114,БИПЦ_НДС!$B:$B,0)) -> 20 | F114: Непроды | G114: 1 | H114: 1 | I114: 0 | J114: 1 | K114: 1 | L114: =INDEX(MoM!B:B,MATCH(Структура!A114,MoM!K:K,0)) -> 1
A115: Куртка мужская из натуральной кожи, шт. | B115: =A115 -> Куртка мужская из натуральной кожи, шт. | C115: =A115 -> Куртка мужская из натуральной кожи, шт. | D115: =C115 -> Куртка мужская из натуральной кожи, шт. | E115: =INDEX(БИПЦ_НДС!$D:$D,MATCH(Структура!A115,БИПЦ_НДС!$B:$B,0)) -> 20 | F115: Непроды | G115: 1 | H115: 1 | I115: 0 | J115: 1 | K115: 1 | L115: =INDEX(MoM!B:B,MATCH(Структура!A115,MoM!K:K,0)) -> 1
A116: Костюм-двойка мужской, шт. | B116: =A116 -> Костюм-двойка мужской, шт. | C116: Костюм-двойка мужской из шерстяных, полушерстяных или смесовых тканей, шт. | D116: Костюм-двойка мужской, шт. | E116: =INDEX(БИПЦ_НДС!$D:$D,MATCH(Структура!A116,БИПЦ_НДС!$B:$B,0)) -> 20 | F116: Непроды | G116: 1 | H116: 1 | I116: 0 | J116: 1 | K116: 1 | L116: =INDEX(MoM!B:B,MATCH(Структура!A116,MoM!K:K,0)) -> 1
A117: Брюки мужские из полушерстяных или смесовых тканей, шт. | B117: =A117 -> Брюки мужские из полушерстяных или смесовых тканей, шт. | C117: =A117 -> Брюки мужские из полушерстяных или смесовых тканей, шт. | D117: =C117 -> Брюки мужские из полушерстяных или смесовых тканей, шт. | E117: =INDEX(БИПЦ_НДС!$D:$D,MATCH(Структура!A117,БИПЦ_НДС!$B:$B,0)) -> 20 | F117: Непроды | G117: 1 | H117: 1 | I117: 0 | J117: 1 | K117: 1 | L117: =INDEX(MoM!B:B,MATCH(Структура!A117,MoM!K:K,0)) -> 1
A118: Брюки мужские из джинсовой ткани (джинсы), шт. | B118: =A118 -> Брюки мужские из джинсовой ткани (джинсы), шт. | C118: =A118 -> Брюки мужские из джинсовой ткани (джинсы), шт. | D118: =C118 -> Брюки мужские из джинсовой ткани (джинсы), шт. | E118: =INDEX(БИПЦ_НДС!$D:$D,MATCH(Структура!A118,БИПЦ_НДС!$B:$B,0)) -> 20 | F118: Непроды | G118: 1 | H118: 1 | I118: 0 | J118: 1 | K118: 1 | L118: =INDEX(MoM!B:B,MATCH(Структура!A118,MoM!K:K,0)) -> 1
A119: Рубашка верхняя мужская, шт. | B119: =A119 -> Рубашка верхняя мужская, шт. | C119: Рубашка верхняя мужская из хлопчатобумажных или смесовых тканей, шт. | D119: Рубашка верхняя мужская, шт. | E119: =INDEX(БИПЦ_НДС!$D:$D,MATCH(Структура!A119,БИПЦ_НДС!$B:$B,0)) -> 20 | F119: Непроды | G119: 1 | H119: 1 | I119: 0 | J119: 1 | K119: 1 | L119: =INDEX(MoM!B:B,MATCH(Структура!A119,MoM!K:K,0)) -> 1
A120: Пальто женское демисезонное, шт. | B120: =A120 -> Пальто женское демисезонное, шт. | C120: Пальто женское зимнее из шерстяных или полушерстяных тканей, шт. | D120: Пальто женское меховое и дубленка, шт. | E120: =INDEX(БИПЦ_НДС!$D:$D,MATCH(Структура!A120,БИПЦ_НДС!$B:$B,0)) -> 20 | F120: Непроды | G120: 1 | H120: 1 | I120: 0 | J120: 1 | K120: 1 | L120: =INDEX(MoM!B:B,MATCH(Структура!A120,MoM!K:K,0)) -> 1
A121: Пальто (полупальто) женское с верхом из плащевых тканей, шт. | B121: =A121 -> Пальто (полупальто) женское с верхом из плащевых тканей, шт. | C121: =A121 -> Пальто (полупальто) женское с верхом из плащевых тканей, шт. | D121: =C121 -> Пальто (полупальто) женское с верхом из плащевых тканей, шт. | E121: =INDEX(БИПЦ_НДС!$D:$D,MATCH(Структура!A121,БИПЦ_НДС!$B:$B,0)) -> 20 | F121: Непроды | G121: 1 | H121: 1 | I121: 0 | J121: 1 | K121: 1 | L121: =INDEX(MoM!B:B,MATCH(Структура!A121,MoM!K:K,0)) -> 1
A122: Куртка женская без утеплителя (ветровка), шт. | B122: =A122 -> Куртка женская без утеплителя (ветровка), шт. | C122: =A122 -> Куртка женская без утеплителя (ветровка), шт. | D122: =C122 -> Куртка женская без утеплителя (ветровка), шт. | E122: =INDEX(БИПЦ_НДС!$D:$D,MATCH(Структура!A122,БИПЦ_НДС!$B:$B,0)) -> 20 | F122: Непроды | G122: 1 | H122: 1 | I122: 0 | J122: 1 | K122: 1 | L122: =INDEX(MoM!B:B,MATCH(Структура!A122,MoM!K:K,0)) -> 1
A123: Платье (платье-костюм) женское из полушерстяных или смесовых тканей, шт. | B123: =A123 -> Платье (платье-костюм) женское из полушерстяных или смесовых тканей, шт. | C123: =A123 -> Платье (платье-костюм) женское из полушерстяных или смесовых тканей, шт. | D123: =C123 -> Платье (платье-костюм) женское из полушерстяных или смесовых тканей, шт. | E123: =INDEX(БИПЦ_НДС!$D:$D,MATCH(Структура!A123,БИПЦ_НДС!$B:$B,0)) -> 20 | F123: Непроды | G123: 1 | H123: 1 | I123: 0 | J123: 1 | K123: 1 | L123: =INDEX(MoM!B:B,MATCH(Структура!A123,MoM!K:K,0)) -> 1
A124: Платье (платье-костюм) женское из хлопчатобумажных или смесовых тканей, шт. | B124: =A124 -> Платье (платье-костюм) женское из хлопчатобумажных или смесовых тканей, шт. | C124: =A124 -> Платье (платье-костюм) женское из хлопчатобумажных или смесовых тканей, шт. | D124: =C124 -> Платье (платье-костюм) женское из хлопчатобумажных или смесовых тканей, шт. | E124: =INDEX(БИПЦ_НДС!$D:$D,MATCH(Структура!A124,БИПЦ_НДС!$B:$B,0)) -> 20 | F124: Непроды | G124: 1 | H124: 1 | I124: 0 | J124: 1 | K124: 1 | L124: =INDEX(MoM!B:B,MATCH(Структура!A124,MoM!K:K,0)) -> 1
A125: Пиджак, жакет женский, шт. | B125: =A125 -> Пиджак, жакет женский, шт. | C125: Пиджак, жакет женский из шерстяных, полушерстяных или смесовых тканей, шт. | D125: Пиджак, жакет женский, шт. | E125: =INDEX(БИПЦ_НДС!$D:$D,MATCH(Структура!A125,БИПЦ_НДС!$B:$B,0)) -> 20 | F125: Непроды | G125: 1 | H125: 1 | I125: 0 | J125: 1 | K125: 1 | L125: =INDEX(MoM!B:B,MATCH(Структура!A125,MoM!K:K,0)) -> 1
A126: Брюки женские из полушерстяных или смесовых тканей, шт. | B126: =A126 -> Брюки женские из полушерстяных или смесовых тканей, шт. | C126: =A126 -> Брюки женские из полушерстяных или смесовых тканей, шт. | D126: =C126 -> Брюки женские из полушерстяных или смесовых тканей, шт. | E126: =INDEX(БИПЦ_НДС!$D:$D,MATCH(Структура!A126,БИПЦ_НДС!$B:$B,0)) -> 20 | F126: Непроды | G126: 1 | H126: 1 | I126: 0 | J126: 1 | K126: 1 | L126: =INDEX(MoM!B:B,MATCH(Структура!A126,MoM!K:K,0)) -> 1
A127: Брюки женские из джинсовой ткани (джинсы), шт. | B127: =A127 -> Брюки женские из джинсовой ткани (джинсы), шт. | C127: Брюки женские из джинсовой ткани (джинсы), шт. | D127: =C127 -> Брюки женские из джинсовой ткани (джинсы), шт. | E127: =INDEX(БИПЦ_НДС!$D:$D,MATCH(Структура!A127,БИПЦ_НДС!$B:$B,0)) -> 20 | F127: Непроды | G127: 1 | H127: 1 | I127: 0 | J127: 1 | K127: 1 | L127: =INDEX(MoM!B:B,MATCH(Структура!A127,MoM!K:K,0)) -> 1
A128: Юбка женская, шт. | B128: =A128 -> Юбка женская, шт. | C128: Юбка женская из полушерстяных или смесовых тканей, шт. | D128: =A128 -> Юбка женская, шт. | E128: =INDEX(БИПЦ_НДС!$D:$D,MATCH(Структура!A128,БИПЦ_НДС!$B:$B,0)) -> 20 | F128: Непроды | G128: 1 | H128: 1 | I128: 0 | J128: 1 | K128: 1 | L128: =INDEX(MoM!B:B,MATCH(Структура!A128,MoM!K:K,0)) -> 1
A129: Блузка женская, шт. | B129: =A129 -> Блузка женская, шт. | C129: =A129 -> Блузка женская, шт. | D129: =C129 -> Блузка женская, шт. | E129: =INDEX(БИПЦ_НДС!$D:$D,MATCH(Структура!A129,БИПЦ_НДС!$B:$B,0)) -> 20 | F129: Непроды | G129: 1 | H129: 1 | I129: 0 | J129: 1 | K129: 1 | L129: =INDEX(MoM!B:B,MATCH(Структура!A129,MoM!K:K,0)) -> 1
A130: Халат женский, шт. | B130: =A130 -> Халат женский, шт. | C130: =A130 -> Халат женский, шт. | D130: =C130 -> Халат женский, шт. | E130: =INDEX(БИПЦ_НДС!$D:$D,MATCH(Структура!A130,БИПЦ_НДС!$B:$B,0)) -> 20 | F130: Непроды | G130: 1 | H130: 1 | I130: 0 | J130: 1 | K130: 1 | L130: =INDEX(MoM!B:B,MATCH(Структура!A130,MoM!K:K,0)) -> 1
A131: Сорочка ночная женская, шт. | B131: =A131 -> Сорочка ночная женская, шт. | C131: =A131 -> Сорочка ночная женская, шт. | D131: =C131 -> Сорочка ночная женская, шт. | E131: =INDEX(БИПЦ_НДС!$D:$D,MATCH(Структура!A131,БИПЦ_НДС!$B:$B,0)) -> 20 | F131: Непроды | G131: 1 | H131: 1 | I131: 0 | J131: 1 | K131: 1 | L131: =INDEX(MoM!B:B,MATCH(Структура!A131,MoM!K:K,0)) -> 1
A132: Куртка для детей школьного возраста с верхом из плащевых тканей утепленная, шт. | B132: =A132 -> Куртка для детей школьного возраста с верхом из плащевых тканей утепленная, шт. | C132: =A132 -> Куртка для детей школьного возраста с верхом из плащевых тканей утепленная, шт. | D132: =C132 -> Куртка для детей школьного возраста с верхом из плащевых тканей утепленная, шт. | E132: =INDEX(БИПЦ_НДС!$D:$D,MATCH(Структура!A132,БИПЦ_НДС!$B:$B,0)) -> 10 | F132: Непроды | G132: 1 | H132: 1 | I132: 0 | J132: 1 | K132: 1 | L132: =INDEX(MoM!B:B,MATCH(Структура!A132,MoM!K:K,0)) -> 1
A133: Брюки для детей школьного возраста из полушерстяных или смесовых тканей, шт. | B133: =A133 -> Брюки для детей школьного возраста из полушерстяных или смесовых тканей, шт. | C133: Брюки для детей школьного возраста из полушерстяных тканей, шт. | D133: =A133 -> Брюки для детей школьного возраста из полушерстяных или смесовых тканей, шт. | E133: =INDEX(БИПЦ_НДС!$D:$D,MATCH(Структура!A133,БИПЦ_НДС!$B:$B,0)) -> 10 | F133: Непроды | G133: 1 | H133: 1 | I133: 0 | J133: 1 | K133: 1 | L133: =INDEX(MoM!B:B,MATCH(Структура!A133,MoM!K:K,0)) -> 1
A134: Брюки для детей школьного возраста из джинсовой ткани, шт. | B134: =A134 -> Брюки для детей школьного возраста из джинсовой ткани, шт. | C134: =A134 -> Брюки для детей школьного возраста из джинсовой ткани, шт. | D134: =C134 -> Брюки для детей школьного возраста из джинсовой ткани, шт. | E134: =INDEX(БИПЦ_НДС!$D:$D,MATCH(Структура!A134,БИПЦ_НДС!$B:$B,0)) -> 10 | F134: Непроды | G134: 1 | H134: 1 | I134: 0 | J134: 1 | K134: 1 | L134: =INDEX(MoM!B:B,MATCH(Структура!A134,MoM!K:K,0)) -> 1
A135: Рубашка верхняя для мальчиков школьного возраста, шт. | B135: =A135 -> Рубашка верхняя для мальчиков школьного возраста, шт. | C135: =A135 -> Рубашка верхняя для мальчиков школьного возраста, шт. | D135: =C135 -> Рубашка верхняя для мальчиков школьного возраста, шт. | E135: =INDEX(БИПЦ_НДС!$D:$D,MATCH(Структура!A135,БИПЦ_НДС!$B:$B,0)) -> 10 | F135: Непроды | G135: 1 | H135: 1 | I135: 0 | J135: 1 | K135: 1 | L135: =INDEX(MoM!B:B,MATCH(Структура!A135,MoM!K:K,0)) -> 1
A136: Платье (платье-костюм, сарафан) для девочек школьного возраста, шт. | B136: =A136 -> Платье (платье-костюм, сарафан) для девочек школьного возраста, шт. | C136: Платье (платье-костюм, сарафан) для девочек школьного возраста из полушерстяных, смесовых тканей, шт. | D136: Платье (платье-костюм) женское из хлопчатобумажных или смесовых тканей, шт. | E136: =INDEX(БИПЦ_НДС!$D:$D,MATCH(Структура!A136,БИПЦ_НДС!$B:$B,0)) -> 10 | F136: Непроды | G136: 1 | H136: 1 | I136: 0 | J136: 1 | K136: 1 | L136: =INDEX(MoM!B:B,MATCH(Структура!A136,MoM!K:K,0)) -> 1
A137: Блузка для девочек школьного возраста, шт. | B137: =A137 -> Блузка для девочек школьного возраста, шт. | C137: =A137 -> Блузка для девочек школьного возраста, шт. | D137: =C137 -> Блузка для девочек школьного возраста, шт. | E137: =INDEX(БИПЦ_НДС!$D:$D,MATCH(Структура!A137,БИПЦ_НДС!$B:$B,0)) -> 10 | F137: Непроды | G137: 1 | H137: 1 | I137: 0 | J137: 1 | K137: 1 | L137: =INDEX(MoM!B:B,MATCH(Структура!A137,MoM!K:K,0)) -> 1
A138: Юбка для девочек школьного возраста, шт. | B138: =A138 -> Юбка для девочек школьного возраста, шт. | C138: Юбка для девочек школьного возраста из полушерстяных тканей, шт. | D138: Юбка для девочек школьного возраста, шт. | E138: =INDEX(БИПЦ_НДС!$D:$D,MATCH(Структура!A138,БИПЦ_НДС!$B:$B,0)) -> 10 | F138: Непроды | G138: 1 | H138: 1 | I138: 0 | J138: 1 | K138: 1 | L138: =INDEX(MoM!B:B,MATCH(Структура!A138,MoM!K:K,0)) -> 1
A139: Куртка для детей дошкольного возраста с верхом из плащевых тканей утепленная, шт. | B139: =A139 -> Куртка для детей дошкольного возраста с верхом из плащевых тканей утепленная, шт. | C139: =A139 -> Куртка для детей дошкольного возраста с верхом из плащевых тканей утепленная, шт. | D139: =C139 -> Куртка для детей дошкольного возраста с верхом из плащевых тканей утепленная, шт. | E139: =INDEX(БИПЦ_НДС!$D:$D,MATCH(Структура!A139,БИПЦ_НДС!$B:$B,0)) -> 10 | F139: Непроды | G139: 1 | H139: 1 | I139: 0 | J139: 1 | K139: 1 | L139: =INDEX(MoM!B:B,MATCH(Структура!A139,MoM!K:K,0)) -> 1
A140: Комбинезон (костюм) утепленный для детей дошкольного возраста, шт. | B140: =A140 -> Комбинезон (костюм) утепленный для детей дошкольного возраста, шт. | C140: =A140 -> Комбинезон (костюм) утепленный для детей дошкольного возраста, шт. | D140: =C140 -> Комбинезон (костюм) утепленный для детей дошкольного возраста, шт. | E140: =INDEX(БИПЦ_НДС!$D:$D,MATCH(Структура!A140,БИПЦ_НДС!$B:$B,0)) -> 10 | F140: Непроды | G140: 1 | H140: 1 | I140: 0 | J140: 1 | K140: 1 | L140: =INDEX(MoM!B:B,MATCH(Структура!A140,MoM!K:K,0)) -> 1
A141: Рубашка верхняя для мальчиков дошкольного возраста, шт. | B141: =A141 -> Рубашка верхняя для мальчиков дошкольного возраста, шт. | C141: =A141 -> Рубашка верхняя для мальчиков дошкольного возраста, шт. | D141: =C141 -> Рубашка верхняя для мальчиков дошкольного возраста, шт. | E141: =INDEX(БИПЦ_НДС!$D:$D,MATCH(Структура!A141,БИПЦ_НДС!$B:$B,0)) -> 10 | F141: Непроды | G141: 1 | H141: 1 | I141: 0 | J141: 1 | K141: 1 | L141: =INDEX(MoM!B:B,MATCH(Структура!A141,MoM!K:K,0)) -> 1
A142: Платье (сарафан) летнее для девочек дошкольного возраста, шт. | B142: =A142 -> Платье (сарафан) летнее для девочек дошкольного возраста, шт. | C142: =A142 -> Платье (сарафан) летнее для девочек дошкольного возраста, шт. | D142: =C142 -> Платье (сарафан) летнее для девочек дошкольного возраста, шт. | E142: =INDEX(БИПЦ_НДС!$D:$D,MATCH(Структура!A142,БИПЦ_НДС!$B:$B,0)) -> 10 | F142: Непроды | G142: 1 | H142: 1 | I142: 0 | J142: 1 | K142: 1 | L142: =INDEX(MoM!B:B,MATCH(Структура!A142,MoM!K:K,0)) -> 1
A143: Комбинезон утепленный для детей до одного года, шт. | B143: =A143 -> Комбинезон утепленный для детей до одного года, шт. | C143: =A143 -> Комбинезон утепленный для детей до одного года, шт. | D143: =C143 -> Комбинезон утепленный для детей до одного года, шт. | E143: =INDEX(БИПЦ_НДС!$D:$D,MATCH(Структура!A143,БИПЦ_НДС!$B:$B,0)) -> 10 | F143: Непроды | G143: 1 | H143: 1 | I143: 0 | J143: 1 | K143: 1 | L143: =INDEX(MoM!B:B,MATCH(Структура!A143,MoM!K:K,0)) -> 1
A144: Пеленки для новорожденных, шт. | B144: =A144 -> Пеленки для новорожденных, шт. | C144: =A144 -> Пеленки для новорожденных, шт. | D144: =C144 -> Пеленки для новорожденных, шт. | E144: =INDEX(БИПЦ_НДС!$D:$D,MATCH(Структура!A144,БИПЦ_НДС!$B:$B,0)) -> 10 | F144: Непроды | G144: 1 | H144: 1 | I144: 0 | J144: 1 | K144: 1 | L144: =INDEX(MoM!B:B,MATCH(Структура!A144,MoM!K:K,0)) -> 1
A145: Ползунки из хлопчатобумажного трикотажного полотна, шт. | B145: =A145 -> Ползунки из хлопчатобумажного трикотажного полотна, шт. | C145: =A145 -> Ползунки из хлопчатобумажного трикотажного полотна, шт. | D145: =C145 -> Ползунки из хлопчатобумажного трикотажного полотна, шт. | E145: =INDEX(БИПЦ_НДС!$D:$D,MATCH(Структура!A145,БИПЦ_НДС!$B:$B,0)) -> 10 | F145: Непроды | G145: 1 | H145: 1 | I145: 0 | J145: 1 | K145: 1 | L145: =INDEX(MoM!B:B,MATCH(Структура!A145,MoM!K:K,0)) -> 1
A146: Белье для новорожденных и детей ясельного возраста, шт. | B146: =A146 -> Белье для новорожденных и детей ясельного возраста, шт. | C146: =A146 -> Белье для новорожденных и детей ясельного возраста, шт. | D146: =C146 -> Белье для новорожденных и детей ясельного возраста, шт. | E146: =INDEX(БИПЦ_НДС!$D:$D,MATCH(Структура!A146,БИПЦ_НДС!$B:$B,0)) -> 10 | F146: Непроды | G146: 1 | H146: 1 | I146: 0 | J146: 1 | K146: 1 | L146: =INDEX(MoM!B:B,MATCH(Структура!A146,MoM!K:K,0)) -> 1
...

Sheet Сводная
E2: Эффекты | L2: Вклад в ИПЦ | T2: СУММ эффект
B3: Вес янв25 | C3: Вес янв26 | D3: Доля по базовой | E3: 45931 | F3: 45962 | G3: 45992 | H3: 46023 | I3: 46054 | J3: 46082 | K3: 46113 | L3: 45931 | M3: 45962 | N3: 45992 | O3: 46023 | P3: 46054 | Q3: 46082 | R3: 46113 | S3: Накоп
A4: БИПЦ | B4: 71.169 | C4: 71.421 | D4: 0.57474692 | E4: 0.011510219 | F4: -0.011573879 | G4: 0.021567031 | H4: 0.20742507 | I4: 0.05447193 | J4: 0 | K4: 0 | L4: =E4*$C4*$D4/100 -> 0.00472483 | M4: =F4*$C4*$D4/100 -> -0.0047509617 | N4: =G4*$C4*$D4/100 -> 0.0088530505 | O4: =H4*$C4*$D4/100 -> 0.085145916 | P4: =I4*$C4*$D4/100 -> 0.022360182 | Q4: 0 | R4: 0 | S4: =SUM(L4:R4) -> 0.11633302 | T4: =SUM(E4:K4) -> 0.28340037
A5: Нефтепродукты | B5: 4.643 | C5: 4.801 | D5: 1 | H5: 0.6 | O5: =H5*$C5*$D5/100 -> 0.028806 | S5: =SUM(L5:R5) -> 0.028806 | T5: =SUM(E5:K5) -> 0.6
A6: ЖУ+КУ | B6: 8.006 | C6: 8.042 | D6: 1 | H6: 1.7 | O6: =H6*$C6*$D6/100 -> 0.136714 | S6: =SUM(L6:R6) -> 0.136714 | T6: =SUM(E6:K6) -> 1.7
A7: Прочее | B7: 16.032 | C7: 15.736 | D7: 0.34710219 | E7: =E4 -> 0.011510219 | F7: =F4 -> -0.011573879 | G7: =G4 -> 0.021567031 | H7: =H4 -> 0.20742507 | I7: =I4 -> 0.05447193 | J7: =J4 -> 0 | K7: =K4 -> 0 | L7: =E7*$C7*$D7/100 -> 0.00062868818 | M7: =F7*$C7*$D7/100 -> -0.00063216528 | N7: =G7*$C7*$D7/100 -> 0.0011779912 | O7: =H7*$C7*$D7/100 -> 0.011329557 | P7: =I7*$C7*$D7/100 -> 0.0029752568 | Q7: =J7*$C7*$D7/100 -> 0 | R7: =K7*$C7*$D7/100 -> 0 | S7: =SUM(L7:R7) -> 0.015479328 | T7: =SUM(E7:K7) -> 0.28340037
A8: СУММ | B8: =SUM(B4:B7) -> 99.85 | C8: =SUM(C4:C7) -> 100 | L8: =SUM(L4:L7) -> 0.0053535181 | M8: =SUM(M4:M7) -> -0.005383127 | N8: =SUM(N4:N7) -> 0.010031042 | O8: =SUM(O4:O7) -> 0.26199547 | P8: =SUM(P4:P7) -> 0.025335439 | Q8: =SUM(Q4:Q7) -> 0 | R8: =SUM(R4:R7) -> 0 | S8: =SUM(L8:R8) -> 0.29733235
A10: Вес по базовой в БИПЦ
A11: Вклад в БИПЦ
A12: Вклад в ИПЦ из БИПЦ
A15: Вес наблюдаемых компонент скорректированной БИПЦ | B15: =SUMIFS(Веса!AR2:AR433,MoM!$B$2:$B$433,1) -> 53.298
A16: Число объектов в донорской группе | B16: =COUNTIFS(ToSep17!$B$2:$B$433,1,ToSep17!$D$2:$D$433,1) -> 127
A17: Число объектов в группе воздействия | B17: =COUNTIFS(ToSep17!$B$2:$B$433,1,ToSep17!$C$2:$C$433,1) -> 188
B18: =SUM(B16:B17) -> 315

Sheet MoM
A1: Доступен весь период | B1: Учитывать | C1: Базовая ставка | D1: Льготная ставка | E1: Проды | F1: Непроды | G1: Непроды без одежды | H1: Одежда | I1: Услуги | J1: Название Классификатор 2015 | K1: Название Классификатор 2026 | L1: Название витрина данных Росстата | M1: 42005 | N1: 42036 | O1: 42064 | P1: 42095 | Q1: 42125 | R1: 42156 | S1: 42186 | T1: 42217 | U1: 42248 | V1: 42278 | W1: 42309 | X1: 42339 | Y1: 42370 | Z1: 42401 | AA1: 42430 | AB1: 42461 | AC1: 42491 | AD1: 42522 | AE1: 42552 | AF1: 42583 | AG1: 42614 | AH1: 42644 | AI1: 42675 | AJ1: 42705 | AK1: 42736 | AL1: 42767 | AM1: 42795 | AN1: 42826 | AO1: 42856 | AP1: 42887 | AQ1: 42917 | AR1: 42948 | AS1: 42979 | AT1: 43009 | AU1: 43040 | AV1: 43070 | AW1: 43101 | AX1: 43132 | AY1: 43160 | AZ1: 43191 | BA1: 43221 | BB1: 43252 | BC1: 43282 | BD1: 43313 | BE1: 43344 | BF1: 43374 | BG1: 43405 | BH1: 43435 | BI1: 43466 | BJ1: 43497 | BK1: 43525 | BL1: 43556 | BM1: 43586 | BN1: 43617 | BO1: 43647 | BP1: 43678 | BQ1: 43709 | BR1: 43739 | BS1: 43770 | BT1: 43800
A2: =Веса!A2 -> 1 | B2: =A2 -> 1 | C2: =БИПЦ_НДС!E2 -> 0 | D2: =1-C2 -> 1 | E2: 1 | F2: 0 | G2: 0 | H2: 0 | I2: 0 | J2: Говядина (кроме бескостного мяса), кг | K2: Говядина (кроме бескостного мяса), кг | L2: Говядина (кроме бескостного мяса), кг | M2: =INDEX('ИПЦ raw2015'!$1:$1048576, MATCH($J2,'ИПЦ raw2015'!$A:$A,0),MATCH(MoM!M$1,'ИПЦ raw2015'!$1:$1,0)) -> 105.82 | N2: =INDEX('ИПЦ raw2015'!$1:$1048576, MATCH($J2,'ИПЦ raw2015'!$A:$A,0),MATCH(MoM!N$1,'ИПЦ raw2015'!$1:$1,0)) -> 103.44 | O2: =INDEX('ИПЦ raw2015'!$1:$1048576, MATCH($J2,'ИПЦ raw2015'!$A:$A,0),MATCH(MoM!O$1,'ИПЦ raw2015'!$1:$1,0)) -> 101.87 | P2: =INDEX('ИПЦ raw2015'!$1:$1048576, MATCH($J2,'ИПЦ raw2015'!$A:$A,0),MATCH(MoM!P$1,'ИПЦ raw2015'!$1:$1,0)) -> 100.51 | Q2: =INDEX('ИПЦ raw2015'!$1:$1048576, MATCH($J2,'ИПЦ raw2015'!$A:$A,0),MATCH(MoM!Q$1,'ИПЦ raw2015'!$1:$1,0)) -> 100.51 | R2: =INDEX('ИПЦ raw2015'!$1:$1048576, MATCH($J2,'ИПЦ raw2015'!$A:$A,0),MATCH(MoM!R$1,'ИПЦ raw2015'!$1:$1,0)) -> 100.04 | S2: =INDEX('ИПЦ raw2015'!$1:$1048576, MATCH($J2,'ИПЦ raw2015'!$A:$A,0),MATCH(MoM!S$1,'ИПЦ raw2015'!$1:$1,0)) -> 100.2 | T2: =INDEX('ИПЦ raw2015'!$1:$1048576, MATCH($J2,'ИПЦ raw2015'!$A:$A,0),MATCH(MoM!T$1,'ИПЦ raw2015'!$1:$1,0)) -> 100.75 | ... BT2: =INDEX('ИПЦ raw2015'!$1:$1048576, MATCH($J2,'ИПЦ raw2015'!$A:$A,0),MATCH(MoM!BT$1,'ИПЦ raw2015'!$1:$1,0)) -> 100.68
A3: =Веса!A3 -> 1 | B3: =A3 -> 1 | C3: =БИПЦ_НДС!E3 -> 0 | D3: =1-C3 -> 1 | E3: 1 | F3: 0 | G3: 0 | H3: 0 | I3: 0 | J3: =L3 -> Говядина бескостная, кг | K3: Говядина бескостная, кг | L3: Говядина бескостная, кг | M3: =INDEX('ИПЦ raw2015'!$1:$1048576, MATCH($J3,'ИПЦ raw2015'!$A:$A,0),MATCH(MoM!M$1,'ИПЦ raw2015'!$1:$1,0)) -> 105.56 | N3: =INDEX('ИПЦ raw2015'!$1:$1048576, MATCH($J3,'ИПЦ raw2015'!$A:$A,0),MATCH(MoM!N$1,'ИПЦ raw2015'!$1:$1,0)) -> 102.81 | O3: =INDEX('ИПЦ raw2015'!$1:$1048576, MATCH($J3,'ИПЦ raw2015'!$A:$A,0),MATCH(MoM!O$1,'ИПЦ raw2015'!$1:$1,0)) -> 101.85 | P3: =INDEX('ИПЦ raw2015'!$1:$1048576, MATCH($J3,'ИПЦ raw2015'!$A:$A,0),MATCH(MoM!P$1,'ИПЦ raw2015'!$1:$1,0)) -> 101.12 | Q3: =INDEX('ИПЦ raw2015'!$1:$1048576, MATCH($J3,'ИПЦ raw2015'!$A:$A,0),MATCH(MoM!Q$1,'ИПЦ raw2015'!$1:$1,0)) -> 100.44 | R3: =INDEX('ИПЦ raw2015'!$1:$1048576, MATCH($J3,'ИПЦ raw2015'!$A:$A,0),MATCH(MoM!R$1,'ИПЦ raw2015'!$1:$1,0)) -> 100.25 | S3: =INDEX('ИПЦ raw2015'!$1:$1048576, MATCH($J3,'ИПЦ raw2015'!$A:$A,0),MATCH(MoM!S$1,'ИПЦ raw2015'!$1:$1,0)) -> 100.32 | T3: =INDEX('ИПЦ raw2015'!$1:$1048576, MATCH($J3,'ИПЦ raw2015'!$A:$A,0),MATCH(MoM!T$1,'ИПЦ raw2015'!$1:$1,0)) -> 100.41 | ... BT3: =INDEX('ИПЦ raw2015'!$1:$1048576, MATCH($J3,'ИПЦ raw2015'!$A:$A,0),MATCH(MoM!BT$1,'ИПЦ raw2015'!$1:$1,0)) -> 100.4
A4: =Веса!A4 -> 1 | B4: =A4 -> 1 | C4: =БИПЦ_НДС!E4 -> 0 | D4: =1-C4 -> 1 | E4: 1 | F4: 0 | G4: 0 | H4: 0 | I4: 0 | J4: =L4 -> Свинина (кроме бескостного мяса), кг | K4: Свинина (кроме бескостного мяса), кг | L4: Свинина (кроме бескостного мяса), кг | M4: =INDEX('ИПЦ raw2015'!$1:$1048576, MATCH($J4,'ИПЦ raw2015'!$A:$A,0),MATCH(MoM!M$1,'ИПЦ raw2015'!$1:$1,0)) -> 101.52 | N4: =INDEX('ИПЦ raw2015'!$1:$1048576, MATCH($J4,'ИПЦ raw2015'!$A:$A,0),MATCH(MoM!N$1,'ИПЦ raw2015'!$1:$1,0)) -> 99.24 | O4: =INDEX('ИПЦ raw2015'!$1:$1048576, MATCH($J4,'ИПЦ raw2015'!$A:$A,0),MATCH(MoM!O$1,'ИПЦ raw2015'!$1:$1,0)) -> 99.53 | P4: =INDEX('ИПЦ raw2015'!$1:$1048576, MATCH($J4,'ИПЦ raw2015'!$A:$A,0),MATCH(MoM!P$1,'ИПЦ raw2015'!$1:$1,0)) -> 100.94 | Q4: =INDEX('ИПЦ raw2015'!$1:$1048576, MATCH($J4,'ИПЦ raw2015'!$A:$A,0),MATCH(MoM!Q$1,'ИПЦ raw2015'!$1:$1,0)) -> 100.35 | R4: =INDEX('ИПЦ raw2015'!$1:$1048576, MATCH($J4,'ИПЦ raw2015'!$A:$A,0),MATCH(MoM!R$1,'ИПЦ raw2015'!$1:$1,0)) -> 99.83 | S4: =INDEX('ИПЦ raw2015'!$1:$1048576, MATCH($J4,'ИПЦ raw2015'!$A:$A,0),MATCH(MoM!S$1,'ИПЦ raw2015'!$1:$1,0)) -> 100.4 | T4: =INDEX('ИПЦ raw2015'!$1:$1048576, MATCH($J4,'ИПЦ raw2015'!$A:$A,0),MATCH(MoM!T$1,'ИПЦ raw2015'!$1:$1,0)) -> 100.11 | ... BT4: =INDEX('ИПЦ raw2015'!$1:$1048576, MATCH($J4,'ИПЦ raw2015'!$A:$A,0),MATCH(MoM!BT$1,'ИПЦ raw2015'!$1:$1,0)) -> 98.89
A5: =Веса!A5 -> 1 | B5: =A5 -> 1 | C5: =БИПЦ_НДС!E5 -> 0 | D5: =1-C5 -> 1 | E5: 1 | F5: 0 | G5: 0 | H5: 0 | I5: 0 | J5: =L5 -> Свинина бескостная, кг | K5: Свинина бескостная, кг | L5: Свинина бескостная, кг | M5: =INDEX('ИПЦ raw2015'!$1:$1048576, MATCH($J5,'ИПЦ raw2015'!$A:$A,0),MATCH(MoM!M$1,'ИПЦ raw2015'!$1:$1,0)) -> 101.94 | N5: =INDEX('ИПЦ raw2015'!$1:$1048576, MATCH($J5,'ИПЦ raw2015'!$A:$A,0),MATCH(MoM!N$1,'ИПЦ raw2015'!$1:$1,0)) -> 99.67 | O5: =INDEX('ИПЦ raw2015'!$1:$1048576, MATCH($J5,'ИПЦ raw2015'!$A:$A,0),MATCH(MoM!O$1,'ИПЦ raw2015'!$1:$1,0)) -> 99.92 | P5: =INDEX('ИПЦ raw2015'!$1:$1048576, MATCH($J5,'ИПЦ raw2015'!$A:$A,0),MATCH(MoM!P$1,'ИПЦ raw2015'!$1:$1,0)) -> 100.42 | Q5: =INDEX('ИПЦ raw2015'!$1:$1048576, MATCH($J5,'ИПЦ raw2015'!$A:$A,0),MATCH(MoM!Q$1,'ИПЦ raw2015'!$1:$1,0)) -> 100.47 | R5: =INDEX('ИПЦ raw2015'!$1:$1048576, MATCH($J5,'ИПЦ raw2015'!$A:$A,0),MATCH(MoM!R$1,'ИПЦ raw2015'!$1:$1,0)) -> 100.23 | S5: =INDEX('ИПЦ raw2015'!$1:$1048576, MATCH($J5,'ИПЦ raw2015'!$A:$A,0),MATCH(MoM!S$1,'ИПЦ raw2015'!$1:$1,0)) -> 100.41 | T5: =INDEX('ИПЦ raw2015'!$1:$1048576, MATCH($J5,'ИПЦ raw2015'!$A:$A,0),MATCH(MoM!T$1,'ИПЦ raw2015'!$1:$1,0)) -> 100.3 | ... BT5: =INDEX('ИПЦ raw2015'!$1:$1048576, MATCH($J5,'ИПЦ raw2015'!$A:$A,0),MATCH(MoM!BT$1,'ИПЦ raw2015'!$1:$1,0)) -> 99.51
A6: =Веса!A6 -> 1 | B6: =A6 -> 1 | C6: =БИПЦ_НДС!E6 -> 0 | D6: =1-C6 -> 1 | E6: 1 | F6: 0 | G6: 0 | H6: 0 | I6: 0 | J6: =L6 -> Баранина (кроме бескостного мяса), кг | K6: Баранина (кроме бескостного мяса), кг | L6: Баранина (кроме бескостного мяса), кг | M6: =INDEX('ИПЦ raw2015'!$1:$1048576, MATCH($J6,'ИПЦ raw2015'!$A:$A,0),MATCH(MoM!M$1,'ИПЦ raw2015'!$1:$1,0)) -> 102.84 | N6: =INDEX('ИПЦ raw2015'!$1:$1048576, MATCH($J6,'ИПЦ raw2015'!$A:$A,0),MATCH(MoM!N$1,'ИПЦ raw2015'!$1:$1,0)) -> 101.95 | O6: =INDEX('ИПЦ raw2015'!$1:$1048576, MATCH($J6,'ИПЦ raw2015'!$A:$A,0),MATCH(MoM!O$1,'ИПЦ raw2015'!$1:$1,0)) -> 101.06 | P6: =INDEX('ИПЦ raw2015'!$1:$1048576, MATCH($J6,'ИПЦ raw2015'!$A:$A,0),MATCH(MoM!P$1,'ИПЦ raw2015'!$1:$1,0)) -> 101.76 | Q6: =INDEX('ИПЦ raw2015'!$1:$1048576, MATCH($J6,'ИПЦ raw2015'!$A:$A,0),MATCH(MoM!Q$1,'ИПЦ raw2015'!$1:$1,0)) -> 100.44 | R6: =INDEX('ИПЦ raw2015'!$1:$1048576, MATCH($J6,'ИПЦ raw2015'!$A:$A,0),MATCH(MoM!R$1,'ИПЦ raw2015'!$1:$1,0)) -> 99.73 | S6: =INDEX('ИПЦ raw2015'!$1:$1048576, MATCH($J6,'ИПЦ raw2015'!$A:$A,0),MATCH(MoM!S$1,'ИПЦ raw2015'!$1:$1,0)) -> 100.2 | T6: =INDEX('ИПЦ raw2015'!$1:$1048576, MATCH($J6,'ИПЦ raw2015'!$A:$A,0),MATCH(MoM!T$1,'ИПЦ raw2015'!$1:$1,0)) -> 100.06 | ... BT6: =INDEX('ИПЦ raw2015'!$1:$1048576, MATCH($J6,'ИПЦ raw2015'!$A:$A,0),MATCH(MoM!BT$1,'ИПЦ raw2015'!$1:$1,0)) -> 100.2
A7: =Веса!A7 -> 1 | B7: =A7 -> 1 | C7: =БИПЦ_НДС!E7 -> 0 | D7: =1-C7 -> 1 | E7: 1 | F7: 0 | G7: 0 | H7: 0 | I7: 0 | J7: =L7 -> Куры охлажденные и мороженые, кг | K7: Куры охлажденные и мороженые, кг | L7: Куры охлажденные и мороженые, кг | M7: =INDEX('ИПЦ raw2015'!$1:$1048576, MATCH($J7,'ИПЦ raw2015'!$A:$A,0),MATCH(MoM!M$1,'ИПЦ raw2015'!$1:$1,0)) -> 102.41 | N7: =INDEX('ИПЦ raw2015'!$1:$1048576, MATCH($J7,'ИПЦ raw2015'!$A:$A,0),MATCH(MoM!N$1,'ИПЦ raw2015'!$1:$1,0)) -> 99.96 | O7: =INDEX('ИПЦ raw2015'!$1:$1048576, MATCH($J7,'ИПЦ raw2015'!$A:$A,0),MATCH(MoM!O$1,'ИПЦ raw2015'!$1:$1,0)) -> 99.31 | P7: =INDEX('ИПЦ raw2015'!$1:$1048576, MATCH($J7,'ИПЦ raw2015'!$A:$A,0),MATCH(MoM!P$1,'ИПЦ raw2015'!$1:$1,0)) -> 98.88 | Q7: =INDEX('ИПЦ raw2015'!$1:$1048576, MATCH($J7,'ИПЦ raw2015'!$A:$A,0),MATCH(MoM!Q$1,'ИПЦ raw2015'!$1:$1,0)) -> 98.99 | R7: =INDEX('ИПЦ raw2015'!$1:$1048576, MATCH($J7,'ИПЦ raw2015'!$A:$A,0),MATCH(MoM!R$1,'ИПЦ raw2015'!$1:$1,0)) -> 99.34 | S7: =INDEX('ИПЦ raw2015'!$1:$1048576, MATCH($J7,'ИПЦ raw2015'!$A:$A,0),MATCH(MoM!S$1,'ИПЦ raw2015'!$1:$1,0)) -> 99.71 | T7: =INDEX('ИПЦ raw2015'!$1:$1048576, MATCH($J7,'ИПЦ raw2015'!$A:$A,0),MATCH(MoM!T$1,'ИПЦ raw2015'!$1:$1,0)) -> 99.78 | ... BT7: =INDEX('ИПЦ raw2015'!$1:$1048576, MATCH($J7,'ИПЦ raw2015'!$A:$A,0),MATCH(MoM!BT$1,'ИПЦ raw2015'!$1:$1,0)) -> 99.82
A8: =Веса!A8 -> 1 | B8: =A8 -> 1 | C8: =БИПЦ_НДС!E8 -> 0 | D8: =1-C8 -> 1 | E8: 1 | F8: 0 | G8: 0 | H8: 0 | I8: 0 | J8: =L8 -> Окорочка куриные, кг | K8: Окорочка куриные, кг | L8: Окорочка куриные, кг | M8: =INDEX('ИПЦ raw2015'!$1:$1048576, MATCH($J8,'ИПЦ raw2015'!$A:$A,0),MATCH(MoM!M$1,'ИПЦ raw2015'!$1:$1,0)) -> 102.66 | N8: =INDEX('ИПЦ raw2015'!$1:$1048576, MATCH($J8,'ИПЦ raw2015'!$A:$A,0),MATCH(MoM!N$1,'ИПЦ raw2015'!$1:$1,0)) -> 100.98 | O8: =INDEX('ИПЦ raw2015'!$1:$1048576, MATCH($J8,'ИПЦ raw2015'!$A:$A,0),MATCH(MoM!O$1,'ИПЦ raw2015'!$1:$1,0)) -> 99.88 | P8: =INDEX('ИПЦ raw2015'!$1:$1048576, MATCH($J8,'ИПЦ raw2015'!$A:$A,0),MATCH(MoM!P$1,'ИПЦ raw2015'!$1:$1,0)) -> 99.25 | Q8: =INDEX('ИПЦ raw2015'!$1:$1048576, MATCH($J8,'ИПЦ raw2015'!$A:$A,0),MATCH(MoM!Q$1,'ИПЦ raw2015'!$1:$1,0)) -> 99.49 | R8: =INDEX('ИПЦ raw2015'!$1:$1048576, MATCH($J8,'ИПЦ raw2015'!$A:$A,0),MATCH(MoM!R$1,'ИПЦ raw2015'!$1:$1,0)) -> 99.65 | S8: =INDEX('ИПЦ raw2015'!$1:$1048576, MATCH($J8,'ИПЦ raw2015'!$A:$A,0),MATCH(MoM!S$1,'ИПЦ raw2015'!$1:$1,0)) -> 99.89 | T8: =INDEX('ИПЦ raw2015'!$1:$1048576, MATCH($J8,'ИПЦ raw2015'!$A:$A,0),MATCH(MoM!T$1,'ИПЦ raw2015'!$1:$1,0)) -> 100.05 | ... BT8: =INDEX('ИПЦ raw2015'!$1:$1048576, MATCH($J8,'ИПЦ raw2015'!$A:$A,0),MATCH(MoM!BT$1,'ИПЦ raw2015'!$1:$1,0)) -> 100.09
A9: =Веса!A9 -> 0 | B9: =A9 -> 0 | C9: =БИПЦ_НДС!E9 -> 0 | D9: =1-C9 -> 1 | E9: 1 | F9: 0 | G9: 0 | H9: 0 | I9: 0 | J9: Мясо индейки, кг | K9: Мясо индейки, кг | L9: Мясо индейки, кг | M9: 0 | N9: 0 | O9: 0 | P9: 0 | Q9: 0 | R9: 0 | S9: 0 | T9: 0 | U9: 0 | V9: 0 | W9: 0 | X9: 0 | Y9: 0 | Z9: 0 | AA9: 0 | AB9: 0 | AC9: 0 | AD9: 0 | AE9: 0 | AF9: 0 | AG9: 0 | AH9: 0 | AI9: 0 | AJ9: 0 | AK9: 0 | AL9: 0 | AM9: 0 | AN9: 0 | AO9: 0 | AP9: 0 | AQ9: 0 | AR9: 0 | AS9: 0 | AT9: 0 | AU9: 0 | AV9: 0 | AW9: 0 | AX9: 0 | AY9: 0 | AZ9: 0 | BA9: 0 | BB9: 0 | BC9: 0 | BD9: 0 | BE9: 0 | BF9: 0 | BG9: 0 | BH9: 0 | BI9: 0 | BJ9: 0 | BK9: 0 | BL9: 0 | BM9: 0 | BN9: 0 | BO9: 0 | BP9: 0 | BQ9: 0 | BR9: 0 | BS9: 0 | BT9: 0
A10: =Веса!A10 -> 1 | B10: =A10 -> 1 | C10: =БИПЦ_НДС!E10 -> 0 | D10: =1-C10 -> 1 | E10: 1 | F10: 0 | G10: 0 | H10: 0 | I10: 0 | J10: Печень говяжья, кг | K10: Печень говяжья, свиная, кг | L10: Печень говяжья, свиная, кг | M10: =INDEX('ИПЦ raw2015'!$1:$1048576, MATCH($J10,'ИПЦ raw2015'!$A:$A,0),MATCH(MoM!M$1,'ИПЦ raw2015'!$1:$1,0)) -> 104.75 | N10: =INDEX('ИПЦ raw2015'!$1:$1048576, MATCH($J10,'ИПЦ raw2015'!$A:$A,0),MATCH(MoM!N$1,'ИПЦ raw2015'!$1:$1,0)) -> 105.04 | O10: =INDEX('ИПЦ raw2015'!$1:$1048576, MATCH($J10,'ИПЦ raw2015'!$A:$A,0),MATCH(MoM!O$1,'ИПЦ raw2015'!$1:$1,0)) -> 102.85 | P10: =INDEX('ИПЦ raw2015'!$1:$1048576, MATCH($J10,'ИПЦ raw2015'!$A:$A,0),MATCH(MoM!P$1,'ИПЦ raw2015'!$1:$1,0)) -> 100.8 | Q10: =INDEX('ИПЦ raw2015'!$1:$1048576, MATCH($J10,'ИПЦ raw2015'!$A:$A,0),MATCH(MoM!Q$1,'ИПЦ raw2015'!$1:$1,0)) -> 98.97 | R10: =INDEX('ИПЦ raw2015'!$1:$1048576, MATCH($J10,'ИПЦ raw2015'!$A:$A,0),MATCH(MoM!R$1,'ИПЦ raw2015'!$1:$1,0)) -> 99.37 | S10: =INDEX('ИПЦ raw2015'!$1:$1048576, MATCH($J10,'ИПЦ raw2015'!$A:$A,0),MATCH(MoM!S$1,'ИПЦ raw2015'!$1:$1,0)) -> 99.25 | T10: =INDEX('ИПЦ raw2015'!$1:$1048576, MATCH($J10,'ИПЦ raw2015'!$A:$A,0),MATCH(MoM!T$1,'ИПЦ raw2015'!$1:$1,0)) -> 99.78 | ... BT10: =INDEX('ИПЦ raw2015'!$1:$1048576, MATCH($J10,'ИПЦ raw2015'!$A:$A,0),MATCH(MoM!BT$1,'ИПЦ raw2015'!$1:$1,0)) -> 100.31
A11: =Веса!A11 -> 1 | B11: =A11 -> 1 | C11: =БИПЦ_НДС!E11 -> 0 | D11: =1-C11 -> 1 | E11: 1 | F11: 0 | G11: 0 | H11: 0 | I11: 0 | J11: =L11 -> Фарш мясной, кг | K11: Фарш мясной, кг | L11: Фарш мясной, кг | M11: =INDEX('ИПЦ raw2015'!$1:$1048576, MATCH($J11,'ИПЦ raw2015'!$A:$A,0),MATCH(MoM!M$1,'ИПЦ raw2015'!$1:$1,0)) -> 103.9 | N11: =INDEX('ИПЦ raw2015'!$1:$1048576, MATCH($J11,'ИПЦ raw2015'!$A:$A,0),MATCH(MoM!N$1,'ИПЦ raw2015'!$1:$1,0)) -> 103 | O11: =INDEX('ИПЦ raw2015'!$1:$1048576, MATCH($J11,'ИПЦ raw2015'!$A:$A,0),MATCH(MoM!O$1,'ИПЦ raw2015'!$1:$1,0)) -> 101.68 | P11: =INDEX('ИПЦ raw2015'!$1:$1048576, MATCH($J11,'ИПЦ raw2015'!$A:$A,0),MATCH(MoM!P$1,'ИПЦ raw2015'!$1:$1,0)) -> 100.77 | Q11: =INDEX('ИПЦ raw2015'!$1:$1048576, MATCH($J11,'ИПЦ raw2015'!$A:$A,0),MATCH(MoM!Q$1,'ИПЦ raw2015'!$1:$1,0)) -> 100.19 | R11: =INDEX('ИПЦ raw2015'!$1:$1048576, MATCH($J11,'ИПЦ raw2015'!$A:$A,0),MATCH(MoM!R$1,'ИПЦ raw2015'!$1:$1,0)) -> 100.13 | S11: =INDEX('ИПЦ raw2015'!$1:$1048576, MATCH($J11,'ИПЦ raw2015'!$A:$A,0),MATCH(MoM!S$1,'ИПЦ raw2015'!$1:$1,0)) -> 100.23 | T11: =INDEX('ИПЦ raw2015'!$1:$1048576, MATCH($J11,'ИПЦ raw2015'!$A:$A,0),MATCH(MoM!T$1,'ИПЦ raw2015'!$1:$1,0)) -> 100.59 | ... BT11: =INDEX('ИПЦ raw2015'!$1:$1048576, MATCH($J11,'ИПЦ raw2015'!$A:$A,0),MATCH(MoM!BT$1,'ИПЦ raw2015'!$1:$1,0)) -> 99.98
A12: =Веса!A12 -> 1 | B12: =A12 -> 1 | C12: =БИПЦ_НДС!E12 -> 0 | D12: =1-C12 -> 1 | E12: 1 | F12: 0 | G12: 0 | H12: 0 | I12: 0 | J12: =L12 -> Пельмени, манты, равиоли, кг | K12: Пельмени, манты, равиоли, кг | L12: Пельмени, манты, равиоли, кг | M12: =INDEX('ИПЦ raw2015'!$1:$1048576, MATCH($J12,'ИПЦ raw2015'!$A:$A,0),MATCH(MoM!M$1,'ИПЦ raw2015'!$1:$1,0)) -> 103.23 | N12: =INDEX('ИПЦ raw2015'!$1:$1048576, MATCH($J12,'ИПЦ raw2015'!$A:$A,0),MATCH(MoM!N$1,'ИПЦ raw2015'!$1:$1,0)) -> 103.1 | O12: =INDEX('ИПЦ raw2015'!$1:$1048576, MATCH($J12,'ИПЦ raw2015'!$A:$A,0),MATCH(MoM!O$1,'ИПЦ raw2015'!$1:$1,0)) -> 102.14 | P12: =INDEX('ИПЦ raw2015'!$1:$1048576, MATCH($J12,'ИПЦ raw2015'!$A:$A,0),MATCH(MoM!P$1,'ИПЦ raw2015'!$1:$1,0)) -> 101.24 | Q12: =INDEX('ИПЦ raw2015'!$1:$1048576, MATCH($J12,'ИПЦ raw2015'!$A:$A,0),MATCH(MoM!Q$1,'ИПЦ raw2015'!$1:$1,0)) -> 100.91 | R12: =INDEX('ИПЦ raw2015'!$1:$1048576, MATCH($J12,'ИПЦ raw2015'!$A:$A,0),MATCH(MoM!R$1,'ИПЦ raw2015'!$1:$1,0)) -> 100.65 | S12: =INDEX('ИПЦ raw2015'!$1:$1048576, MATCH($J12,'ИПЦ raw2015'!$A:$A,0),MATCH(MoM!S$1,'ИПЦ raw2015'!$1:$1,0)) -> 100.52 | T12: =INDEX('ИПЦ raw2015'!$1:$1048576, MATCH($J12,'ИПЦ raw2015'!$A:$A,0),MATCH(MoM!T$1,'ИПЦ raw2015'!$1:$1,0)) -> 100.25 | ... BT12: =INDEX('ИПЦ raw2015'!$1:$1048576, MATCH($J12,'ИПЦ raw2015'!$A:$A,0),MATCH(MoM!BT$1,'ИПЦ raw2015'!$1:$1,0)) -> 100.34
A13: =Веса!A13 -> 1 | B13: =A13 -> 1 | C13: =БИПЦ_НДС!E13 -> 0 | D13: =1-C13 -> 1 | E13: 1 | F13: 0 | G13: 0 | H13: 0 | I13: 0 | J13: =L13 -> Сосиски, сардельки, кг | K13: Сосиски, сардельки, кг | L13: Сосиски, сардельки, кг | M13: =INDEX('ИПЦ raw2015'!$1:$1048576, MATCH($J13,'ИПЦ raw2015'!$A:$A,0),MATCH(MoM!M$1,'ИПЦ raw2015'!$1:$1,0)) -> 102.34 | N13: =INDEX('ИПЦ raw2015'!$1:$1048576, MATCH($J13,'ИПЦ raw2015'!$A:$A,0),MATCH(MoM!N$1,'ИПЦ raw2015'!$1:$1,0)) -> 102.47 | O13: =INDEX('ИПЦ raw2015'!$1:$1048576, MATCH($J13,'ИПЦ raw2015'!$A:$A,0),MATCH(MoM!O$1,'ИПЦ raw2015'!$1:$1,0)) -> 101.66 | P13: =INDEX('ИПЦ raw2015'!$1:$1048576, MATCH($J13,'ИПЦ raw2015'!$A:$A,0),MATCH(MoM!P$1,'ИПЦ raw2015'!$1:$1,0)) -> 101.17 | Q13: =INDEX('ИПЦ raw2015'!$1:$1048576, MATCH($J13,'ИПЦ raw2015'!$A:$A,0),MATCH(MoM!Q$1,'ИПЦ raw2015'!$1:$1,0)) -> 100.57 | R13: =INDEX('ИПЦ raw2015'!$1:$1048576, MATCH($J13,'ИПЦ raw2015'!$A:$A,0),MATCH(MoM!R$1,'ИПЦ raw2015'!$1:$1,0)) -> 100.19 | S13: =INDEX('ИПЦ raw2015'!$1:$1048576, MATCH($J13,'ИПЦ raw2015'!$A:$A,0),MATCH(MoM!S$1,'ИПЦ raw2015'!$1:$1,0)) -> 100.33 | T13: =INDEX('ИПЦ raw2015'!$1:$1048576, MATCH($J13,'ИПЦ raw2015'!$A:$A,0),MATCH(MoM!T$1,'ИПЦ raw2015'!$1:$1,0)) -> 100.26 | ... BT13: =INDEX('ИПЦ raw2015'!$1:$1048576, MATCH($J13,'ИПЦ raw2015'!$A:$A,0),MATCH(MoM!BT$1,'ИПЦ raw2015'!$1:$1,0)) -> 100.11
A14: =Веса!A14 -> 1 | B14: =A14 -> 1 | C14: =БИПЦ_НДС!E14 -> 0 | D14: =1-C14 -> 1 | E14: 1 | F14: 0 | G14: 0 | H14: 0 | I14: 0 | J14: =L14 -> Колбаса полукопченая и варено-копченая, кг | K14: Колбаса полукопченая и варено-копченая, кг | L14: Колбаса полукопченая и варено-копченая, кг | M14: =INDEX('ИПЦ raw2015'!$1:$1048576, MATCH($J14,'ИПЦ raw2015'!$A:$A,0),MATCH(MoM!M$1,'ИПЦ raw2015'!$1:$1,0)) -> 102.87 | N14: =INDEX('ИПЦ raw2015'!$1:$1048576, MATCH($J14,'ИПЦ raw2015'!$A:$A,0),MATCH(MoM!N$1,'ИПЦ raw2015'!$1:$1,0)) -> 102.63 | O14: =INDEX('ИПЦ raw2015'!$1:$1048576, MATCH($J14,'ИПЦ raw2015'!$A:$A,0),MATCH(MoM!O$1,'ИПЦ raw2015'!$1:$1,0)) -> 101.48 | P14: =INDEX('ИПЦ raw2015'!$1:$1048576, MATCH($J14,'ИПЦ raw2015'!$A:$A,0),MATCH(MoM!P$1,'ИПЦ raw2015'!$1:$1,0)) -> 101.09 | Q14: =INDEX('ИПЦ raw2015'!$1:$1048576, MATCH($J14,'ИПЦ raw2015'!$A:$A,0),MATCH(MoM!Q$1,'ИПЦ raw2015'!$1:$1,0)) -> 100.52 | R14: =INDEX('ИПЦ raw2015'!$1:$1048576, MATCH($J14,'ИПЦ raw2015'!$A:$A,0),MATCH(MoM!R$1,'ИПЦ raw2015'!$1:$1,0)) -> 100.23 | S14: =INDEX('ИПЦ raw2015'!$1:$1048576, MATCH($J14,'ИПЦ raw2015'!$A:$A,0),MATCH(MoM!S$1,'ИПЦ raw2015'!$1:$1,0)) -> 100.22 | T14: =INDEX('ИПЦ raw2015'!$1:$1048576, MATCH($J14,'ИПЦ raw2015'!$A:$A,0),MATCH(MoM!T$1,'ИПЦ raw2015'!$1:$1,0)) -> 100.21 | ... BT14: =INDEX('ИПЦ raw2015'!$1:$1048576, MATCH($J14,'ИПЦ raw2015'!$A:$A,0),MATCH(MoM!BT$1,'ИПЦ raw2015'!$1:$1,0)) -> 99.99
A15: =Веса!A15 -> 1 | B15: =A15 -> 1 | C15: =БИПЦ_НДС!E15 -> 0 | D15: =1-C15 -> 1 | E15: 1 | F15: 0 | G15: 0 | H15: 0 | I15: 0 | J15: =L15 -> Колбаса сырокопченая, кг | K15: Колбаса сырокопченая, кг | L15: Колбаса сырокопченая, кг | M15: =INDEX('ИПЦ raw2015'!$1:$1048576, MATCH($J15,'ИПЦ raw2015'!$A:$A,0),MATCH(MoM!M$1,'ИПЦ raw2015'!$1:$1,0)) -> 102.41 | N15: =INDEX('ИПЦ raw2015'!$1:$1048576, MATCH($J15,'ИПЦ raw2015'!$A:$A,0),MATCH(MoM!N$1,'ИПЦ raw2015'!$1:$1,0)) -> 102.14 | O15: =INDEX('ИПЦ raw2015'!$1:$1048576, MATCH($J15,'ИПЦ raw2015'!$A:$A,0),MATCH(MoM!O$1,'ИПЦ raw2015'!$1:$1,0)) -> 101.61 | P15: =INDEX('ИПЦ raw2015'!$1:$1048576, MATCH($J15,'ИПЦ raw2015'!$A:$A,0),MATCH(MoM!P$1,'ИПЦ raw2015'!$1:$1,0)) -> 101.08 | Q15: =INDEX('ИПЦ raw2015'!$1:$1048576, MATCH($J15,'ИПЦ raw2015'!$A:$A,0),MATCH(MoM!Q$1,'ИПЦ raw2015'!$1:$1,0)) -> 100.95 | R15: =INDEX('ИПЦ raw2015'!$1:$1048576, MATCH($J15,'ИПЦ raw2015'!$A:$A,0),MATCH(MoM!R$1,'ИПЦ raw2015'!$1:$1,0)) -> 100.4 | S15: =INDEX('ИПЦ raw2015'!$1:$1048576, MATCH($J15,'ИПЦ raw2015'!$A:$A,0),MATCH(MoM!S$1,'ИПЦ raw2015'!$1:$1,0)) -> 100.25 | T15: =INDEX('ИПЦ raw2015'!$1:$1048576, MATCH($J15,'ИПЦ raw2015'!$A:$A,0),MATCH(MoM!T$1,'ИПЦ raw2015'!$1:$1,0)) -> 100.45 | ... BT15: =INDEX('ИПЦ raw2015'!$1:$1048576, MATCH($J15,'ИПЦ raw2015'!$A:$A,0),MATCH(MoM!BT$1,'ИПЦ raw2015'!$1:$1,0)) -> 100.2
A16: =Веса!A16 -> 1 | B16: =A16 -> 1 | C16: =БИПЦ_НДС!E16 -> 0 | D16: =1-C16 -> 1 | E16: 1 | F16: 0 | G16: 0 | H16: 0 | I16: 0 | J16: =L16 -> Колбаса вареная, кг | K16: Колбаса вареная, кг | L16: Колбаса вареная, кг | M16: =INDEX('ИПЦ raw2015'!$1:$1048576, MATCH($J16,'ИПЦ raw2015'!$A:$A,0),MATCH(MoM!M$1,'ИПЦ raw2015'!$1:$1,0)) -> 102.47 | N16: =INDEX('ИПЦ raw2015'!$1:$1048576, MATCH($J16,'ИПЦ raw2015'!$A:$A,0),MATCH(MoM!N$1,'ИПЦ raw2015'!$1:$1,0)) -> 102.36 | O16: =INDEX('ИПЦ raw2015'!$1:$1048576, MATCH($J16,'ИПЦ raw2015'!$A:$A,0),MATCH(MoM!O$1,'ИПЦ raw2015'!$1:$1,0)) -> 101.73 | P16: =INDEX('ИПЦ raw2015'!$1:$1048576, MATCH($J16,'ИПЦ raw2015'!$A:$A,0),MATCH(MoM!P$1,'ИПЦ raw2015'!$1:$1,0)) -> 100.99 | Q16: =INDEX('ИПЦ raw2015'!$1:$1048576, MATCH($J16,'ИПЦ raw2015'!$A:$A,0),MATCH(MoM!Q$1,'ИПЦ raw2015'!$1:$1,0)) -> 100.6 | R16: =INDEX('ИПЦ raw2015'!$1:$1048576, MATCH($J16,'ИПЦ raw2015'!$A:$A,0),MATCH(MoM!R$1,'ИПЦ raw2015'!$1:$1,0)) -> 100.58 | S16: =INDEX('ИПЦ raw2015'!$1:$1048576, MATCH($J16,'ИПЦ raw2015'!$A:$A,0),MATCH(MoM!S$1,'ИПЦ raw2015'!$1:$1,0)) -> 100.25 | T16: =INDEX('ИПЦ raw2015'!$1:$1048576, MATCH($J16,'ИПЦ raw2015'!$A:$A,0),MATCH(MoM!T$1,'ИПЦ raw2015'!$1:$1,0)) -> 100.27 | ... BT16: =INDEX('ИПЦ raw2015'!$1:$1048576, MATCH($J16,'ИПЦ raw2015'!$A:$A,0),MATCH(MoM!BT$1,'ИПЦ raw2015'!$1:$1,0)) -> 100.27
A17: =Веса!A17 -> 1 | B17: =A17 -> 1 | C17: =БИПЦ_НДС!E17 -> 1 | D17: =1-C17 -> 0 | E17: 1 | F17: 0 | G17: 0 | H17: 0 | I17: 0 | J17: =L17 -> Мясокопчености, кг | K17: Мясокопчености, кг | L17: Мясокопчености, кг | M17: =INDEX('ИПЦ raw2015'!$1:$1048576, MATCH($J17,'ИПЦ raw2015'!$A:$A,0),MATCH(MoM!M$1,'ИПЦ raw2015'!$1:$1,0)) -> 102.06 | N17: =INDEX('ИПЦ raw2015'!$1:$1048576, MATCH($J17,'ИПЦ raw2015'!$A:$A,0),MATCH(MoM!N$1,'ИПЦ raw2015'!$1:$1,0)) -> 102.4 | O17: =INDEX('ИПЦ raw2015'!$1:$1048576, MATCH($J17,'ИПЦ raw2015'!$A:$A,0),MATCH(MoM!O$1,'ИПЦ raw2015'!$1:$1,0)) -> 101.55 | P17: =INDEX('ИПЦ raw2015'!$1:$1048576, MATCH($J17,'ИПЦ raw2015'!$A:$A,0),MATCH(MoM!P$1,'ИПЦ raw2015'!$1:$1,0)) -> 101.02 | Q17: =INDEX('ИПЦ raw2015'!$1:$1048576, MATCH($J17,'ИПЦ raw2015'!$A:$A,0),MATCH(MoM!Q$1,'ИПЦ raw2015'!$1:$1,0)) -> 100.66 | R17: =INDEX('ИПЦ raw2015'!$1:$1048576, MATCH($J17,'ИПЦ raw2015'!$A:$A,0),MATCH(MoM!R$1,'ИПЦ raw2015'!$1:$1,0)) -> 100.47 | S17: =INDEX('ИПЦ raw2015'!$1:$1048576, MATCH($J17,'ИПЦ raw2015'!$A:$A,0),MATCH(MoM!S$1,'ИПЦ raw2015'!$1:$1,0)) -> 100.14 | T17: =INDEX('ИПЦ raw2015'!$1:$1048576, MATCH($J17,'ИПЦ raw2015'!$A:$A,0),MATCH(MoM!T$1,'ИПЦ raw2015'!$1:$1,0)) -> 100.17 | ... BT17: =INDEX('ИПЦ raw2015'!$1:$1048576, MATCH($J17,'ИПЦ raw2015'!$A:$A,0),MATCH(MoM!BT$1,'ИПЦ raw2015'!$1:$1,0)) -> 100.15
A18: =Веса!A18 -> 1 | B18: =A18 -> 1 | C18: =БИПЦ_НДС!E18 -> 0 | D18: =1-C18 -> 1 | E18: 1 | F18: 0 | G18: 0 | H18: 0 | I18: 0 | J18: =L18 -> Кулинарные изделия из птицы, кг | K18: Кулинарные изделия из птицы, кг | L18: Кулинарные изделия из птицы, кг | M18: =INDEX('ИПЦ raw2015'!$1:$1048576, MATCH($J18,'ИПЦ raw2015'!$A:$A,0),MATCH(MoM!M$1,'ИПЦ raw2015'!$1:$1,0)) -> 102.51 | N18: =INDEX('ИПЦ raw2015'!$1:$1048576, MATCH($J18,'ИПЦ raw2015'!$A:$A,0),MATCH(MoM!N$1,'ИПЦ raw2015'!$1:$1,0)) -> 101.89 | O18: =INDEX('ИПЦ raw2015'!$1:$1048576, MATCH($J18,'ИПЦ raw2015'!$A:$A,0),MATCH(MoM!O$1,'ИПЦ raw2015'!$1:$1,0)) -> 100.47 | P18: =INDEX('ИПЦ raw2015'!$1:$1048576, MATCH($J18,'ИПЦ raw2015'!$A:$A,0),MATCH(MoM!P$1,'ИПЦ raw2015'!$1:$1,0)) -> 100.25 | Q18: =INDEX('ИПЦ raw2015'!$1:$1048576, MATCH($J18,'ИПЦ raw2015'!$A:$A,0),MATCH(MoM!Q$1,'ИПЦ raw2015'!$1:$1,0)) -> 100.33 | R18: =INDEX('ИПЦ raw2015'!$1:$1048576, MATCH($J18,'ИПЦ raw2015'!$A:$A,0),MATCH(MoM!R$1,'ИПЦ raw2015'!$1:$1,0)) -> 99.83 | S18: =INDEX('ИПЦ raw2015'!$1:$1048576, MATCH($J18,'ИПЦ raw2015'!$A:$A,0),MATCH(MoM!S$1,'ИПЦ raw2015'!$1:$1,0)) -> 100.31 | T18: =INDEX('ИПЦ raw2015'!$1:$1048576, MATCH($J18,'ИПЦ raw2015'!$A:$A,0),MATCH(MoM!T$1,'ИПЦ raw2015'!$1:$1,0)) -> 100.3 | ... BT18: =INDEX('ИПЦ raw2015'!$1:$1048576, MATCH($J18,'ИПЦ raw2015'!$A:$A,0),MATCH(MoM!BT$1,'ИПЦ raw2015'!$1:$1,0)) -> 100.55
A19: =Веса!A19 -> 1 | B19: =A19 -> 1 | C19: =БИПЦ_НДС!E19 -> 0 | D19: =1-C19 -> 1 | E19: 1 | F19: 0 | G19: 0 | H19: 0 | I19: 0 | J19: Консервы мясные, 350 г | K19: Консервы мясные, кг | L19: Консервы мясные, кг | M19: =INDEX('ИПЦ raw2015'!$1:$1048576, MATCH($J19,'ИПЦ raw2015'!$A:$A,0),MATCH(MoM!M$1,'ИПЦ raw2015'!$1:$1,0)) -> 104.92 | N19: =INDEX('ИПЦ raw2015'!$1:$1048576, MATCH($J19,'ИПЦ raw2015'!$A:$A,0),MATCH(MoM!N$1,'ИПЦ raw2015'!$1:$1,0)) -> 104.66 | O19: =INDEX('ИПЦ raw2015'!$1:$1048576, MATCH($J19,'ИПЦ raw2015'!$A:$A,0),MATCH(MoM!O$1,'ИПЦ raw2015'!$1:$1,0)) -> 103.44 | P19: =INDEX('ИПЦ raw2015'!$1:$1048576, MATCH($J19,'ИПЦ raw2015'!$A:$A,0),MATCH(MoM!P$1,'ИПЦ raw2015'!$1:$1,0)) -> 102.27 | Q19: =INDEX('ИПЦ raw2015'!$1:$1048576, MATCH($J19,'ИПЦ raw2015'!$A:$A,0),MATCH(MoM!Q$1,'ИПЦ raw2015'!$1:$1,0)) -> 101.07 | R19: =INDEX('ИПЦ raw2015'!$1:$1048576, MATCH($J19,'ИПЦ raw2015'!$A:$A,0),MATCH(MoM!R$1,'ИПЦ raw2015'!$1:$1,0)) -> 100.84 | S19: =INDEX('ИПЦ raw2015'!$1:$1048576, MATCH($J19,'ИПЦ raw2015'!$A:$A,0),MATCH(MoM!S$1,'ИПЦ raw2015'!$1:$1,0)) -> 100.44 | T19: =INDEX('ИПЦ raw2015'!$1:$1048576, MATCH($J19,'ИПЦ raw2015'!$A:$A,0),MATCH(MoM!T$1,'ИПЦ raw2015'!$1:$1,0)) -> 100.61 | ... BT19: =INDEX('ИПЦ raw2015'!$1:$1048576, MATCH($J19,'ИПЦ raw2015'!$A:$A,0),MATCH(MoM!BT$1,'ИПЦ raw2015'!$1:$1,0)) -> 100.61
A20: =Веса!A20 -> 0 | B20: =A20 -> 0 | C20: =БИПЦ_НДС!E20 -> 0 | D20: =1-C20 -> 1 | E20: 1 | F20: 0 | G20: 0 | H20: 0 | I20: 0 | J20: =L20 -> Консервы мясные для детского питания, кг | K20: Консервы мясные для детского питания, кг | L20: Консервы мясные для детского питания, кг | M20: 0 | N20: 0 | O20: 0 | P20: 0 | Q20: 0 | R20: 0 | S20: 0 | T20: 0 | U20: 0 | V20: 0 | W20: 0 | X20: 0 | Y20: 0 | Z20: 0 | AA20: 0 | AB20: 0 | AC20: 0 | AD20: 0 | AE20: 0 | AF20: 0 | AG20: 0 | AH20: 0 | AI20: 0 | AJ20: 0 | AK20: 0 | AL20: 0 | AM20: 0 | AN20: 0 | AO20: 0 | AP20: 0 | AQ20: 0 | AR20: 0 | AS20: 0 | AT20: 0 | AU20: 0 | AV20: 0 | AW20: 0 | AX20: 0 | AY20: 0 | AZ20: 0 | BA20: 0 | BB20: 0 | BC20: 0 | BD20: 0 | BE20: 0 | BF20: 0 | BG20: 0 | BH20: 0 | BI20: 0 | BJ20: 0 | BK20: 0 | BL20: 0 | BM20: 0 | BN20: 0 | BO20: 0 | BP20: 0 | BQ20: 0 | BR20: 0 | BS20: 0 | BT20: 0
A21: =Веса!A21 -> 1 | B21: =A21 -> 1 | C21: =БИПЦ_НДС!E21 -> 0 | D21: =1-C21 -> 1 | E21: 1 | F21: 0 | G21: 0 | H21: 0 | I21: 0 | J21: =L21 -> Рыба живая и охлажденная, кг | K21: Рыба живая и охлажденная, кг | L21: Рыба живая и охлажденная, кг | M21: =INDEX('ИПЦ raw2015'!$1:$1048576, MATCH($J21,'ИПЦ raw2015'!$A:$A,0),MATCH(MoM!M$1,'ИПЦ raw2015'!$1:$1,0)) -> 105.48 | N21: =INDEX('ИПЦ raw2015'!$1:$1048576, MATCH($J21,'ИПЦ raw2015'!$A:$A,0),MATCH(MoM!N$1,'ИПЦ raw2015'!$1:$1,0)) -> 104.04 | O21: =INDEX('ИПЦ raw2015'!$1:$1048576, MATCH($J21,'ИПЦ raw2015'!$A:$A,0),MATCH(MoM!O$1,'ИПЦ raw2015'!$1:$1,0)) -> 102.48 | P21: =INDEX('ИПЦ raw2015'!$1:$1048576, MATCH($J21,'ИПЦ raw2015'!$A:$A,0),MATCH(MoM!P$1,'ИПЦ raw2015'!$1:$1,0)) -> 101.66 | Q21: =INDEX('ИПЦ raw2015'!$1:$1048576, MATCH($J21,'ИПЦ raw2015'!$A:$A,0),MATCH(MoM!Q$1,'ИПЦ raw2015'!$1:$1,0)) -> 101.04 | R21: =INDEX('ИПЦ raw2015'!$1:$1048576, MATCH($J21,'ИПЦ raw2015'!$A:$A,0),MATCH(MoM!R$1,'ИПЦ raw2015'!$1:$1,0)) -> 102.14 | S21: =INDEX('ИПЦ raw2015'!$1:$1048576, MATCH($J21,'ИПЦ raw2015'!$A:$A,0),MATCH(MoM!S$1,'ИПЦ raw2015'!$1:$1,0)) -> 101.44 | T21: =INDEX('ИПЦ raw2015'!$1:$1048576, MATCH($J21,'ИПЦ raw2015'!$A:$A,0),MATCH(MoM!T$1,'ИПЦ raw2015'!$1:$1,0)) -> 102.22 | ... BT21: =INDEX('ИПЦ raw2015'!$1:$1048576, MATCH($J21,'ИПЦ raw2015'!$A:$A,0),MATCH(MoM!BT$1,'ИПЦ raw2015'!$1:$1,0)) -> 99.52
A22: =Веса!A22 -> 1 | B22: =A22 -> 1 | C22: =БИПЦ_НДС!E22 -> 0 | D22: =1-C22 -> 1 | E22: 1 | F22: 0 | G22: 0 | H22: 0 | I22: 0 | J22: =L22 -> Рыба соленая, маринованная, копченая, кг | K22: Рыба соленая, маринованная, копченая, кг | L22: Рыба соленая, маринованная, копченая, кг | M22: =INDEX('ИПЦ raw2015'!$1:$1048576, MATCH($J22,'ИПЦ raw2015'!$A:$A,0),MATCH(MoM!M$1,'ИПЦ raw2015'!$1:$1,0)) -> 104.96 | N22: =INDEX('ИПЦ raw2015'!$1:$1048576, MATCH($J22,'ИПЦ raw2015'!$A:$A,0),MATCH(MoM!N$1,'ИПЦ raw2015'!$1:$1,0)) -> 103.54 | O22: =INDEX('ИПЦ raw2015'!$1:$1048576, MATCH($J22,'ИПЦ raw2015'!$A:$A,0),MATCH(MoM!O$1,'ИПЦ raw2015'!$1:$1,0)) -> 102.86 | P22: =INDEX('ИПЦ raw2015'!$1:$1048576, MATCH($J22,'ИПЦ raw2015'!$A:$A,0),MATCH(MoM!P$1,'ИПЦ raw2015'!$1:$1,0)) -> 101.56 | Q22: =INDEX('ИПЦ raw2015'!$1:$1048576, MATCH($J22,'ИПЦ raw2015'!$A:$A,0),MATCH(MoM!Q$1,'ИПЦ raw2015'!$1:$1,0)) -> 100.63 | R22: =INDEX('ИПЦ raw2015'!$1:$1048576, MATCH($J22,'ИПЦ raw2015'!$A:$A,0),MATCH(MoM!R$1,'ИПЦ raw2015'!$1:$1,0)) -> 100.53 | S22: =INDEX('ИПЦ raw2015'!$1:$1048576, MATCH($J22,'ИПЦ raw2015'!$A:$A,0),MATCH(MoM!S$1,'ИПЦ raw2015'!$1:$1,0)) -> 100.49 | T22: =INDEX('ИПЦ raw2015'!$1:$1048576, MATCH($J22,'ИПЦ raw2015'!$A:$A,0),MATCH(MoM!T$1,'ИПЦ raw2015'!$1:$1,0)) -> 100.41 | ... BT22: =INDEX('ИПЦ raw2015'!$1:$1048576, MATCH($J22,'ИПЦ raw2015'!$A:$A,0),MATCH(MoM!BT$1,'ИПЦ raw2015'!$1:$1,0)) -> 100.48
A23: =Веса!A23 -> 1 | B23: =A23 -> 1 | C23: =БИПЦ_НДС!E23 -> 1 | D23: =1-C23 -> 0 | E23: 1 | F23: 0 | G23: 0 | H23: 0 | I23: 0 | J23: =L23 -> Соленые и копченые деликатесные продукты из рыбы, кг | K23: Соленые и копченые деликатесные продукты из рыбы, кг | L23: Соленые и копченые деликатесные продукты из рыбы, кг | M23: =INDEX('ИПЦ raw2015'!$1:$1048576, MATCH($J23,'ИПЦ raw2015'!$A:$A,0),MATCH(MoM!M$1,'ИПЦ raw2015'!$1:$1,0)) -> 107.47 | N23: =INDEX('ИПЦ raw2015'!$1:$1048576, MATCH($J23,'ИПЦ raw2015'!$A:$A,0),MATCH(MoM!N$1,'ИПЦ raw2015'!$1:$1,0)) -> 105.19 | O23: =INDEX('ИПЦ raw2015'!$1:$1048576, MATCH($J23,'ИПЦ raw2015'!$A:$A,0),MATCH(MoM!O$1,'ИПЦ raw2015'!$1:$1,0)) -> 102.31 | P23: =INDEX('ИПЦ raw2015'!$1:$1048576, MATCH($J23,'ИПЦ raw2015'!$A:$A,0),MATCH(MoM!P$1,'ИПЦ raw2015'!$1:$1,0)) -> 100.42 | Q23: =INDEX('ИПЦ raw2015'!$1:$1048576, MATCH($J23,'ИПЦ raw2015'!$A:$A,0),MATCH(MoM!Q$1,'ИПЦ raw2015'!$1:$1,0)) -> 99.66 | R23: =INDEX('ИПЦ raw2015'!$1:$1048576, MATCH($J23,'ИПЦ raw2015'!$A:$A,0),MATCH(MoM!R$1,'ИПЦ raw2015'!$1:$1,0)) -> 99.73 | S23: =INDEX('ИПЦ raw2015'!$1:$1048576, MATCH($J23,'ИПЦ raw2015'!$A:$A,0),MATCH(MoM!S$1,'ИПЦ raw2015'!$1:$1,0)) -> 99.35 | T23: =INDEX('ИПЦ raw2015'!$1:$1048576, MATCH($J23,'ИПЦ raw2015'!$A:$A,0),MATCH(MoM!T$1,'ИПЦ raw2015'!$1:$1,0)) -> 99.82 | ... BT23: =INDEX('ИПЦ raw2015'!$1:$1048576, MATCH($J23,'ИПЦ raw2015'!$A:$A,0),MATCH(MoM!BT$1,'ИПЦ raw2015'!$1:$1,0)) -> 100.34
A24: =Веса!A24 -> 1 | B24: =A24 -> 1 | C24: =БИПЦ_НДС!E24 -> 1 | D24: =1-C24 -> 0 | E24: 1 | F24: 0 | G24: 0 | H24: 0 | I24: 0 | J24: =L24 -> Икра лососевых рыб отечественная, кг | K24: Икра лососевых рыб отечественная, кг | L24: Икра лососевых рыб отечественная, кг | M24: =INDEX('ИПЦ raw2015'!$1:$1048576, MATCH($J24,'ИПЦ raw2015'!$A:$A,0),MATCH(MoM!M$1,'ИПЦ raw2015'!$1:$1,0)) -> 101.32 | N24: =INDEX('ИПЦ raw2015'!$1:$1048576, MATCH($J24,'ИПЦ raw2015'!$A:$A,0),MATCH(MoM!N$1,'ИПЦ raw2015'!$1:$1,0)) -> 100.87 | O24: =INDEX('ИПЦ raw2015'!$1:$1048576, MATCH($J24,'ИПЦ raw2015'!$A:$A,0),MATCH(MoM!O$1,'ИПЦ raw2015'!$1:$1,0)) -> 100.63 | P24: =INDEX('ИПЦ raw2015'!$1:$1048576, MATCH($J24,'ИПЦ raw2015'!$A:$A,0),MATCH(MoM!P$1,'ИПЦ raw2015'!$1:$1,0)) -> 100.47 | Q24: =INDEX('ИПЦ raw2015'!$1:$1048576, MATCH($J24,'ИПЦ raw2015'!$A:$A,0),MATCH(MoM!Q$1,'ИПЦ raw2015'!$1:$1,0)) -> 100.52 | R24: =INDEX('ИПЦ raw2015'!$1:$1048576, MATCH($J24,'ИПЦ raw2015'!$A:$A,0),MATCH(MoM!R$1,'ИПЦ raw2015'!$1:$1,0)) -> 100.01 | S24: =INDEX('ИПЦ raw2015'!$1:$1048576, MATCH($J24,'ИПЦ raw2015'!$A:$A,0),MATCH(MoM!S$1,'ИПЦ raw2015'!$1:$1,0)) -> 99.98 | T24: =INDEX('ИПЦ raw2015'!$1:$1048576, MATCH($J24,'ИПЦ raw2015'!$A:$A,0),MATCH(MoM!T$1,'ИПЦ raw2015'!$1:$1,0)) -> 100.44 | ... BT24: =INDEX('ИПЦ raw2015'!$1:$1048576, MATCH($J24,'ИПЦ raw2015'!$A:$A,0),MATCH(MoM!BT$1,'ИПЦ raw2015'!$1:$1,0)) -> 100.23
A25: =Веса!A25 -> 1 | B25: =A25 -> 1 | C25: =БИПЦ_НДС!E25 -> 0 | D25: =1-C25 -> 1 | E25: 1 | F25: 0 | G25: 0 | H25: 0 | I25: 0 | J25: =L25 -> Рыба мороженая разделанная (кроме лососевых пород), кг | K25: Рыба мороженая разделанная (кроме лососевых пород), кг | L25: Рыба мороженая разделанная (кроме лососевых пород), кг | M25: =INDEX('ИПЦ raw2015'!$1:$1048576, MATCH($J25,'ИПЦ raw2015'!$A:$A,0),MATCH(MoM!M$1,'ИПЦ raw2015'!$1:$1,0)) -> 107.5 | N25: =INDEX('ИПЦ raw2015'!$1:$1048576, MATCH($J25,'ИПЦ raw2015'!$A:$A,0),MATCH(MoM!N$1,'ИПЦ raw2015'!$1:$1,0)) -> 107.9 | O25: =INDEX('ИПЦ raw2015'!$1:$1048576, MATCH($J25,'ИПЦ raw2015'!$A:$A,0),MATCH(MoM!O$1,'ИПЦ raw2015'!$1:$1,0)) -> 104.23 | P25: =INDEX('ИПЦ raw2015'!$1:$1048576, MATCH($J25,'ИПЦ raw2015'!$A:$A,0),MATCH(MoM!P$1,'ИПЦ raw2015'!$1:$1,0)) -> 101.45 | Q25: =INDEX('ИПЦ raw2015'!$1:$1048576, MATCH($J25,'ИПЦ raw2015'!$A:$A,0),MATCH(MoM!Q$1,'ИПЦ raw2015'!$1:$1,0)) -> 99.08 | R25: =INDEX('ИПЦ raw2015'!$1:$1048576, MATCH($J25,'ИПЦ raw2015'!$A:$A,0),MATCH(MoM!R$1,'ИПЦ raw2015'!$1:$1,0)) -> 99.2 | S25: =INDEX('ИПЦ raw2015'!$1:$1048576, MATCH($J25,'ИПЦ raw2015'!$A:$A,0),MATCH(MoM!S$1,'ИПЦ raw2015'!$1:$1,0)) -> 99.69 | T25: =INDEX('ИПЦ raw2015'!$1:$1048576, MATCH($J25,'ИПЦ raw2015'!$A:$A,0),MATCH(MoM!T$1,'ИПЦ raw2015'!$1:$1,0)) -> 99.95 | ... BT25: =INDEX('ИПЦ raw2015'!$1:$1048576, MATCH($J25,'ИПЦ raw2015'!$A:$A,0),MATCH(MoM!BT$1,'ИПЦ raw2015'!$1:$1,0)) -> 100.79
A26: =Веса!A26 -> 1 | B26: =A26 -> 1 | C26: =БИПЦ_НДС!E26 -> 1 | D26: =1-C26 -> 0 | E26: 1 | F26: 0 | G26: 0 | H26: 0 | I26: 0 | J26: =L26 -> Рыба охлажденная и мороженая разделанная лососевых пород, кг | K26: Рыба охлажденная и мороженая разделанная лососевых пород, кг | L26: Рыба охлажденная и мороженая разделанная лососевых пород, кг | M26: =INDEX('ИПЦ raw2015'!$1:$1048576, MATCH($J26,'ИПЦ raw2015'!$A:$A,0),MATCH(MoM!M$1,'ИПЦ raw2015'!$1:$1,0)) -> 107.79 | N26: =INDEX('ИПЦ raw2015'!$1:$1048576, MATCH($J26,'ИПЦ raw2015'!$A:$A,0),MATCH(MoM!N$1,'ИПЦ raw2015'!$1:$1,0)) -> 103.73 | O26: =INDEX('ИПЦ raw2015'!$1:$1048576, MATCH($J26,'ИПЦ raw2015'!$A:$A,0),MATCH(MoM!O$1,'ИПЦ raw2015'!$1:$1,0)) -> 102.8 | P26: =INDEX('ИПЦ raw2015'!$1:$1048576, MATCH($J26,'ИПЦ raw2015'!$A:$A,0),MATCH(MoM!P$1,'ИПЦ raw2015'!$1:$1,0)) -> 100.83 | Q26: =INDEX('ИПЦ raw2015'!$1:$1048576, MATCH($J26,'ИПЦ raw2015'!$A:$A,0),MATCH(MoM!Q$1,'ИПЦ raw2015'!$1:$1,0)) -> 100.13 | R26: =INDEX('ИПЦ raw2015'!$1:$1048576, MATCH($J26,'ИПЦ raw2015'!$A:$A,0),MATCH(MoM!R$1,'ИПЦ raw2015'!$1:$1,0)) -> 100.51 | S26: =INDEX('ИПЦ raw2015'!$1:$1048576, MATCH($J26,'ИПЦ raw2015'!$A:$A,0),MATCH(MoM!S$1,'ИПЦ raw2015'!$1:$1,0)) -> 99.9 | T26: =INDEX('ИПЦ raw2015'!$1:$1048576, MATCH($J26,'ИПЦ raw2015'!$A:$A,0),MATCH(MoM!T$1,'ИПЦ raw2015'!$1:$1,0)) -> 100.48 | ... BT26: =INDEX('ИПЦ raw2015'!$1:$1048576, MATCH($J26,'ИПЦ raw2015'!$A:$A,0),MATCH(MoM!BT$1,'ИПЦ raw2015'!$1:$1,0)) -> 100.34
A27: =Веса!A27 -> 1 | B27: =A27 -> 1 | C27: =БИПЦ_НДС!E27 -> 0 | D27: =1-C27 -> 1 | E27: 1 | F27: 0 | G27: 0 | H27: 0 | I27: 0 | J27: =L27 -> Рыба мороженая неразделанная, кг | K27: Рыба мороженая неразделанная, кг | L27: Рыба мороженая неразделанная, кг | M27: =INDEX('ИПЦ raw2015'!$1:$1048576, MATCH($J27,'ИПЦ raw2015'!$A:$A,0),MATCH(MoM!M$1,'ИПЦ raw2015'!$1:$1,0)) -> 107.7 | N27: =INDEX('ИПЦ raw2015'!$1:$1048576, MATCH($J27,'ИПЦ raw2015'!$A:$A,0),MATCH(MoM!N$1,'ИПЦ raw2015'!$1:$1,0)) -> 108.06 | O27: =INDEX('ИПЦ raw2015'!$1:$1048576, MATCH($J27,'ИПЦ raw2015'!$A:$A,0),MATCH(MoM!O$1,'ИПЦ raw2015'!$1:$1,0)) -> 104.06 | P27: =INDEX('ИПЦ raw2015'!$1:$1048576, MATCH($J27,'ИПЦ raw2015'!$A:$A,0),MATCH(MoM!P$1,'ИПЦ raw2015'!$1:$1,0)) -> 101.38 | Q27: =INDEX('ИПЦ raw2015'!$1:$1048576, MATCH($J27,'ИПЦ raw2015'!$A:$A,0),MATCH(MoM!Q$1,'ИПЦ raw2015'!$1:$1,0)) -> 99.36 | R27: =INDEX('ИПЦ raw2015'!$1:$1048576, MATCH($J27,'ИПЦ raw2015'!$A:$A,0),MATCH(MoM!R$1,'ИПЦ raw2015'!$1:$1,0)) -> 99.7 | S27: =INDEX('ИПЦ raw2015'!$1:$1048576, MATCH($J27,'ИПЦ raw2015'!$A:$A,0),MATCH(MoM!S$1,'ИПЦ raw2015'!$1:$1,0)) -> 99.81 | T27: =INDEX('ИПЦ raw2015'!$1:$1048576, MATCH($J27,'ИПЦ raw2015'!$A:$A,0),MATCH(MoM!T$1,'ИПЦ raw2015'!$1:$1,0)) -> 99.22 | ... BT27: =INDEX('ИПЦ raw2015'!$1:$1048576, MATCH($J27,'ИПЦ raw2015'!$A:$A,0),MATCH(MoM!BT$1,'ИПЦ raw2015'!$1:$1,0)) -> 100.42
A28: =Веса!A28 -> 1 | B28: =A28 -> 1 | C28: =БИПЦ_НДС!E28 -> 0 | D28: =1-C28 -> 1 | E28: 1 | F28: 0 | G28: 0 | H28: 0 | I28: 0 | J28: =L28 -> Филе рыбное, кг | K28: Филе рыбное, кг | L28: Филе рыбное, кг | M28: =INDEX('ИПЦ raw2015'!$1:$1048576, MATCH($J28,'ИПЦ raw2015'!$A:$A,0),MATCH(MoM!M$1,'ИПЦ raw2015'!$1:$1,0)) -> 106.83 | N28: =INDEX('ИПЦ raw2015'!$1:$1048576, MATCH($J28,'ИПЦ raw2015'!$A:$A,0),MATCH(MoM!N$1,'ИПЦ raw2015'!$1:$1,0)) -> 107.22 | O28: =INDEX('ИПЦ raw2015'!$1:$1048576, MATCH($J28,'ИПЦ raw2015'!$A:$A,0),MATCH(MoM!O$1,'ИПЦ raw2015'!$1:$1,0)) -> 103.74 | P28: =INDEX('ИПЦ raw2015'!$1:$1048576, MATCH($J28,'ИПЦ raw2015'!$A:$A,0),MATCH(MoM!P$1,'ИПЦ raw2015'!$1:$1,0)) -> 101.49 | Q28: =INDEX('ИПЦ raw2015'!$1:$1048576, MATCH($J28,'ИПЦ raw2015'!$A:$A,0),MATCH(MoM!Q$1,'ИПЦ raw2015'!$1:$1,0)) -> 100.69 | R28: =INDEX('ИПЦ raw2015'!$1:$1048576, MATCH($J28,'ИПЦ raw2015'!$A:$A,0),MATCH(MoM!R$1,'ИПЦ raw2015'!$1:$1,0)) -> 100.3 | S28: =INDEX('ИПЦ raw2015'!$1:$1048576, MATCH($J28,'ИПЦ raw2015'!$A:$A,0),MATCH(MoM!S$1,'ИПЦ raw2015'!$1:$1,0)) -> 99.89 | T28: =INDEX('ИПЦ raw2015'!$1:$1048576, MATCH($J28,'ИПЦ raw2015'!$A:$A,0),MATCH(MoM!T$1,'ИПЦ raw2015'!$1:$1,0)) -> 100.26 | ... BT28: =INDEX('ИПЦ raw2015'!$1:$1048576, MATCH($J28,'ИПЦ raw2015'!$A:$A,0),MATCH(MoM!BT$1,'ИПЦ raw2015'!$1:$1,0)) -> 100.39
A29: =Веса!A29 -> 0 | B29: =A29 -> 0 | C29: =БИПЦ_НДС!E29 -> 0 | D29: =1-C29 -> 1 | E29: 1 | F29: 0 | G29: 0 | H29: 0 | I29: 0 | J29: =L29 -> Креветки мороженые, неразделанные, кг | K29: Креветки мороженые, неразделанные, кг | L29: Креветки мороженые, неразделанные, кг | M29: 0 | N29: 0 | O29: 0 | P29: 0 | Q29: 0 | R29: 0 | S29: 0 | T29: 0 | U29: 0 | V29: 0 | W29: 0 | X29: 0 | Y29: 0 | Z29: 0 | AA29: 0 | AB29: 0 | AC29: 0 | AD29: 0 | AE29: 0 | AF29: 0 | AG29: 0 | AH29: 0 | AI29: 0 | AJ29: 0 | AK29: 0 | AL29: 0 | AM29: 0 | AN29: 0 | AO29: 0 | AP29: 0 | AQ29: 0 | AR29: 0 | AS29: 0 | AT29: 0 | AU29: 0 | AV29: 0 | AW29: 0 | AX29: 0 | AY29: 0 | AZ29: 0 | BA29: 0 | BB29: 0 | BC29: 0 | BD29: 0 | BE29: 0 | BF29: 0 | BG29: 0 | BH29: 0 | BI29: 0 | BJ29: 0 | BK29: 0 | BL29: 0 | BM29: 0 | BN29: 0 | BO29: 0 | BP29: 0 | BQ29: 0 | BR29: 0 | BS29: 0 | BT29: 0
A30: =Веса!A30 -> 0 | B30: =A30 -> 0 | C30: =БИПЦ_НДС!E30 -> 0 | D30: =1-C30 -> 1 | E30: 1 | F30: 0 | G30: 0 | H30: 0 | I30: 0 | J30: =L30 -> Кальмары мороженые, кг | K30: Кальмары мороженые, кг | L30: Кальмары мороженые, кг | M30: 0 | N30: 0 | O30: 0 | P30: 0 | Q30: 0 | R30: 0 | S30: 0 | T30: 0 | U30: 0 | V30: 0 | W30: 0 | X30: 0 | Y30: 0 | Z30: 0 | AA30: 0 | AB30: 0 | AC30: 0 | AD30: 0 | AE30: 0 | AF30: 0 | AG30: 0 | AH30: 0 | AI30: 0 | AJ30: 0 | AK30: 0 | AL30: 0 | AM30: 0 | AN30: 0 | AO30: 0 | AP30: 0 | AQ30: 0 | AR30: 0 | AS30: 0 | AT30: 0 | AU30: 0 | AV30: 0 | AW30: 0 | AX30: 0 | AY30: 0 | AZ30: 0 | BA30: 0 | BB30: 0 | BC30: 0 | BD30: 0 | BE30: 0 | BF30: 0 | BG30: 0 | BH30: 0 | BI30: 0 | BJ30: 0 | BK30: 0 | BL30: 0 | BM30: 0 | BN30: 0 | BO30: 0 | BP30: 0 | BQ30: 0 | BR30: 0 | BS30: 0 | BT30: 0
A31: =Веса!A31 -> 1 | B31: =A31 -> 1 | C31: =БИПЦ_НДС!E31 -> 0 | D31: =1-C31 -> 1 | E31: 1 | F31: 0 | G31: 0 | H31: 0 | I31: 0 | J31: =L31 -> Сельдь соленая, кг | K31: Сельдь соленая, кг | L31: Сельдь соленая, кг | M31: =INDEX('ИПЦ raw2015'!$1:$1048576, MATCH($J31,'ИПЦ raw2015'!$A:$A,0),MATCH(MoM!M$1,'ИПЦ raw2015'!$1:$1,0)) -> 108.05 | N31: =INDEX('ИПЦ raw2015'!$1:$1048576, MATCH($J31,'ИПЦ raw2015'!$A:$A,0),MATCH(MoM!N$1,'ИПЦ raw2015'!$1:$1,0)) -> 106.09 | O31: =INDEX('ИПЦ raw2015'!$1:$1048576, MATCH($J31,'ИПЦ raw2015'!$A:$A,0),MATCH(MoM!O$1,'ИПЦ raw2015'!$1:$1,0)) -> 103.44 | P31: =INDEX('ИПЦ raw2015'!$1:$1048576, MATCH($J31,'ИПЦ raw2015'!$A:$A,0),MATCH(MoM!P$1,'ИПЦ raw2015'!$1:$1,0)) -> 101.73 | Q31: =INDEX('ИПЦ raw2015'!$1:$1048576, MATCH($J31,'ИПЦ raw2015'!$A:$A,0),MATCH(MoM!Q$1,'ИПЦ raw2015'!$1:$1,0)) -> 100.26 | R31: =INDEX('ИПЦ raw2015'!$1:$1048576, MATCH($J31,'ИПЦ raw2015'!$A:$A,0),MATCH(MoM!R$1,'ИПЦ raw2015'!$1:$1,0)) -> 100.43 | S31: =INDEX('ИПЦ raw2015'!$1:$1048576, MATCH($J31,'ИПЦ raw2015'!$A:$A,0),MATCH(MoM!S$1,'ИПЦ raw2015'!$1:$1,0)) -> 100.14 | T31: =INDEX('ИПЦ raw2015'!$1:$1048576, MATCH($J31,'ИПЦ raw2015'!$A:$A,0),MATCH(MoM!T$1,'ИПЦ raw2015'!$1:$1,0)) -> 101.06 | ... BT31: =INDEX('ИПЦ raw2015'!$1:$1048576, MATCH($J31,'ИПЦ raw2015'!$A:$A,0),MATCH(MoM!BT$1,'ИПЦ raw2015'!$1:$1,0)) -> 100.14
A32: =Веса!A32 -> 1 | B32: =A32 -> 1 | C32: =БИПЦ_НДС!E32 -> 0 | D32: =1-C32 -> 1 | E32: 1 | F32: 0 | G32: 0 | H32: 0 | I32: 0 | J32: =L32 -> Филе сельди соленое, кг | K32: Филе сельди соленое, кг | L32: Филе сельди соленое, кг | M32: =INDEX('ИПЦ raw2015'!$1:$1048576, MATCH($J32,'ИПЦ raw2015'!$A:$A,0),MATCH(MoM!M$1,'ИПЦ raw2015'!$1:$1,0)) -> 108.69 | N32: =INDEX('ИПЦ raw2015'!$1:$1048576, MATCH($J32,'ИПЦ raw2015'!$A:$A,0),MATCH(MoM!N$1,'ИПЦ raw2015'!$1:$1,0)) -> 105.52 | O32: =INDEX('ИПЦ raw2015'!$1:$1048576, MATCH($J32,'ИПЦ raw2015'!$A:$A,0),MATCH(MoM!O$1,'ИПЦ raw2015'!$1:$1,0)) -> 102.75 | P32: =INDEX('ИПЦ raw2015'!$1:$1048576, MATCH($J32,'ИПЦ raw2015'!$A:$A,0),MATCH(MoM!P$1,'ИПЦ raw2015'!$1:$1,0)) -> 101.46 | Q32: =INDEX('ИПЦ raw2015'!$1:$1048576, MATCH($J32,'ИПЦ raw2015'!$A:$A,0),MATCH(MoM!Q$1,'ИПЦ raw2015'!$1:$1,0)) -> 100.37 | R32: =INDEX('ИПЦ raw2015'!$1:$1048576, MATCH($J32,'ИПЦ raw2015'!$A:$A,0),MATCH(MoM!R$1,'ИПЦ raw2015'!$1:$1,0)) -> 99.94 | S32: =INDEX('ИПЦ raw2015'!$1:$1048576, MATCH($J32,'ИПЦ raw2015'!$A:$A,0),MATCH(MoM!S$1,'ИПЦ raw2015'!$1:$1,0)) -> 99.91 | T32: =INDEX('ИПЦ raw2015'!$1:$1048576, MATCH($J32,'ИПЦ raw2015'!$A:$A,0),MATCH(MoM!T$1,'ИПЦ raw2015'!$1:$1,0)) -> 100.25 | ... BT32: =INDEX('ИПЦ raw2015'!$1:$1048576, MATCH($J32,'ИПЦ raw2015'!$A:$A,0),MATCH(MoM!BT$1,'ИПЦ raw2015'!$1:$1,0)) -> 100.3
A33: =Веса!A33 -> 1 | B33: =A33 -> 1 | C33: =БИПЦ_НДС!E33 -> 0 | D33: =1-C33 -> 1 | E33: 1 | F33: 0 | G33: 0 | H33: 0 | I33: 0 | J33: Консервы рыбные натуральные и с добавлением масла, 350 г | K33: Консервы рыбные натуральные и с добавлением масла, кг | L33: Консервы рыбные натуральные и с добавлением масла, кг | M33: =INDEX('ИПЦ raw2015'!$1:$1048576, MATCH($J33,'ИПЦ raw2015'!$A:$A,0),MATCH(MoM!M$1,'ИПЦ raw2015'!$1:$1,0)) -> 103.51 | N33: =INDEX('ИПЦ raw2015'!$1:$1048576, MATCH($J33,'ИПЦ raw2015'!$A:$A,0),MATCH(MoM!N$1,'ИПЦ raw2015'!$1:$1,0)) -> 104.42 | O33: =INDEX('ИПЦ raw2015'!$1:$1048576, MATCH($J33,'ИПЦ raw2015'!$A:$A,0),MATCH(MoM!O$1,'ИПЦ raw2015'!$1:$1,0)) -> 103.6 | P33: =INDEX('ИПЦ raw2015'!$1:$1048576, MATCH($J33,'ИПЦ raw2015'!$A:$A,0),MATCH(MoM!P$1,'ИПЦ raw2015'!$1:$1,0)) -> 102.94 | Q33: =INDEX('ИПЦ raw2015'!$1:$1048576, MATCH($J33,'ИПЦ raw2015'!$A:$A,0),MATCH(MoM!Q$1,'ИПЦ raw2015'!$1:$1,0)) -> 101.53 | R33: =INDEX('ИПЦ raw2015'!$1:$1048576, MATCH($J33,'ИПЦ raw2015'!$A:$A,0),MATCH(MoM!R$1,'ИПЦ raw2015'!$1:$1,0)) -> 101.12 | S33: =INDEX('ИПЦ raw2015'!$1:$1048576, MATCH($J33,'ИПЦ raw2015'!$A:$A,0),MATCH(MoM!S$1,'ИПЦ raw2015'!$1:$1,0)) -> 100.89 | T33: =INDEX('ИПЦ raw2015'!$1:$1048576, MATCH($J33,'ИПЦ raw2015'!$A:$A,0),MATCH(MoM!T$1,'ИПЦ raw2015'!$1:$1,0)) -> 100.88 | ... BT33: =INDEX('ИПЦ raw2015'!$1:$1048576, MATCH($J33,'ИПЦ raw2015'!$A:$A,0),MATCH(MoM!BT$1,'ИПЦ raw2015'!$1:$1,0)) -> 100.73
A34: =Веса!A34 -> 1 | B34: =A34 -> 1 | C34: =БИПЦ_НДС!E34 -> 0 | D34: =1-C34 -> 1 | E34: 1 | F34: 0 | G34: 0 | H34: 0 | I34: 0 | J34: Консервы рыбные в томатном соусе, 350 г | K34: Консервы рыбные в томатном соусе, кг | L34: Консервы рыбные в томатном соусе, кг | M34: =INDEX('ИПЦ raw2015'!$1:$1048576, MATCH($J34,'ИПЦ raw2015'!$A:$A,0),MATCH(MoM!M$1,'ИПЦ raw2015'!$1:$1,0)) -> 103.56 | N34: =INDEX('ИПЦ raw2015'!$1:$1048576, MATCH($J34,'ИПЦ raw2015'!$A:$A,0),MATCH(MoM!N$1,'ИПЦ raw2015'!$1:$1,0)) -> 103.16 | O34: =INDEX('ИПЦ raw2015'!$1:$1048576, MATCH($J34,'ИПЦ raw2015'!$A:$A,0),MATCH(MoM!O$1,'ИПЦ raw2015'!$1:$1,0)) -> 102.93 | P34: =INDEX('ИПЦ raw2015'!$1:$1048576, MATCH($J34,'ИПЦ raw2015'!$A:$A,0),MATCH(MoM!P$1,'ИПЦ raw2015'!$1:$1,0)) -> 102.52 | Q34: =INDEX('ИПЦ raw2015'!$1:$1048576, MATCH($J34,'ИПЦ raw2015'!$A:$A,0),MATCH(MoM!Q$1,'ИПЦ raw2015'!$1:$1,0)) -> 101.23 | R34: =INDEX('ИПЦ raw2015'!$1:$1048576, MATCH($J34,'ИПЦ raw2015'!$A:$A,0),MATCH(MoM!R$1,'ИПЦ raw2015'!$1:$1,0)) -> 100.82 | S34: =INDEX('ИПЦ raw2015'!$1:$1048576, MATCH($J34,'ИПЦ raw2015'!$A:$A,0),MATCH(MoM!S$1,'ИПЦ raw2015'!$1:$1,0)) -> 100.94 | T34: =INDEX('ИПЦ raw2015'!$1:$1048576, MATCH($J34,'ИПЦ raw2015'!$A:$A,0),MATCH(MoM!T$1,'ИПЦ raw2015'!$1:$1,0)) -> 100.75 | ... BT34: =INDEX('ИПЦ raw2015'!$1:$1048576, MATCH($J34,'ИПЦ raw2015'!$A:$A,0),MATCH(MoM!BT$1,'ИПЦ raw2015'!$1:$1,0)) -> 101.02
A35: =Веса!A35 -> 1 | B35: =A35 -> 1 | C35: =БИПЦ_НДС!E35 -> 0 | D35: =1-C35 -> 1 | E35: 1 | F35: 0 | G35: 0 | H35: 0 | I35: 0 | J35: =L35 -> Масло сливочное, кг | K35: Масло сливочное, кг | L35: Масло сливочное, кг | M35: =INDEX('ИПЦ raw2015'!$1:$1048576, MATCH($J35,'ИПЦ raw2015'!$A:$A,0),MATCH(MoM!M$1,'ИПЦ raw2015'!$1:$1,0)) -> 103.78 | N35: =INDEX('ИПЦ raw2015'!$1:$1048576, MATCH($J35,'ИПЦ raw2015'!$A:$A,0),MATCH(MoM!N$1,'ИПЦ raw2015'!$1:$1,0)) -> 103.11 | O35: =INDEX('ИПЦ raw2015'!$1:$1048576, MATCH($J35,'ИПЦ raw2015'!$A:$A,0),MATCH(MoM!O$1,'ИПЦ raw2015'!$1:$1,0)) -> 101.02 | P35: =INDEX('ИПЦ raw2015'!$1:$1048576, MATCH($J35,'ИПЦ raw2015'!$A:$A,0),MATCH(MoM!P$1,'ИПЦ raw2015'!$1:$1,0)) -> 99.95 | Q35: =INDEX('ИПЦ raw2015'!$1:$1048576, MATCH($J35,'ИПЦ raw2015'!$A:$A,0),MATCH(MoM!Q$1,'ИПЦ raw2015'!$1:$1,0)) -> 99.96 | R35: =INDEX('ИПЦ raw2015'!$1:$1048576, MATCH($J35,'ИПЦ raw2015'!$A:$A,0),MATCH(MoM!R$1,'ИПЦ raw2015'!$1:$1,0)) -> 99.39 | S35: =INDEX('ИПЦ raw2015'!$1:$1048576, MATCH($J35,'ИПЦ raw2015'!$A:$A,0),MATCH(MoM!S$1,'ИПЦ raw2015'!$1:$1,0)) -> 99.85 | T35: =INDEX('ИПЦ raw2015'!$1:$1048576, MATCH($J35,'ИПЦ raw2015'!$A:$A,0),MATCH(MoM!T$1,'ИПЦ raw2015'!$1:$1,0)) -> 100.14 | ... BT35: =INDEX('ИПЦ raw2015'!$1:$1048576, MATCH($J35,'ИПЦ raw2015'!$A:$A,0),MATCH(MoM!BT$1,'ИПЦ raw2015'!$1:$1,0)) -> 100.89
A36: =Веса!A36 -> 1 | B36: =A36 -> 1 | C36: =БИПЦ_НДС!E36 -> 0 | D36: =1-C36 -> 1 | E36: 1 | F36: 0 | G36: 0 | H36: 0 | I36: 0 | J36: Масло подсолнечное, кг | K36: Масло подсолнечное, л | L36: Масло подсолнечное, л | M36: =INDEX('ИПЦ raw2015'!$1:$1048576, MATCH($J36,'ИПЦ raw2015'!$A:$A,0),MATCH(MoM!M$1,'ИПЦ raw2015'!$1:$1,0)) -> 107.62 | N36: =INDEX('ИПЦ raw2015'!$1:$1048576, MATCH($J36,'ИПЦ raw2015'!$A:$A,0),MATCH(MoM!N$1,'ИПЦ raw2015'!$1:$1,0)) -> 105.62 | O36: =INDEX('ИПЦ raw2015'!$1:$1048576, MATCH($J36,'ИПЦ raw2015'!$A:$A,0),MATCH(MoM!O$1,'ИПЦ raw2015'!$1:$1,0)) -> 103.42 | P36: =INDEX('ИПЦ raw2015'!$1:$1048576, MATCH($J36,'ИПЦ raw2015'!$A:$A,0),MATCH(MoM!P$1,'ИПЦ raw2015'!$1:$1,0)) -> 101.32 | Q36: =INDEX('ИПЦ raw2015'!$1:$1048576, MATCH($J36,'ИПЦ raw2015'!$A:$A,0),MATCH(MoM!Q$1,'ИПЦ raw2015'!$1:$1,0)) -> 100.06 | R36: =INDEX('ИПЦ raw2015'!$1:$1048576, MATCH($J36,'ИПЦ raw2015'!$A:$A,0),MATCH(MoM!R$1,'ИПЦ raw2015'!$1:$1,0)) -> 99.77 | S36: =INDEX('ИПЦ raw2015'!$1:$1048576, MATCH($J36,'ИПЦ raw2015'!$A:$A,0),MATCH(MoM!S$1,'ИПЦ raw2015'!$1:$1,0)) -> 100.02 | T36: =INDEX('ИПЦ raw2015'!$1:$1048576, MATCH($J36,'ИПЦ raw2015'!$A:$A,0),MATCH(MoM!T$1,'ИПЦ raw2015'!$1:$1,0)) -> 101.52 | ... BT36: =INDEX('ИПЦ raw2015'!$1:$1048576, MATCH($J36,'ИПЦ raw2015'!$A:$A,0),MATCH(MoM!BT$1,'ИПЦ raw2015'!$1:$1,0)) -> 100.05
A37: =Веса!A37 -> 1 | B37: =A37 -> 1 | C37: =БИПЦ_НДС!E37 -> 0 | D37: =1-C37 -> 1 | E37: 1 | F37: 0 | G37: 0 | H37: 0 | I37: 0 | J37: =L37 -> Масло оливковое, л | K37: Масло оливковое, л | L37: Масло оливковое, л | M37: =INDEX('ИПЦ raw2015'!$1:$1048576, MATCH($J37,'ИПЦ raw2015'!$A:$A,0),MATCH(MoM!M$1,'ИПЦ raw2015'!$1:$1,0)) -> 106.89 | N37: =INDEX('ИПЦ raw2015'!$1:$1048576, MATCH($J37,'ИПЦ raw2015'!$A:$A,0),MATCH(MoM!N$1,'ИПЦ raw2015'!$1:$1,0)) -> 109.57 | O37: =INDEX('ИПЦ raw2015'!$1:$1048576, MATCH($J37,'ИПЦ raw2015'!$A:$A,0),MATCH(MoM!O$1,'ИПЦ raw2015'!$1:$1,0)) -> 105.92 | P37: =INDEX('ИПЦ raw2015'!$1:$1048576, MATCH($J37,'ИПЦ raw2015'!$A:$A,0),MATCH(MoM!P$1,'ИПЦ raw2015'!$1:$1,0)) -> 103.78 | Q37: =INDEX('ИПЦ raw2015'!$1:$1048576, MATCH($J37,'ИПЦ raw2015'!$A:$A,0),MATCH(MoM!Q$1,'ИПЦ raw2015'!$1:$1,0)) -> 100.32 | R37: =INDEX('ИПЦ raw2015'!$1:$1048576, MATCH($J37,'ИПЦ raw2015'!$A:$A,0),MATCH(MoM!R$1,'ИПЦ raw2015'!$1:$1,0)) -> 100.36 | S37: =INDEX('ИПЦ raw2015'!$1:$1048576, MATCH($J37,'ИПЦ raw2015'!$A:$A,0),MATCH(MoM!S$1,'ИПЦ raw2015'!$1:$1,0)) -> 101.05 | T37: =INDEX('ИПЦ raw2015'!$1:$1048576, MATCH($J37,'ИПЦ raw2015'!$A:$A,0),MATCH(MoM!T$1,'ИПЦ raw2015'!$1:$1,0)) -> 100.31 | ... BT37: =INDEX('ИПЦ raw2015'!$1:$1048576, MATCH($J37,'ИПЦ raw2015'!$A:$A,0),MATCH(MoM!BT$1,'ИПЦ raw2015'!$1:$1,0)) -> 99.96
A38: =Веса!A38 -> 1 | B38: =A38 -> 1 | C38: =БИПЦ_НДС!E38 -> 0 | D38: =1-C38 -> 1 | E38: 1 | F38: 0 | G38: 0 | H38: 0 | I38: 0 | J38: =L38 -> Маргарин, кг | K38: Маргарин, кг | L38: Маргарин, кг | M38: =INDEX('ИПЦ raw2015'!$1:$1048576, MATCH($J38,'ИПЦ raw2015'!$A:$A,0),MATCH(MoM!M$1,'ИПЦ raw2015'!$1:$1,0)) -> 106.87 | N38: =INDEX('ИПЦ raw2015'!$1:$1048576, MATCH($J38,'ИПЦ raw2015'!$A:$A,0),MATCH(MoM!N$1,'ИПЦ raw2015'!$1:$1,0)) -> 106.39 | O38: =INDEX('ИПЦ raw2015'!$1:$1048576, MATCH($J38,'ИПЦ raw2015'!$A:$A,0),MATCH(MoM!O$1,'ИПЦ raw2015'!$1:$1,0)) -> 103.02 | P38: =INDEX('ИПЦ raw2015'!$1:$1048576, MATCH($J38,'ИПЦ raw2015'!$A:$A,0),MATCH(MoM!P$1,'ИПЦ raw2015'!$1:$1,0)) -> 102.02 | Q38: =INDEX('ИПЦ raw2015'!$1:$1048576, MATCH($J38,'ИПЦ raw2015'!$A:$A,0),MATCH(MoM!Q$1,'ИПЦ raw2015'!$1:$1,0)) -> 101.34 | R38: =INDEX('ИПЦ raw2015'!$1:$1048576, MATCH($J38,'ИПЦ raw2015'!$A:$A,0),MATCH(MoM!R$1,'ИПЦ raw2015'!$1:$1,0)) -> 100.78 | S38: =INDEX('ИПЦ raw2015'!$1:$1048576, MATCH($J38,'ИПЦ raw2015'!$A:$A,0),MATCH(MoM!S$1,'ИПЦ raw2015'!$1:$1,0)) -> 100.6 | T38: =INDEX('ИПЦ raw2015'!$1:$1048576, MATCH($J38,'ИПЦ raw2015'!$A:$A,0),MATCH(MoM!T$1,'ИПЦ raw2015'!$1:$1,0)) -> 100.66 | ... BT38: =INDEX('ИПЦ raw2015'!$1:$1048576, MATCH($J38,'ИПЦ raw2015'!$A:$A,0),MATCH(MoM!BT$1,'ИПЦ raw2015'!$1:$1,0)) -> 100.54
A39: =Веса!A39 -> 1 | B39: =A39 -> 1 | C39: =БИПЦ_НДС!E39 -> 0 | D39: =1-C39 -> 1 | E39: 1 | F39: 0 | G39: 0 | H39: 0 | I39: 0 | J39: =L39 -> Молоко питьевое цельное пастеризованное 2,5-3,2% жирности, л | K39: Молоко питьевое цельное пастеризованное 2,5-3,2% жирности, л | L39: Молоко питьевое цельное пастеризованное 2,5-3,2% жирности, л | M39: =INDEX('ИПЦ raw2015'!$1:$1048576, MATCH($J39,'ИПЦ raw2015'!$A:$A,0),MATCH(MoM!M$1,'ИПЦ raw2015'!$1:$1,0)) -> 102.32 | N39: =INDEX('ИПЦ raw2015'!$1:$1048576, MATCH($J39,'ИПЦ raw2015'!$A:$A,0),MATCH(MoM!N$1,'ИПЦ raw2015'!$1:$1,0)) -> 102.19 | O39: =INDEX('ИПЦ raw2015'!$1:$1048576, MATCH($J39,'ИПЦ raw2015'!$A:$A,0),MATCH(MoM!O$1,'ИПЦ raw2015'!$1:$1,0)) -> 100.84 | P39: =INDEX('ИПЦ raw2015'!$1:$1048576, MATCH($J39,'ИПЦ raw2015'!$A:$A,0),MATCH(MoM!P$1,'ИПЦ raw2015'!$1:$1,0)) -> 100.18 | Q39: =INDEX('ИПЦ raw2015'!$1:$1048576, MATCH($J39,'ИПЦ raw2015'!$A:$A,0),MATCH(MoM!Q$1,'ИПЦ raw2015'!$1:$1,0)) -> 99.62 | R39: =INDEX('ИПЦ raw2015'!$1:$1048576, MATCH($J39,'ИПЦ raw2015'!$A:$A,0),MATCH(MoM!R$1,'ИПЦ raw2015'!$1:$1,0)) -> 99.49 | S39: =INDEX('ИПЦ raw2015'!$1:$1048576, MATCH($J39,'ИПЦ raw2015'!$A:$A,0),MATCH(MoM!S$1,'ИПЦ raw2015'!$1:$1,0)) -> 100.12 | T39: =INDEX('ИПЦ raw2015'!$1:$1048576, MATCH($J39,'ИПЦ raw2015'!$A:$A,0),MATCH(MoM!T$1,'ИПЦ raw2015'!$1:$1,0)) -> 100.28 | ... BT39: =INDEX('ИПЦ raw2015'!$1:$1048576, MATCH($J39,'ИПЦ raw2015'!$A:$A,0),MATCH(MoM!BT$1,'ИПЦ raw2015'!$1:$1,0)) -> 100.82
A40: =Веса!A40 -> 0 | B40: =A40 -> 0 | C40: =БИПЦ_НДС!E40 -> 0 | D40: =1-C40 -> 1 | E40: 1 | F40: 0 | G40: 0 | H40: 0 | I40: 0 | J40: =L40 -> Молоко питьевое цельное ультрапастеризованное 2,5-3,2% жирности, л | K40: Молоко питьевое цельное ультрапастеризованное 2,5-3,2% жирности, л | L40: Молоко питьевое цельное ультрапастеризованное 2,5-3,2% жирности, л | M40: 0 | N40: 0 | O40: 0 | P40: 0 | Q40: 0 | R40: 0 | S40: 0 | T40: 0 | U40: 0 | V40: 0 | W40: 0 | X40: 0 | Y40: 0 | Z40: 0 | AA40: 0 | AB40: 0 | AC40: 0 | AD40: 0 | AE40: 0 | AF40: 0 | AG40: 0 | AH40: 0 | AI40: 0 | AJ40: 0 | AK40: 0 | AL40: 0 | AM40: 0 | AN40: 0 | AO40: 0 | AP40: 0 | AQ40: 0 | AR40: 0 | AS40: 0 | AT40: 0 | AU40: 0 | AV40: 0 | AW40: 0 | AX40: 0 | AY40: 0 | AZ40: 0 | BA40: 0 | BB40: 0 | BC40: 0 | BD40: 0 | BE40: 0 | BF40: 0 | BG40: 0 | BH40: 0 | BI40: 0 | BJ40: 0 | BK40: 0 | BL40: 0 | BM40: 0 | BN40: 0 | BO40: 0 | BP40: 0 | BQ40: 0 | BR40: 0 | BS40: 0 | BT40: 0
A41: =Веса!A41 -> 0 | B41: =A41 -> 0 | C41: =БИПЦ_НДС!E41 -> 0 | D41: =1-C41 -> 1 | E41: 1 | F41: 0 | G41: 0 | H41: 0 | I41: 0 | J41: =L41 -> Молоко питьевое цельное пастеризованное более 3,2% жирности, л | K41: Молоко питьевое цельное пастеризованное более 3,2% жирности, л | L41: Молоко питьевое цельное пастеризованное более 3,2% жирности, л | M41: 0 | N41: 0 | O41: 0 | P41: 0 | Q41: 0 | R41: 0 | S41: 0 | T41: 0 | U41: 0 | V41: 0 | W41: 0 | X41: 0 | Y41: 0 | Z41: 0 | AA41: 0 | AB41: 0 | AC41: 0 | AD41: 0 | AE41: 0 | AF41: 0 | AG41: 0 | AH41: 0 | AI41: 0 | AJ41: 0 | AK41: 0 | AL41: 0 | AM41: 0 | AN41: 0 | AO41: 0 | AP41: 0 | AQ41: 0 | AR41: 0 | AS41: 0 | AT41: 0 | AU41: 0 | AV41: 0 | AW41: 0 | AX41: 0 | AY41: 0 | AZ41: 0 | BA41: 0 | BB41: 0 | BC41: 0 | BD41: 0 | BE41: 0 | BF41: 0 | BG41: 0 | BH41: 0 | BI41: 0 | BJ41: 0 | BK41: 0 | BL41: 0 | BM41: 0 | BN41: 0 | BO41: 0 | BP41: 0 | BQ41: 0 | BR41: 0 | BS41: 0 | BT41: 0
A42: =Веса!A42 -> 1 | B42: =A42 -> 1 | C42: =БИПЦ_НДС!E42 -> 0 | D42: =1-C42 -> 1 | E42: 1 | F42: 0 | G42: 0 | H42: 0 | I42: 0 | J42: =L42 -> Сметана, кг | K42: Сметана, кг | L42: Сметана, кг | M42: =INDEX('ИПЦ raw2015'!$1:$1048576, MATCH($J42,'ИПЦ raw2015'!$A:$A,0),MATCH(MoM!M$1,'ИПЦ raw2015'!$1:$1,0)) -> 102.52 | N42: =INDEX('ИПЦ raw2015'!$1:$1048576, MATCH($J42,'ИПЦ raw2015'!$A:$A,0),MATCH(MoM!N$1,'ИПЦ raw2015'!$1:$1,0)) -> 102.56 | O42: =INDEX('ИПЦ raw2015'!$1:$1048576, MATCH($J42,'ИПЦ raw2015'!$A:$A,0),MATCH(MoM!O$1,'ИПЦ raw2015'!$1:$1,0)) -> 101.01 | P42: =INDEX('ИПЦ raw2015'!$1:$1048576, MATCH($J42,'ИПЦ raw2015'!$A:$A,0),MATCH(MoM!P$1,'ИПЦ raw2015'!$1:$1,0)) -> 100.46 | Q42: =INDEX('ИПЦ raw2015'!$1:$1048576, MATCH($J42,'ИПЦ raw2015'!$A:$A,0),MATCH(MoM!Q$1,'ИПЦ raw2015'!$1:$1,0)) -> 100.76 | R42: =INDEX('ИПЦ raw2015'!$1:$1048576, MATCH($J42,'ИПЦ raw2015'!$A:$A,0),MATCH(MoM!R$1,'ИПЦ raw2015'!$1:$1,0)) -> 100.22 | S42: =INDEX('ИПЦ raw2015'!$1:$1048576, MATCH($J42,'ИПЦ raw2015'!$A:$A,0),MATCH(MoM!S$1,'ИПЦ raw2015'!$1:$1,0)) -> 100.2 | T42: =INDEX('ИПЦ raw2015'!$1:$1048576, MATCH($J42,'ИПЦ raw2015'!$A:$A,0),MATCH(MoM!T$1,'ИПЦ raw2015'!$1:$1,0)) -> 100.35 | ... BT42: =INDEX('ИПЦ raw2015'!$1:$1048576, MATCH($J42,'ИПЦ raw2015'!$A:$A,0),MATCH(MoM!BT$1,'ИПЦ raw2015'!$1:$1,0)) -> 100.51
A43: =Веса!A43 -> 1 | B43: =A43 -> 1 | C43: =БИПЦ_НДС!E43 -> 0 | D43: =1-C43 -> 1 | E43: 1 | F43: 0 | G43: 0 | H43: 0 | I43: 0 | J43: =L43 -> Кисломолочные продукты, кг | K43: Кисломолочные продукты, кг | L43: Кисломолочные продукты, кг | M43: =INDEX('ИПЦ raw2015'!$1:$1048576, MATCH($J43,'ИПЦ raw2015'!$A:$A,0),MATCH(MoM!M$1,'ИПЦ raw2015'!$1:$1,0)) -> 102 | N43: =INDEX('ИПЦ raw2015'!$1:$1048576, MATCH($J43,'ИПЦ raw2015'!$A:$A,0),MATCH(MoM!N$1,'ИПЦ raw2015'!$1:$1,0)) -> 102.31 | O43: =INDEX('ИПЦ raw2015'!$1:$1048576, MATCH($J43,'ИПЦ raw2015'!$A:$A,0),MATCH(MoM!O$1,'ИПЦ raw2015'!$1:$1,0)) -> 101.05 | P43: =INDEX('ИПЦ raw2015'!$1:$1048576, MATCH($J43,'ИПЦ raw2015'!$A:$A,0),MATCH(MoM!P$1,'ИПЦ raw2015'!$1:$1,0)) -> 100.6 | Q43: =INDEX('ИПЦ raw2015'!$1:$1048576, MATCH($J43,'ИПЦ raw2015'!$A:$A,0),MATCH(MoM!Q$1,'ИПЦ raw2015'!$1:$1,0)) -> 100.47 | R43: =INDEX('ИПЦ raw2015'!$1:$1048576, MATCH($J43,'ИПЦ raw2015'!$A:$A,0),MATCH(MoM!R$1,'ИПЦ raw2015'!$1:$1,0)) -> 100.15 | S43: =INDEX('ИПЦ raw2015'!$1:$1048576, MATCH($J43,'ИПЦ raw2015'!$A:$A,0),MATCH(MoM!S$1,'ИПЦ raw2015'!$1:$1,0)) -> 99.93 | T43: =INDEX('ИПЦ raw2015'!$1:$1048576, MATCH($J43,'ИПЦ raw2015'!$A:$A,0),MATCH(MoM!T$1,'ИПЦ raw2015'!$1:$1,0)) -> 99.99 | ... BT43: =INDEX('ИПЦ raw2015'!$1:$1048576, MATCH($J43,'ИПЦ raw2015'!$A:$A,0),MATCH(MoM!BT$1,'ИПЦ raw2015'!$1:$1,0)) -> 100.43
A44: =Веса!A44 -> 1 | B44: =A44 -> 1 | C44: =БИПЦ_НДС!E44 -> 0 | D44: =1-C44 -> 1 | E44: 1 | F44: 0 | G44: 0 | H44: 0 | I44: 0 | J44: Йогурт, 125 г | K44: Йогурт, кг | L44: Йогурт, кг | M44: =INDEX('ИПЦ raw2015'!$1:$1048576, MATCH($J44,'ИПЦ raw2015'!$A:$A,0),MATCH(MoM!M$1,'ИПЦ raw2015'!$1:$1,0)) -> 101.64 | N44: =INDEX('ИПЦ raw2015'!$1:$1048576, MATCH($J44,'ИПЦ raw2015'!$A:$A,0),MATCH(MoM!N$1,'ИПЦ raw2015'!$1:$1,0)) -> 103.91 | O44: =INDEX('ИПЦ raw2015'!$1:$1048576, MATCH($J44,'ИПЦ raw2015'!$A:$A,0),MATCH(MoM!O$1,'ИПЦ raw2015'!$1:$1,0)) -> 101.99 | P44: =INDEX('ИПЦ raw2015'!$1:$1048576, MATCH($J44,'ИПЦ raw2015'!$A:$A,0),MATCH(MoM!P$1,'ИПЦ raw2015'!$1:$1,0)) -> 101.78 | Q44: =INDEX('ИПЦ raw2015'!$1:$1048576, MATCH($J44,'ИПЦ raw2015'!$A:$A,0),MATCH(MoM!Q$1,'ИПЦ raw2015'!$1:$1,0)) -> 101.59 | R44: =INDEX('ИПЦ raw2015'!$1:$1048576, MATCH($J44,'ИПЦ raw2015'!$A:$A,0),MATCH(MoM!R$1,'ИПЦ raw2015'!$1:$1,0)) -> 100.63 | S44: =INDEX('ИПЦ raw2015'!$1:$1048576, MATCH($J44,'ИПЦ raw2015'!$A:$A,0),MATCH(MoM!S$1,'ИПЦ raw2015'!$1:$1,0)) -> 100.27 | T44: =INDEX('ИПЦ raw2015'!$1:$1048576, MATCH($J44,'ИПЦ raw2015'!$A:$A,0),MATCH(MoM!T$1,'ИПЦ raw2015'!$1:$1,0)) -> 100.3 | ... BT44: =INDEX('ИПЦ raw2015'!$1:$1048576, MATCH($J44,'ИПЦ raw2015'!$A:$A,0),MATCH(MoM!BT$1,'ИПЦ raw2015'!$1:$1,0)) -> 100.47
A45: =Веса!A45 -> 0 | B45: =A45 -> 0 | C45: =БИПЦ_НДС!E45 -> 0 | D45: =1-C45 -> 1 | E45: 1 | F45: 0 | G45: 0 | H45: 0 | I45: 0 | J45: =L45 -> Сливки питьевые, л | K45: Сливки питьевые, л | L45: Сливки питьевые, л | M45: 0 | N45: 0 | O45: 0 | P45: 0 | Q45: 0 | R45: 0 | S45: 0 | T45: 0 | U45: 0 | V45: 0 | W45: 0 | X45: 0 | Y45: 0 | Z45: 0 | AA45: 0 | AB45: 0 | AC45: 0 | AD45: 0 | AE45: 0 | AF45: 0 | AG45: 0 | AH45: 0 | AI45: 0 | AJ45: 0 | AK45: 0 | AL45: 0 | AM45: 0 | AN45: 0 | AO45: 0 | AP45: 0 | AQ45: 0 | AR45: 0 | AS45: 0 | AT45: 0 | AU45: 0 | AV45: 0 | AW45: 0 | AX45: 0 | AY45: 0 | AZ45: 0 | BA45: 0 | BB45: 0 | BC45: 0 | BD45: 0 | BE45: 0 | BF45: 0 | BG45: 0 | BH45: 0 | BI45: 0 | BJ45: 0 | BK45: 0 | BL45: 0 | BM45: 0 | BN45: 0 | BO45: 0 | BP45: 0 | BQ45: 0 | BR45: 0 | BS45: 0 | BT45: 0
A46: =Веса!A46 -> 1 | B46: =A46 -> 1 | C46: =БИПЦ_НДС!E46 -> 0 | D46: =1-C46 -> 1 | E46: 1 | F46: 0 | G46: 0 | H46: 0 | I46: 0 | J46: Творог | K46: Творог, кг | L46: Творог, кг | M46: =INDEX('ИПЦ raw2015'!$1:$1048576, MATCH($J46,'ИПЦ raw2015'!$A:$A,0),MATCH(MoM!M$1,'ИПЦ raw2015'!$1:$1,0)) -> 102.5 | N46: =INDEX('ИПЦ raw2015'!$1:$1048576, MATCH($J46,'ИПЦ raw2015'!$A:$A,0),MATCH(MoM!N$1,'ИПЦ raw2015'!$1:$1,0)) -> 102.74 | O46: =INDEX('ИПЦ raw2015'!$1:$1048576, MATCH($J46,'ИПЦ raw2015'!$A:$A,0),MATCH(MoM!O$1,'ИПЦ raw2015'!$1:$1,0)) -> 101.34 | P46: =INDEX('ИПЦ raw2015'!$1:$1048576, MATCH($J46,'ИПЦ raw2015'!$A:$A,0),MATCH(MoM!P$1,'ИПЦ raw2015'!$1:$1,0)) -> 100.6 | Q46: =INDEX('ИПЦ raw2015'!$1:$1048576, MATCH($J46,'ИПЦ raw2015'!$A:$A,0),MATCH(MoM!Q$1,'ИПЦ raw2015'!$1:$1,0)) -> 99.97 | R46: =INDEX('ИПЦ raw2015'!$1:$1048576, MATCH($J46,'ИПЦ raw2015'!$A:$A,0),MATCH(MoM!R$1,'ИПЦ raw2015'!$1:$1,0)) -> 99.95 | S46: =INDEX('ИПЦ raw2015'!$1:$1048576, MATCH($J46,'ИПЦ raw2015'!$A:$A,0),MATCH(MoM!S$1,'ИПЦ raw2015'!$1:$1,0)) -> 99.92 | T46: =INDEX('ИПЦ raw2015'!$1:$1048576, MATCH($J46,'ИПЦ raw2015'!$A:$A,0),MATCH(MoM!T$1,'ИПЦ raw2015'!$1:$1,0)) -> 100.11 | ... BT46: =INDEX('ИПЦ raw2015'!$1:$1048576, MATCH($J46,'ИПЦ raw2015'!$A:$A,0),MATCH(MoM!BT$1,'ИПЦ raw2015'!$1:$1,0)) -> 100.54
A47: =Веса!A47 -> 0 | B47: =A47 -> 0 | C47: =БИПЦ_НДС!E47 -> 0 | D47: =1-C47 -> 1 | E47: 1 | F47: 0 | G47: 0 | H47: 0 | I47: 0 | J47: =L47 -> Сырки творожные, глазированные, кг | K47: Сырки творожные, глазированные, кг | L47: Сырки творожные, глазированные, кг | M47: 0 | N47: 0 | O47: 0 | P47: 0 | Q47: 0 | R47: 0 | S47: 0 | T47: 0 | U47: 0 | V47: 0 | W47: 0 | X47: 0 | Y47: 0 | Z47: 0 | AA47: 0 | AB47: 0 | AC47: 0 | AD47: 0 | AE47: 0 | AF47: 0 | AG47: 0 | AH47: 0 | AI47: 0 | AJ47: 0 | AK47: 0 | AL47: 0 | AM47: 0 | AN47: 0 | AO47: 0 | AP47: 0 | AQ47: 0 | AR47: 0 | AS47: 0 | AT47: 0 | AU47: 0 | AV47: 0 | AW47: 0 | AX47: 0 | AY47: 0 | AZ47: 0 | BA47: 0 | BB47: 0 | BC47: 0 | BD47: 0 | BE47: 0 | BF47: 0 | BG47: 0 | BH47: 0 | BI47: 0 | BJ47: 0 | BK47: 0 | BL47: 0 | BM47: 0 | BN47: 0 | BO47: 0 | BP47: 0 | BQ47: 0 | BR47: 0 | BS47: 0 | BT47: 0
A48: =Веса!A48 -> 1 | B48: =A48 -> 1 | C48: =БИПЦ_НДС!E48 -> 0 | D48: =1-C48 -> 1 | E48: 1 | F48: 0 | G48: 0 | H48: 0 | I48: 0 | J48: Молоко сгущенное с сахаром, 400 г | K48: Молоко сгущенное с сахаром, кг | L48: Молоко сгущенное с сахаром, кг | M48: =INDEX('ИПЦ raw2015'!$1:$1048576, MATCH($J48,'ИПЦ raw2015'!$A:$A,0),MATCH(MoM!M$1,'ИПЦ raw2015'!$1:$1,0)) -> 105.16 | N48: =INDEX('ИПЦ raw2015'!$1:$1048576, MATCH($J48,'ИПЦ raw2015'!$A:$A,0),MATCH(MoM!N$1,'ИПЦ raw2015'!$1:$1,0)) -> 105.03 | O48: =INDEX('ИПЦ raw2015'!$1:$1048576, MATCH($J48,'ИПЦ raw2015'!$A:$A,0),MATCH(MoM!O$1,'ИПЦ raw2015'!$1:$1,0)) -> 103.59 | P48: =INDEX('ИПЦ raw2015'!$1:$1048576, MATCH($J48,'ИПЦ raw2015'!$A:$A,0),MATCH(MoM!P$1,'ИПЦ raw2015'!$1:$1,0)) -> 101.4 | Q48: =INDEX('ИПЦ raw2015'!$1:$1048576, MATCH($J48,'ИПЦ raw2015'!$A:$A,0),MATCH(MoM!Q$1,'ИПЦ raw2015'!$1:$1,0)) -> 100.86 | R48: =INDEX('ИПЦ raw2015'!$1:$1048576, MATCH($J48,'ИПЦ raw2015'!$A:$A,0),MATCH(MoM!R$1,'ИПЦ raw2015'!$1:$1,0)) -> 99.98 | S48: =INDEX('ИПЦ raw2015'!$1:$1048576, MATCH($J48,'ИПЦ raw2015'!$A:$A,0),MATCH(MoM!S$1,'ИПЦ raw2015'!$1:$1,0)) -> 100.23 | T48: =INDEX('ИПЦ raw2015'!$1:$1048576, MATCH($J48,'ИПЦ raw2015'!$A:$A,0),MATCH(MoM!T$1,'ИПЦ raw2015'!$1:$1,0)) -> 100.35 | ... BT48: =INDEX('ИПЦ raw2015'!$1:$1048576, MATCH($J48,'ИПЦ raw2015'!$A:$A,0),MATCH(MoM!BT$1,'ИПЦ raw2015'!$1:$1,0)) -> 100.56
A49: =Веса!A49 -> 0 | B49: =A49 -> 0 | C49: =БИПЦ_НДС!E49 -> 0 | D49: =1-C49 -> 1 | E49: 1 | F49: 0 | G49: 0 | H49: 0 | I49: 0 | J49: =L49 -> Молоко для детей, л | K49: Молоко для детей, л | L49: Молоко для детей, л | M49: 0 | N49: 0 | O49: 0 | P49: 0 | Q49: 0 | R49: 0 | S49: 0 | T49: 0 | U49: 0 | V49: 0 | W49: 0 | X49: 0 | Y49: 0 | Z49: 0 | AA49: 0 | AB49: 0 | AC49: 0 | AD49: 0 | AE49: 0 | AF49: 0 | AG49: 0 | AH49: 0 | AI49: 0 | AJ49: 0 | AK49: 0 | AL49: 0 | AM49: 0 | AN49: 0 | AO49: 0 | AP49: 0 | AQ49: 0 | AR49: 0 | AS49: 0 | AT49: 0 | AU49: 0 | AV49: 0 | AW49: 0 | AX49: 0 | AY49: 0 | AZ49: 0 | BA49: 0 | BB49: 0 | BC49: 0 | BD49: 0 | BE49: 0 | BF49: 0 | BG49: 0 | BH49: 0 | BI49: 0 | BJ49: 0 | BK49: 0 | BL49: 0 | BM49: 0 | BN49: 0 | BO49: 0 | BP49: 0 | BQ49: 0 | BR49: 0 | BS49: 0 | BT49: 0
A50: =Веса!A50 -> 0 | B50: =A50 -> 0 | C50: =БИПЦ_НДС!E50 -> 0 | D50: =1-C50 -> 1 | E50: 1 | F50: 0 | G50: 0 | H50: 0 | I50: 0 | J50: =L50 -> Творожок детский, кг | K50: Творожок детский, кг | L50: Творожок детский, кг | M50: 0 | N50: 0 | O50: 0 | P50: 0 | Q50: 0 | R50: 0 | S50: 0 | T50: 0 | U50: 0 | V50: 0 | W50: 0 | X50: 0 | Y50: 0 | Z50: 0 | AA50: 0 | AB50: 0 | AC50: 0 | AD50: 0 | AE50: 0 | AF50: 0 | AG50: 0 | AH50: 0 | AI50: 0 | AJ50: 0 | AK50: 0 | AL50: 0 | AM50: 0 | AN50: 0 | AO50: 0 | AP50: 0 | AQ50: 0 | AR50: 0 | AS50: 0 | AT50: 0 | AU50: 0 | AV50: 0 | AW50: 0 | AX50: 0 | AY50: 0 | AZ50: 0 | BA50: 0 | BB50: 0 | BC50: 0 | BD50: 0 | BE50: 0 | BF50: 0 | BG50: 0 | BH50: 0 | BI50: 0 | BJ50: 0 | BK50: 0 | BL50: 0 | BM50: 0 | BN50: 0 | BO50: 0 | BP50: 0 | BQ50: 0 | BR50: 0 | BS50: 0 | BT50: 0
A51: =Веса!A51 -> 1 | B51: =A51 -> 1 | C51: =БИПЦ_НДС!E51 -> 0 | D51: =1-C51 -> 1 | E51: 1 | F51: 0 | G51: 0 | H51: 0 | I51: 0 | J51: =L51 -> Смеси сухие молочные для детского питания, кг | K51: Смеси сухие молочные для детского питания, кг | L51: Смеси сухие молочные для детского питания, кг | M51: =INDEX('ИПЦ raw2015'!$1:$1048576, MATCH($J51,'ИПЦ raw2015'!$A:$A,0),MATCH(MoM!M$1,'ИПЦ raw2015'!$1:$1,0)) -> 101.09 | N51: =INDEX('ИПЦ raw2015'!$1:$1048576, MATCH($J51,'ИПЦ raw2015'!$A:$A,0),MATCH(MoM!N$1,'ИПЦ raw2015'!$1:$1,0)) -> 104.19 | O51: =INDEX('ИПЦ raw2015'!$1:$1048576, MATCH($J51,'ИПЦ raw2015'!$A:$A,0),MATCH(MoM!O$1,'ИПЦ raw2015'!$1:$1,0)) -> 102.72 | P51: =INDEX('ИПЦ raw2015'!$1:$1048576, MATCH($J51,'ИПЦ raw2015'!$A:$A,0),MATCH(MoM!P$1,'ИПЦ raw2015'!$1:$1,0)) -> 102.91 | Q51: =INDEX('ИПЦ raw2015'!$1:$1048576, MATCH($J51,'ИПЦ raw2015'!$A:$A,0),MATCH(MoM!Q$1,'ИПЦ raw2015'!$1:$1,0)) -> 101.11 | R51: =INDEX('ИПЦ raw2015'!$1:$1048576, MATCH($J51,'ИПЦ raw2015'!$A:$A,0),MATCH(MoM!R$1,'ИПЦ raw2015'!$1:$1,0)) -> 100.75 | S51: =INDEX('ИПЦ raw2015'!$1:$1048576, MATCH($J51,'ИПЦ raw2015'!$A:$A,0),MATCH(MoM!S$1,'ИПЦ raw2015'!$1:$1,0)) -> 101.03 | T51: =INDEX('ИПЦ raw2015'!$1:$1048576, MATCH($J51,'ИПЦ raw2015'!$A:$A,0),MATCH(MoM!T$1,'ИПЦ raw2015'!$1:$1,0)) -> 101 | ... BT51: =INDEX('ИПЦ raw2015'!$1:$1048576, MATCH($J51,'ИПЦ raw2015'!$A:$A,0),MATCH(MoM!BT$1,'ИПЦ raw2015'!$1:$1,0)) -> 100.22
A52: =Веса!A52 -> 1 | B52: =A52 -> 1 | C52: =БИПЦ_НДС!E52 -> 0 | D52: =1-C52 -> 1 | E52: 1 | F52: 0 | G52: 0 | H52: 0 | I52: 0 | J52: =L52 -> Национальные сыры и брынза, кг | K52: Национальные сыры и брынза, кг | L52: Национальные сыры и брынза, кг | M52: =INDEX('ИПЦ raw2015'!$1:$1048576, MATCH($J52,'ИПЦ raw2015'!$A:$A,0),MATCH(MoM!M$1,'ИПЦ raw2015'!$1:$1,0)) -> 103.63 | N52: =INDEX('ИПЦ raw2015'!$1:$1048576, MATCH($J52,'ИПЦ raw2015'!$A:$A,0),MATCH(MoM!N$1,'ИПЦ raw2015'!$1:$1,0)) -> 103.78 | O52: =INDEX('ИПЦ raw2015'!$1:$1048576, MATCH($J52,'ИПЦ raw2015'!$A:$A,0),MATCH(MoM!O$1,'ИПЦ raw2015'!$1:$1,0)) -> 100.68 | P52: =INDEX('ИПЦ raw2015'!$1:$1048576, MATCH($J52,'ИПЦ raw2015'!$A:$A,0),MATCH(MoM!P$1,'ИПЦ raw2015'!$1:$1,0)) -> 97.97 | Q52: =INDEX('ИПЦ raw2015'!$1:$1048576, MATCH($J52,'ИПЦ raw2015'!$A:$A,0),MATCH(MoM!Q$1,'ИПЦ raw2015'!$1:$1,0)) -> 98.38 | R52: =INDEX('ИПЦ raw2015'!$1:$1048576, MATCH($J52,'ИПЦ raw2015'!$A:$A,0),MATCH(MoM!R$1,'ИПЦ raw2015'!$1:$1,0)) -> 99.72 | S52: =INDEX('ИПЦ raw2015'!$1:$1048576, MATCH($J52,'ИПЦ raw2015'!$A:$A,0),MATCH(MoM!S$1,'ИПЦ raw2015'!$1:$1,0)) -> 99.76 | T52: =INDEX('ИПЦ raw2015'!$1:$1048576, MATCH($J52,'ИПЦ raw2015'!$A:$A,0),MATCH(MoM!T$1,'ИПЦ raw2015'!$1:$1,0)) -> 102.06 | ... BT52: =INDEX('ИПЦ raw2015'!$1:$1048576, MATCH($J52,'ИПЦ raw2015'!$A:$A,0),MATCH(MoM!BT$1,'ИПЦ raw2015'!$1:$1,0)) -> 100.58
A53: =Веса!A53 -> 1 | B53: =A53 -> 1 | C53: =БИПЦ_НДС!E53 -> 1 | D53: =1-C53 -> 0 | E53: 1 | F53: 0 | G53: 0 | H53: 0 | I53: 0 | J53: =L53 -> Овощи натуральные консервированные, маринованные, кг | K53: Овощи натуральные консервированные, маринованные, кг | L53: Овощи натуральные консервированные, маринованные, кг | M53: =INDEX('ИПЦ raw2015'!$1:$1048576, MATCH($J53,'ИПЦ raw2015'!$A:$A,0),MATCH(MoM!M$1,'ИПЦ raw2015'!$1:$1,0)) -> 105.27 | N53: =INDEX('ИПЦ raw2015'!$1:$1048576, MATCH($J53,'ИПЦ raw2015'!$A:$A,0),MATCH(MoM!N$1,'ИПЦ raw2015'!$1:$1,0)) -> 105.62 | O53: =INDEX('ИПЦ raw2015'!$1:$1048576, MATCH($J53,'ИПЦ raw2015'!$A:$A,0),MATCH(MoM!O$1,'ИПЦ raw2015'!$1:$1,0)) -> 103.2 | P53: =INDEX('ИПЦ raw2015'!$1:$1048576, MATCH($J53,'ИПЦ raw2015'!$A:$A,0),MATCH(MoM!P$1,'ИПЦ raw2015'!$1:$1,0)) -> 102.35 | Q53: =INDEX('ИПЦ raw2015'!$1:$1048576, MATCH($J53,'ИПЦ raw2015'!$A:$A,0),MATCH(MoM!Q$1,'ИПЦ raw2015'!$1:$1,0)) -> 101.88 | R53: =INDEX('ИПЦ raw2015'!$1:$1048576, MATCH($J53,'ИПЦ raw2015'!$A:$A,0),MATCH(MoM!R$1,'ИПЦ raw2015'!$1:$1,0)) -> 100.86 | S53: =INDEX('ИПЦ raw2015'!$1:$1048576, MATCH($J53,'ИПЦ raw2015'!$A:$A,0),MATCH(MoM!S$1,'ИПЦ raw2015'!$1:$1,0)) -> 100.98 | T53: =INDEX('ИПЦ raw2015'!$1:$1048576, MATCH($J53,'ИПЦ raw2015'!$A:$A,0),MATCH(MoM!T$1,'ИПЦ raw2015'!$1:$1,0)) -> 101.01 | ... BT53: =INDEX('ИПЦ raw2015'!$1:$1048576, MATCH($J53,'ИПЦ raw2015'!$A:$A,0),MATCH(MoM!BT$1,'ИПЦ raw2015'!$1:$1,0)) -> 100.67
A54: =Веса!A54 -> 0 | B54: =A54 -> 0 | C54: =БИПЦ_НДС!E54 -> 1 | D54: =1-C54 -> 0 | E54: 1 | F54: 0 | G54: 0 | H54: 0 | I54: 0 | J54: =L54 -> Горошек зеленый консервированный, кг | K54: Горошек зеленый консервированный, кг | L54: Горошек зеленый консервированный, кг | M54: 0 | N54: 0 | O54: 0 | P54: 0 | Q54: 0 | R54: 0 | S54: 0 | T54: 0 | U54: 0 | V54: 0 | W54: 0 | X54: 0 | Y54: 0 | Z54: 0 | AA54: 0 | AB54: 0 | AC54: 0 | AD54: 0 | AE54: 0 | AF54: 0 | AG54: 0 | AH54: 0 | AI54: 0 | AJ54: 0 | AK54: 0 | AL54: 0 | AM54: 0 | AN54: 0 | AO54: 0 | AP54: 0 | AQ54: 0 | AR54: 0 | AS54: 0 | AT54: 0 | AU54: 0 | AV54: 0 | AW54: 0 | AX54: 0 | AY54: 0 | AZ54: 0 | BA54: 0 | BB54: 0 | BC54: 0 | BD54: 0 | BE54: 0 | BF54: 0 | BG54: 0 | BH54: 0 | BI54: 0 | BJ54: 0 | BK54: 0 | BL54: 0 | BM54: 0 | BN54: 0 | BO54: 0 | BP54: 0 | BQ54: 0 | BR54: 0 | BS54: 0 | BT54: 0
A55: =Веса!A55 -> 1 | B55: =A55 -> 1 | C55: =БИПЦ_НДС!E55 -> 0 | D55: =1-C55 -> 1 | E55: 1 | F55: 0 | G55: 0 | H55: 0 | I55: 0 | J55: =L55 -> Консервы овощные для детского питания, кг | K55: Консервы овощные для детского питания, кг | L55: Консервы овощные для детского питания, кг | M55: =INDEX('ИПЦ raw2015'!$1:$1048576, MATCH($J55,'ИПЦ raw2015'!$A:$A,0),MATCH(MoM!M$1,'ИПЦ raw2015'!$1:$1,0)) -> 102.58 | N55: =INDEX('ИПЦ raw2015'!$1:$1048576, MATCH($J55,'ИПЦ raw2015'!$A:$A,0),MATCH(MoM!N$1,'ИПЦ raw2015'!$1:$1,0)) -> 105.28 | O55: =INDEX('ИПЦ raw2015'!$1:$1048576, MATCH($J55,'ИПЦ raw2015'!$A:$A,0),MATCH(MoM!O$1,'ИПЦ raw2015'!$1:$1,0)) -> 102.58 | P55: =INDEX('ИПЦ raw2015'!$1:$1048576, MATCH($J55,'ИПЦ raw2015'!$A:$A,0),MATCH(MoM!P$1,'ИПЦ raw2015'!$1:$1,0)) -> 102.77 | Q55: =INDEX('ИПЦ raw2015'!$1:$1048576, MATCH($J55,'ИПЦ raw2015'!$A:$A,0),MATCH(MoM!Q$1,'ИПЦ raw2015'!$1:$1,0)) -> 102.16 | R55: =INDEX('ИПЦ raw2015'!$1:$1048576, MATCH($J55,'ИПЦ raw2015'!$A:$A,0),MATCH(MoM!R$1,'ИПЦ raw2015'!$1:$1,0)) -> 101.32 | S55: =INDEX('ИПЦ raw2015'!$1:$1048576, MATCH($J55,'ИПЦ raw2015'!$A:$A,0),MATCH(MoM!S$1,'ИПЦ raw2015'!$1:$1,0)) -> 101.06 | T55: =INDEX('ИПЦ raw2015'!$1:$1048576, MATCH($J55,'ИПЦ raw2015'!$A:$A,0),MATCH(MoM!T$1,'ИПЦ raw2015'!$1:$1,0)) -> 101.01 | ... BT55: =INDEX('ИПЦ raw2015'!$1:$1048576, MATCH($J55,'ИПЦ raw2015'!$A:$A,0),MATCH(MoM!BT$1,'ИПЦ raw2015'!$1:$1,0)) -> 100.17
A56: =Веса!A56 -> 1 | B56: =A56 -> 1 | C56: =БИПЦ_НДС!E56 -> 1 | D56: =1-C56 -> 0 | E56: 1 | F56: 0 | G56: 0 | H56: 0 | I56: 0 | J56: =L56 -> Консервы томатные, кг | K56: Консервы томатные, кг | L56: Консервы томатные, кг | M56: =INDEX('ИПЦ raw2015'!$1:$1048576, MATCH($J56,'ИПЦ raw2015'!$A:$A,0),MATCH(MoM!M$1,'ИПЦ raw2015'!$1:$1,0)) -> 105.11 | N56: =INDEX('ИПЦ raw2015'!$1:$1048576, MATCH($J56,'ИПЦ raw2015'!$A:$A,0),MATCH(MoM!N$1,'ИПЦ raw2015'!$1:$1,0)) -> 105.26 | O56: =INDEX('ИПЦ raw2015'!$1:$1048576, MATCH($J56,'ИПЦ raw2015'!$A:$A,0),MATCH(MoM!O$1,'ИПЦ raw2015'!$1:$1,0)) -> 104.69 | P56: =INDEX('ИПЦ raw2015'!$1:$1048576, MATCH($J56,'ИПЦ raw2015'!$A:$A,0),MATCH(MoM!P$1,'ИПЦ raw2015'!$1:$1,0)) -> 102.49 | Q56: =INDEX('ИПЦ raw2015'!$1:$1048576, MATCH($J56,'ИПЦ raw2015'!$A:$A,0),MATCH(MoM!Q$1,'ИПЦ raw2015'!$1:$1,0)) -> 101.29 | R56: =INDEX('ИПЦ raw2015'!$1:$1048576, MATCH($J56,'ИПЦ raw2015'!$A:$A,0),MATCH(MoM!R$1,'ИПЦ raw2015'!$1:$1,0)) -> 100.59 | S56: =INDEX('ИПЦ raw2015'!$1:$1048576, MATCH($J56,'ИПЦ raw2015'!$A:$A,0),MATCH(MoM!S$1,'ИПЦ raw2015'!$1:$1,0)) -> 100.43 | T56: =INDEX('ИПЦ raw2015'!$1:$1048576, MATCH($J56,'ИПЦ raw2015'!$A:$A,0),MATCH(MoM!T$1,'ИПЦ raw2015'!$1:$1,0)) -> 100.5 | ... BT56: =INDEX('ИПЦ raw2015'!$1:$1048576, MATCH($J56,'ИПЦ raw2015'!$A:$A,0),MATCH(MoM!BT$1,'ИПЦ raw2015'!$1:$1,0)) -> 100.37
A57: =Веса!A57 -> 1 | B57: =A57 -> 1 | C57: =БИПЦ_НДС!E57 -> 0 | D57: =1-C57 -> 1 | E57: 1 | F57: 0 | G57: 0 | H57: 0 | I57: 0 | J57: =L57 -> Соки фруктовые, л | K57: Соки фруктовые, л | L57: Соки фруктовые, л | M57: =INDEX('ИПЦ raw2015'!$1:$1048576, MATCH($J57,'ИПЦ raw2015'!$A:$A,0),MATCH(MoM!M$1,'ИПЦ raw2015'!$1:$1,0)) -> 101.61 | N57: =INDEX('ИПЦ raw2015'!$1:$1048576, MATCH($J57,'ИПЦ raw2015'!$A:$A,0),MATCH(MoM!N$1,'ИПЦ raw2015'!$1:$1,0)) -> 105.47 | O57: =INDEX('ИПЦ raw2015'!$1:$1048576, MATCH($J57,'ИПЦ raw2015'!$A:$A,0),MATCH(MoM!O$1,'ИПЦ raw2015'!$1:$1,0)) -> 103.31 | P57: =INDEX('ИПЦ raw2015'!$1:$1048576, MATCH($J57,'ИПЦ raw2015'!$A:$A,0),MATCH(MoM!P$1,'ИПЦ raw2015'!$1:$1,0)) -> 101.58 | Q57: =INDEX('ИПЦ raw2015'!$1:$1048576, MATCH($J57,'ИПЦ raw2015'!$A:$A,0),MATCH(MoM!Q$1,'ИПЦ raw2015'!$1:$1,0)) -> 100.5 | R57: =INDEX('ИПЦ raw2015'!$1:$1048576, MATCH($J57,'ИПЦ raw2015'!$A:$A,0),MATCH(MoM!R$1,'ИПЦ raw2015'!$1:$1,0)) -> 100.88 | S57: =INDEX('ИПЦ raw2015'!$1:$1048576, MATCH($J57,'ИПЦ raw2015'!$A:$A,0),MATCH(MoM!S$1,'ИПЦ raw2015'!$1:$1,0)) -> 100.34 | T57: =INDEX('ИПЦ raw2015'!$1:$1048576, MATCH($J57,'ИПЦ raw2015'!$A:$A,0),MATCH(MoM!T$1,'ИПЦ raw2015'!$1:$1,0)) -> 99.98 | ... BT57: =INDEX('ИПЦ raw2015'!$1:$1048576, MATCH($J57,'ИПЦ raw2015'!$A:$A,0),MATCH(MoM!BT$1,'ИПЦ raw2015'!$1:$1,0)) -> 100.47
A58: =Веса!A58 -> 1 | B58: =A58 -> 1 | C58: =БИПЦ_НДС!E58 -> 0 | D58: =1-C58 -> 1 | E58: 1 | F58: 0 | G58: 0 | H58: 0 | I58: 0 | J58: =L58 -> Консервы фруктово-ягодные для детского питания, кг | K58: Консервы фруктово-ягодные для детского питания, кг | L58: Консервы фруктово-ягодные для детского питания, кг | M58: =INDEX('ИПЦ raw2015'!$1:$1048576, MATCH($J58,'ИПЦ raw2015'!$A:$A,0),MATCH(MoM!M$1,'ИПЦ raw2015'!$1:$1,0)) -> 102.57 | N58: =INDEX('ИПЦ raw2015'!$1:$1048576, MATCH($J58,'ИПЦ raw2015'!$A:$A,0),MATCH(MoM!N$1,'ИПЦ raw2015'!$1:$1,0)) -> 104.54 | O58: =INDEX('ИПЦ raw2015'!$1:$1048576, MATCH($J58,'ИПЦ raw2015'!$A:$A,0),MATCH(MoM!O$1,'ИПЦ raw2015'!$1:$1,0)) -> 102.92 | P58: =INDEX('ИПЦ raw2015'!$1:$1048576, MATCH($J58,'ИПЦ raw2015'!$A:$A,0),MATCH(MoM!P$1,'ИПЦ raw2015'!$1:$1,0)) -> 102.7 | Q58: =INDEX('ИПЦ raw2015'!$1:$1048576, MATCH($J58,'ИПЦ raw2015'!$A:$A,0),MATCH(MoM!Q$1,'ИПЦ raw2015'!$1:$1,0)) -> 101.48 | R58: =INDEX('ИПЦ raw2015'!$1:$1048576, MATCH($J58,'ИПЦ raw2015'!$A:$A,0),MATCH(MoM!R$1,'ИПЦ raw2015'!$1:$1,0)) -> 100.8 | S58: =INDEX('ИПЦ raw2015'!$1:$1048576, MATCH($J58,'ИПЦ raw2015'!$A:$A,0),MATCH(MoM!S$1,'ИПЦ raw2015'!$1:$1,0)) -> 100.71 | T58: =INDEX('ИПЦ raw2015'!$1:$1048576, MATCH($J58,'ИПЦ raw2015'!$A:$A,0),MATCH(MoM!T$1,'ИПЦ raw2015'!$1:$1,0)) -> 100.96 | ... BT58: =INDEX('ИПЦ raw2015'!$1:$1048576, MATCH($J58,'ИПЦ raw2015'!$A:$A,0),MATCH(MoM!BT$1,'ИПЦ raw2015'!$1:$1,0)) -> 99.9
A59: =Веса!A59 -> 1 | B59: =A59 -> 1 | C59: =БИПЦ_НДС!E59 -> 1 | D59: =1-C59 -> 0 | E59: 1 | F59: 0 | G59: 0 | H59: 0 | I59: 0 | J59: =L59 -> Зефир, пастила, кг | K59: Зефир, пастила, кг | L59: Зефир, пастила, кг | M59: =INDEX('ИПЦ raw2015'!$1:$1048576, MATCH($J59,'ИПЦ raw2015'!$A:$A,0),MATCH(MoM!M$1,'ИПЦ raw2015'!$1:$1,0)) -> 104.19 | N59: =INDEX('ИПЦ raw2015'!$1:$1048576, MATCH($J59,'ИПЦ raw2015'!$A:$A,0),MATCH(MoM!N$1,'ИПЦ raw2015'!$1:$1,0)) -> 105.07 | O59: =INDEX('ИПЦ raw2015'!$1:$1048576, MATCH($J59,'ИПЦ raw2015'!$A:$A,0),MATCH(MoM!O$1,'ИПЦ raw2015'!$1:$1,0)) -> 102.76 | P59: =INDEX('ИПЦ raw2015'!$1:$1048576, MATCH($J59,'ИПЦ raw2015'!$A:$A,0),MATCH(MoM!P$1,'ИПЦ raw2015'!$1:$1,0)) -> 101.97 | Q59: =INDEX('ИПЦ raw2015'!$1:$1048576, MATCH($J59,'ИПЦ raw2015'!$A:$A,0),MATCH(MoM!Q$1,'ИПЦ raw2015'!$1:$1,0)) -> 100.97 | R59: =INDEX('ИПЦ raw2015'!$1:$1048576, MATCH($J59,'ИПЦ raw2015'!$A:$A,0),MATCH(MoM!R$1,'ИПЦ raw2015'!$1:$1,0)) -> 100.87 | S59: =INDEX('ИПЦ raw2015'!$1:$1048576, MATCH($J59,'ИПЦ raw2015'!$A:$A,0),MATCH(MoM!S$1,'ИПЦ raw2015'!$1:$1,0)) -> 100.36 | T59: =INDEX('ИПЦ raw2015'!$1:$1048576, MATCH($J59,'ИПЦ raw2015'!$A:$A,0),MATCH(MoM!T$1,'ИПЦ raw2015'!$1:$1,0)) -> 100.87 | ... BT59: =INDEX('ИПЦ raw2015'!$1:$1048576, MATCH($J59,'ИПЦ raw2015'!$A:$A,0),MATCH(MoM!BT$1,'ИПЦ raw2015'!$1:$1,0)) -> 100.32
A60: =Веса!A60 -> 1 | B60: =A60 -> 1 | C60: =БИПЦ_НДС!E60 -> 1 | D60: =1-C60 -> 0 | E60: 1 | F60: 0 | G60: 0 | H60: 0 | I60: 0 | J60: =L60 -> Карамель, кг | K60: Карамель, кг | L60: Карамель, кг | M60: =INDEX('ИПЦ raw2015'!$1:$1048576, MATCH($J60,'ИПЦ raw2015'!$A:$A,0),MATCH(MoM!M$1,'ИПЦ raw2015'!$1:$1,0)) -> 103.95 | N60: =INDEX('ИПЦ raw2015'!$1:$1048576, MATCH($J60,'ИПЦ raw2015'!$A:$A,0),MATCH(MoM!N$1,'ИПЦ raw2015'!$1:$1,0)) -> 105.21 | O60: =INDEX('ИПЦ raw2015'!$1:$1048576, MATCH($J60,'ИПЦ raw2015'!$A:$A,0),MATCH(MoM!O$1,'ИПЦ raw2015'!$1:$1,0)) -> 102.5 | P60: =INDEX('ИПЦ raw2015'!$1:$1048576, MATCH($J60,'ИПЦ raw2015'!$A:$A,0),MATCH(MoM!P$1,'ИПЦ raw2015'!$1:$1,0)) -> 101.6 | Q60: =INDEX('ИПЦ raw2015'!$1:$1048576, MATCH($J60,'ИПЦ raw2015'!$A:$A,0),MATCH(MoM!Q$1,'ИПЦ raw2015'!$1:$1,0)) -> 102.57 | R60: =INDEX('ИПЦ raw2015'!$1:$1048576, MATCH($J60,'ИПЦ raw2015'!$A:$A,0),MATCH(MoM!R$1,'ИПЦ raw2015'!$1:$1,0)) -> 101.15 | S60: =INDEX('ИПЦ raw2015'!$1:$1048576, MATCH($J60,'ИПЦ raw2015'!$A:$A,0),MATCH(MoM!S$1,'ИПЦ raw2015'!$1:$1,0)) -> 100.95 | T60: =INDEX('ИПЦ raw2015'!$1:$1048576, MATCH($J60,'ИПЦ raw2015'!$A:$A,0),MATCH(MoM!T$1,'ИПЦ raw2015'!$1:$1,0)) -> 100.73 | ... BT60: =INDEX('ИПЦ raw2015'!$1:$1048576, MATCH($J60,'ИПЦ raw2015'!$A:$A,0),MATCH(MoM!BT$1,'ИПЦ raw2015'!$1:$1,0)) -> 100.21
A61: =Веса!A61 -> 1 | B61: =A61 -> 1 | C61: =БИПЦ_НДС!E61 -> 1 | D61: =1-C61 -> 0 | E61: 1 | F61: 0 | G61: 0 | H61: 0 | I61: 0 | J61: =L61 -> Шоколад, кг | K61: Шоколад, кг | L61: Шоколад, кг | M61: =INDEX('ИПЦ raw2015'!$1:$1048576, MATCH($J61,'ИПЦ raw2015'!$A:$A,0),MATCH(MoM!M$1,'ИПЦ raw2015'!$1:$1,0)) -> 103.06 | N61: =INDEX('ИПЦ raw2015'!$1:$1048576, MATCH($J61,'ИПЦ raw2015'!$A:$A,0),MATCH(MoM!N$1,'ИПЦ raw2015'!$1:$1,0)) -> 105.62 | O61: =INDEX('ИПЦ raw2015'!$1:$1048576, MATCH($J61,'ИПЦ raw2015'!$A:$A,0),MATCH(MoM!O$1,'ИПЦ raw2015'!$1:$1,0)) -> 104.2 | P61: =INDEX('ИПЦ raw2015'!$1:$1048576, MATCH($J61,'ИПЦ raw2015'!$A:$A,0),MATCH(MoM!P$1,'ИПЦ raw2015'!$1:$1,0)) -> 103.65 | Q61: =INDEX('ИПЦ raw2015'!$1:$1048576, MATCH($J61,'ИПЦ raw2015'!$A:$A,0),MATCH(MoM!Q$1,'ИПЦ raw2015'!$1:$1,0)) -> 103.45 | R61: =INDEX('ИПЦ raw2015'!$1:$1048576, MATCH($J61,'ИПЦ raw2015'!$A:$A,0),MATCH(MoM!R$1,'ИПЦ raw2015'!$1:$1,0)) -> 102.5 | S61: =INDEX('ИПЦ raw2015'!$1:$1048576, MATCH($J61,'ИПЦ raw2015'!$A:$A,0),MATCH(MoM!S$1,'ИПЦ raw2015'!$1:$1,0)) -> 101.49 | T61: =INDEX('ИПЦ raw2015'!$1:$1048576, MATCH($J61,'ИПЦ raw2015'!$A:$A,0),MATCH(MoM!T$1,'ИПЦ raw2015'!$1:$1,0)) -> 101.6 | ... BT61: =INDEX('ИПЦ raw2015'!$1:$1048576, MATCH($J61,'ИПЦ raw2015'!$A:$A,0),MATCH(MoM!BT$1,'ИПЦ raw2015'!$1:$1,0)) -> 100.32
A62: =Веса!A62 -> 1 | B62: =A62 -> 1 | C62: =БИПЦ_НДС!E62 -> 1 | D62: =1-C62 -> 0 | E62: 1 | F62: 0 | G62: 0 | H62: 0 | I62: 0 | J62: =L62 -> Конфеты мягкие, глазированные шоколадом, кг | K62: Конфеты мягкие, глазированные шоколадом, кг | L62: Конфеты мягкие, глазированные шоколадом, кг | M62: =INDEX('ИПЦ raw2015'!$1:$1048576, MATCH($J62,'ИПЦ raw2015'!$A:$A,0),MATCH(MoM!M$1,'ИПЦ raw2015'!$1:$1,0)) -> 104.13 | N62: =INDEX('ИПЦ raw2015'!$1:$1048576, MATCH($J62,'ИПЦ raw2015'!$A:$A,0),MATCH(MoM!N$1,'ИПЦ raw2015'!$1:$1,0)) -> 104.31 | O62: =INDEX('ИПЦ raw2015'!$1:$1048576, MATCH($J62,'ИПЦ raw2015'!$A:$A,0),MATCH(MoM!O$1,'ИПЦ raw2015'!$1:$1,0)) -> 102.52 | P62: =INDEX('ИПЦ raw2015'!$1:$1048576, MATCH($J62,'ИПЦ raw2015'!$A:$A,0),MATCH(MoM!P$1,'ИПЦ raw2015'!$1:$1,0)) -> 102.04 | Q62: =INDEX('ИПЦ raw2015'!$1:$1048576, MATCH($J62,'ИПЦ raw2015'!$A:$A,0),MATCH(MoM!Q$1,'ИПЦ raw2015'!$1:$1,0)) -> 102.36 | R62: =INDEX('ИПЦ raw2015'!$1:$1048576, MATCH($J62,'ИПЦ raw2015'!$A:$A,0),MATCH(MoM!R$1,'ИПЦ raw2015'!$1:$1,0)) -> 101.57 | S62: =INDEX('ИПЦ raw2015'!$1:$1048576, MATCH($J62,'ИПЦ raw2015'!$A:$A,0),MATCH(MoM!S$1,'ИПЦ raw2015'!$1:$1,0)) -> 100.82 | T62: =INDEX('ИПЦ raw2015'!$1:$1048576, MATCH($J62,'ИПЦ raw2015'!$A:$A,0),MATCH(MoM!T$1,'ИПЦ raw2015'!$1:$1,0)) -> 100.53 | ... BT62: =INDEX('ИПЦ raw2015'!$1:$1048576, MATCH($J62,'ИПЦ raw2015'!$A:$A,0),MATCH(MoM!BT$1,'ИПЦ raw2015'!$1:$1,0)) -> 100.14
A63: =Веса!A63 -> 1 | B63: =A63 -> 1 | C63: =БИПЦ_НДС!E63 -> 1 | D63: =1-C63 -> 0 | E63: 1 | F63: 0 | G63: 0 | H63: 0 | I63: 0 | J63: =L63 -> Конфеты шоколадные натуральные и с добавками, кг | K63: Конфеты шоколадные натуральные и с добавками, кг | L63: Конфеты шоколадные натуральные и с добавками, кг | M63: =INDEX('ИПЦ raw2015'!$1:$1048576, MATCH($J63,'ИПЦ raw2015'!$A:$A,0),MATCH(MoM!M$1,'ИПЦ raw2015'!$1:$1,0)) -> 104.4 | N63: =INDEX('ИПЦ raw2015'!$1:$1048576, MATCH($J63,'ИПЦ raw2015'!$A:$A,0),MATCH(MoM!N$1,'ИПЦ raw2015'!$1:$1,0)) -> 103.83 | O63: =INDEX('ИПЦ raw2015'!$1:$1048576, MATCH($J63,'ИПЦ raw2015'!$A:$A,0),MATCH(MoM!O$1,'ИПЦ raw2015'!$1:$1,0)) -> 102.36 | P63: =INDEX('ИПЦ raw2015'!$1:$1048576, MATCH($J63,'ИПЦ raw2015'!$A:$A,0),MATCH(MoM!P$1,'ИПЦ raw2015'!$1:$1,0)) -> 101.9 | Q63: =INDEX('ИПЦ raw2015'!$1:$1048576, MATCH($J63,'ИПЦ raw2015'!$A:$A,0),MATCH(MoM!Q$1,'ИПЦ raw2015'!$1:$1,0)) -> 102.57 | R63: =INDEX('ИПЦ raw2015'!$1:$1048576, MATCH($J63,'ИПЦ raw2015'!$A:$A,0),MATCH(MoM!R$1,'ИПЦ raw2015'!$1:$1,0)) -> 101.43 | S63: =INDEX('ИПЦ raw2015'!$1:$1048576, MATCH($J63,'ИПЦ raw2015'!$A:$A,0),MATCH(MoM!S$1,'ИПЦ raw2015'!$1:$1,0)) -> 100.91 | T63: =INDEX('ИПЦ raw2015'!$1:$1048576, MATCH($J63,'ИПЦ raw2015'!$A:$A,0),MATCH(MoM!T$1,'ИПЦ raw2015'!$1:$1,0)) -> 100.83 | ... BT63: =INDEX('ИПЦ raw2015'!$1:$1048576, MATCH($J63,'ИПЦ raw2015'!$A:$A,0),MATCH(MoM!BT$1,'ИПЦ raw2015'!$1:$1,0)) -> 100.44
A64: =Веса!A64 -> 1 | B64: =A64 -> 1 | C64: =БИПЦ_НДС!E64 -> 1 | D64: =1-C64 -> 0 | E64: 1 | F64: 0 | G64: 0 | H64: 0 | I64: 0 | J64: =L64 -> Жевательная резинка, упаковка | K64: Жевательная резинка, упаковка | L64: Жевательная резинка, упаковка | M64: =INDEX('ИПЦ raw2015'!$1:$1048576, MATCH($J64,'ИПЦ raw2015'!$A:$A,0),MATCH(MoM!M$1,'ИПЦ raw2015'!$1:$1,0)) -> 101.22 | N64: =INDEX('ИПЦ raw2015'!$1:$1048576, MATCH($J64,'ИПЦ raw2015'!$A:$A,0),MATCH(MoM!N$1,'ИПЦ raw2015'!$1:$1,0)) -> 103.56 | O64: =INDEX('ИПЦ raw2015'!$1:$1048576, MATCH($J64,'ИПЦ raw2015'!$A:$A,0),MATCH(MoM!O$1,'ИПЦ raw2015'!$1:$1,0)) -> 101.38 | P64: =INDEX('ИПЦ raw2015'!$1:$1048576, MATCH($J64,'ИПЦ raw2015'!$A:$A,0),MATCH(MoM!P$1,'ИПЦ raw2015'!$1:$1,0)) -> 101.27 | Q64: =INDEX('ИПЦ raw2015'!$1:$1048576, MATCH($J64,'ИПЦ raw2015'!$A:$A,0),MATCH(MoM!Q$1,'ИПЦ raw2015'!$1:$1,0)) -> 102.21 | R64: =INDEX('ИПЦ raw2015'!$1:$1048576, MATCH($J64,'ИПЦ raw2015'!$A:$A,0),MATCH(MoM!R$1,'ИПЦ raw2015'!$1:$1,0)) -> 101.17 | S64: =INDEX('ИПЦ raw2015'!$1:$1048576, MATCH($J64,'ИПЦ raw2015'!$A:$A,0),MATCH(MoM!S$1,'ИПЦ raw2015'!$1:$1,0)) -> 101.05 | T64: =INDEX('ИПЦ raw2015'!$1:$1048576, MATCH($J64,'ИПЦ raw2015'!$A:$A,0),MATCH(MoM!T$1,'ИПЦ raw2015'!$1:$1,0)) -> 101.02 | ... BT64: =INDEX('ИПЦ raw2015'!$1:$1048576, MATCH($J64,'ИПЦ raw2015'!$A:$A,0),MATCH(MoM!BT$1,'ИПЦ raw2015'!$1:$1,0)) -> 100.6
A65: =Веса!A65 -> 1 | B65: =A65 -> 1 | C65: =БИПЦ_НДС!E65 -> 1 | D65: =1-C65 -> 0 | E65: 1 | F65: 0 | G65: 0 | H65: 0 | I65: 0 | J65: =L65 -> Печенье, кг | K65: Печенье, кг | L65: Печенье, кг | M65: =INDEX('ИПЦ raw2015'!$1:$1048576, MATCH($J65,'ИПЦ raw2015'!$A:$A,0),MATCH(MoM!M$1,'ИПЦ raw2015'!$1:$1,0)) -> 103.65 | N65: =INDEX('ИПЦ raw2015'!$1:$1048576, MATCH($J65,'ИПЦ raw2015'!$A:$A,0),MATCH(MoM!N$1,'ИПЦ raw2015'!$1:$1,0)) -> 104.1 | O65: =INDEX('ИПЦ raw2015'!$1:$1048576, MATCH($J65,'ИПЦ raw2015'!$A:$A,0),MATCH(MoM!O$1,'ИПЦ raw2015'!$1:$1,0)) -> 102.58 | P65: =INDEX('ИПЦ raw2015'!$1:$1048576, MATCH($J65,'ИПЦ raw2015'!$A:$A,0),MATCH(MoM!P$1,'ИПЦ raw2015'!$1:$1,0)) -> 101.54 | Q65: =INDEX('ИПЦ raw2015'!$1:$1048576, MATCH($J65,'ИПЦ raw2015'!$A:$A,0),MATCH(MoM!Q$1,'ИПЦ raw2015'!$1:$1,0)) -> 101.18 | R65: =INDEX('ИПЦ raw2015'!$1:$1048576, MATCH($J65,'ИПЦ raw2015'!$A:$A,0),MATCH(MoM!R$1,'ИПЦ raw2015'!$1:$1,0)) -> 100.45 | S65: =INDEX('ИПЦ raw2015'!$1:$1048576, MATCH($J65,'ИПЦ raw2015'!$A:$A,0),MATCH(MoM!S$1,'ИПЦ raw2015'!$1:$1,0)) -> 100.33 | T65: =INDEX('ИПЦ raw2015'!$1:$1048576, MATCH($J65,'ИПЦ raw2015'!$A:$A,0),MATCH(MoM!T$1,'ИПЦ raw2015'!$1:$1,0)) -> 100.79 | ... BT65: =INDEX('ИПЦ raw2015'!$1:$1048576, MATCH($J65,'ИПЦ raw2015'!$A:$A,0),MATCH(MoM!BT$1,'ИПЦ raw2015'!$1:$1,0)) -> 100.07
A66: =Веса!A66 -> 1 | B66: =A66 -> 1 | C66: =БИПЦ_НДС!E66 -> 1 | D66: =1-C66 -> 0 | E66: 1 | F66: 0 | G66: 0 | H66: 0 | I66: 0 | J66: =L66 -> Пряники, кг | K66: Пряники, кг | L66: Пряники, кг | M66: =INDEX('ИПЦ raw2015'!$1:$1048576, MATCH($J66,'ИПЦ raw2015'!$A:$A,0),MATCH(MoM!M$1,'ИПЦ raw2015'!$1:$1,0)) -> 103.55 | N66: =INDEX('ИПЦ raw2015'!$1:$1048576, MATCH($J66,'ИПЦ raw2015'!$A:$A,0),MATCH(MoM!N$1,'ИПЦ raw2015'!$1:$1,0)) -> 103.45 | O66: =INDEX('ИПЦ raw2015'!$1:$1048576, MATCH($J66,'ИПЦ raw2015'!$A:$A,0),MATCH(MoM!O$1,'ИПЦ raw2015'!$1:$1,0)) -> 102.51 | P66: =INDEX('ИПЦ raw2015'!$1:$1048576, MATCH($J66,'ИПЦ raw2015'!$A:$A,0),MATCH(MoM!P$1,'ИПЦ raw2015'!$1:$1,0)) -> 101.47 | Q66: =INDEX('ИПЦ raw2015'!$1:$1048576, MATCH($J66,'ИПЦ raw2015'!$A:$A,0),MATCH(MoM!Q$1,'ИПЦ raw2015'!$1:$1,0)) -> 101.1 | R66: =INDEX('ИПЦ raw2015'!$1:$1048576, MATCH($J66,'ИПЦ raw2015'!$A:$A,0),MATCH(MoM!R$1,'ИПЦ raw2015'!$1:$1,0)) -> 100.61 | S66: =INDEX('ИПЦ raw2015'!$1:$1048576, MATCH($J66,'ИПЦ raw2015'!$A:$A,0),MATCH(MoM!S$1,'ИПЦ raw2015'!$1:$1,0)) -> 100.61 | T66: =INDEX('ИПЦ raw2015'!$1:$1048576, MATCH($J66,'ИПЦ raw2015'!$A:$A,0),MATCH(MoM!T$1,'ИПЦ raw2015'!$1:$1,0)) -> 100.32 | ... BT66: =INDEX('ИПЦ raw2015'!$1:$1048576, MATCH($J66,'ИПЦ raw2015'!$A:$A,0),MATCH(MoM!BT$1,'ИПЦ raw2015'!$1:$1,0)) -> 100.38
... A74: =Веса!A74 -> 1 | B74: =A74 -> 1 | C74: =БИПЦ_НДС!E74 -> 1 | D74: =1-C74 -> 0 | E74: 1 | F74: 0 | G74: 0 | H74: 0 | I74: 0 | J74: =L74 -> Чай черный байховый пакетированный, 25 пакетиков | K74: Чай черный байховый пакетированный, 25 пакетиков | L74: Чай черный байховый пакетированный, 25 пакетиков | M74: =INDEX('ИПЦ raw2015'!$1:$1048576, MATCH($J74,'ИПЦ raw2015'!$A:$A,0),MATCH(MoM!M$1,'ИПЦ raw2015'!$1:$1,0)) -> 106.56 | N74: =INDEX('ИПЦ raw2015'!$1:$1048576, MATCH($J74,'ИПЦ raw2015'!$A:$A,0),MATCH(MoM!N$1,'ИПЦ raw2015'!$1:$1,0)) -> 105.64 | O74: =INDEX('ИПЦ raw2015'!$1:$1048576, MATCH($J74,'ИПЦ raw2015'!$A:$A,0),MATCH(MoM!O$1,'ИПЦ raw2015'!$1:$1,0)) -> 103.61 | P74: =INDEX('ИПЦ raw2015'!$1:$1048576, MATCH($J74,'ИПЦ raw2015'!$A:$A,0),MATCH(MoM!P$1,'ИПЦ raw2015'!$1:$1,0)) -> 103.27 | Q74: =INDEX('ИПЦ raw2015'!$1:$1048576, MATCH($J74,'ИПЦ raw2015'!$A:$A,0),MATCH(MoM!Q$1,'ИПЦ raw2015'!$1:$1,0)) -> 101.13 | R74: =INDEX('ИПЦ raw2015'!$1:$1048576, MATCH($J74,'ИПЦ raw2015'!$A:$A,0),MATCH(MoM!R$1,'ИПЦ raw2015'!$1:$1,0)) -> 100.34 | S74: =INDEX('ИПЦ raw2015'!$1:$1048576, MATCH($J74,'ИПЦ raw2015'!$A:$A,0),MATCH(MoM!S$1,'ИПЦ raw2015'!$1:$1,0)) -> 100.52 | T74: =INDEX('ИПЦ raw2015'!$1:$1048576, MATCH($J74,'ИПЦ raw2015'!$A:$A,0),MATCH(MoM!T$1,'ИПЦ raw2015'!$1:$1,0)) -> 100.36 | ... BT74: =INDEX('ИПЦ raw2015'!$1:$1048576, MATCH($J74,'ИПЦ raw2015'!$A:$A,0),MATCH(MoM!BT$1,'ИПЦ raw2015'!$1:$1,0)) -> 99.78
A75: =Веса!A75 -> 0 | B75: =A75 -> 0 | C75: =БИПЦ_НДС!E75 -> 1 | D75: =1-C75 -> 0 | E75: 1 | F75: 0 | G75: 0 | H75: 0 | I75: 0 | J75: =L75 -> Чай зеленый, кг | K75: Чай зеленый, кг | L75: Чай зеленый, кг | M75: 0 | N75: 0 | O75: 0 | P75: 0 | Q75: 0 | R75: 0 | S75: 0 | T75: 0 | U75: 0 | V75: 0 | W75: 0 | X75: 0 | Y75: 0 | Z75: 0 | AA75: 0 | AB75: 0 | AC75: 0 | AD75: 0 | AE75: 0 | AF75: 0 | AG75: 0 | AH75: 0 | AI75: 0 | AJ75: 0 | AK75: 0 | AL75: 0 | AM75: 0 | AN75: 0 | AO75: 0 | AP75: 0 | AQ75: 0 | AR75: 0 | AS75: 0 | AT75: 0 | AU75: 0 | AV75: 0 | AW75: 0 | AX75: 0 | AY75: 0 | AZ75: 0 | BA75: 0 | BB75: 0 | BC75: 0 | BD75: 0 | BE75: 0 | BF75: 0 | BG75: 0 | BH75: 0 | BI75: 0 | BJ75: 0 | BK75: 0 | BL75: 0 | BM75: 0 | BN75: 0 | BO75: 0 | BP75: 0 | BQ75: 0 | BR75: 0 | BS75: 0 | BT75: 0
A76: =Веса!A76 -> 0 | B76: =A76 -> 0 | C76: =БИПЦ_НДС!E76 -> 1 | D76: =1-C76 -> 0 | E76: 1 | F76: 0 | G76: 0 | H76: 0 | I76: 0 | J76: =L76 -> Какао, кг | K76: Какао, кг | L76: Какао, кг | M76: 0 | N76: 0 | O76: 0 | P76: 0 | Q76: 0 | R76: 0 | S76: 0 | T76: 0 | U76: 0 | V76: 0 | W76: 0 | X76: 0 | Y76: 0 | Z76: 0 | AA76: 0 | AB76: 0 | AC76: 0 | AD76: 0 | AE76: 0 | AF76: 0 | AG76: 0 | AH76: 0 | AI76: 0 | AJ76: 0 | AK76: 0 | AL76: 0 | AM76: 0 | AN76: 0 | AO76: 0 | AP76: 0 | AQ76: 0 | AR76: 0 | AS76: 0 | AT76: 0 | AU76: 0 | AV76: 0 | AW76: 0 | AX76: 0 | AY76: 0 | AZ76: 0 | BA76: 0 | BB76: 0 | BC76: 0 | BD76: 0 | BE76: 0 | BF76: 0 | BG76: 0 | BH76: 0 | BI76: 0 | BJ76: 0 | BK76: 0 | BL76: 0 | BM76: 0 | BN76: 0 | BO76: 0 | BP76: 0 | BQ76: 0 | BR76: 0 | BS76: 0 | BT76: 0
A77: =Веса!A77 -> 1 | B77: =A77 -> 1 | C77: =БИПЦ_НДС!E77 -> 1 | D77: =1-C77 -> 0 | E77: 1 | F77: 0 | G77: 0 | H77: 0 | I77: 0 | J77: =L77 -> Майонез, кг | K77: Майонез, кг | L77: Майонез, кг | M77: =INDEX('ИПЦ raw2015'!$1:$1048576, MATCH($J77,'ИПЦ raw2015'!$A:$A,0),MATCH(MoM!M$1,'ИПЦ raw2015'!$1:$1,0)) -> 106.06 | N77: =INDEX('ИПЦ raw2015'!$1:$1048576, MATCH($J77,'ИПЦ raw2015'!$A:$A,0),MATCH(MoM!N$1,'ИПЦ raw2015'!$1:$1,0)) -> 105.64 | O77: =INDEX('ИПЦ raw2015'!$1:$1048576, MATCH($J77,'ИПЦ raw2015'!$A:$A,0),MATCH(MoM!O$1,'ИПЦ raw2015'!$1:$1,0)) -> 103.38 | P77: =INDEX('ИПЦ raw2015'!$1:$1048576, MATCH($J77,'ИПЦ raw2015'!$A:$A,0),MATCH(MoM!P$1,'ИПЦ raw2015'!$1:$1,0)) -> 102.38 | Q77: =INDEX('ИПЦ raw2015'!$1:$1048576, MATCH($J77,'ИПЦ raw2015'!$A:$A,0),MATCH(MoM!Q$1,'ИПЦ raw2015'!$1:$1,0)) -> 101.27 | R77: =INDEX('ИПЦ raw2015'!$1:$1048576, MATCH($J77,'ИПЦ raw2015'!$A:$A,0),MATCH(MoM!R$1,'ИПЦ raw2015'!$1:$1,0)) -> 100.7 | S77: =INDEX('ИПЦ raw2015'!$1:$1048576, MATCH($J77,'ИПЦ raw2015'!$A:$A,0),MATCH(MoM!S$1,'ИПЦ raw2015'!$1:$1,0)) -> 100.41 | T77: =INDEX('ИПЦ raw2015'!$1:$1048576, MATCH($J77,'ИПЦ raw2015'!$A:$A,0),MATCH(MoM!T$1,'ИПЦ raw2015'!$1:$1,0)) -> 100.57 | ... BT77: =INDEX('ИПЦ raw2015'!$1:$1048576, MATCH($J77,'ИПЦ raw2015'!$A:$A,0),MATCH(MoM!BT$1,'ИПЦ raw2015'!$1:$1,0)) -> 100.06
A78: =Веса!A78 -> 1 | B78: =A78 -> 1 | C78: =БИПЦ_НДС!E78 -> 1 | D78: =1-C78 -> 0 | E78: 1 | F78: 0 | G78: 0 | H78: 0 | I78: 0 | J78: =L78 -> Кетчуп, кг | K78: Кетчуп, кг | L78: Кетчуп, кг | M78: =INDEX('ИПЦ raw2015'!$1:$1048576, MATCH($J78,'ИПЦ raw2015'!$A:$A,0),MATCH(MoM!M$1,'ИПЦ raw2015'!$1:$1,0)) -> 104.29 | N78: =INDEX('ИПЦ raw2015'!$1:$1048576, MATCH($J78,'ИПЦ raw2015'!$A:$A,0),MATCH(MoM!N$1,'ИПЦ raw2015'!$1:$1,0)) -> 104.86 | O78: =INDEX('ИПЦ raw2015'!$1:$1048576, MATCH($J78,'ИПЦ raw2015'!$A:$A,0),MATCH(MoM!O$1,'ИПЦ raw2015'!$1:$1,0)) -> 103.01 | P78: =INDEX('ИПЦ raw2015'!$1:$1048576, MATCH($J78,'ИПЦ raw2015'!$A:$A,0),MATCH(MoM!P$1,'ИПЦ raw2015'!$1:$1,0)) -> 101.57 | Q78: =INDEX('ИПЦ raw2015'!$1:$1048576, MATCH($J78,'ИПЦ raw2015'!$A:$A,0),MATCH(MoM!Q$1,'ИПЦ raw2015'!$1:$1,0)) -> 100.75 | R78: =INDEX('ИПЦ raw2015'!$1:$1048576, MATCH($J78,'ИПЦ raw2015'!$A:$A,0),MATCH(MoM!R$1,'ИПЦ raw2015'!$1:$1,0)) -> 100.38 | S78: =INDEX('ИПЦ raw2015'!$1:$1048576, MATCH($J78,'ИПЦ raw2015'!$A:$A,0),MATCH(MoM!S$1,'ИПЦ raw2015'!$1:$1,0)) -> 100.28 | T78: =INDEX('ИПЦ raw2015'!$1:$1048576, MATCH($J78,'ИПЦ raw2015'!$A:$A,0),MATCH(MoM!T$1,'ИПЦ raw2015'!$1:$1,0)) -> 100.65 | ... BT78: =INDEX('ИПЦ raw2015'!$1:$1048576, MATCH($J78,'ИПЦ raw2015'!$A:$A,0),MATCH(MoM!BT$1,'ИПЦ raw2015'!$1:$1,0)) -> 100.26
A79: =Веса!A79 -> 1 | B79: =A79 -> 1 | C79: =БИПЦ_НДС!E79 -> 0 | D79: =1-C79 -> 1 | E79: 1 | F79: 0 | G79: 0 | H79: 0 | I79: 0 | J79: =L79 -> Соль поваренная пищевая, кг | K79: Соль поваренная пищевая, кг | L79: Соль поваренная пищевая, кг | M79: =INDEX('ИПЦ raw2015'!$1:$1048576, MATCH($J79,'ИПЦ raw2015'!$A:$A,0),MATCH(MoM!M$1,'ИПЦ raw2015'!$1:$1,0)) -> 103.28 | N79: =INDEX('ИПЦ raw2015'!$1:$1048576, MATCH($J79,'ИПЦ raw2015'!$A:$A,0),MATCH(MoM!N$1,'ИПЦ raw2015'!$1:$1,0)) -> 103 | O79: =INDEX('ИПЦ raw2015'!$1:$1048576, MATCH($J79,'ИПЦ raw2015'!$A:$A,0),MATCH(MoM!O$1,'ИПЦ raw2015'!$1:$1,0)) -> 101.89 | P79: =INDEX('ИПЦ raw2015'!$1:$1048576, MATCH($J79,'ИПЦ raw2015'!$A:$A,0),MATCH(MoM!P$1,'ИПЦ raw2015'!$1:$1,0)) -> 101.14 | Q79: =INDEX('ИПЦ raw2015'!$1:$1048576, MATCH($J79,'ИПЦ raw2015'!$A:$A,0),MATCH(MoM!Q$1,'ИПЦ raw2015'!$1:$1,0)) -> 100.71 | R79: =INDEX('ИПЦ raw2015'!$1:$1048576, MATCH($J79,'ИПЦ raw2015'!$A:$A,0),MATCH(MoM!R$1,'ИПЦ raw2015'!$1:$1,0)) -> 100.29 | S79: =INDEX('ИПЦ raw2015'!$1:$1048576, MATCH($J79,'ИПЦ raw2015'!$A:$A,0),MATCH(MoM!S$1,'ИПЦ raw2015'!$1:$1,0)) -> 100.06 | T79: =INDEX('ИПЦ raw2015'!$1:$1048576, MATCH($J79,'ИПЦ raw2015'!$A:$A,0),MATCH(MoM!T$1,'ИПЦ raw2015'!$1:$1,0)) -> 100.13 | ... BT79: =INDEX('ИПЦ raw2015'!$1:$1048576, MATCH($J79,'ИПЦ raw2015'!$A:$A,0),MATCH(MoM!BT$1,'ИПЦ raw2015'!$1:$1,0)) -> 100.01
A80: =Веса!A80 -> 0 | B80: =A80 -> 0 | C80: =БИПЦ_НДС!E80 -> 1 | D80: =1-C80 -> 0 | E80: 1 | F80: 0 | G80: 0 | H80: 0 | I80: 0 | J80: =L80 -> Сухие приправы, специи, кг | K80: Сухие приправы, специи, кг | L80: Сухие приправы, специи, кг | M80: 0 | N80: 0 | O80: 0 | P80: 0 | Q80: 0 | R80: 0 | S80: 0 | T80: 0 | U80: 0 | V80: 0 | W80: 0 | X80: 0 | Y80: 0 | Z80: 0 | AA80: 0 | AB80: 0 | AC80: 0 | AD80: 0 | AE80: 0 | AF80: 0 | AG80: 0 | AH80: 0 | AI80: 0 | AJ80: 0 | AK80: 0 | AL80: 0 | AM80: 0 | AN80: 0 | AO80: 0 | AP80: 0 | AQ80: 0 | AR80: 0 | AS80: 0 | AT80: 0 | AU80: 0 | AV80: 0 | AW80: 0 | AX80: 0 | AY80: 0 | AZ80: 0 | BA80: 0 | BB80: 0 | BC80: 0 | BD80: 0 | BE80: 0 | BF80: 0 | BG80: 0 | BH80: 0 | BI80: 0 | BJ80: 0 | BK80: 0 | BL80: 0 | BM80: 0 | BN80: 0 | BO80: 0 | BP80: 0 | BQ80: 0 | BR80: 0 | BS80: 0 | BT80: 0
A81: =Веса!A81 -> 1 | B81: =A81 -> 1 | C81: =БИПЦ_НДС!E81 -> 1 | D81: =1-C81 -> 0 | E81: 1 | F81: 0 | G81: 0 | H81: 0 | I81: 0 | J81: Сухие супы в пакетах, 100 г | K81: Сухие супы в пакетах, кг | L81: Сухие супы в пакетах, кг | M81: =INDEX('ИПЦ raw2015'!$1:$1048576, MATCH($J81,'ИПЦ raw2015'!$A:$A,0),MATCH(MoM!M$1,'ИПЦ raw2015'!$1:$1,0)) -> 103.11 | N81: =INDEX('ИПЦ raw2015'!$1:$1048576, MATCH($J81,'ИПЦ raw2015'!$A:$A,0),MATCH(MoM!N$1,'ИПЦ raw2015'!$1:$1,0)) -> 106.08 | O81: =INDEX('ИПЦ raw2015'!$1:$1048576, MATCH($J81,'ИПЦ raw2015'!$A:$A,0),MATCH(MoM!O$1,'ИПЦ raw2015'!$1:$1,0)) -> 103.93 | P81: =INDEX('ИПЦ raw2015'!$1:$1048576, MATCH($J81,'ИПЦ raw2015'!$A:$A,0),MATCH(MoM!P$1,'ИПЦ raw2015'!$1:$1,0)) -> 103.09 | Q81: =INDEX('ИПЦ raw2015'!$1:$1048576, MATCH($J81,'ИПЦ raw2015'!$A:$A,0),MATCH(MoM!Q$1,'ИПЦ raw2015'!$1:$1,0)) -> 101.66 | R81: =INDEX('ИПЦ raw2015'!$1:$1048576, MATCH($J81,'ИПЦ raw2015'!$A:$A,0),MATCH(MoM!R$1,'ИПЦ raw2015'!$1:$1,0)) -> 101.03 | S81: =INDEX('ИПЦ raw2015'!$1:$1048576, MATCH($J81,'ИПЦ raw2015'!$A:$A,0),MATCH(MoM!S$1,'ИПЦ raw2015'!$1:$1,0)) -> 100.28 | T81: =INDEX('ИПЦ raw2015'!$1:$1048576, MATCH($J81,'ИПЦ raw2015'!$A:$A,0),MATCH(MoM!T$1,'ИПЦ raw2015'!$1:$1,0)) -> 100.4 | ... BT81: =INDEX('ИПЦ raw2015'!$1:$1048576, MATCH($J81,'ИПЦ raw2015'!$A:$A,0),MATCH(MoM!BT$1,'ИПЦ raw2015'!$1:$1,0)) -> 99.96
A82: =Веса!A82 -> 1 | B82: =A82 -> 1 | C82: =БИПЦ_НДС!E82 -> 0 | D82: =1-C82 -> 1 | E82: 1 | F82: 0 | G82: 0 | H82: 0 | I82: 0 | J82: =L82 -> Мука пшеничная, кг | K82: Мука пшеничная, кг | L82: Мука пшеничная, кг | M82: =INDEX('ИПЦ raw2015'!$1:$1048576, MATCH($J82,'ИПЦ raw2015'!$A:$A,0),MATCH(MoM!M$1,'ИПЦ raw2015'!$1:$1,0)) -> 105.29 | N82: =INDEX('ИПЦ raw2015'!$1:$1048576, MATCH($J82,'ИПЦ raw2015'!$A:$A,0),MATCH(MoM!N$1,'ИПЦ raw2015'!$1:$1,0)) -> 103.69 | O82: =INDEX('ИПЦ raw2015'!$1:$1048576, MATCH($J82,'ИПЦ raw2015'!$A:$A,0),MATCH(MoM!O$1,'ИПЦ raw2015'!$1:$1,0)) -> 101.87 | P82: =INDEX('ИПЦ raw2015'!$1:$1048576, MATCH($J82,'ИПЦ raw2015'!$A:$A,0),MATCH(MoM!P$1,'ИПЦ raw2015'!$1:$1,0)) -> 100.5 | Q82: =INDEX('ИПЦ raw2015'!$1:$1048576, MATCH($J82,'ИПЦ raw2015'!$A:$A,0),MATCH(MoM!Q$1,'ИПЦ raw2015'!$1:$1,0)) -> 99.51 | R82: =INDEX('ИПЦ raw2015'!$1:$1048576, MATCH($J82,'ИПЦ raw2015'!$A:$A,0),MATCH(MoM!R$1,'ИПЦ raw2015'!$1:$1,0)) -> 99.49 | S82: =INDEX('ИПЦ raw2015'!$1:$1048576, MATCH($J82,'ИПЦ raw2015'!$A:$A,0),MATCH(MoM!S$1,'ИПЦ raw2015'!$1:$1,0)) -> 99.73 | T82: =INDEX('ИПЦ raw2015'!$1:$1048576, MATCH($J82,'ИПЦ raw2015'!$A:$A,0),MATCH(MoM!T$1,'ИПЦ raw2015'!$1:$1,0)) -> 100.08 | ... BT82: =INDEX('ИПЦ raw2015'!$1:$1048576, MATCH($J82,'ИПЦ raw2015'!$A:$A,0),MATCH(MoM!BT$1,'ИПЦ raw2015'!$1:$1,0)) -> 100.13
A83: =Веса!A83 -> 1 | B83: =A83 -> 1 | C83: =БИПЦ_НДС!E83 -> 0 | D83: =1-C83 -> 1 | E83: 1 | F83: 0 | G83: 0 | H83: 0 | I83: 0 | J83: =L83 -> Хлеб из ржаной муки и из смеси муки ржаной и пшеничной, кг | K83: Хлеб из ржаной муки и из смеси муки ржаной и пшеничной, кг | L83: Хлеб из ржаной муки и из смеси муки ржаной и пшеничной, кг | M83: =INDEX('ИПЦ raw2015'!$1:$1048576, MATCH($J83,'ИПЦ raw2015'!$A:$A,0),MATCH(MoM!M$1,'ИПЦ raw2015'!$1:$1,0)) -> 103.95 | N83: =INDEX('ИПЦ raw2015'!$1:$1048576, MATCH($J83,'ИПЦ raw2015'!$A:$A,0),MATCH(MoM!N$1,'ИПЦ raw2015'!$1:$1,0)) -> 102.67 | O83: =INDEX('ИПЦ raw2015'!$1:$1048576, MATCH($J83,'ИПЦ raw2015'!$A:$A,0),MATCH(MoM!O$1,'ИПЦ raw2015'!$1:$1,0)) -> 101.1 | P83: =INDEX('ИПЦ raw2015'!$1:$1048576, MATCH($J83,'ИПЦ raw2015'!$A:$A,0),MATCH(MoM!P$1,'ИПЦ raw2015'!$1:$1,0)) -> 100.95 | Q83: =INDEX('ИПЦ raw2015'!$1:$1048576, MATCH($J83,'ИПЦ raw2015'!$A:$A,0),MATCH(MoM!Q$1,'ИПЦ raw2015'!$1:$1,0)) -> 100.52 | R83: =INDEX('ИПЦ raw2015'!$1:$1048576, MATCH($J83,'ИПЦ raw2015'!$A:$A,0),MATCH(MoM!R$1,'ИПЦ raw2015'!$1:$1,0)) -> 100.17 | S83: =INDEX('ИПЦ raw2015'!$1:$1048576, MATCH($J83,'ИПЦ raw2015'!$A:$A,0),MATCH(MoM!S$1,'ИПЦ raw2015'!$1:$1,0)) -> 100.44 | T83: =INDEX('ИПЦ raw2015'!$1:$1048576, MATCH($J83,'ИПЦ raw2015'!$A:$A,0),MATCH(MoM!T$1,'ИПЦ raw2015'!$1:$1,0)) -> 100.18 | ... BT83: =INDEX('ИПЦ raw2015'!$1:$1048576, MATCH($J83,'ИПЦ raw2015'!$A:$A,0),MATCH(MoM!BT$1,'ИПЦ raw2015'!$1:$1,0)) -> 100.54
A84: =Веса!A84 -> 1 | B84: =A84 -> 1 | C84: =БИПЦ_НДС!E84 -> 0 | D84: =1-C84 -> 1 | E84: 1 | F84: 0 | G84: 0 | H84: 0 | I84: 0 | J84: Хлеб и булочные изделия из пшеничной муки 1 и 2 сортов, кг | K84: Хлеб и булочные изделия из пшеничной муки различных сортов, кг | L84: Хлеб и булочные изделия из пшеничной муки различных сортов, кг | M84: =INDEX('ИПЦ raw2015'!$1:$1048576, MATCH($J84,'ИПЦ raw2015'!$A:$A,0),MATCH(MoM!M$1,'ИПЦ raw2015'!$1:$1,0)) -> 103.26 | N84: =INDEX('ИПЦ raw2015'!$1:$1048576, MATCH($J84,'ИПЦ raw2015'!$A:$A,0),MATCH(MoM!N$1,'ИПЦ raw2015'!$1:$1,0)) -> 102.57 | O84: =INDEX('ИПЦ raw2015'!$1:$1048576, MATCH($J84,'ИПЦ raw2015'!$A:$A,0),MATCH(MoM!O$1,'ИПЦ raw2015'!$1:$1,0)) -> 101.03 | P84: =INDEX('ИПЦ raw2015'!$1:$1048576, MATCH($J84,'ИПЦ raw2015'!$A:$A,0),MATCH(MoM!P$1,'ИПЦ raw2015'!$1:$1,0)) -> 100.4 | Q84: =INDEX('ИПЦ raw2015'!$1:$1048576, MATCH($J84,'ИПЦ raw2015'!$A:$A,0),MATCH(MoM!Q$1,'ИПЦ raw2015'!$1:$1,0)) -> 100.6 | R84: =INDEX('ИПЦ raw2015'!$1:$1048576, MATCH($J84,'ИПЦ raw2015'!$A:$A,0),MATCH(MoM!R$1,'ИПЦ raw2015'!$1:$1,0)) -> 100.45 | S84: =INDEX('ИПЦ raw2015'!$1:$1048576, MATCH($J84,'ИПЦ raw2015'!$A:$A,0),MATCH(MoM!S$1,'ИПЦ raw2015'!$1:$1,0)) -> 100.27 | T84: =INDEX('ИПЦ raw2015'!$1:$1048576, MATCH($J84,'ИПЦ raw2015'!$A:$A,0),MATCH(MoM!T$1,'ИПЦ raw2015'!$1:$1,0)) -> 100.14 | ... BT84: =INDEX('ИПЦ raw2015'!$1:$1048576, MATCH($J84,'ИПЦ raw2015'!$A:$A,0),MATCH(MoM!BT$1,'ИПЦ raw2015'!$1:$1,0)) -> 100.53
A85: =Веса!A85 -> 1 | B85: =A85 -> 1 | C85: =БИПЦ_НДС!E85 -> 0 | D85: =1-C85 -> 1 | E85: 1 | F85: 0 | G85: 0 | H85: 0 | I85: 0 | J85: =L85 -> Булочные изделия сдобные из муки высшего сорта штучные, кг | K85: Булочные изделия сдобные из муки высшего сорта штучные, кг | L85: Булочные изделия сдобные из муки высшего сорта штучные, кг | M85: =INDEX('ИПЦ raw2015'!$1:$1048576, MATCH($J85,'ИПЦ raw2015'!$A:$A,0),MATCH(MoM!M$1,'ИПЦ raw2015'!$1:$1,0)) -> 103.48 | N85: =INDEX('ИПЦ raw2015'!$1:$1048576, MATCH($J85,'ИПЦ raw2015'!$A:$A,0),MATCH(MoM!N$1,'ИПЦ raw2015'!$1:$1,0)) -> 102.58 | O85: =INDEX('ИПЦ raw2015'!$1:$1048576, MATCH($J85,'ИПЦ raw2015'!$A:$A,0),MATCH(MoM!O$1,'ИПЦ raw2015'!$1:$1,0)) -> 101.49 | P85: =INDEX('ИПЦ raw2015'!$1:$1048576, MATCH($J85,'ИПЦ raw2015'!$A:$A,0),MATCH(MoM!P$1,'ИПЦ raw2015'!$1:$1,0)) -> 100.87 | Q85: =INDEX('ИПЦ raw2015'!$1:$1048576, MATCH($J85,'ИПЦ raw2015'!$A:$A,0),MATCH(MoM!Q$1,'ИПЦ raw2015'!$1:$1,0)) -> 100.42 | R85: =INDEX('ИПЦ raw2015'!$1:$1048576, MATCH($J85,'ИПЦ raw2015'!$A:$A,0),MATCH(MoM!R$1,'ИПЦ raw2015'!$1:$1,0)) -> 100.58 | S85: =INDEX('ИПЦ raw2015'!$1:$1048576, MATCH($J85,'ИПЦ raw2015'!$A:$A,0),MATCH(MoM!S$1,'ИПЦ raw2015'!$1:$1,0)) -> 100.14 | T85: =INDEX('ИПЦ raw2015'!$1:$1048576, MATCH($J85,'ИПЦ raw2015'!$A:$A,0),MATCH(MoM!T$1,'ИПЦ raw2015'!$1:$1,0)) -> 100.47 | ... BT85: =INDEX('ИПЦ raw2015'!$1:$1048576, MATCH($J85,'ИПЦ raw2015'!$A:$A,0),MATCH(MoM!BT$1,'ИПЦ raw2015'!$1:$1,0)) -> 100.5
A86: =Веса!A86 -> 1 | B86: =A86 -> 1 | C86: =БИПЦ_НДС!E86 -> 0 | D86: =1-C86 -> 1 | E86: 1 | F86: 0 | G86: 0 | H86: 0 | I86: 0 | J86: =L86 -> Бараночные изделия, кг | K86: Бараночные изделия, кг | L86: Бараночные изделия, кг | M86: =INDEX('ИПЦ raw2015'!$1:$1048576, MATCH($J86,'ИПЦ raw2015'!$A:$A,0),MATCH(MoM!M$1,'ИПЦ raw2015'!$1:$1,0)) -> 103.21 | N86: =INDEX('ИПЦ raw2015'!$1:$1048576, MATCH($J86,'ИПЦ raw2015'!$A:$A,0),MATCH(MoM!N$1,'ИПЦ raw2015'!$1:$1,0)) -> 102.69 | O86: =INDEX('ИПЦ raw2015'!$1:$1048576, MATCH($J86,'ИПЦ raw2015'!$A:$A,0),MATCH(MoM!O$1,'ИПЦ raw2015'!$1:$1,0)) -> 102.17 | P86: =INDEX('ИПЦ raw2015'!$1:$1048576, MATCH($J86,'ИПЦ raw2015'!$A:$A,0),MATCH(MoM!P$1,'ИПЦ raw2015'!$1:$1,0)) -> 101.63 | Q86: =INDEX('ИПЦ raw2015'!$1:$1048576, MATCH($J86,'ИПЦ raw2015'!$A:$A,0),MATCH(MoM!Q$1,'ИПЦ raw2015'!$1:$1,0)) -> 100.7 | R86: =INDEX('ИПЦ raw2015'!$1:$1048576, MATCH($J86,'ИПЦ raw2015'!$A:$A,0),MATCH(MoM!R$1,'ИПЦ raw2015'!$1:$1,0)) -> 100.58 | S86: =INDEX('ИПЦ raw2015'!$1:$1048576, MATCH($J86,'ИПЦ raw2015'!$A:$A,0),MATCH(MoM!S$1,'ИПЦ raw2015'!$1:$1,0)) -> 100.63 | T86: =INDEX('ИПЦ raw2015'!$1:$1048576, MATCH($J86,'ИПЦ raw2015'!$A:$A,0),MATCH(MoM!T$1,'ИПЦ raw2015'!$1:$1,0)) -> 100.46 | ... BT86: =INDEX('ИПЦ raw2015'!$1:$1048576, MATCH($J86,'ИПЦ raw2015'!$A:$A,0),MATCH(MoM!BT$1,'ИПЦ raw2015'!$1:$1,0)) -> 100.45
A87: =Веса!A87 -> 1 | B87: =A87 -> 1 | C87: =БИПЦ_НДС!E87 -> 0 | D87: =1-C87 -> 1 | E87: 1 | F87: 0 | G87: 0 | H87: 0 | I87: 0 | J87: =L87 -> Хлопья из злаков (сухие завтраки), кг | K87: Хлопья из злаков (сухие завтраки), кг | L87: Хлопья из злаков (сухие завтраки), кг | M87: =INDEX('ИПЦ raw2015'!$1:$1048576, MATCH($J87,'ИПЦ raw2015'!$A:$A,0),MATCH(MoM!M$1,'ИПЦ raw2015'!$1:$1,0)) -> 102.52 | N87: =INDEX('ИПЦ raw2015'!$1:$1048576, MATCH($J87,'ИПЦ raw2015'!$A:$A,0),MATCH(MoM!N$1,'ИПЦ raw2015'!$1:$1,0)) -> 103.87 | O87: =INDEX('ИПЦ raw2015'!$1:$1048576, MATCH($J87,'ИПЦ raw2015'!$A:$A,0),MATCH(MoM!O$1,'ИПЦ raw2015'!$1:$1,0)) -> 103.76 | P87: =INDEX('ИПЦ raw2015'!$1:$1048576, MATCH($J87,'ИПЦ raw2015'!$A:$A,0),MATCH(MoM!P$1,'ИПЦ raw2015'!$1:$1,0)) -> 101.89 | Q87: =INDEX('ИПЦ raw2015'!$1:$1048576, MATCH($J87,'ИПЦ raw2015'!$A:$A,0),MATCH(MoM!Q$1,'ИПЦ raw2015'!$1:$1,0)) -> 100.92 | R87: =INDEX('ИПЦ raw2015'!$1:$1048576, MATCH($J87,'ИПЦ raw2015'!$A:$A,0),MATCH(MoM!R$1,'ИПЦ raw2015'!$1:$1,0)) -> 100.24 | S87: =INDEX('ИПЦ raw2015'!$1:$1048576, MATCH($J87,'ИПЦ raw2015'!$A:$A,0),MATCH(MoM!S$1,'ИПЦ raw2015'!$1:$1,0)) -> 100.32 | T87: =INDEX('ИПЦ raw2015'!$1:$1048576, MATCH($J87,'ИПЦ raw2015'!$A:$A,0),MATCH(MoM!T$1,'ИПЦ raw2015'!$1:$1,0)) -> 100.45 | ... BT87: =INDEX('ИПЦ raw2015'!$1:$1048576, MATCH($J87,'ИПЦ raw2015'!$A:$A,0),MATCH(MoM!BT$1,'ИПЦ raw2015'!$1:$1,0)) -> 100.1
A88: =Веса!A88 -> 1 | B88: =A88 -> 1 | C88: =БИПЦ_НДС!E88 -> 0 | D88: =1-C88 -> 1 | E88: 1 | F88: 0 | G88: 0 | H88: 0 | I88: 0 | J88: =L88 -> Крупа манная, кг | K88: Крупа манная, кг | L88: Крупа манная, кг | M88: =INDEX('ИПЦ raw2015'!$1:$1048576, MATCH($J88,'ИПЦ raw2015'!$A:$A,0),MATCH(MoM!M$1,'ИПЦ raw2015'!$1:$1,0)) -> 106.52 | N88: =INDEX('ИПЦ raw2015'!$1:$1048576, MATCH($J88,'ИПЦ raw2015'!$A:$A,0),MATCH(MoM!N$1,'ИПЦ raw2015'!$1:$1,0)) -> 105.94 | O88: =INDEX('ИПЦ raw2015'!$1:$1048576, MATCH($J88,'ИПЦ raw2015'!$A:$A,0),MATCH(MoM!O$1,'ИПЦ raw2015'!$1:$1,0)) -> 102.88 | P88: =INDEX('ИПЦ raw2015'!$1:$1048576, MATCH($J88,'ИПЦ raw2015'!$A:$A,0),MATCH(MoM!P$1,'ИПЦ raw2015'!$1:$1,0)) -> 100.81 | Q88: =INDEX('ИПЦ raw2015'!$1:$1048576, MATCH($J88,'ИПЦ raw2015'!$A:$A,0),MATCH(MoM!Q$1,'ИПЦ raw2015'!$1:$1,0)) -> 99.27 | R88: =INDEX('ИПЦ raw2015'!$1:$1048576, MATCH($J88,'ИПЦ raw2015'!$A:$A,0),MATCH(MoM!R$1,'ИПЦ raw2015'!$1:$1,0)) -> 98.84 | S88: =INDEX('ИПЦ raw2015'!$1:$1048576, MATCH($J88,'ИПЦ raw2015'!$A:$A,0),MATCH(MoM!S$1,'ИПЦ raw2015'!$1:$1,0)) -> 99.37 | T88: =INDEX('ИПЦ raw2015'!$1:$1048576, MATCH($J88,'ИПЦ raw2015'!$A:$A,0),MATCH(MoM!T$1,'ИПЦ raw2015'!$1:$1,0)) -> 99.56 | ... BT88: =INDEX('ИПЦ raw2015'!$1:$1048576, MATCH($J88,'ИПЦ raw2015'!$A:$A,0),MATCH(MoM!BT$1,'ИПЦ raw2015'!$1:$1,0)) -> 100.14
A89: =Веса!A89 -> 1 | B89: =A89 -> 1 | C89: =БИПЦ_НДС!E89 -> 0 | D89: =1-C89 -> 1 | E89: 1 | F89: 0 | G89: 0 | H89: 0 | I89: 0 | J89: =L89 -> Горох и фасоль, кг | K89: Горох и фасоль, кг | L89: Горох и фасоль, кг | M89: =INDEX('ИПЦ raw2015'!$1:$1048576, MATCH($J89,'ИПЦ raw2015'!$A:$A,0),MATCH(MoM!M$1,'ИПЦ raw2015'!$1:$1,0)) -> 108.49 | N89: =INDEX('ИПЦ raw2015'!$1:$1048576, MATCH($J89,'ИПЦ raw2015'!$A:$A,0),MATCH(MoM!N$1,'ИПЦ raw2015'!$1:$1,0)) -> 107.96 | O89: =INDEX('ИПЦ raw2015'!$1:$1048576, MATCH($J89,'ИПЦ raw2015'!$A:$A,0),MATCH(MoM!O$1,'ИПЦ raw2015'!$1:$1,0)) -> 103.35 | P89: =INDEX('ИПЦ raw2015'!$1:$1048576, MATCH($J89,'ИПЦ raw2015'!$A:$A,0),MATCH(MoM!P$1,'ИПЦ raw2015'!$1:$1,0)) -> 101.05 | Q89: =INDEX('ИПЦ raw2015'!$1:$1048576, MATCH($J89,'ИПЦ raw2015'!$A:$A,0),MATCH(MoM!Q$1,'ИПЦ raw2015'!$1:$1,0)) -> 99.89 | R89: =INDEX('ИПЦ raw2015'!$1:$1048576, MATCH($J89,'ИПЦ raw2015'!$A:$A,0),MATCH(MoM!R$1,'ИПЦ raw2015'!$1:$1,0)) -> 99.54 | S89: =INDEX('ИПЦ raw2015'!$1:$1048576, MATCH($J89,'ИПЦ raw2015'!$A:$A,0),MATCH(MoM!S$1,'ИПЦ raw2015'!$1:$1,0)) -> 99.83 | T89: =INDEX('ИПЦ raw2015'!$1:$1048576, MATCH($J89,'ИПЦ raw2015'!$A:$A,0),MATCH(MoM!T$1,'ИПЦ raw2015'!$1:$1,0)) -> 100.28 | ... BT89: =INDEX('ИПЦ raw2015'!$1:$1048576, MATCH($J89,'ИПЦ raw2015'!$A:$A,0),MATCH(MoM!BT$1,'ИПЦ raw2015'!$1:$1,0)) -> 99.86
A90: =Веса!A90 -> 1 | B90: =A90 -> 1 | C90: =БИПЦ_НДС!E90 -> 0 | D90: =1-C90 -> 1 | E90: 1 | F90: 0 | G90: 0 | H90: 0 | I90: 0 | J90: =L90 -> Крупы овсяная и перловая, кг | K90: Крупы овсяная и перловая, кг | L90: Крупы овсяная и перловая, кг | M90: =INDEX('ИПЦ raw2015'!$1:$1048576, MATCH($J90,'ИПЦ raw2015'!$A:$A,0),MATCH(MoM!M$1,'ИПЦ raw2015'!$1:$1,0)) -> 104.59 | N90: =INDEX('ИПЦ raw2015'!$1:$1048576, MATCH($J90,'ИПЦ raw2015'!$A:$A,0),MATCH(MoM!N$1,'ИПЦ raw2015'!$1:$1,0)) -> 103.25 | O90: =INDEX('ИПЦ raw2015'!$1:$1048576, MATCH($J90,'ИПЦ raw2015'!$A:$A,0),MATCH(MoM!O$1,'ИПЦ raw2015'!$1:$1,0)) -> 101.77 | P90: =INDEX('ИПЦ raw2015'!$1:$1048576, MATCH($J90,'ИПЦ raw2015'!$A:$A,0),MATCH(MoM!P$1,'ИПЦ raw2015'!$1:$1,0)) -> 100.27 | Q90: =INDEX('ИПЦ raw2015'!$1:$1048576, MATCH($J90,'ИПЦ raw2015'!$A:$A,0),MATCH(MoM!Q$1,'ИПЦ raw2015'!$1:$1,0)) -> 99.58 | R90: =INDEX('ИПЦ raw2015'!$1:$1048576, MATCH($J90,'ИПЦ raw2015'!$A:$A,0),MATCH(MoM!R$1,'ИПЦ raw2015'!$1:$1,0)) -> 99.63 | S90: =INDEX('ИПЦ raw2015'!$1:$1048576, MATCH($J90,'ИПЦ raw2015'!$A:$A,0),MATCH(MoM!S$1,'ИПЦ raw2015'!$1:$1,0)) -> 100.33 | T90: =INDEX('ИПЦ raw2015'!$1:$1048576, MATCH($J90,'ИПЦ raw2015'!$A:$A,0),MATCH(MoM!T$1,'ИПЦ raw2015'!$1:$1,0)) -> 100.02 | ... BT90: =INDEX('ИПЦ raw2015'!$1:$1048576, MATCH($J90,'ИПЦ raw2015'!$A:$A,0),MATCH(MoM!BT$1,'ИПЦ raw2015'!$1:$1,0)) -> 100.3
A91: =Веса!A91 -> 1 | B91: =A91 -> 1 | C91: =БИПЦ_НДС!E91 -> 0 | D91: =1-C91 -> 1 | E91: 1 | F91: 0 | G91: 0 | H91: 0 | I91: 0 | J91: =L91 -> Овсяные хлопья "Геркулес", кг | K91: Овсяные хлопья "Геркулес", кг | L91: Овсяные хлопья "Геркулес", кг | M91: =INDEX('ИПЦ raw2015'!$1:$1048576, MATCH($J91,'ИПЦ raw2015'!$A:$A,0),MATCH(MoM!M$1,'ИПЦ raw2015'!$1:$1,0)) -> 103.19 | N91: =INDEX('ИПЦ raw2015'!$1:$1048576, MATCH($J91,'ИПЦ raw2015'!$A:$A,0),MATCH(MoM!N$1,'ИПЦ raw2015'!$1:$1,0)) -> 102.17 | O91: =INDEX('ИПЦ raw2015'!$1:$1048576, MATCH($J91,'ИПЦ raw2015'!$A:$A,0),MATCH(MoM!O$1,'ИПЦ raw2015'!$1:$1,0)) -> 100.87 | P91: =INDEX('ИПЦ raw2015'!$1:$1048576, MATCH($J91,'ИПЦ raw2015'!$A:$A,0),MATCH(MoM!P$1,'ИПЦ raw2015'!$1:$1,0)) -> 100.32 | Q91: =INDEX('ИПЦ raw2015'!$1:$1048576, MATCH($J91,'ИПЦ raw2015'!$A:$A,0),MATCH(MoM!Q$1,'ИПЦ raw2015'!$1:$1,0)) -> 99.64 | R91: =INDEX('ИПЦ raw2015'!$1:$1048576, MATCH($J91,'ИПЦ raw2015'!$A:$A,0),MATCH(MoM!R$1,'ИПЦ raw2015'!$1:$1,0)) -> 99.48 | S91: =INDEX('ИПЦ raw2015'!$1:$1048576, MATCH($J91,'ИПЦ raw2015'!$A:$A,0),MATCH(MoM!S$1,'ИПЦ raw2015'!$1:$1,0)) -> 100.21 | T91: =INDEX('ИПЦ raw2015'!$1:$1048576, MATCH($J91,'ИПЦ raw2015'!$A:$A,0),MATCH(MoM!T$1,'ИПЦ raw2015'!$1:$1,0)) -> 100.36 | ... BT91: =INDEX('ИПЦ raw2015'!$1:$1048576, MATCH($J91,'ИПЦ raw2015'!$A:$A,0),MATCH(MoM!BT$1,'ИПЦ raw2015'!$1:$1,0)) -> 100.47
A92: =Веса!A92 -> 1 | B92: =A92 -> 1 | C92: =БИПЦ_НДС!E92 -> 0 | D92: =1-C92 -> 1 | E92: 1 | F92: 0 | G92: 0 | H92: 0 | I92: 0 | J92: =L92 -> Вермишель, кг | K92: Вермишель, кг | L92: Вермишель, кг | M92: =INDEX('ИПЦ raw2015'!$1:$1048576, MATCH($J92,'ИПЦ raw2015'!$A:$A,0),MATCH(MoM!M$1,'ИПЦ raw2015'!$1:$1,0)) -> 105.75 | N92: =INDEX('ИПЦ raw2015'!$1:$1048576, MATCH($J92,'ИПЦ raw2015'!$A:$A,0),MATCH(MoM!N$1,'ИПЦ raw2015'!$1:$1,0)) -> 104.91 | O92: =INDEX('ИПЦ raw2015'!$1:$1048576, MATCH($J92,'ИПЦ raw2015'!$A:$A,0),MATCH(MoM!O$1,'ИПЦ raw2015'!$1:$1,0)) -> 102.65 | P92: =INDEX('ИПЦ raw2015'!$1:$1048576, MATCH($J92,'ИПЦ raw2015'!$A:$A,0),MATCH(MoM!P$1,'ИПЦ raw2015'!$1:$1,0)) -> 101.02 | Q92: =INDEX('ИПЦ raw2015'!$1:$1048576, MATCH($J92,'ИПЦ raw2015'!$A:$A,0),MATCH(MoM!Q$1,'ИПЦ raw2015'!$1:$1,0)) -> 100.57 | R92: =INDEX('ИПЦ raw2015'!$1:$1048576, MATCH($J92,'ИПЦ raw2015'!$A:$A,0),MATCH(MoM!R$1,'ИПЦ raw2015'!$1:$1,0)) -> 100.33 | S92: =INDEX('ИПЦ raw2015'!$1:$1048576, MATCH($J92,'ИПЦ raw2015'!$A:$A,0),MATCH(MoM!S$1,'ИПЦ raw2015'!$1:$1,0)) -> 99.88 | T92: =INDEX('ИПЦ raw2015'!$1:$1048576, MATCH($J92,'ИПЦ raw2015'!$A:$A,0),MATCH(MoM!T$1,'ИПЦ raw2015'!$1:$1,0)) -> 100.17 | ... BT92: =INDEX('ИПЦ raw2015'!$1:$1048576, MATCH($J92,'ИПЦ raw2015'!$A:$A,0),MATCH(MoM!BT$1,'ИПЦ raw2015'!$1:$1,0)) -> 100.33
A93: =Веса!A93 -> 1 | B93: =A93 -> 1 | C93: =БИПЦ_НДС!E93 -> 0 | D93: =1-C93 -> 1 | E93: 1 | F93: 0 | G93: 0 | H93: 0 | I93: 0 | J93: =L93 -> Макаронные изделия из пшеничной муки высшего сорта, кг | K93: Макаронные изделия из пшеничной муки высшего сорта, кг | L93: Макаронные изделия из пшеничной муки высшего сорта, кг | M93: =INDEX('ИПЦ raw2015'!$1:$1048576, MATCH($J93,'ИПЦ raw2015'!$A:$A,0),MATCH(MoM!M$1,'ИПЦ raw2015'!$1:$1,0)) -> 105.69 | N93: =INDEX('ИПЦ raw2015'!$1:$1048576, MATCH($J93,'ИПЦ raw2015'!$A:$A,0),MATCH(MoM!N$1,'ИПЦ raw2015'!$1:$1,0)) -> 105.38 | O93: =INDEX('ИПЦ raw2015'!$1:$1048576, MATCH($J93,'ИПЦ raw2015'!$A:$A,0),MATCH(MoM!O$1,'ИПЦ raw2015'!$1:$1,0)) -> 102.69 | P93: =INDEX('ИПЦ raw2015'!$1:$1048576, MATCH($J93,'ИПЦ raw2015'!$A:$A,0),MATCH(MoM!P$1,'ИПЦ raw2015'!$1:$1,0)) -> 100.99 | Q93: =INDEX('ИПЦ raw2015'!$1:$1048576, MATCH($J93,'ИПЦ raw2015'!$A:$A,0),MATCH(MoM!Q$1,'ИПЦ raw2015'!$1:$1,0)) -> 100.55 | R93: =INDEX('ИПЦ raw2015'!$1:$1048576, MATCH($J93,'ИПЦ raw2015'!$A:$A,0),MATCH(MoM!R$1,'ИПЦ raw2015'!$1:$1,0)) -> 99.9 | S93: =INDEX('ИПЦ raw2015'!$1:$1048576, MATCH($J93,'ИПЦ raw2015'!$A:$A,0),MATCH(MoM!S$1,'ИПЦ raw2015'!$1:$1,0)) -> 99.92 | T93: =INDEX('ИПЦ raw2015'!$1:$1048576, MATCH($J93,'ИПЦ raw2015'!$A:$A,0),MATCH(MoM!T$1,'ИПЦ raw2015'!$1:$1,0)) -> 100.47 | ... BT93: =INDEX('ИПЦ raw2015'!$1:$1048576, MATCH($J93,'ИПЦ raw2015'!$A:$A,0),MATCH(MoM!BT$1,'ИПЦ raw2015'!$1:$1,0)) -> 100.33
A94: =Веса!A94 -> 1 | B94: =A94 -> 1 | C94: =БИПЦ_НДС!E94 -> 1 | D94: =1-C94 -> 0 | E94: 1 | F94: 0 | G94: 0 | H94: 0 | I94: 0 | J94: =L94 -> Овощи замороженные, кг | K94: Овощи замороженные, кг | L94: Овощи замороженные, кг | M94: =INDEX('ИПЦ raw2015'!$1:$1048576, MATCH($J94,'ИПЦ raw2015'!$A:$A,0),MATCH(MoM!M$1,'ИПЦ raw2015'!$1:$1,0)) -> 114.04 | N94: =INDEX('ИПЦ raw2015'!$1:$1048576, MATCH($J94,'ИПЦ raw2015'!$A:$A,0),MATCH(MoM!N$1,'ИПЦ raw2015'!$1:$1,0)) -> 109 | O94: =INDEX('ИПЦ raw2015'!$1:$1048576, MATCH($J94,'ИПЦ raw2015'!$A:$A,0),MATCH(MoM!O$1,'ИПЦ raw2015'!$1:$1,0)) -> 105.4 | P94: =INDEX('ИПЦ raw2015'!$1:$1048576, MATCH($J94,'ИПЦ raw2015'!$A:$A,0),MATCH(MoM!P$1,'ИПЦ raw2015'!$1:$1,0)) -> 102.52 | Q94: =INDEX('ИПЦ raw2015'!$1:$1048576, MATCH($J94,'ИПЦ raw2015'!$A:$A,0),MATCH(MoM!Q$1,'ИПЦ raw2015'!$1:$1,0)) -> 100.54 | R94: =INDEX('ИПЦ raw2015'!$1:$1048576, MATCH($J94,'ИПЦ raw2015'!$A:$A,0),MATCH(MoM!R$1,'ИПЦ raw2015'!$1:$1,0)) -> 100.19 | S94: =INDEX('ИПЦ raw2015'!$1:$1048576, MATCH($J94,'ИПЦ raw2015'!$A:$A,0),MATCH(MoM!S$1,'ИПЦ raw2015'!$1:$1,0)) -> 99.95 | T94: =INDEX('ИПЦ raw2015'!$1:$1048576, MATCH($J94,'ИПЦ raw2015'!$A:$A,0),MATCH(MoM!T$1,'ИПЦ raw2015'!$1:$1,0)) -> 99.71 | ... BT94: =INDEX('ИПЦ raw2015'!$1:$1048576, MATCH($J94,'ИПЦ raw2015'!$A:$A,0),MATCH(MoM!BT$1,'ИПЦ raw2015'!$1:$1,0)) -> 100.32
A95: =Веса!A95 -> 1 | B95: =A95 -> 1 | C95: =БИПЦ_НДС!E95 -> 1 | D95: =1-C95 -> 0 | E95: 1 | F95: 0 | G95: 0 | H95: 0 | I95: 0 | J95: =L95 -> Сухофрукты, кг | K95: Сухофрукты, кг | L95: Сухофрукты, кг | M95: =INDEX('ИПЦ raw2015'!$1:$1048576, MATCH($J95,'ИПЦ raw2015'!$A:$A,0),MATCH(MoM!M$1,'ИПЦ raw2015'!$1:$1,0)) -> 109 | N95: =INDEX('ИПЦ raw2015'!$1:$1048576, MATCH($J95,'ИПЦ raw2015'!$A:$A,0),MATCH(MoM!N$1,'ИПЦ raw2015'!$1:$1,0)) -> 108.15 | O95: =INDEX('ИПЦ raw2015'!$1:$1048576, MATCH($J95,'ИПЦ raw2015'!$A:$A,0),MATCH(MoM!O$1,'ИПЦ raw2015'!$1:$1,0)) -> 105.2 | P95: =INDEX('ИПЦ raw2015'!$1:$1048576, MATCH($J95,'ИПЦ raw2015'!$A:$A,0),MATCH(MoM!P$1,'ИПЦ raw2015'!$1:$1,0)) -> 102.41 | Q95: =INDEX('ИПЦ raw2015'!$1:$1048576, MATCH($J95,'ИПЦ raw2015'!$A:$A,0),MATCH(MoM!Q$1,'ИПЦ raw2015'!$1:$1,0)) -> 102.77 | R95: =INDEX('ИПЦ raw2015'!$1:$1048576, MATCH($J95,'ИПЦ raw2015'!$A:$A,0),MATCH(MoM!R$1,'ИПЦ raw2015'!$1:$1,0)) -> 102.27 | S95: =INDEX('ИПЦ raw2015'!$1:$1048576, MATCH($J95,'ИПЦ raw2015'!$A:$A,0),MATCH(MoM!S$1,'ИПЦ raw2015'!$1:$1,0)) -> 102.01 | T95: =INDEX('ИПЦ raw2015'!$1:$1048576, MATCH($J95,'ИПЦ raw2015'!$A:$A,0),MATCH(MoM!T$1,'ИПЦ raw2015'!$1:$1,0)) -> 102.54 | ... BT95: =INDEX('ИПЦ raw2015'!$1:$1048576, MATCH($J95,'ИПЦ raw2015'!$A:$A,0),MATCH(MoM!BT$1,'ИПЦ raw2015'!$1:$1,0)) -> 99.96
A96: =Веса!A96 -> 1 | B96: =A96 -> 1 | C96: =БИПЦ_НДС!E96 -> 1 | D96: =1-C96 -> 0 | E96: 1 | F96: 0 | G96: 0 | H96: 0 | I96: 0 | J96: =L96 -> Орехи, кг | K96: Орехи, кг | L96: Орехи, кг | M96: =INDEX('ИПЦ raw2015'!$1:$1048576, MATCH($J96,'ИПЦ raw2015'!$A:$A,0),MATCH(MoM!M$1,'ИПЦ raw2015'!$1:$1,0)) -> 114.45 | N96: =INDEX('ИПЦ raw2015'!$1:$1048576, MATCH($J96,'ИПЦ raw2015'!$A:$A,0),MATCH(MoM!N$1,'ИПЦ raw2015'!$1:$1,0)) -> 108.36 | O96: =INDEX('ИПЦ raw2015'!$1:$1048576, MATCH($J96,'ИПЦ raw2015'!$A:$A,0),MATCH(MoM!O$1,'ИПЦ raw2015'!$1:$1,0)) -> 105.74 | P96: =INDEX('ИПЦ raw2015'!$1:$1048576, MATCH($J96,'ИПЦ raw2015'!$A:$A,0),MATCH(MoM!P$1,'ИПЦ raw2015'!$1:$1,0)) -> 102.91 | Q96: =INDEX('ИПЦ raw2015'!$1:$1048576, MATCH($J96,'ИПЦ raw2015'!$A:$A,0),MATCH(MoM!Q$1,'ИПЦ raw2015'!$1:$1,0)) -> 100.98 | R96: =INDEX('ИПЦ raw2015'!$1:$1048576, MATCH($J96,'ИПЦ raw2015'!$A:$A,0),MATCH(MoM!R$1,'ИПЦ raw2015'!$1:$1,0)) -> 99.98 | S96: =INDEX('ИПЦ raw2015'!$1:$1048576, MATCH($J96,'ИПЦ raw2015'!$A:$A,0),MATCH(MoM!S$1,'ИПЦ raw2015'!$1:$1,0)) -> 100.31 | T96: =INDEX('ИПЦ raw2015'!$1:$1048576, MATCH($J96,'ИПЦ raw2015'!$A:$A,0),MATCH(MoM!T$1,'ИПЦ raw2015'!$1:$1,0)) -> 100.46 | ... BT96: =INDEX('ИПЦ raw2015'!$1:$1048576, MATCH($J96,'ИПЦ raw2015'!$A:$A,0),MATCH(MoM!BT$1,'ИПЦ raw2015'!$1:$1,0)) -> 100.11
A97: =Веса!A97 -> 0 | B97: =A97 -> 0 | C97: =БИПЦ_НДС!E97 -> 0 | D97: =1-C97 -> 1 | E97: 1 | F97: 0 | G97: 0 | H97: 0 | I97: 0 | J97: =L97 -> Ягоды замороженные, кг | K97: Ягоды замороженные, кг | L97: Ягоды замороженные, кг | M97: 0 | N97: 0 | O97: 0 | P97: 0 | Q97: 0 | R97: 0 | S97: 0 | T97: 0 | U97: 0 | V97: 0 | W97: 0 | X97: 0 | Y97: 0 | Z97: 0 | AA97: 0 | AB97: 0 | AC97: 0 | AD97: 0 | AE97: 0 | AF97: 0 | AG97: 0 | AH97: 0 | AI97: 0 | AJ97: 0 | AK97: 0 | AL97: 0 | AM97: 0 | AN97: 0 | AO97: 0 | AP97: 0 | AQ97: 0 | AR97: 0 | AS97: 0 | AT97: 0 | AU97: 0 | AV97: 0 | AW97: 0 | AX97: 0 | AY97: 0 | AZ97: 0 | BA97: 0 | BB97: 0 | BC97: 0 | BD97: 0 | BE97: 0 | BF97: 0 | BG97: 0 | BH97: 0 | BI97: 0 | BJ97: 0 | BK97: 0 | BL97: 0 | BM97: 0 | BN97: 0 | BO97: 0 | BP97: 0 | BQ97: 0 | BR97: 0 | BS97: 0 | BT97: 0
A98: =Веса!A98 -> 1 | B98: =A98 -> 1 | C98: =БИПЦ_НДС!E98 -> 1 | D98: =1-C98 -> 0 | E98: 1 | F98: 0 | G98: 0 | H98: 0 | I98: 0 | J98: Пиво | K98: Пиво, л | L98: Пиво, л | M98: =INDEX('ИПЦ raw2015'!$1:$1048576, MATCH($J98,'ИПЦ raw2015'!$A:$A,0),MATCH(MoM!M$1,'ИПЦ raw2015'!$1:$1,0)) -> 101.67 | N98: =INDEX('ИПЦ raw2015'!$1:$1048576, MATCH($J98,'ИПЦ raw2015'!$A:$A,0),MATCH(MoM!N$1,'ИПЦ raw2015'!$1:$1,0)) -> 101.18 | O98: =INDEX('ИПЦ raw2015'!$1:$1048576, MATCH($J98,'ИПЦ raw2015'!$A:$A,0),MATCH(MoM!O$1,'ИПЦ raw2015'!$1:$1,0)) -> 101.93 | P98: =INDEX('ИПЦ raw2015'!$1:$1048576, MATCH($J98,'ИПЦ raw2015'!$A:$A,0),MATCH(MoM!P$1,'ИПЦ raw2015'!$1:$1,0)) -> 101.22 | Q98: =INDEX('ИПЦ raw2015'!$1:$1048576, MATCH($J98,'ИПЦ raw2015'!$A:$A,0),MATCH(MoM!Q$1,'ИПЦ raw2015'!$1:$1,0)) -> 100.87 | R98: =INDEX('ИПЦ raw2015'!$1:$1048576, MATCH($J98,'ИПЦ raw2015'!$A:$A,0),MATCH(MoM!R$1,'ИПЦ raw2015'!$1:$1,0)) -> 101.66 | S98: =INDEX('ИПЦ raw2015'!$1:$1048576, MATCH($J98,'ИПЦ raw2015'!$A:$A,0),MATCH(MoM!S$1,'ИПЦ raw2015'!$1:$1,0)) -> 100.97 | T98: =INDEX('ИПЦ raw2015'!$1:$1048576, MATCH($J98,'ИПЦ raw2015'!$A:$A,0),MATCH(MoM!T$1,'ИПЦ raw2015'!$1:$1,0)) -> 100.43 | ... BT98: =INDEX('ИПЦ raw2015'!$1:$1048576, MATCH($J98,'ИПЦ raw2015'!$A:$A,0),MATCH(MoM!BT$1,'ИПЦ raw2015'!$1:$1,0)) -> 100
A99: =Веса!A99 -> 1 | B99: =A99 -> 1 | C99: =БИПЦ_НДС!E99 -> 1 | D99: =1-C99 -> 0 | E99: 1 | F99: 0 | G99: 0 | H99: 0 | I99: 0 | J99: Вода минеральная и питьевая, л | K99: Вода минеральная и питьевая, л | L99: Вода минеральная и питьевая | M99: =INDEX('ИПЦ raw2015'!$1:$1048576, MATCH($J99,'ИПЦ raw2015'!$A:$A,0),MATCH(MoM!M$1,'ИПЦ raw2015'!$1:$1,0)) -> 101.98 | N99: =INDEX('ИПЦ raw2015'!$1:$1048576, MATCH($J99,'ИПЦ raw2015'!$A:$A,0),MATCH(MoM!N$1,'ИПЦ raw2015'!$1:$1,0)) -> 103.2 | O99: =INDEX('ИПЦ raw2015'!$1:$1048576, MATCH($J99,'ИПЦ raw2015'!$A:$A,0),MATCH(MoM!O$1,'ИПЦ raw2015'!$1:$1,0)) -> 102.64 | P99: =INDEX('ИПЦ raw2015'!$1:$1048576, MATCH($J99,'ИПЦ raw2015'!$A:$A,0),MATCH(MoM!P$1,'ИПЦ raw2015'!$1:$1,0)) -> 101.51 | Q99: =INDEX('ИПЦ raw2015'!$1:$1048576, MATCH($J99,'ИПЦ raw2015'!$A:$A,0),MATCH(MoM!Q$1,'ИПЦ raw2015'!$1:$1,0)) -> 100.59 | R99: =INDEX('ИПЦ raw2015'!$1:$1048576, MATCH($J99,'ИПЦ raw2015'!$A:$A,0),MATCH(MoM!R$1,'ИПЦ raw2015'!$1:$1,0)) -> 100.51 | S99: =INDEX('ИПЦ raw2015'!$1:$1048576, MATCH($J99,'ИПЦ raw2015'!$A:$A,0),MATCH(MoM!S$1,'ИПЦ raw2015'!$1:$1,0)) -> 100.09 | T99: =INDEX('ИПЦ raw2015'!$1:$1048576, MATCH($J99,'ИПЦ raw2015'!$A:$A,0),MATCH(MoM!T$1,'ИПЦ raw2015'!$1:$1,0)) -> 100.48 | ... BT99: =INDEX('ИПЦ raw2015'!$1:$1048576, MATCH($J99,'ИПЦ raw2015'!$A:$A,0),MATCH(MoM!BT$1,'ИПЦ raw2015'!$1:$1,0)) -> 100.02
A100: =Веса!A100 -> 1 | B100: =A100 -> 1 | C100: =БИПЦ_НДС!E100 -> 1 | D100: =1-C100 -> 0 | E100: 1 | F100: 0 | G100: 0 | H100: 0 | I100: 0 | J100: =L100 -> Напитки газированные, л | K100: Напитки газированные, л | L100: Напитки газированные, л | M100: =INDEX('ИПЦ raw2015'!$1:$1048576, MATCH($J100,'ИПЦ raw2015'!$A:$A,0),MATCH(MoM!M$1,'ИПЦ raw2015'!$1:$1,0)) -> 102.32 | N100: =INDEX('ИПЦ raw2015'!$1:$1048576, MATCH($J100,'ИПЦ raw2015'!$A:$A,0),MATCH(MoM!N$1,'ИПЦ raw2015'!$1:$1,0)) -> 103.61 | O100: =INDEX('ИПЦ raw2015'!$1:$1048576, MATCH($J100,'ИПЦ raw2015'!$A:$A,0),MATCH(MoM!O$1,'ИПЦ raw2015'!$1:$1,0)) -> 102.45 | P100: =INDEX('ИПЦ raw2015'!$1:$1048576, MATCH($J100,'ИПЦ raw2015'!$A:$A,0),MATCH(MoM!P$1,'ИПЦ raw2015'!$1:$1,0)) -> 101.47 | Q100: =INDEX('ИПЦ raw2015'!$1:$1048576, MATCH($J100,'ИПЦ raw2015'!$A:$A,0),MATCH(MoM!Q$1,'ИПЦ raw2015'!$1:$1,0)) -> 100.93 | R100: =INDEX('ИПЦ raw2015'!$1:$1048576, MATCH($J100,'ИПЦ raw2015'!$A:$A,0),MATCH(MoM!R$1,'ИПЦ raw2015'!$1:$1,0)) -> 100.85 | S100: =INDEX('ИПЦ raw2015'!$1:$1048576, MATCH($J100,'ИПЦ raw2015'!$A:$A,0),MATCH(MoM!S$1,'ИПЦ raw2015'!$1:$1,0)) -> 100.45 | T100: =INDEX('ИПЦ raw2015'!$1:$1048576, MATCH($J100,'ИПЦ raw2015'!$A:$A,0),MATCH(MoM!T$1,'ИПЦ raw2015'!$1:$1,0)) -> 100.19 | ... BT100: =INDEX('ИПЦ raw2015'!$1:$1048576, MATCH($J100,'ИПЦ raw2015'!$A:$A,0),MATCH(MoM!BT$1,'ИПЦ raw2015'!$1:$1,0)) -> 100.02
A101: =Веса!A101 -> 1 | B101: =A101 -> 1 | C101: =БИПЦ_НДС!E101 -> 0 | D101: =1-C101 -> 1 | E101: 1 | F101: 0 | G101: 0 | H101: 0 | I101: 0 | J101: =L101 -> Мороженое сливочное, кг | K101: Мороженое сливочное, кг | L101: Мороженое сливочное, кг | M101: =INDEX('ИПЦ raw2015'!$1:$1048576, MATCH($J101,'ИПЦ raw2015'!$A:$A,0),MATCH(MoM!M$1,'ИПЦ raw2015'!$1:$1,0)) -> 102.26 | N101: =INDEX('ИПЦ raw2015'!$1:$1048576, MATCH($J101,'ИПЦ raw2015'!$A:$A,0),MATCH(MoM!N$1,'ИПЦ raw2015'!$1:$1,0)) -> 102.65 | O101: =INDEX('ИПЦ raw2015'!$1:$1048576, MATCH($J101,'ИПЦ raw2015'!$A:$A,0),MATCH(MoM!O$1,'ИПЦ raw2015'!$1:$1,0)) -> 102.92 | P101: =INDEX('ИПЦ raw2015'!$1:$1048576, MATCH($J101,'ИПЦ raw2015'!$A:$A,0),MATCH(MoM!P$1,'ИПЦ raw2015'!$1:$1,0)) -> 103.16 | Q101: =INDEX('ИПЦ raw2015'!$1:$1048576, MATCH($J101,'ИПЦ raw2015'!$A:$A,0),MATCH(MoM!Q$1,'ИПЦ raw2015'!$1:$1,0)) -> 101.89 | R101: =INDEX('ИПЦ raw2015'!$1:$1048576, MATCH($J101,'ИПЦ raw2015'!$A:$A,0),MATCH(MoM!R$1,'ИПЦ raw2015'!$1:$1,0)) -> 101.33 | S101: =INDEX('ИПЦ raw2015'!$1:$1048576, MATCH($J101,'ИПЦ raw2015'!$A:$A,0),MATCH(MoM!S$1,'ИПЦ raw2015'!$1:$1,0)) -> 101.11 | T101: =INDEX('ИПЦ raw2015'!$1:$1048576, MATCH($J101,'ИПЦ raw2015'!$A:$A,0),MATCH(MoM!T$1,'ИПЦ raw2015'!$1:$1,0)) -> 100.36 | ... BT101: =INDEX('ИПЦ raw2015'!$1:$1048576, MATCH($J101,'ИПЦ raw2015'!$A:$A,0),MATCH(MoM!BT$1,'ИПЦ raw2015'!$1:$1,0)) -> 100.28
A102: =Веса!A102 -> 1 | B102: 0 | C102: =БИПЦ_НДС!E102 -> 1 | D102: =1-C102 -> 0 | E102: 1 | F102: 0 | G102: 0 | H102: 0 | I102: 0 | J102: =L102 -> Кофе в организациях быстрого обслуживания, 200 г | K102: Кофе в организациях быстрого обслуживания, 200 г | L102: Кофе в организациях быстрого обслуживания, 200 г | M102: =INDEX('ИПЦ raw2015'!$1:$1048576, MATCH($J102,'ИПЦ raw2015'!$A:$A,0),MATCH(MoM!M$1,'ИПЦ raw2015'!$1:$1,0)) -> 102.83 | N102: =INDEX('ИПЦ raw2015'!$1:$1048576, MATCH($J102,'ИПЦ raw2015'!$A:$A,0),MATCH(MoM!N$1,'ИПЦ raw2015'!$1:$1,0)) -> 101.15 | O102: =INDEX('ИПЦ raw2015'!$1:$1048576, MATCH($J102,'ИПЦ raw2015'!$A:$A,0),MATCH(MoM!O$1,'ИПЦ raw2015'!$1:$1,0)) -> 101.39 | P102: =INDEX('ИПЦ raw2015'!$1:$1048576, MATCH($J102,'ИПЦ raw2015'!$A:$A,0),MATCH(MoM!P$1,'ИПЦ raw2015'!$1:$1,0)) -> 100.83 | Q102: =INDEX('ИПЦ raw2015'!$1:$1048576, MATCH($J102,'ИПЦ raw2015'!$A:$A,0),MATCH(MoM!Q$1,'ИПЦ raw2015'!$1:$1,0)) -> 100.51 | R102: =INDEX('ИПЦ raw2015'!$1:$1048576, MATCH($J102,'ИПЦ raw2015'!$A:$A,0),MATCH(MoM!R$1,'ИПЦ raw2015'!$1:$1,0)) -> 100.7 | S102: =INDEX('ИПЦ raw2015'!$1:$1048576, MATCH($J102,'ИПЦ raw2015'!$A:$A,0),MATCH(MoM!S$1,'ИПЦ raw2015'!$1:$1,0)) -> 100.69 | T102: =INDEX('ИПЦ raw2015'!$1:$1048576, MATCH($J102,'ИПЦ raw2015'!$A:$A,0),MATCH(MoM!T$1,'ИПЦ raw2015'!$1:$1,0)) -> 100.81 | ... BT102: =INDEX('ИПЦ raw2015'!$1:$1048576, MATCH($J102,'ИПЦ raw2015'!$A:$A,0),MATCH(MoM!BT$1,'ИПЦ raw2015'!$1:$1,0)) -> 100.16
A103: =Веса!A103 -> 1 | B103: 0 | C103: =БИПЦ_НДС!E103 -> 1 | D103: =1-C103 -> 0 | E103: 0 | F103: 0 | G103: 0 | H103: 0 | I103: 0 | J103: =L103 -> Продукция предприятий общественного питания быстрого обслуживания, шт. | K103: Продукция предприятий общественного питания быстрого обслуживания, шт. | L103: Продукция предприятий общественного питания быстрого обслуживания, шт. | M103: =INDEX('ИПЦ raw2015'!$1:$1048576, MATCH($J103,'ИПЦ raw2015'!$A:$A,0),MATCH(MoM!M$1,'ИПЦ raw2015'!$1:$1,0)) -> 102.55 | N103: =INDEX('ИПЦ raw2015'!$1:$1048576, MATCH($J103,'ИПЦ raw2015'!$A:$A,0),MATCH(MoM!N$1,'ИПЦ raw2015'!$1:$1,0)) -> 101.54 | O103: =INDEX('ИПЦ raw2015'!$1:$1048576, MATCH($J103,'ИПЦ raw2015'!$A:$A,0),MATCH(MoM!O$1,'ИПЦ raw2015'!$1:$1,0)) -> 101.41 | P103: =INDEX('ИПЦ raw2015'!$1:$1048576, MATCH($J103,'ИПЦ raw2015'!$A:$A,0),MATCH(MoM!P$1,'ИПЦ raw2015'!$1:$1,0)) -> 101.38 | Q103: =INDEX('ИПЦ raw2015'!$1:$1048576, MATCH($J103,'ИПЦ raw2015'!$A:$A,0),MATCH(MoM!Q$1,'ИПЦ raw2015'!$1:$1,0)) -> 100.65 | R103: =INDEX('ИПЦ raw2015'!$1:$1048576, MATCH($J103,'ИПЦ raw2015'!$A:$A,0),MATCH(MoM!R$1,'ИПЦ raw2015'!$1:$1,0)) -> 100.84 | S103: =INDEX('ИПЦ raw2015'!$1:$1048576, MATCH($J103,'ИПЦ raw2015'!$A:$A,0),MATCH(MoM!S$1,'ИПЦ raw2015'!$1:$1,0)) -> 101.17 | T103: =INDEX('ИПЦ raw2015'!$1:$1048576, MATCH($J103,'ИПЦ raw2015'!$A:$A,0),MATCH(MoM!T$1,'ИПЦ raw2015'!$1:$1,0)) -> 100.8 | ... BT103: =INDEX('ИПЦ raw2015'!$1:$1048576, MATCH($J103,'ИПЦ raw2015'!$A:$A,0),MATCH(MoM!BT$1,'ИПЦ raw2015'!$1:$1,0)) -> 100.06
A104: =Веса!A104 -> 1 | B104: 0 | C104: =БИПЦ_НДС!E104 -> 1 | D104: =1-C104 -> 0 | E104: 0 | F104: 0 | G104: 0 | H104: 0 | I104: 0 | J104: =L104 -> Обед в столовой, кафе, закусочной (кроме столовой в организации), на 1 человека | K104: Обед в столовой, кафе, закусочной (кроме столовой в организации), на 1 человека | L104: Обед в столовой, кафе, закусочной (кроме столовой в организации), на 1 человека | M104: =INDEX('ИПЦ raw2015'!$1:$1048576, MATCH($J104,'ИПЦ raw2015'!$A:$A,0),MATCH(MoM!M$1,'ИПЦ raw2015'!$1:$1,0)) -> 102.29 | N104: =INDEX('ИПЦ raw2015'!$1:$1048576, MATCH($J104,'ИПЦ raw2015'!$A:$A,0),MATCH(MoM!N$1,'ИПЦ raw2015'!$1:$1,0)) -> 101.56 | O104: =INDEX('ИПЦ raw2015'!$1:$1048576, MATCH($J104,'ИПЦ raw2015'!$A:$A,0),MATCH(MoM!O$1,'ИПЦ raw2015'!$1:$1,0)) -> 100.97 | P104: =INDEX('ИПЦ raw2015'!$1:$1048576, MATCH($J104,'ИПЦ raw2015'!$A:$A,0),MATCH(MoM!P$1,'ИПЦ raw2015'!$1:$1,0)) -> 100.96 | Q104: =INDEX('ИПЦ raw2015'!$1:$1048576, MATCH($J104,'ИПЦ raw2015'!$A:$A,0),MATCH(MoM!Q$1,'ИПЦ raw2015'!$1:$1,0)) -> 100.41 | R104: =INDEX('ИПЦ raw2015'!$1:$1048576, MATCH($J104,'ИПЦ raw2015'!$A:$A,0),MATCH(MoM!R$1,'ИПЦ raw2015'!$1:$1,0)) -> 100.4 | S104: =INDEX('ИПЦ raw2015'!$1:$1048576, MATCH($J104,'ИПЦ raw2015'!$A:$A,0),MATCH(MoM!S$1,'ИПЦ raw2015'!$1:$1,0)) -> 100.17 | T104: =INDEX('ИПЦ raw2015'!$1:$1048576, MATCH($J104,'ИПЦ raw2015'!$A:$A,0),MATCH(MoM!T$1,'ИПЦ raw2015'!$1:$1,0)) -> 100.46 | ... BT104: =INDEX('ИПЦ raw2015'!$1:$1048576, MATCH($J104,'ИПЦ raw2015'!$A:$A,0),MATCH(MoM!BT$1,'ИПЦ raw2015'!$1:$1,0)) -> 100.21
A105: =Веса!A105 -> 1 | B105: 0 | C105: =БИПЦ_НДС!E105 -> 1 | D105: =1-C105 -> 0 | E105: 0 | F105: 0 | G105: 0 | H105: 0 | I105: 0 | J105: =L105 -> Обед в ресторане, на 1 человека | K105: Обед в ресторане, на 1 человека | L105: Обед в ресторане, на 1 человека | M105: =INDEX('ИПЦ raw2015'!$1:$1048576, MATCH($J105,'ИПЦ raw2015'!$A:$A,0),MATCH(MoM!M$1,'ИПЦ raw2015'!$1:$1,0)) -> 102.12 | N105: =INDEX('ИПЦ raw2015'!$1:$1048576, MATCH($J105,'ИПЦ raw2015'!$A:$A,0),MATCH(MoM!N$1,'ИПЦ raw2015'!$1:$1,0)) -> 101.47 | O105: =INDEX('ИПЦ raw2015'!$1:$1048576, MATCH($J105,'ИПЦ raw2015'!$A:$A,0),MATCH(MoM!O$1,'ИПЦ raw2015'!$1:$1,0)) -> 100.81 | P105: =INDEX('ИПЦ raw2015'!$1:$1048576, MATCH($J105,'ИПЦ raw2015'!$A:$A,0),MATCH(MoM!P$1,'ИПЦ raw2015'!$1:$1,0)) -> 100.63 | Q105: =INDEX('ИПЦ raw2015'!$1:$1048576, MATCH($J105,'ИПЦ raw2015'!$A:$A,0),MATCH(MoM!Q$1,'ИПЦ raw2015'!$1:$1,0)) -> 100.3 | R105: =INDEX('ИПЦ raw2015'!$1:$1048576, MATCH($J105,'ИПЦ raw2015'!$A:$A,0),MATCH(MoM!R$1,'ИПЦ raw2015'!$1:$1,0)) -> 100.22 | S105: =INDEX('ИПЦ raw2015'!$1:$1048576, MATCH($J105,'ИПЦ raw2015'!$A:$A,0),MATCH(MoM!S$1,'ИПЦ raw2015'!$1:$1,0)) -> 100.14 | T105: =INDEX('ИПЦ raw2015'!$1:$1048576, MATCH($J105,'ИПЦ raw2015'!$A:$A,0),MATCH(MoM!T$1,'ИПЦ raw2015'!$1:$1,0)) -> 100.32 | ... BT105: =INDEX('ИПЦ raw2015'!$1:$1048576, MATCH($J105,'ИПЦ raw2015'!$A:$A,0),MATCH(MoM!BT$1,'ИПЦ raw2015'!$1:$1,0)) -> 99.97
A106: =Веса!A106 -> 1 | B106: 0 | C106: =БИПЦ_НДС!E106 -> 1 | D106: =1-C106 -> 0 | E106: 0 | F106: 0 | G106: 0 | H106: 0 | I106: 0 | J106: =L106 -> Ужин в ресторане, на 1 человека | K106: Ужин в ресторане, на 1 человека | L106: Ужин в ресторане, на 1 человека | M106: =INDEX('ИПЦ raw2015'!$1:$1048576, MATCH($J106,'ИПЦ raw2015'!$A:$A,0),MATCH(MoM!M$1,'ИПЦ raw2015'!$1:$1,0)) -> 102.48 | N106: =INDEX('ИПЦ raw2015'!$1:$1048576, MATCH($J106,'ИПЦ raw2015'!$A:$A,0),MATCH(MoM!N$1,'ИПЦ raw2015'!$1:$1,0)) -> 101.38 | O106: =INDEX('ИПЦ raw2015'!$1:$1048576, MATCH($J106,'ИПЦ raw2015'!$A:$A,0),MATCH(MoM!O$1,'ИПЦ raw2015'!$1:$1,0)) -> 100.68 | P106: =INDEX('ИПЦ raw2015'!$1:$1048576, MATCH($J106,'ИПЦ raw2015'!$A:$A,0),MATCH(MoM!P$1,'ИПЦ raw2015'!$1:$1,0)) -> 100.72 | Q106: =INDEX('ИПЦ raw2015'!$1:$1048576, MATCH($J106,'ИПЦ raw2015'!$A:$A,0),MATCH(MoM!Q$1,'ИПЦ raw2015'!$1:$1,0)) -> 100.6 | R106: =INDEX('ИПЦ raw2015'!$1:$1048576, MATCH($J106,'ИПЦ raw2015'!$A:$A,0),MATCH(MoM!R$1,'ИПЦ raw2015'!$1:$1,0)) -> 100.27 | S106: =INDEX('ИПЦ raw2015'!$1:$1048576, MATCH($J106,'ИПЦ raw2015'!$A:$A,0),MATCH(MoM!S$1,'ИПЦ raw2015'!$1:$1,0)) -> 100.23 | T106: =INDEX('ИПЦ raw2015'!$1:$1048576, MATCH($J106,'ИПЦ raw2015'!$A:$A,0),MATCH(MoM!T$1,'ИПЦ raw2015'!$1:$1,0)) -> 100.25 | ... BT106: =INDEX('ИПЦ raw2015'!$1:$1048576, MATCH($J106,'ИПЦ raw2015'!$A:$A,0),MATCH(MoM!BT$1,'ИПЦ raw2015'!$1:$1,0)) -> 100.05
A107: =Веса!A107 -> 1 | B107: =A107 -> 1 | C107: =БИПЦ_НДС!E107 -> 1 | D107: =1-C107 -> 0 | E107: 0 | F107: 1 | G107: 0 | H107: 1 | I107: 0 | J107: =L107 -> Ткани хлопчатобумажные бельевые, м | K107: Ткани хлопчатобумажные бельевые, м | L107: Ткани хлопчатобумажные бельевые, м | M107: =INDEX('ИПЦ raw2015'!$1:$1048576, MATCH($J107,'ИПЦ raw2015'!$A:$A,0),MATCH(MoM!M$1,'ИПЦ raw2015'!$1:$1,0)) -> 104.22 | N107: =INDEX('ИПЦ raw2015'!$1:$1048576, MATCH($J107,'ИПЦ raw2015'!$A:$A,0),MATCH(MoM!N$1,'ИПЦ raw2015'!$1:$1,0)) -> 103.65 | O107: =INDEX('ИПЦ raw2015'!$1:$1048576, MATCH($J107,'ИПЦ raw2015'!$A:$A,0),MATCH(MoM!O$1,'ИПЦ raw2015'!$1:$1,0)) -> 102.8 | P107: =INDEX('ИПЦ raw2015'!$1:$1048576, MATCH($J107,'ИПЦ raw2015'!$A:$A,0),MATCH(MoM!P$1,'ИПЦ raw2015'!$1:$1,0)) -> 103.19 | Q107: =INDEX('ИПЦ raw2015'!$1:$1048576, MATCH($J107,'ИПЦ raw2015'!$A:$A,0),MATCH(MoM!Q$1,'ИПЦ raw2015'!$1:$1,0)) -> 100.72 | R107: =INDEX('ИПЦ raw2015'!$1:$1048576, MATCH($J107,'ИПЦ raw2015'!$A:$A,0),MATCH(MoM!R$1,'ИПЦ raw2015'!$1:$1,0)) -> 100.98 | S107: =INDEX('ИПЦ raw2015'!$1:$1048576, MATCH($J107,'ИПЦ raw2015'!$A:$A,0),MATCH(MoM!S$1,'ИПЦ raw2015'!$1:$1,0)) -> 100.63 | T107: =INDEX('ИПЦ raw2015'!$1:$1048576, MATCH($J107,'ИПЦ raw2015'!$A:$A,0),MATCH(MoM!T$1,'ИПЦ raw2015'!$1:$1,0)) -> 100.55 | ... BT107: =INDEX('ИПЦ raw2015'!$1:$1048576, MATCH($J107,'ИПЦ raw2015'!$A:$A,0),MATCH(MoM!BT$1,'ИПЦ raw2015'!$1:$1,0)) -> 100.22
...

Sheet ToSep17
A1: Доступен весь период | B1: Учитывать | C1: Базовая ставка | D1: Льготная ставка | E1: Проды | F1: Непроды | G1: Непроды без одежды | H1: Одежда | I1: Услуги | J1: Название Классификатор 2026 | K1: Название витрина данных Росстата | L1: Название Классификатор 2015 | M1: 42005 | N1: 42036 | O1: 42064 | P1: 42095 | Q1: 42125 | R1: 42156 | S1: 42186 | T1: 42217 | U1: 42248 | V1: 42278 | W1: 42309 | X1: 42339 | Y1: 42370 | Z1: 42401 | AA1: 42430 | AB1: 42461 | AC1: 42491 | AD1: 42522 | AE1: 42552 | AF1: 42583 | AG1: 42614 | AH1: 42644 | AI1: 42675 | AJ1: 42705 | AK1: 42736 | AL1: 42767 | AM1: 42795 | AN1: 42826 | AO1: 42856 | AP1: 42887 | AQ1: 42917 | AR1: 42948 | AS1: 42979 | AT1: 43009 | AU1: 43040 | AV1: 43070 | AW1: 43101 | AX1: 43132 | AY1: 43160 | AZ1: 43191 | BA1: 43221 | BB1: 43252 | BC1: 43282 | BD1: 43313 | BE1: 43344 | BF1: 43374 | BG1: 43405 | BH1: 43435 | BI1: 43466 | BJ1: 43497 | BK1: 43525 | BL1: 43556 | BM1: 43586 | BN1: 43617 | BO1: 43647 | BP1: 43678 | BQ1: 43709 | BR1: 43739 | BS1: 43770 | BT1: 43800
A2: =Веса!A2 -> 1 | B2: =MoM!B2 -> 1 | C2: =БИПЦ_НДС!E2 -> 0 | D2: =1-C2 -> 1 | E2: 1 | F2: 0 | G2: 0 | H2: 0 | I2: 0 | J2: Говядина (кроме бескостного мяса), кг | K2: Говядина (кроме бескостного мяса), кг | L2: =MoM!J2 -> Говядина (кроме бескостного мяса), кг | M2: =IF(MoM!N2=0,0,N2/MoM!N2*100) -> 0.89358831 | N2: =IF(MoM!O2=0,0,O2/MoM!O2*100) -> 0.92432775 | O2: =IF(MoM!P2=0,0,P2/MoM!P2*100) -> 0.94161268 | P2: =IF(MoM!Q2=0,0,Q2/MoM!Q2*100) -> 0.94641491 | Q2: =IF(MoM!R2=0,0,R2/MoM!R2*100) -> 0.95124162 | R2: =IF(MoM!S2=0,0,S2/MoM!S2*100) -> 0.95162212 | S2: =IF(MoM!T2=0,0,T2/MoM!T2*100) -> 0.95352536 | T2: =IF(MoM!U2=0,0,U2/MoM!U2*100) -> 0.9606768 | ... AR2: =IF(MoM!AS2=0,0,AS2/MoM!AS2*100) -> 0.99880144 | AS2: 1 | AT2: =AS2*MoM!AT2/100 -> 1.0027 | AU2: =AT2*MoM!AU2/100 -> 1.0033016 | AV2: =AU2*MoM!AV2/100 -> 1.0062112 | AW2: =AV2*MoM!AW2/100 -> 1.0066137 | AX2: =AW2*MoM!AX2/100 -> 1.0064124 | AY2: =AX2*MoM!AY2/100 -> 1.0067143 | AZ2: =AY2*MoM!AZ2/100 -> 1.007721
A3: =Веса!A3 -> 1 | B3: =MoM!B3 -> 1 | C3: =БИПЦ_НДС!E3 -> 0 | D3: =1-C3 -> 1 | E3: 1 | F3: 0 | G3: 0 | H3: 0 | I3: 0 | J3: Говядина бескостная, кг | K3: Говядина бескостная, кг | L3: =MoM!J3 -> Говядина бескостная, кг | M3: =IF(MoM!N3=0,0,N3/MoM!N3*100) -> 0.89627687 | N3: =IF(MoM!O3=0,0,O3/MoM!O3*100) -> 0.92146225 | O3: =IF(MoM!P3=0,0,P3/MoM!P3*100) -> 0.9385093 | P3: =IF(MoM!Q3=0,0,Q3/MoM!Q3*100) -> 0.94902061 | Q3: =IF(MoM!R3=0,0,R3/MoM!R3*100) -> 0.9531963 | R3: =IF(MoM!S3=0,0,S3/MoM!S3*100) -> 0.95557929 | S3: =IF(MoM!T3=0,0,T3/MoM!T3*100) -> 0.95863714 | T3: =IF(MoM!U3=0,0,U3/MoM!U3*100) -> 0.96256755 | ... AR3: =IF(MoM!AS3=0,0,AS3/MoM!AS3*100) -> 0.99930049 | AS3: 1 | AT3: =AS3*MoM!AT3/100 -> 1.0016 | AU3: =AT3*MoM!AU3/100 -> 1.0032026 | AV3: =AU3*MoM!AV3/100 -> 1.007416 | AW3: =AV3*MoM!AW3/100 -> 1.0103375 | AX3: =AW3*MoM!AX3/100 -> 1.011752 | AY3: =AX3*MoM!AY3/100 -> 1.0126626 | AZ3: =AY3*MoM!AZ3/100 -> 1.0145866
A4: =Веса!A4 -> 1 | B4: =MoM!B4 -> 1 | C4: =БИПЦ_НДС!E4 -> 0 | D4: =1-C4 -> 1 | E4: 1 | F4: 0 | G4: 0 | H4: 0 | I4: 0 | J4: Свинина (кроме бескостного мяса), кг | K4: Свинина (кроме бескостного мяса), кг | L4: =MoM!J4 -> Свинина (кроме бескостного мяса), кг | M4: =IF(MoM!N4=0,0,N4/MoM!N4*100) -> 1.042179 | N4: =IF(MoM!O4=0,0,O4/MoM!O4*100) -> 1.0342584 | O4: =IF(MoM!P4=0,0,P4/MoM!P4*100) -> 1.0293974 | P4: =IF(MoM!Q4=0,0,Q4/MoM!Q4*100) -> 1.0390737 | Q4: =IF(MoM!R4=0,0,R4/MoM!R4*100) -> 1.0427105 | R4: =IF(MoM!S4=0,0,S4/MoM!S4*100) -> 1.0409379 | S4: =IF(MoM!T4=0,0,T4/MoM!T4*100) -> 1.0451016 | T4: =IF(MoM!U4=0,0,U4/MoM!U4*100) -> 1.0462512 | ... AR4: =IF(MoM!AS4=0,0,AS4/MoM!AS4*100) -> 0.99940036 | AS4: 1 | AT4: =AS4*MoM!AT4/100 -> 0.9966 | AU4: =AT4*MoM!AU4/100 -> 0.98683332 | AV4: =AU4*MoM!AV4/100 -> 0.98594517 | AW4: =AV4*MoM!AW4/100 -> 0.98032528 | AX4: =AW4*MoM!AX4/100 -> 0.96836531 | AY4: =AX4*MoM!AY4/100 -> 0.95839115 | AZ4: =AY4*MoM!AZ4/100 -> 0.9707544
A5: =Веса!A5 -> 1 | B5: =MoM!B5 -> 1 | C5: =БИПЦ_НДС!E5 -> 0 | D5: =1-C5 -> 1 | E5: 1 | F5: 0 | G5: 0 | H5: 0 | I5: 0 | J5: Свинина бескостная, кг | K5: Свинина бескостная, кг | L5: =MoM!J5 -> Свинина бескостная, кг | M5: =IF(MoM!N5=0,0,N5/MoM!N5*100) -> 1.0188765 | N5: =IF(MoM!O5=0,0,O5/MoM!O5*100) -> 1.0155142 | O5: =IF(MoM!P5=0,0,P5/MoM!P5*100) -> 1.0147018 | P5: =IF(MoM!Q5=0,0,Q5/MoM!Q5*100) -> 1.0189636 | Q5: =IF(MoM!R5=0,0,R5/MoM!R5*100) -> 1.0237527 | R5: =IF(MoM!S5=0,0,S5/MoM!S5*100) -> 1.0261073 | S5: =IF(MoM!T5=0,0,T5/MoM!T5*100) -> 1.0303144 | T5: =IF(MoM!U5=0,0,U5/MoM!U5*100) -> 1.0334053 | ... AR5: =IF(MoM!AS5=0,0,AS5/MoM!AS5*100) -> 1.0007005 | AS5: 1 | AT5: =AS5*MoM!AT5/100 -> 0.9946 | AU5: =AT5*MoM!AU5/100 -> 0.9876378 | AV5: =AU5*MoM!AV5/100 -> 0.98556376 | AW5: =AV5*MoM!AW5/100 -> 0.98359263 | AX5: =AW5*MoM!AX5/100 -> 0.97769108 | AY5: =AX5*MoM!AY5/100 -> 0.97211824 | AZ5: =AY5*MoM!AZ5/100 -> 0.97824258
A6: =Веса!A6 -> 1 | B6: =MoM!B6 -> 1 | C6: =БИПЦ_НДС!E6 -> 0 | D6: =1-C6 -> 1 | E6: 1 | F6: 0 | G6: 0 | H6: 0 | I6: 0 | J6: Баранина (кроме бескостного мяса), кг | K6: Баранина (кроме бескостного мяса), кг | L6: =MoM!J6 -> Баранина (кроме бескостного мяса), кг | M6: =IF(MoM!N6=0,0,N6/MoM!N6*100) -> 0.91480492 | N6: =IF(MoM!O6=0,0,O6/MoM!O6*100) -> 0.93264361 | O6: =IF(MoM!P6=0,0,P6/MoM!P6*100) -> 0.94252963 | P6: =IF(MoM!Q6=0,0,Q6/MoM!Q6*100) -> 0.95911816 | Q6: =IF(MoM!R6=0,0,R6/MoM!R6*100) -> 0.96333828 | R6: =IF(MoM!S6=0,0,S6/MoM!S6*100) -> 0.96073726 | S6: =IF(MoM!T6=0,0,T6/MoM!T6*100) -> 0.96265874 | T6: =IF(MoM!U6=0,0,U6/MoM!U6*100) -> 0.96323633 | ... AR6: =IF(MoM!AS6=0,0,AS6/MoM!AS6*100) -> 0.99930049 | AS6: 1 | AT6: =AS6*MoM!AT6/100 -> 0.9975 | AU6: =AT6*MoM!AU6/100 -> 0.99540525 | AV6: =AU6*MoM!AV6/100 -> 0.99988457 | AW6: =AV6*MoM!AW6/100 -> 1.0027842 | AX6: =AW6*MoM!AX6/100 -> 1.0025837 | AY6: =AX6*MoM!AY6/100 -> 1.0024834 | AZ6: =AY6*MoM!AZ6/100 -> 1.0061926
A7: =Веса!A7 -> 1 | B7: =MoM!B7 -> 1 | C7: =БИПЦ_НДС!E7 -> 0 | D7: =1-C7 -> 1 | E7: 1 | F7: 0 | G7: 0 | H7: 0 | I7: 0 | J7: Куры охлажденные и мороженые, кг | K7: Куры охлажденные и мороженые, кг | L7: =MoM!J7 -> Куры охлажденные и мороженые, кг | M7: =IF(MoM!N7=0,0,N7/MoM!N7*100) -> 1.0591533 | N7: =IF(MoM!O7=0,0,O7/MoM!O7*100) -> 1.0587297 | O7: =IF(MoM!P7=0,0,P7/MoM!P7*100) -> 1.0514244 | P7: =IF(MoM!Q7=0,0,Q7/MoM!Q7*100) -> 1.0396485 | Q7: =IF(MoM!R7=0,0,R7/MoM!R7*100) -> 1.029148 | R7: =IF(MoM!S7=0,0,S7/MoM!S7*100) -> 1.0223556 | S7: =IF(MoM!T7=0,0,T7/MoM!T7*100) -> 1.0193908 | T7: =IF(MoM!U7=0,0,U7/MoM!U7*100) -> 1.0171481 | ... AR7: =IF(MoM!AS7=0,0,AS7/MoM!AS7*100) -> 1.003613 | AS7: 1 | AT7: =AS7*MoM!AT7/100 -> 0.9952 | AU7: =AT7*MoM!AU7/100 -> 0.98236192 | AV7: =AU7*MoM!AV7/100 -> 0.97489597 | AW7: =AV7*MoM!AW7/100 -> 0.96758425 | AX7: =AW7*MoM!AX7/100 -> 0.96052088 | AY7: =AX7*MoM!AY7/100 -> 0.95005121 | AZ7: =AY7*MoM!AZ7/100 -> 0.94653602
A8: =Веса!A8 -> 1 | B8: =MoM!B8 -> 1 | C8: =БИПЦ_НДС!E8 -> 0 | D8: =1-C8 -> 1 | E8: 1 | F8: 0 | G8: 0 | H8: 0 | I8: 0 | J8: Окорочка куриные, кг | K8: Окорочка куриные, кг | L8: =MoM!J8 -> Окорочка куриные, кг | M8: =IF(MoM!N8=0,0,N8/MoM!N8*100) -> 0.99793082 | N8: =IF(MoM!O8=0,0,O8/MoM!O8*100) -> 1.0077105 | O8: =IF(MoM!P8=0,0,P8/MoM!P8*100) -> 1.0065013 | P8: =IF(MoM!Q8=0,0,Q8/MoM!Q8*100) -> 0.99895253 | Q8: =IF(MoM!R8=0,0,R8/MoM!R8*100) -> 0.99385787 | R8: =IF(MoM!S8=0,0,S8/MoM!S8*100) -> 0.99037937 | S8: =IF(MoM!T8=0,0,T8/MoM!T8*100) -> 0.98928995 | T8: =IF(MoM!U8=0,0,U8/MoM!U8*100) -> 0.9897846 | ... AR8: =IF(MoM!AS8=0,0,AS8/MoM!AS8*100) -> 1.0017029 | AS8: 1 | AT8: =AS8*MoM!AT8/100 -> 0.998 | AU8: =AT8*MoM!AU8/100 -> 0.9928104 | AV8: =AU8*MoM!AV8/100 -> 0.99022909 | AW8: =AV8*MoM!AW8/100 -> 0.98527795 | AX8: =AW8*MoM!AX8/100 -> 0.97887364 | AY8: =AX8*MoM!AY8/100 -> 0.97202153 | AZ8: =AY8*MoM!AZ8/100 -> 0.96793903
A9: =Веса!A9 -> 0 | B9: =MoM!B9 -> 0 | C9: =БИПЦ_НДС!E9 -> 0 | D9: =1-C9 -> 1 | E9: 1 | F9: 0 | G9: 0 | H9: 0 | I9: 0 | J9: Мясо индейки, кг | K9: Мясо индейки,кг | L9: =MoM!J9 -> Мясо индейки, кг | M9: =IF(MoM!N9=0,0,N9/MoM!N9*100) -> 0 | N9: =IF(MoM!O9=0,0,O9/MoM!O9*100) -> 0 | O9: =IF(MoM!P9=0,0,P9/MoM!P9*100) -> 0 | P9: =IF(MoM!Q9=0,0,Q9/MoM!Q9*100) -> 0 | Q9: =IF(MoM!R9=0,0,R9/MoM!R9*100) -> 0 | R9: =IF(MoM!S9=0,0,S9/MoM!S9*100) -> 0 | S9: =IF(MoM!T9=0,0,T9/MoM!T9*100) -> 0 | T9: =IF(MoM!U9=0,0,U9/MoM!U9*100) -> 0 | ... AR9: =IF(MoM!AS9=0,0,AS9/MoM!AS9*100) -> 0 | AS9: 1 | AT9: =AS9*MoM!AT9/100 -> 0 | AU9: =AT9*MoM!AU9/100 -> 0 | AV9: =AU9*MoM!AV9/100 -> 0 | AW9: =AV9*MoM!AW9/100 -> 0 | AX9: =AW9*MoM!AX9/100 -> 0 | AY9: =AX9*MoM!AY9/100 -> 0 | AZ9: =AY9*MoM!AZ9/100 -> 0
A10: =Веса!A10 -> 1 | B10: =MoM!B10 -> 1 | C10: =БИПЦ_НДС!E10 -> 0 | D10: =1-C10 -> 1 | E10: 1 | F10: 0 | G10: 0 | H10: 0 | I10: 0 | J10: Печень говяжья, свиная, кг | K10: Печень говяжья, свиная, кг | L10: =MoM!J10 -> Печень говяжья, кг | M10: =IF(MoM!N10=0,0,N10/MoM!N10*100) -> 0.9000657 | N10: =IF(MoM!O10=0,0,O10/MoM!O10*100) -> 0.94542901 | O10: =IF(MoM!P10=0,0,P10/MoM!P10*100) -> 0.97237374 | P10: =IF(MoM!Q10=0,0,Q10/MoM!Q10*100) -> 0.98015273 | Q10: =IF(MoM!R10=0,0,R10/MoM!R10*100) -> 0.97005716 | R10: =IF(MoM!S10=0,0,S10/MoM!S10*100) -> 0.9639458 | S10: =IF(MoM!T10=0,0,T10/MoM!T10*100) -> 0.9567162 | T10: =IF(MoM!U10=0,0,U10/MoM!U10*100) -> 0.95461143 | ... AR10: =IF(MoM!AS10=0,0,AS10/MoM!AS10*100) -> 0.99990001 | AS10: 1 | AT10: =AS10*MoM!AT10/100 -> 1.0023 | AU10: =AT10*MoM!AU10/100 -> 1.0051064 | AV10: =AU10*MoM!AV10/100 -> 1.0119412 | AW10: =AV10*MoM!AW10/100 -> 1.01184 | AX10: =AW10*MoM!AX10/100 -> 1.0128518 | AY10: =AX10*MoM!AY10/100 -> 1.0120415 | AZ10: =AY10*MoM!AZ10/100 -> 1.0104223
A11: =Веса!A11 -> 1 | B11: =MoM!B11 -> 1 | C11: =БИПЦ_НДС!E11 -> 0 | D11: =1-C11 -> 1 | E11: 1 | F11: 0 | G11: 0 | H11: 0 | I11: 0 | J11: Фарш мясной, кг | K11: Фарш мясной, кг | L11: =MoM!J11 -> Фарш мясной, кг | M11: =IF(MoM!N11=0,0,N11/MoM!N11*100) -> 0.90404606 | N11: =IF(MoM!O11=0,0,O11/MoM!O11*100) -> 0.93116744 | O11: =IF(MoM!P11=0,0,P11/MoM!P11*100) -> 0.94681105 | P11: =IF(MoM!Q11=0,0,Q11/MoM!Q11*100) -> 0.9541015 | Q11: =IF(MoM!R11=0,0,R11/MoM!R11*100) -> 0.95591429 | R11: =IF(MoM!S11=0,0,S11/MoM!S11*100) -> 0.95715698 | S11: =IF(MoM!T11=0,0,T11/MoM!T11*100) -> 0.95935844 | T11: =IF(MoM!U11=0,0,U11/MoM!U11*100) -> 0.96501866 | ... AR11: =IF(MoM!AS11=0,0,AS11/MoM!AS11*100) -> 1.0033109 | AS11: 1 | AT11: =AS11*MoM!AT11/100 -> 0.9991 | AU11: =AT11*MoM!AU11/100 -> 0.99969946 | AV11: =AU11*MoM!AV11/100 -> 0.99999937 | AW11: =AV11*MoM!AW11/100 -> 1.0010994 | AX11: =AW11*MoM!AX11/100 -> 0.99959772 | AY11: =AX11*MoM!AY11/100 -> 0.99589921 | AZ11: =AY11*MoM!AZ11/100 -> 0.99729347
A12: =Веса!A12 -> 1 | B12: =MoM!B12 -> 1 | C12: =БИПЦ_НДС!E12 -> 0 | D12: =1-C12 -> 1 | E12: 1 | F12: 0 | G12: 0 | H12: 0 | I12: 0 | J12: Пельмени, манты, равиоли, кг | K12: Пельмени, манты, равиоли, кг | L12: =MoM!J12 -> Пельмени, манты, равиоли, кг | M12: =IF(MoM!N12=0,0,N12/MoM!N12*100) -> 0.83698115 | N12: =IF(MoM!O12=0,0,O12/MoM!O12*100) -> 0.86292756 | O12: =IF(MoM!P12=0,0,P12/MoM!P12*100) -> 0.88139421 | P12: =IF(MoM!Q12=0,0,Q12/MoM!Q12*100) -> 0.8923235 | Q12: =IF(MoM!R12=0,0,R12/MoM!R12*100) -> 0.90044364 | R12: =IF(MoM!S12=0,0,S12/MoM!S12*100) -> 0.90629653 | S12: =IF(MoM!T12=0,0,T12/MoM!T12*100) -> 0.91100927 | T12: =IF(MoM!U12=0,0,U12/MoM!U12*100) -> 0.91328679 | ... AR12: =IF(MoM!AS12=0,0,AS12/MoM!AS12*100) -> 0.9981036 | AS12: 1 | AT12: =AS12*MoM!AT12/100 -> 1.0044 | AU12: =AT12*MoM!AU12/100 -> 1.0070114 | AV12: =AU12*MoM!AV12/100 -> 1.0100325 | AW12: =AV12*MoM!AW12/100 -> 1.0143756 | AX12: =AW12*MoM!AX12/100 -> 1.0155929 | AY12: =AX12*MoM!AY12/100 -> 1.0166085 | AZ12: =AY12*MoM!AZ12/100 -> 1.0171168
A13: =Веса!A13 -> 1 | B13: =MoM!B13 -> 1 | C13: =БИПЦ_НДС!E13 -> 0 | D13: =1-C13 -> 1 | E13: 1 | F13: 0 | G13: 0 | H13: 0 | I13: 0 | J13: Сосиски, сардельки, кг | K13: Сосиски, сардельки, кг | L13: =MoM!J13 -> Сосиски, сардельки, кг | M13: =IF(MoM!N13=0,0,N13/MoM!N13*100) -> 0.86590719 | N13: =IF(MoM!O13=0,0,O13/MoM!O13*100) -> 0.8872951 | O13: =IF(MoM!P13=0,0,P13/MoM!P13*100) -> 0.9020242 | P13: =IF(MoM!Q13=0,0,Q13/MoM!Q13*100) -> 0.91257788 | Q13: =IF(MoM!R13=0,0,R13/MoM!R13*100) -> 0.91777958 | R13: =IF(MoM!S13=0,0,S13/MoM!S13*100) -> 0.91952336 | S13: =IF(MoM!T13=0,0,T13/MoM!T13*100) -> 0.92255779 | T13: =IF(MoM!U13=0,0,U13/MoM!U13*100) -> 0.92495644 | ... AR13: =IF(MoM!AS13=0,0,AS13/MoM!AS13*100) -> 0.99910081 | AS13: 1 | AT13: =AS13*MoM!AT13/100 -> 1.0004 | AU13: =AT13*MoM!AU13/100 -> 1.0033012 | AV13: =AU13*MoM!AV13/100 -> 1.0066121 | AW13: =AV13*MoM!AW13/100 -> 1.0087259 | AX13: =AW13*MoM!AX13/100 -> 1.0093312 | AY13: =AX13*MoM!AY13/100 -> 1.0123592 | AZ13: =AY13*MoM!AZ13/100 -> 1.0131691
... A433: =Веса!A433 -> 1 | B433: =MoM!B433 -> 1 | C433: =БИПЦ_НДС!E433 -> 1 | D433: =1-C433 -> 0 | E433: 0 | F433: 0 | G433: 0 | H433: 0 | I433: 1 | J433: Пользование общественным туалетом, посещение | K433: Пользование общественным туалетом, посещение | L433: =MoM!J433 -> Пользование общественным туалетом, посещение | M433: =IF(MoM!N433=0,0,N433/MoM!N433*100) -> 0.85499656 | N433: =IF(MoM!O433=0,0,O433/MoM!O433*100) -> 0.86158004 | O433: =IF(MoM!P433=0,0,P433/MoM!P433*100) -> 0.8659741 | P433: =IF(MoM!Q433=0,0,Q433/MoM!Q433*100) -> 0.86770604 | Q433: =IF(MoM!R433=0,0,R433/MoM!R433*100) -> 0.87013562 | R433: =IF(MoM!S433=0,0,S433/MoM!S433*100) -> 0.87335512 | S433: =IF(MoM!T433=0,0,T433/MoM!T433*100) -> 0.87658654 | T433: =IF(MoM!U433=0,0,U433/MoM!U433*100) -> 0.88728089 | ... AR433: =IF(MoM!AS433=0,0,AS433/MoM!AS433*100) -> 0.99621439 | AS433: 1 | AT433: =AS433*MoM!AT433/100 -> 1.0004 | AU433: =AT433*MoM!AU433/100 -> 1.0021007 | AV433: =AU433*MoM!AV433/100 -> 1.0081133 | AW433: =AV433*MoM!AW433/100 -> 1.0134563 | AX433: =AW433*MoM!AX433/100 -> 1.0138617 | AY433: =AX433*MoM!AY433/100 -> 1.0177143 | AZ433: =AY433*MoM!AZ433/100 -> 1.0179179
L435: Treatment | M435: =SUMPRODUCT(M2:M433,Веса!H2:H433,ToSep17!$C2:$C433,$B2:$B433)/SUMPRODUCT(Веса!H2:H433,ToSep17!$C2:$C433, $B2:$B433) -> 0.83726896 | N435: =SUMPRODUCT(N2:N433,Веса!I2:I433,ToSep17!$C2:$C433,$B2:$B433)/SUMPRODUCT(Веса!I2:I433,ToSep17!$C2:$C433, $B2:$B433) -> 0.85613842 | O435: =SUMPRODUCT(O2:O433,Веса!J2:J433,ToSep17!$C2:$C433,$B2:$B433)/SUMPRODUCT(Веса!J2:J433,ToSep17!$C2:$C433, $B2:$B433) -> 0.870992 | P435: =SUMPRODUCT(P2:P433,Веса!K2:K433,ToSep17!$C2:$C433,$B2:$B433)/SUMPRODUCT(Веса!K2:K433,ToSep17!$C2:$C433, $B2:$B433) -> 0.88190596 | Q435: =SUMPRODUCT(Q2:Q433,Веса!L2:L433,ToSep17!$C2:$C433,$B2:$B433)/SUMPRODUCT(Веса!L2:L433,ToSep17!$C2:$C433, $B2:$B433) -> 0.88792262 | R435: =SUMPRODUCT(R2:R433,Веса!M2:M433,ToSep17!$C2:$C433,$B2:$B433)/SUMPRODUCT(Веса!M2:M433,ToSep17!$C2:$C433, $B2:$B433) -> 0.89174681 | S435: =SUMPRODUCT(S2:S433,Веса!N2:N433,ToSep17!$C2:$C433,$B2:$B433)/SUMPRODUCT(Веса!N2:N433,ToSep17!$C2:$C433, $B2:$B433) -> 0.89425391 | T435: =SUMPRODUCT(T2:T433,Веса!O2:O433,ToSep17!$C2:$C433,$B2:$B433)/SUMPRODUCT(Веса!O2:O433,ToSep17!$C2:$C433, $B2:$B433) -> 0.89900953 | ... AZ435: =SUMPRODUCT(AZ2:AZ433,Веса!AU2:AU433,ToSep17!$C2:$C433,$B2:$B433)/SUMPRODUCT(Веса!AU2:AU433,ToSep17!$C2:$C433, $B2:$B433) -> 1.0130941
L436: Treatment Проды | M436: =SUMPRODUCT(M2:M433,Веса!H2:H433,ToSep17!$C2:$C433,$E2:$E433,$B2:$B433)/SUMPRODUCT(Веса!H2:H433,ToSep17!$C2:$C433,$E2:$E433,$B2:$B433) -> 0.78810901 | N436: =SUMPRODUCT(N2:N433,Веса!I2:I433,ToSep17!$C2:$C433,$E2:$E433,$B2:$B433)/SUMPRODUCT(Веса!I2:I433,ToSep17!$C2:$C433,$E2:$E433,$B2:$B433) -> 0.8185874 | O436: =SUMPRODUCT(O2:O433,Веса!J2:J433,ToSep17!$C2:$C433,$E2:$E433,$B2:$B433)/SUMPRODUCT(Веса!J2:J433,ToSep17!$C2:$C433,$E2:$E433,$B2:$B433) -> 0.84086109 | P436: =SUMPRODUCT(P2:P433,Веса!K2:K433,ToSep17!$C2:$C433,$E2:$E433,$B2:$B433)/SUMPRODUCT(Веса!K2:K433,ToSep17!$C2:$C433,$E2:$E433,$B2:$B433) -> 0.85665108 | Q436: =SUMPRODUCT(Q2:Q433,Веса!L2:L433,ToSep17!$C2:$C433,$E2:$E433,$B2:$B433)/SUMPRODUCT(Веса!L2:L433,ToSep17!$C2:$C433,$E2:$E433,$B2:$B433) -> 0.86732598 | R436: =SUMPRODUCT(R2:R433,Веса!M2:M433,ToSep17!$C2:$C433,$E2:$E433,$B2:$B433)/SUMPRODUCT(Веса!M2:M433,ToSep17!$C2:$C433,$E2:$E433,$B2:$B433) -> 0.87526124 | S436: =SUMPRODUCT(S2:S433,Веса!N2:N433,ToSep17!$C2:$C433,$E2:$E433,$B2:$B433)/SUMPRODUCT(Веса!N2:N433,ToSep17!$C2:$C433,$E2:$E433,$B2:$B433) -> 0.88038687 | T436: =SUMPRODUCT(T2:T433,Веса!O2:O433,ToSep17!$C2:$C433,$E2:$E433,$B2:$B433)/SUMPRODUCT(Веса!O2:O433,ToSep17!$C2:$C433,$E2:$E433,$B2:$B433) -> 0.88556559 | ... AR436: =SUMPRODUCT(AR2:AR433,Веса!AM2:AM433,ToSep17!$C2:$C433,$E2:$E433,$B2:$B433)/SUMPRODUCT(Веса!AM2:AM433,ToSep17!$C2:$C433,$E2:$E433,$B2:$B433) -> 0.99850932 | AS436: 1 | AT436: =SUMPRODUCT(AT2:AT433,Веса!AO2:AO433,ToSep17!$C2:$C433,$E2:$E433,$B2:$B433)/SUMPRODUCT(Веса!AO2:AO433,ToSep17!$C2:$C433,$E2:$E433,$B2:$B433) -> 1.0025587 | AU436: =SUMPRODUCT(AU2:AU433,Веса!AP2:AP433,ToSep17!$C2:$C433,$E2:$E433,$B2:$B433)/SUMPRODUCT(Веса!AP2:AP433,ToSep17!$C2:$C433,$E2:$E433,$B2:$B433) -> 1.0038926 | AV436: =SUMPRODUCT(AV2:AV433,Веса!AQ2:AQ433,ToSep17!$C2:$C433,$E2:$E433,$B2:$B433)/SUMPRODUCT(Веса!AQ2:AQ433,ToSep17!$C2:$C433,$E2:$E433,$B2:$B433) -> 1.0055085 | AW436: =SUMPRODUCT(AW2:AW433,Веса!AR2:AR433,ToSep17!$C2:$C433,$E2:$E433,$B2:$B433)/SUMPRODUCT(Веса!AR2:AR433,ToSep17!$C2:$C433,$E2:$E433,$B2:$B433) -> 1.0067652 | AX436: =SUMPRODUCT(AX2:AX433,Веса!AS2:AS433,ToSep17!$C2:$C433,$E2:$E433,$B2:$B433)/SUMPRODUCT(Веса!AS2:AS433,ToSep17!$C2:$C433,$E2:$E433,$B2:$B433) -> 1.0086155 | AY436: =SUMPRODUCT(AY2:AY433,Веса!AT2:AT433,ToSep17!$C2:$C433,$E2:$E433,$B2:$B433)/SUMPRODUCT(Веса!AT2:AT433,ToSep17!$C2:$C433,$E2:$E433,$B2:$B433) -> 1.0094402 | AZ436: =SUMPRODUCT(AZ2:AZ433,Веса!AU2:AU433,ToSep17!$C2:$C433,$E2:$E433,$B2:$B433)/SUMPRODUCT(Веса!AU2:AU433,ToSep17!$C2:$C433,$E2:$E433,$B2:$B433) -> 1.0109377
L437: Treatment Непроды | M437: =SUMPRODUCT(M2:M433,Веса!H2:H433,ToSep17!$C2:$C433,$F2:$F433,$B2:$B433)/SUMPRODUCT(Веса!H2:H433,ToSep17!$C2:$C433,$F2:$F433,$B2:$B433) -> 0.84142204 | N437: =SUMPRODUCT(N2:N433,Веса!I2:I433,ToSep17!$C2:$C433,$F2:$F433,$B2:$B433)/SUMPRODUCT(Веса!I2:I433,ToSep17!$C2:$C433,$F2:$F433,$B2:$B433) -> 0.8591314 | O437: =SUMPRODUCT(O2:O433,Веса!J2:J433,ToSep17!$C2:$C433,$F2:$F433,$B2:$B433)/SUMPRODUCT(Веса!J2:J433,ToSep17!$C2:$C433,$F2:$F433,$B2:$B433) -> 0.87364531 | P437: =SUMPRODUCT(P2:P433,Веса!K2:K433,ToSep17!$C2:$C433,$F2:$F433,$B2:$B433)/SUMPRODUCT(Веса!K2:K433,ToSep17!$C2:$C433,$F2:$F433,$B2:$B433) -> 0.88257011 | Q437: =SUMPRODUCT(Q2:Q433,Веса!L2:L433,ToSep17!$C2:$C433,$F2:$F433,$B2:$B433)/SUMPRODUCT(Веса!L2:L433,ToSep17!$C2:$C433,$F2:$F433,$B2:$B433) -> 0.88810771 | R437: =SUMPRODUCT(R2:R433,Веса!M2:M433,ToSep17!$C2:$C433,$F2:$F433,$B2:$B433)/SUMPRODUCT(Веса!M2:M433,ToSep17!$C2:$C433,$F2:$F433,$B2:$B433) -> 0.89015671 | S437: =SUMPRODUCT(S2:S433,Веса!N2:N433,ToSep17!$C2:$C433,$F2:$F433,$B2:$B433)/SUMPRODUCT(Веса!N2:N433,ToSep17!$C2:$C433,$F2:$F433,$B2:$B433) -> 0.89215197 | T437: =SUMPRODUCT(T2:T433,Веса!O2:O433,ToSep17!$C2:$C433,$F2:$F433,$B2:$B433)/SUMPRODUCT(Веса!O2:O433,ToSep17!$C2:$C433,$F2:$F433,$B2:$B433) -> 0.89772107 | ... AR437: =SUMPRODUCT(AR2:AR433,Веса!AM2:AM433,ToSep17!$C2:$C433,$F2:$F433,$B2:$B433)/SUMPRODUCT(Веса!AM2:AM433,ToSep17!$C2:$C433,$F2:$F433,$B2:$B433) -> 0.99805892 | AS437: 1 | AT437: =SUMPRODUCT(AT2:AT433,Веса!AO2:AO433,ToSep17!$C2:$C433,$F2:$F433,$B2:$B433)/SUMPRODUCT(Веса!AO2:AO433,ToSep17!$C2:$C433,$F2:$F433,$B2:$B433) -> 1.0028631 | AU437: =SUMPRODUCT(AU2:AU433,Веса!AP2:AP433,ToSep17!$C2:$C433,$F2:$F433,$B2:$B433)/SUMPRODUCT(Веса!AP2:AP433,ToSep17!$C2:$C433,$F2:$F433,$B2:$B433) -> 1.0051993 | AV437: =SUMPRODUCT(AV2:AV433,Веса!AQ2:AQ433,ToSep17!$C2:$C433,$F2:$F433,$B2:$B433)/SUMPRODUCT(Веса!AQ2:AQ433,ToSep17!$C2:$C433,$F2:$F433,$B2:$B433) -> 1.0063708 | AW437: =SUMPRODUCT(AW2:AW433,Веса!AR2:AR433,ToSep17!$C2:$C433,$F2:$F433,$B2:$B433)/SUMPRODUCT(Веса!AR2:AR433,ToSep17!$C2:$C433,$F2:$F433,$B2:$B433) -> 1.0083748 | AX437: =SUMPRODUCT(AX2:AX433,Веса!AS2:AS433,ToSep17!$C2:$C433,$F2:$F433,$B2:$B433)/SUMPRODUCT(Веса!AS2:AS433,ToSep17!$C2:$C433,$F2:$F433,$B2:$B433) -> 1.0096906 | AY437: =SUMPRODUCT(AY2:AY433,Веса!AT2:AT433,ToSep17!$C2:$C433,$F2:$F433,$B2:$B433)/SUMPRODUCT(Веса!AT2:AT433,ToSep17!$C2:$C433,$F2:$F433,$B2:$B433) -> 1.0112736 | AZ437: =SUMPRODUCT(AZ2:AZ433,Веса!AU2:AU433,ToSep17!$C2:$C433,$F2:$F433,$B2:$B433)/SUMPRODUCT(Веса!AU2:AU433,ToSep17!$C2:$C433,$F2:$F433,$B2:$B433) -> 1.0136544
L438: Treatment Непроды без одежды | M438: =SUMPRODUCT(M2:M433,Веса!H2:H433,ToSep17!$C2:$C433,$G2:$G433,$B2:$B433)/SUMPRODUCT(Веса!H2:H433,ToSep17!$C2:$C433,$G2:$G433,$B2:$B433) -> 0.85429577 | N438: =SUMPRODUCT(N2:N433,Веса!I2:I433,ToSep17!$C2:$C433,$G2:$G433,$B2:$B433)/SUMPRODUCT(Веса!I2:I433,ToSep17!$C2:$C433,$G2:$G433,$B2:$B433) -> 0.87431583 | O438: =SUMPRODUCT(O2:O433,Веса!J2:J433,ToSep17!$C2:$C433,$G2:$G433,$B2:$B433)/SUMPRODUCT(Веса!J2:J433,ToSep17!$C2:$C433,$G2:$G433,$B2:$B433) -> 0.88823443 | P438: =SUMPRODUCT(P2:P433,Веса!K2:K433,ToSep17!$C2:$C433,$G2:$G433,$B2:$B433)/SUMPRODUCT(Веса!K2:K433,ToSep17!$C2:$C433,$G2:$G433,$B2:$B433) -> 0.89652086 | Q438: =SUMPRODUCT(Q2:Q433,Веса!L2:L433,ToSep17!$C2:$C433,$G2:$G433,$B2:$B433)/SUMPRODUCT(Веса!L2:L433,ToSep17!$C2:$C433,$G2:$G433,$B2:$B433) -> 0.9012411 | R438: =SUMPRODUCT(R2:R433,Веса!M2:M433,ToSep17!$C2:$C433,$G2:$G433,$B2:$B433)/SUMPRODUCT(Веса!M2:M433,ToSep17!$C2:$C433,$G2:$G433,$B2:$B433) -> 0.90275191 | S438: =SUMPRODUCT(S2:S433,Веса!N2:N433,ToSep17!$C2:$C433,$G2:$G433,$B2:$B433)/SUMPRODUCT(Веса!N2:N433,ToSep17!$C2:$C433,$G2:$G433,$B2:$B433) -> 0.90467665 | T438: =SUMPRODUCT(T2:T433,Веса!O2:O433,ToSep17!$C2:$C433,$G2:$G433,$B2:$B433)/SUMPRODUCT(Веса!O2:O433,ToSep17!$C2:$C433,$G2:$G433,$B2:$B433) -> 0.90980171 | ... AR438: =SUMPRODUCT(AR2:AR433,Веса!AM2:AM433,ToSep17!$C2:$C433,$G2:$G433,$B2:$B433)/SUMPRODUCT(Веса!AM2:AM433,ToSep17!$C2:$C433,$G2:$G433,$B2:$B433) -> 0.99923764 | AS438: 1 | AT438: =SUMPRODUCT(AT2:AT433,Веса!AO2:AO433,ToSep17!$C2:$C433,$G2:$G433,$B2:$B433)/SUMPRODUCT(Веса!AO2:AO433,ToSep17!$C2:$C433,$G2:$G433,$B2:$B433) -> 1.0017768 | AU438: =SUMPRODUCT(AU2:AU433,Веса!AP2:AP433,ToSep17!$C2:$C433,$G2:$G433,$B2:$B433)/SUMPRODUCT(Веса!AP2:AP433,ToSep17!$C2:$C433,$G2:$G433,$B2:$B433) -> 1.0039711 | AV438: =SUMPRODUCT(AV2:AV433,Веса!AQ2:AQ433,ToSep17!$C2:$C433,$G2:$G433,$B2:$B433)/SUMPRODUCT(Веса!AQ2:AQ433,ToSep17!$C2:$C433,$G2:$G433,$B2:$B433) -> 1.0050537 | AW438: =SUMPRODUCT(AW2:AW433,Веса!AR2:AR433,ToSep17!$C2:$C433,$G2:$G433,$B2:$B433)/SUMPRODUCT(Веса!AR2:AR433,ToSep17!$C2:$C433,$G2:$G433,$B2:$B433) -> 1.0076533 | AX438: =SUMPRODUCT(AX2:AX433,Веса!AS2:AS433,ToSep17!$C2:$C433,$G2:$G433,$B2:$B433)/SUMPRODUCT(Веса!AS2:AS433,ToSep17!$C2:$C433,$G2:$G433,$B2:$B433) -> 1.0089874 | AY438: =SUMPRODUCT(AY2:AY433,Веса!AT2:AT433,ToSep17!$C2:$C433,$G2:$G433,$B2:$B433)/SUMPRODUCT(Веса!AT2:AT433,ToSep17!$C2:$C433,$G2:$G433,$B2:$B433) -> 1.0102042 | AZ438: =SUMPRODUCT(AZ2:AZ433,Веса!AU2:AU433,ToSep17!$C2:$C433,$G2:$G433,$B2:$B433)/SUMPRODUCT(Веса!AU2:AU433,ToSep17!$C2:$C433,$G2:$G433,$B2:$B433) -> 1.0127222
